Workbook

Sheet Briefing_FID
A1: Portfolio | B1: Estratégia | C1: Elegibilidade | D1: Oi Vende | E1: Canais | AM1: Campanha | AP1: Data | AR1: Configurações da Campanha | AY1: Regras de Campanha | BB1: Configurações da Oferta | BE1: ="Preço Fixo "&DOLLAR(ARBOR!C2,2) -> Preço Fixo R$ 75,84 | BH1: ="Oi TV Start HD (PCS-OzTL40) "&DOLLAR(VLOOKUP("PCS-OzTL40",ARBOR!$A:$C,3,0),2) -> Oi TV Start HD (PCS-OzTL40) R$ 99,00 | BK1: ="Oi TV Mix HD (PCS-OzTL41) "&DOLLAR(VLOOKUP("PCS-OzTL41",ARBOR!$A:$C,3,0),2) -> Oi TV Mix HD (PCS-OzTL41) R$ 121,03 | BN1: ="Oi TV Mix HBO Max HD (PCS-OzTL44) "&DOLLAR(VLOOKUP("PCS-OzTL44",ARBOR!$A:$C,3,0),2) -> Oi TV Mix HBO Max HD (PCS-OzTL44) R$ 192,61 | BQ1: ="Oi TV Mix Telecine HD (PCS-OzTL43) "&DOLLAR(VLOOKUP("PCS-OzTL43",ARBOR!$A:$C,3,0),2) -> Oi TV Mix Telecine HD (PCS-OzTL43) R$ 203,63 | BT1: ="Oi TV Mix Cinema HD (PCS-OzTL45) "&DOLLAR(VLOOKUP("PCS-OzTL45",ARBOR!$A:$C,3,0),2) -> Oi TV Mix Cinema HD (PCS-OzTL45) R$ 209,13 | BW1: ="Oi TV Mix HD DVR (PCS-OzTL741) "&DOLLAR(VLOOKUP("PCS-OzTL741",ARBOR!$A:$C,3,0),2) -> Oi TV Mix HD DVR (PCS-OzTL741) R$ 176,09 | BZ1: ="Oi TV Mix HBOMax HD DVR (PCS-OzTL744) "&DOLLAR(VLOOKUP("PCS-OzTL744",ARBOR!$A:$C,3,0),2) -> Oi TV Mix HBOMax HD DVR (PCS-OzTL744) R$ 209,13 | CC1: ="Oi TV Mix Telecine HD DVR (PCS-OzTL743) "&DOLLAR(VLOOKUP("PCS-OzTL743",ARBOR!$A:$C,3,0),2) -> Oi TV Mix Telecine HD DVR (PCS-OzTL743) R$ 220,14 | CF1: ="Oi TV Mix Cinema HD DVR (PCS-OzTL745) "&DOLLAR(VLOOKUP("PCS-OzTL745",ARBOR!$A:$C,3,0),2) -> Oi TV Mix Cinema HD DVR (PCS-OzTL745) R$ 253,18 | CI1: ="Oi TV Total HD (PCS-OzTL42) "&DOLLAR(VLOOKUP("PCS-OzTL42",ARBOR!$A:$C,3,0),2) -> Oi TV Total HD (PCS-OzTL42) R$ 165,08 | CL1: ="Oi TV Total HBO Max HD (PCS-OzTL47) "&DOLLAR(VLOOKUP("PCS-OzTL47",ARBOR!$A:$C,3,0),2) -> Oi TV Total HBO Max HD (PCS-OzTL47) R$ 203,63 | CO1: ="Oi TV Total Telecine HD (PCS-OzTL46) "&DOLLAR(VLOOKUP("PCS-OzTL46",ARBOR!$A:$C,3,0),2) -> Oi TV Total Telecine HD (PCS-OzTL46) R$ 214,64 | CR1: ="Oi TV Total Cinema HD (PCS-OzTL48) "&DOLLAR(VLOOKUP("PCS-OzTL48",ARBOR!$A:$C,3,0),2) -> Oi TV Total Cinema HD (PCS-OzTL48) R$ 253,18 | CU1: ="Oi TV Total HD DVR (PCS-OzTL742) "&DOLLAR(VLOOKUP("PCS-OzTL742",ARBOR!$A:$C,3,0),2) -> Oi TV Total HD DVR (PCS-OzTL742) R$ 220,14 | CX1: ="Oi TV Total HBOMax HD DVR (PCS-OzTL747) "&DOLLAR(VLOOKUP("PCS-OzTL747",ARBOR!$A:$C,3,0),2) -> Oi TV Total HBOMax HD DVR (PCS-OzTL747) R$ 258,69 | DA1: ="Oi TV Total Telecine HD DVR (PCS-OzTL746) "&DOLLAR(VLOOKUP("PCS-OzTL746",ARBOR!$A:$C,3,0),2) -> Oi TV Total Telecine HD DVR (PCS-OzTL746) R$ 269,70 | DD1: ="Oi TV Total Cinema HD DVR (PCS-OzTL748) "&DOLLAR(VLOOKUP("PCS-OzTL748",ARBOR!$A:$C,3,0),2) -> Oi TV Total Cinema HD DVR (PCS-OzTL748) R$ 308,25 | DG1: ="Oi TV Combate (PCS-OzTL34) "&DOLLAR(VLOOKUP("PCS-OzTL34",ARBOR!$A:$C,3,0),2) -> Oi TV Combate (PCS-OzTL34) R$ 110,13 | DJ1: ="Oi TV Sexy Hot (PCS-OzTL31) "&DOLLAR(VLOOKUP("PCS-OzTL31",ARBOR!$A:$C,3,0),2) -> Oi TV Sexy Hot (PCS-OzTL31) R$ 21,91 | DM1: ="Oi TV Playboy (PCS-OzTL32) "&DOLLAR(VLOOKUP("PCS-OzTL32",ARBOR!$A:$C,3,0),2) -> Oi TV Playboy (PCS-OzTL32) R$ 21,91 | DP1: ="Oi TV Sexy Hot + Playboy (PCS-OzTL33) "&DOLLAR(VLOOKUP("PCS-OzTL33",ARBOR!$A:$C,3,0),2) -> Oi TV Sexy Hot + Playboy (PCS-OzTL33) R$ 32,92 | DS1: ="Oi TV SexPrivê (PCS-OzTL503) "&DOLLAR(VLOOKUP("PCS-OzTL503",ARBOR!$A:$C,3,0),2) -> Oi TV SexPrivê (PCS-OzTL503) R$ 16,40 | DV1: ="Oi TV Étnicos (PCS-OzTL500) "&DOLLAR(VLOOKUP("PCS-OzTL500",ARBOR!$A:$C,3,0),2) -> Oi TV Étnicos (PCS-OzTL500) R$ 11,01 | DY1: ="Coleção OI (PCS-OzTL50)" -> Coleção OI (PCS-OzTL50) | EB1: ="Fox Premium (PCS-OzTL51)" -> Fox Premium (PCS-OzTL51) | EE1: ="PenVr (PCS-OzTL52)" -> PenVr (PCS-OzTL52) | EH1: ="PFC Completo (PCS-OzTL53)" -> PFC Completo (PCS-OzTL53) | EK1: ="PFC Básico (PCS-OzTL54)" -> PFC Básico (PCS-OzTL54) | EN1: ="Oi TV Ponto Adicional (PCS-OzTL99) "&DOLLAR(VLOOKUP("PCS-OzTL99",ARBOR!$A:$C,3,0),2) -> Oi TV Ponto Adicional (PCS-OzTL99) R$ 29,90 | ES1: Multa | EZ1: Benefícios de Minutos/SMS | FC1: Benefícios de Minutos/SMS | FF1: Chip Alone | FG1: TOTAIS | FX1: Campos de uso livre
A2: Portfolio (linguagem comercial) | B2: Estratégia (aquisição, retenção ou Oi Pontos) | C2: Cliente Elegivel | D2: Visível no Oi Vende? | E2: Oi BSIM R1 | F2: Oi BSIM R2 | G2: Atendimento | H2: BO Atendimento | I2: Ouvidoria | J2: Auditoria de Vendas | K2: BO Contratos | L2: Hotline | M2: BO Hotline | N2: Faranqua Alto Valor | O2: Franquia Oi Atende | P2: Agex | Q2: Agex Simples | R2: Lojas Próprias | S2: Pap | T2: Televendas Ativo 3P RES | U2: Televendas Ativo 4P/ 3P Móvel | V2: Televendas Receptivo 3P RES | W2: Televendas Receptivo 4P/ 3P MÓVEL | X2: Teleagentes | Y2: Teleagentes 4P | Z2: Web | AA2: Retenção | AB2: BO Retenção | AC2: Blindagem Oi ToTal | AD2: Blindagem | AE2: Ilha de Migração | AF2: Rentabilização | AG2: Procon | AH2: JEC | AI2: BO Oi Pontos | AK2: Operações Especiais Retenção (Propenso e Ativo Reversão) | AL2: PDV's específicos | AM2: Nome da campanha | AN2: Objetivo da Campanha | AO2: Resumo da Campanha | AP2: Data inicio | AQ2: Data fim | AR2: Localidade | AS2: Filial | AT2: DDD's | AU2: Unidade de Negócio | AV2: nº Maximo de oportunidades | AW2: Nº de adesões esperadas | AX2: Publico Alvo | AY2: Campanha Subsidiada | AZ2: DACC | BA2: CSP | BB2: Nome Oferta | BC2: Plano Voz (campo obrigatório) | BD2: Código SBL | BE2: Comercial | BF2: % Desc Ajust | BG2: Código | BH2: Comercial | BI2: % Desc (ind) | BJ2: Código | BK2: Comercial | BL2: % Desc (ind) | BM2: Código | BN2: Comercial | BO2: % Desc (ind) | BP2: Código | BQ2: Comercial | BR2: % Desc (ind) | BS2: Código | BT2: Comercial | BU2: % Desc (ind) | BV2: Código | BW2: Comercial | BX2: % Desc (ind) | BY2: Código | BZ2: Comercial | CA2: % Desc (ind) | CB2: Código | CC2: Comercial | CD2: % Desc (ind) | CE2: Código | CF2: Comercial | CG2: % Desc (ind) | CH2: Código | CI2: Comercial | CJ2: % Desc (ind) | CK2: Código | CL2: Comercial | CM2: % Desc (ind) | CN2: Código | CO2: Comercial | CP2: % Desc (ind) | CQ2: Código | CR2: Comercial | CS2: % Desc (ind) | CT2: Código | CU2: Comercial | CV2: % Desc (ind) | CW2: Código | CX2: Comercial | CY2: % Desc (ind) | CZ2: Código | DA2: Comercial | DB2: % Desc (ind) | DC2: Código | DD2: Comercial | DE2: % Desc (ind) | DF2: Código | DG2: Comercial | DH2: % Desc | DI2: Cod | DJ2: Comercial | DK2: % Desc | DL2: Cod | DM2: Comercial | DN2: % Desc | DO2: Cod | DP2: Comercial | DQ2: % Desc | DR2: Cod | DS2: Comercial | DT2: % Desc | DU2: Cod | DV2: Comercial | DW2: % Desc | DX2: Cod | DY2: Comercial | DZ2: % Desc | EA2: Código | EB2: Comercial | EC2: % Desc | ED2: Código | EE2: Comercial | EF2: % Desc | EG2: Código | EH2: Comercial | EI2: % Desc | EJ2: Código | EK2: Comercial | EL2: % Desc | EM2: Código | EN2: Comercial | EO2: % Desc | EP2: Cod | EQ2: 1o Ponto Adicional Gratuito? | ER2: Cod | ES2: Sim/ Não | ET2: Tipo Benefício/ Aparelho/ Oi Pontos | EU2: Valor da multa | EV2: Duração (meses) | EW2: Benefício que gerou a fidelização | EX2: Código Benefício que gerou Fidelização | EY2: ELEMENTO DE MULTA | EZ2: Tipo do benefício | FA2: Nome do benefício | FB2: Código | FC2: Tipo do benefício | FD2: Nome do benefício | FE2: Código | FF2: Elementos | FG2: [Fixo] START | FH2: [Fixo] MIX | FI2: [Fixo] MIX HBO | FJ2: [Fixo] MIX Telecine | FK2: [Fixo] MIX Cinema | FL2: [Fixo] MIX DVR | FM2: [Fixo] MIX HBO DVR | FN2: [Fixo] MIX Telecine DVR | FO2: [Fixo] MIX Cinema DVR | FP2: [Fixo] Total | FQ2: [Fixo] Total HBO | FR2: [Fixo] Total Telecine | FS2: [Fixo] Total Cinema | FT2: [Fixo] Total DVR | FU2: [Fixo] Total HBO DVR | FV2: [Fixo] Total Telecine DVR | FW2: [Fixo] Total Cinema DVR | FX2: Livre 1 | FY2: Livre 2 | FZ2: Livre 3 | GA2: Livre 4 | GB2: Livre 5 | GC2: Livre 6 | GD2: Livre 7 | GE2: Livre 8 | GF2: Livre 9 | GG2: Livre 10
A3: Oi Total | B3: Migração | C3: Atuais | D3: Não | AM3: OT_ATV_JUL17_FID_DACC_2PTV_TV1_ST_LD-VC_OF1 | AN3: Rentabilizar atuais clientes do plano | AO3: Produto Fixo + TV , Produto com fidelização | AP3: 42917 | AQ3: 43039 | AR3: 20. Oi Total | AS3: 20. Oi Total | AU3: Varejo | AV3: 20 | AW3: 10000 | AX3: Campanha Restrita | AY3: Sim | AZ3: Sim | BA3: Não | BB3: OT_ATV_JUL17_FID_DACC_2PTV_TV1_ST_LD-VC_OF1 | BC3: Oi Total Fixo + TV 1 | BD3: =IF(BC3="Oi Total Fixo + TV 1","CFG-2Plowpi",IF(BC3="Oi Total Fixo + TV 2","PCS-2PMepi",IF(BC3="Oi Total Fixo + TV 3","PCS-2PHipi",""))) -> CFG-2Plowpi | BE3: 60 | BF3: =IF(BE3=0,"",IF(BE3=VLOOKUP("FIXO",ARBOR!$A:$C,3,0),0.0001,IF(BE3>VLOOKUP("FIXO",ARBOR!$A:$C,3,0),"Maior que CAP!",IF((DOLLAR(BE3+(VLOOKUP("FIXO",ARBOR!$A:$C,3,0)*-TRUNC(BE3/VLOOKUP("FIXO",ARBOR!$A:$C,3,0)-1,4)),6))<>(DOLLAR(VLOOKUP("FIXO",ARBOR!$A:$C,3,0),6)),-TRUNC(BE3/VLOOKUP("FIXO",ARBOR!$A:$C,3,0)-1,4)+0.0001,-TRUNC(BE3/VLOOKUP("FIXO",ARBOR!$A:$C,3,0)-1,4))))) -> 0.2089 | BG3: =IF(ISERROR(IF(BF3="","",VLOOKUP(($BC3&BF3&"Template de desconto FLAT bundle - Fixo - Varejo - Ganho Tributário Cross"),BENEFICIOS!$A:$G,5,0))),"Criar",IF(BF3="","",VLOOKUP(($BC3&BF3&"Template de desconto FLAT bundle - Fixo - Varejo - Ganho Tributário Cross"),BENEFICIOS!$A:$G,5,0))) -> Criar | BH3: 74.9 | BI3: =IF(BH3=0,"",IF(BH3=VLOOKUP("PCS-OzTL40",ARBOR!$A:$C,3,0),0.0001,IF(BH3>VLOOKUP("PCS-OzTL40",ARBOR!$A:$C,3,0),"Maior que CAP!",IF((DOLLAR(BH3+(VLOOKUP("PCS-OzTL40",ARBOR!$A:$C,3,0)*-TRUNC(BH3/VLOOKUP("PCS-OzTL40",ARBOR!$A:$C,3,0)-1,4)),6))<>(DOLLAR(VLOOKUP("PCS-OzTL40",ARBOR!$A:$C,3,0),6)),-TRUNC(BH3/VLOOKUP("PCS-OzTL40",ARBOR!$A:$C,3,0)-1,4)+0.0001,-TRUNC(BH3/VLOOKUP("PCS-OzTL40",ARBOR!$A:$C,3,0)-1,4))))) -> 0.2435 | BJ3: =IF(ISERROR(IF(BI3="","",VLOOKUP((BC3&BI3&"Template desconto FLAT Plano Principal Oi TV nível conta"),BENEFICIOS!$A:$G,5,0))),"Criar",IF(BI3="","",VLOOKUP((BC3&BI3&"Template desconto FLAT Plano Principal Oi TV nível conta"),BENEFICIOS!$A:$G,5,0))) -> Criar | BL3: =IF(BK3=0,"",IF(BK3=VLOOKUP("PCS-OzTL41",ARBOR!$A:$C,3,0),0.0001,IF(BK3>VLOOKUP("PCS-OzTL41",ARBOR!$A:$C,3,0),"Maior que CAP!",IF((DOLLAR(BK3+(VLOOKUP("PCS-OzTL41",ARBOR!$A:$C,3,0)*-TRUNC(BK3/VLOOKUP("PCS-OzTL41",ARBOR!$A:$C,3,0)-1,4)),6))<>(DOLLAR(VLOOKUP("PCS-OzTL41",ARBOR!$A:$C,3,0),6)),-TRUNC(BK3/VLOOKUP("PCS-OzTL41",ARBOR!$A:$C,3,0)-1,4)+0.0001,-TRUNC(BK3/VLOOKUP("PCS-OzTL41",ARBOR!$A:$C,3,0)-1,4))))) | BM3: =IF(ISERROR(IF(BL3="","",VLOOKUP((BC3&BL3&"Template desconto FLAT Plano Principal Oi TV nível conta"),BENEFICIOS!$A:$G,5,0))),"Criar",IF(BL3="","",VLOOKUP((BC3&BL3&"Template desconto FLAT Plano Principal Oi TV nível conta"),BENEFICIOS!$A:$G,5,0))) | BO3: =IF(BN3=0,"",IF(BN3=VLOOKUP("PCS-OzTL44",ARBOR!$A:$C,3,0),0.0001,IF(BN3>VLOOKUP("PCS-OzTL44",ARBOR!$A:$C,3,0),"Maior que CAP!",IF((DOLLAR(BN3+(VLOOKUP("PCS-OzTL44",ARBOR!$A:$C,3,0)*-TRUNC(BN3/VLOOKUP("PCS-OzTL44",ARBOR!$A:$C,3,0)-1,4)),6))<>(DOLLAR(VLOOKUP("PCS-OzTL44",ARBOR!$A:$C,3,0),6)),-TRUNC(BN3/VLOOKUP("PCS-OzTL44",ARBOR!$A:$C,3,0)-1,4)+0.0001,-TRUNC(BN3/VLOOKUP("PCS-OzTL44",ARBOR!$A:$C,3,0)-1,4))))) | BP3: =IF(ISERROR(IF(BO3="","",VLOOKUP((BC3&BO3&"Template desconto FLAT Plano Principal Oi TV nível conta"),BENEFICIOS!$A:$G,5,0))),"Criar",IF(BO3="","",VLOOKUP((BC3&BO3&"Template desconto FLAT Plano Principal Oi TV nível conta"),BENEFICIOS!$A:$G,5,0))) | BR3: =IF(BQ3=0,"",IF(BQ3=VLOOKUP("PCS-OzTL43",ARBOR!$A:$C,3,0),0.0001,IF(BQ3>VLOOKUP("PCS-OzTL43",ARBOR!$A:$C,3,0),"Maior que CAP!",IF((DOLLAR(BQ3+(VLOOKUP("PCS-OzTL43",ARBOR!$A:$C,3,0)*-TRUNC(BQ3/VLOOKUP("PCS-OzTL43",ARBOR!$A:$C,3,0)-1,4)),6))<>(DOLLAR(VLOOKUP("PCS-OzTL43",ARBOR!$A:$C,3,0),6)),-TRUNC(BQ3/VLOOKUP("PCS-OzTL43",ARBOR!$A:$C,3,0)-1,4)+0.0001,-TRUNC(BQ3/VLOOKUP("PCS-OzTL43",ARBOR!$A:$C,3,0)-1,4))))) | BS3: =IF(ISERROR(IF(BR3="","",VLOOKUP((BC3&BR3&"Template desconto FLAT Plano Principal Oi TV nível conta"),BENEFICIOS!$A:$G,5,0))),"Criar",IF(BR3="","",VLOOKUP((BC3&BR3&"Template desconto FLAT Plano Principal Oi TV nível conta"),BENEFICIOS!$A:$G,5,0))) | BU3: =IF(BT3=0,"",IF(BT3=VLOOKUP("PCS-OzTL45",ARBOR!$A:$C,3,0),0.0001,IF(BT3>VLOOKUP("PCS-OzTL45",ARBOR!$A:$C,3,0),"Maior que CAP!",IF((DOLLAR(BT3+(VLOOKUP("PCS-OzTL45",ARBOR!$A:$C,3,0)*-TRUNC(BT3/VLOOKUP("PCS-OzTL45",ARBOR!$A:$C,3,0)-1,4)),6))<>(DOLLAR(VLOOKUP("PCS-OzTL45",ARBOR!$A:$C,3,0),6)),-TRUNC(BT3/VLOOKUP("PCS-OzTL45",ARBOR!$A:$C,3,0)-1,4)+0.0001,-TRUNC(BT3/VLOOKUP("PCS-OzTL45",ARBOR!$A:$C,3,0)-1,4))))) | BV3: =IF(ISERROR(IF(BU3="","",VLOOKUP((BC3&BU3&"Template desconto FLAT Plano Principal Oi TV nível conta"),BENEFICIOS!$A:$G,5,0))),"Criar",IF(BU3="","",VLOOKUP((BC3&BU3&"Template desconto FLAT Plano Principal Oi TV nível conta"),BENEFICIOS!$A:$G,5,0))) | BX3: =IF(BW3=0,"",IF(BW3=VLOOKUP("PCS-OzTL741",ARBOR!$A:$C,3,0),0.0001,IF(BW3>VLOOKUP("PCS-OzTL741",ARBOR!$A:$C,3,0),"Maior que CAP!",IF((DOLLAR(BW3+(VLOOKUP("PCS-OzTL741",ARBOR!$A:$C,3,0)*-TRUNC(BW3/VLOOKUP("PCS-OzTL741",ARBOR!$A:$C,3,0)-1,4)),6))<>(DOLLAR(VLOOKUP("PCS-OzTL741",ARBOR!$A:$C,3,0),6)),-TRUNC(BW3/VLOOKUP("PCS-OzTL741",ARBOR!$A:$C,3,0)-1,4)+0.0001,-TRUNC(BW3/VLOOKUP("PCS-OzTL741",ARBOR!$A:$C,3,0)-1,4))))) | BY3: =IF(ISERROR(IF(BX3="","",VLOOKUP((BC3&BX3&"Template desconto FLAT Plano Principal Oi TV nível conta"),BENEFICIOS!$A:$G,5,0))),"Criar",IF(BX3="","",VLOOKUP((BC3&BX3&"Template desconto FLAT Plano Principal Oi TV nível conta"),BENEFICIOS!$A:$G,5,0))) | CA3: =IF(BZ3=0,"",IF(BZ3=VLOOKUP("PCS-OzTL744",ARBOR!$A:$C,3,0),0.0001,IF(BZ3>VLOOKUP("PCS-OzTL744",ARBOR!$A:$C,3,0),"Maior que CAP!",IF((DOLLAR(BZ3+(VLOOKUP("PCS-OzTL744",ARBOR!$A:$C,3,0)*-TRUNC(BZ3/VLOOKUP("PCS-OzTL744",ARBOR!$A:$C,3,0)-1,4)),6))<>(DOLLAR(VLOOKUP("PCS-OzTL744",ARBOR!$A:$C,3,0),6)),-TRUNC(BZ3/VLOOKUP("PCS-OzTL744",ARBOR!$A:$C,3,0)-1,4)+0.0001,-TRUNC(BZ3/VLOOKUP("PCS-OzTL744",ARBOR!$A:$C,3,0)-1,4))))) | CB3: =IF(ISERROR(IF(CA3="","",VLOOKUP(($BC3&CA3&"Template desconto FLAT Plano Principal Oi TV nível conta"),BENEFICIOS!$A:$G,5,0))),"Criar",IF(CA3="","",VLOOKUP(($BC3&CA3&"Template desconto FLAT Plano Principal Oi TV nível conta"),BENEFICIOS!$A:$G,5,0))) | CD3: =IF(CC3=0,"",IF(CC3=VLOOKUP("PCS-OzTL743",ARBOR!$A:$C,3,0),0.0001,IF(CC3>VLOOKUP("PCS-OzTL743",ARBOR!$A:$C,3,0),"Maior que CAP!",IF((DOLLAR(CC3+(VLOOKUP("PCS-OzTL743",ARBOR!$A:$C,3,0)*-TRUNC(CC3/VLOOKUP("PCS-OzTL743",ARBOR!$A:$C,3,0)-1,4)),6))<>(DOLLAR(VLOOKUP("PCS-OzTL743",ARBOR!$A:$C,3,0),6)),-TRUNC(CC3/VLOOKUP("PCS-OzTL743",ARBOR!$A:$C,3,0)-1,4)+0.0001,-TRUNC(CC3/VLOOKUP("PCS-OzTL743",ARBOR!$A:$C,3,0)-1,4))))) | CE3: =IF(ISERROR(IF(CD3="","",VLOOKUP(($BC3&CD3&"Template desconto FLAT Plano Principal Oi TV nível conta"),BENEFICIOS!$A:$G,5,0))),"Criar",IF(CD3="","",VLOOKUP(($BC3&CD3&"Template desconto FLAT Plano Principal Oi TV nível conta"),BENEFICIOS!$A:$G,5,0))) | CG3: =IF(CF3=0,"",IF(CF3=VLOOKUP("PCS-OzTL745",ARBOR!$A:$C,3,0),0.0001,IF(CF3>VLOOKUP("PCS-OzTL745",ARBOR!$A:$C,3,0),"Maior que CAP!",IF((DOLLAR(CF3+(VLOOKUP("PCS-OzTL745",ARBOR!$A:$C,3,0)*-TRUNC(CF3/VLOOKUP("PCS-OzTL745",ARBOR!$A:$C,3,0)-1,4)),6))<>(DOLLAR(VLOOKUP("PCS-OzTL745",ARBOR!$A:$C,3,0),6)),-TRUNC(CF3/VLOOKUP("PCS-OzTL745",ARBOR!$A:$C,3,0)-1,4)+0.0001,-TRUNC(CF3/VLOOKUP("PCS-OzTL745",ARBOR!$A:$C,3,0)-1,4))))) | CH3: =IF(ISERROR(IF(CG3="","",VLOOKUP(($BC3&CG3&"Template desconto FLAT Plano Principal Oi TV nível conta"),BENEFICIOS!$A:$G,5,0))),"Criar",IF(CG3="","",VLOOKUP(($BC3&CG3&"Template desconto FLAT Plano Principal Oi TV nível conta"),BENEFICIOS!$A:$G,5,0))) | CJ3: =IF(CI3=0,"",IF(CI3=VLOOKUP("PCS-OzTL42",ARBOR!$A:$C,3,0),0.0001,IF(CI3>VLOOKUP("PCS-OzTL42",ARBOR!$A:$C,3,0),"Maior que CAP!",IF((DOLLAR(CI3+(VLOOKUP("PCS-OzTL42",ARBOR!$A:$C,3,0)*-TRUNC(CI3/VLOOKUP("PCS-OzTL42",ARBOR!$A:$C,3,0)-1,4)),6))<>(DOLLAR(VLOOKUP("PCS-OzTL42",ARBOR!$A:$C,3,0),6)),-TRUNC(CI3/VLOOKUP("PCS-OzTL42",ARBOR!$A:$C,3,0)-1,4)+0.0001,-TRUNC(CI3/VLOOKUP("PCS-OzTL42",ARBOR!$A:$C,3,0)-1,4))))) | CK3: =IF(ISERROR(IF(CJ3="","",VLOOKUP(($BC3&CJ3&"Template desconto FLAT Plano Principal Oi TV nível conta"),BENEFICIOS!$A:$G,5,0))),"Criar",IF(CJ3="","",VLOOKUP(($BC3&CJ3&"Template desconto FLAT Plano Principal Oi TV nível conta"),BENEFICIOS!$A:$G,5,0))) | CM3: =IF(CL3=0,"",IF(CL3=VLOOKUP("PCS-OzTL47",ARBOR!$A:$C,3,0),0.0001,IF(CL3>VLOOKUP("PCS-OzTL47",ARBOR!$A:$C,3,0),"Maior que CAP!",IF((DOLLAR(CL3+(VLOOKUP("PCS-OzTL47",ARBOR!$A:$C,3,0)*-TRUNC(CL3/VLOOKUP("PCS-OzTL47",ARBOR!$A:$C,3,0)-1,4)),6))<>(DOLLAR(VLOOKUP("PCS-OzTL47",ARBOR!$A:$C,3,0),6)),-TRUNC(CL3/VLOOKUP("PCS-OzTL47",ARBOR!$A:$C,3,0)-1,4)+0.0001,-TRUNC(CL3/VLOOKUP("PCS-OzTL47",ARBOR!$A:$C,3,0)-1,4))))) | CN3: =IF(ISERROR(IF(CM3="","",VLOOKUP(($BC3&CM3&"Template desconto FLAT Plano Principal Oi TV nível conta"),BENEFICIOS!$A:$G,5,0))),"Criar",IF(CM3="","",VLOOKUP(($BC3&CM3&"Template desconto FLAT Plano Principal Oi TV nível conta"),BENEFICIOS!$A:$G,5,0))) | CP3: =IF(CO3=0,"",IF(CO3=VLOOKUP("PCS-OzTL46",ARBOR!$A:$C,3,0),0.0001,IF(CO3>VLOOKUP("PCS-OzTL46",ARBOR!$A:$C,3,0),"Maior que CAP!",IF((DOLLAR(CO3+(VLOOKUP("PCS-OzTL46",ARBOR!$A:$C,3,0)*-TRUNC(CO3/VLOOKUP("PCS-OzTL46",ARBOR!$A:$C,3,0)-1,4)),6))<>(DOLLAR(VLOOKUP("PCS-OzTL46",ARBOR!$A:$C,3,0),6)),-TRUNC(CO3/VLOOKUP("PCS-OzTL46",ARBOR!$A:$C,3,0)-1,4)+0.0001,-TRUNC(CO3/VLOOKUP("PCS-OzTL46",ARBOR!$A:$C,3,0)-1,4))))) | CQ3: =IF(ISERROR(IF(CP3="","",VLOOKUP(($BC3&CP3&"Template desconto FLAT Plano Principal Oi TV nível conta"),BENEFICIOS!$A:$G,5,0))),"Criar",IF(CP3="","",VLOOKUP(($BC3&CP3&"Template desconto FLAT Plano Principal Oi TV nível conta"),BENEFICIOS!$A:$G,5,0))) | CS3: =IF(CR3=0,"",IF(CR3=VLOOKUP("PCS-OzTL48",ARBOR!$A:$C,3,0),0.0001,IF(CR3>VLOOKUP("PCS-OzTL48",ARBOR!$A:$C,3,0),"Maior que CAP!",IF((DOLLAR(CR3+(VLOOKUP("PCS-OzTL48",ARBOR!$A:$C,3,0)*-TRUNC(CR3/VLOOKUP("PCS-OzTL48",ARBOR!$A:$C,3,0)-1,4)),6))<>(DOLLAR(VLOOKUP("PCS-OzTL48",ARBOR!$A:$C,3,0),6)),-TRUNC(CR3/VLOOKUP("PCS-OzTL48",ARBOR!$A:$C,3,0)-1,4)+0.0001,-TRUNC(CR3/VLOOKUP("PCS-OzTL48",ARBOR!$A:$C,3,0)-1,4))))) | CT3: =IF(ISERROR(IF(CS3="","",VLOOKUP(($BC3&CS3&"Template desconto FLAT Plano Principal Oi TV nível conta"),BENEFICIOS!$A:$G,5,0))),"Criar",IF(CS3="","",VLOOKUP(($BC3&CS3&"Template desconto FLAT Plano Principal Oi TV nível conta"),BENEFICIOS!$A:$G,5,0))) | CV3: =IF(CU3=0,"",IF(CU3=VLOOKUP("PCS-OzTL742",ARBOR!$A:$C,3,0),0.0001,IF(CU3>VLOOKUP("PCS-OzTL742",ARBOR!$A:$C,3,0),"Maior que CAP!",IF((DOLLAR(CU3+(VLOOKUP("PCS-OzTL742",ARBOR!$A:$C,3,0)*-TRUNC(CU3/VLOOKUP("PCS-OzTL742",ARBOR!$A:$C,3,0)-1,4)),6))<>(DOLLAR(VLOOKUP("PCS-OzTL742",ARBOR!$A:$C,3,0),6)),-TRUNC(CU3/VLOOKUP("PCS-OzTL742",ARBOR!$A:$C,3,0)-1,4)+0.0001,-TRUNC(CU3/VLOOKUP("PCS-OzTL742",ARBOR!$A:$C,3,0)-1,4))))) | CW3: =IF(ISERROR(IF(CV3="","",VLOOKUP(($BC3&CV3&"Template desconto FLAT Plano Principal Oi TV nível conta"),BENEFICIOS!$A:$G,5,0))),"Criar",IF(CV3="","",VLOOKUP(($BC3&CV3&"Template desconto FLAT Plano Principal Oi TV nível conta"),BENEFICIOS!$A:$G,5,0))) | CY3: =IF(CX3=0,"",IF(CX3=VLOOKUP("PCS-OzTL747",ARBOR!$A:$C,3,0),0.0001,IF(CX3>VLOOKUP("PCS-OzTL747",ARBOR!$A:$C,3,0),"Maior que CAP!",IF((DOLLAR(CX3+(VLOOKUP("PCS-OzTL747",ARBOR!$A:$C,3,0)*-TRUNC(CX3/VLOOKUP("PCS-OzTL747",ARBOR!$A:$C,3,0)-1,4)),6))<>(DOLLAR(VLOOKUP("PCS-OzTL747",ARBOR!$A:$C,3,0),6)),-TRUNC(CX3/VLOOKUP("PCS-OzTL747",ARBOR!$A:$C,3,0)-1,4)+0.0001,-TRUNC(CX3/VLOOKUP("PCS-OzTL747",ARBOR!$A:$C,3,0)-1,4))))) | CZ3: =IF(ISERROR(IF(CY3="","",VLOOKUP(($BC3&CY3&"Template desconto FLAT Plano Principal Oi TV nível conta"),BENEFICIOS!$A:$G,5,0))),"Criar",IF(CY3="","",VLOOKUP(($BC3&CY3&"Template desconto FLAT Plano Principal Oi TV nível conta"),BENEFICIOS!$A:$G,5,0))) | DB3: =IF(DA3=0,"",IF(DA3=VLOOKUP("PCS-OzTL746",ARBOR!$A:$C,3,0),0.0001,IF(DA3>VLOOKUP("PCS-OzTL746",ARBOR!$A:$C,3,0),"Maior que CAP!",IF((DOLLAR(DA3+(VLOOKUP("PCS-OzTL746",ARBOR!$A:$C,3,0)*-TRUNC(DA3/VLOOKUP("PCS-OzTL746",ARBOR!$A:$C,3,0)-1,4)),6))<>(DOLLAR(VLOOKUP("PCS-OzTL746",ARBOR!$A:$C,3,0),6)),-TRUNC(DA3/VLOOKUP("PCS-OzTL746",ARBOR!$A:$C,3,0)-1,4)+0.0001,-TRUNC(DA3/VLOOKUP("PCS-OzTL746",ARBOR!$A:$C,3,0)-1,4))))) | DC3: =IF(ISERROR(IF(DB3="","",VLOOKUP(($BC3&DB3&"Template desconto FLAT Plano Principal Oi TV nível conta"),BENEFICIOS!$A:$G,5,0))),"Criar",IF(DB3="","",VLOOKUP(($BC3&DB3&"Template desconto FLAT Plano Principal Oi TV nível conta"),BENEFICIOS!$A:$G,5,0))) | DE3: =IF(DD3=0,"",IF(DD3=VLOOKUP("PCS-OzTL748",ARBOR!$A:$C,3,0),0.0001,IF(DD3>VLOOKUP("PCS-OzTL748",ARBOR!$A:$C,3,0),"Maior que CAP!",IF((DOLLAR(DD3+(VLOOKUP("PCS-OzTL748",ARBOR!$A:$C,3,0)*-TRUNC(DD3/VLOOKUP("PCS-OzTL748",ARBOR!$A:$C,3,0)-1,4)),6))<>(DOLLAR(VLOOKUP("PCS-OzTL748",ARBOR!$A:$C,3,0),6)),-TRUNC(DD3/VLOOKUP("PCS-OzTL748",ARBOR!$A:$C,3,0)-1,4)+0.0001,-TRUNC(DD3/VLOOKUP("PCS-OzTL748",ARBOR!$A:$C,3,0)-1,4))))) | DF3: =IF(ISERROR(IF(DE3="","",VLOOKUP(($BC3&DE3&"Template desconto FLAT Plano Principal Oi TV nível conta"),BENEFICIOS!$A:$G,5,0))),"Criar",IF(DE3="","",VLOOKUP(($BC3&DE3&"Template desconto FLAT Plano Principal Oi TV nível conta"),BENEFICIOS!$A:$G,5,0))) | DG3: 75 | DH3: =IF(DG3=0,"",IF(DG3=VLOOKUP("PCS-OzTL34",ARBOR!$A:$C,3,0),0.0001,IF(DG3>VLOOKUP("PCS-OzTL34",ARBOR!$A:$C,3,0),"Maior que CAP!",IF((DOLLAR(DG3+(VLOOKUP("PCS-OzTL34",ARBOR!$A:$C,3,0)*-TRUNC(DG3/VLOOKUP("PCS-OzTL34",ARBOR!$A:$C,3,0)-1,4)),6))<>(DOLLAR(VLOOKUP("PCS-OzTL34",ARBOR!$A:$C,3,0),6)),-TRUNC(DG3/VLOOKUP("PCS-OzTL34",ARBOR!$A:$C,3,0)-1,4)+0.0001,-TRUNC(DG3/VLOOKUP("PCS-OzTL34",ARBOR!$A:$C,3,0)-1,4))))) -> 0.319 | DI3: =IF(DH3="S/Desc","S/Desc",IF(ISERROR(IF(DH3="","",VLOOKUP(($BC3&DH3&"Template desconto % Combate nível conta"),BENEFICIOS!$A:$G,5,0))),"Criar",IF(DH3="","",VLOOKUP(($BC3&DH3&"Template desconto % Combate nível conta"),BENEFICIOS!$A:$G,5,0)))) -> Criar | DJ3: 19.9 | DK3: =IF(DJ3=0,"",IF(DJ3=VLOOKUP("PCS-OzTL31",ARBOR!$A:$C,3,0),0.0001,IF(DJ3>VLOOKUP("PCS-OzTL31",ARBOR!$A:$C,3,0),"Maior que CAP!",IF((DOLLAR(DJ3+(VLOOKUP("PCS-OzTL31",ARBOR!$A:$C,3,0)*-TRUNC(DJ3/VLOOKUP("PCS-OzTL31",ARBOR!$A:$C,3,0)-1,4)),6))<>(DOLLAR(VLOOKUP("PCS-OzTL31",ARBOR!$A:$C,3,0),6)),-TRUNC(DJ3/VLOOKUP("PCS-OzTL31",ARBOR!$A:$C,3,0)-1,4)+0.0001,-TRUNC(DJ3/VLOOKUP("PCS-OzTL31",ARBOR!$A:$C,3,0)-1,4))))) -> 0.0918 | DL3: =IF(DK3="S/Desc","S/Desc",IF(ISERROR(IF(DK3="","",VLOOKUP(($BC3&DK3&"Template desconto % Sexy Hot nível conta"),BENEFICIOS!$A:$G,5,0))),"Criar",IF(DK3="","",VLOOKUP(($BC3&DK3&"Template desconto % Sexy Hot nível conta"),BENEFICIOS!$A:$G,5,0)))) -> Criar | DM3: 19.9 | DN3: =IF(DM3=0,"",IF(DM3=VLOOKUP("PCS-OzTL32",ARBOR!$A:$C,3,0),0.0001,IF(DM3>VLOOKUP("PCS-OzTL32",ARBOR!$A:$C,3,0),"Maior que CAP!",IF((DOLLAR(DM3+(VLOOKUP("PCS-OzTL32",ARBOR!$A:$C,3,0)*-TRUNC(DM3/VLOOKUP("PCS-OzTL32",ARBOR!$A:$C,3,0)-1,4)),6))<>(DOLLAR(VLOOKUP("PCS-OzTL32",ARBOR!$A:$C,3,0),6)),-TRUNC(DM3/VLOOKUP("PCS-OzTL32",ARBOR!$A:$C,3,0)-1,4)+0.0001,-TRUNC(DM3/VLOOKUP("PCS-OzTL32",ARBOR!$A:$C,3,0)-1,4))))) -> 0.0918 | DO3: =IF(DN3="S/Desc","S/Desc",IF(ISERROR(IF(DN3="","",VLOOKUP(($BC3&DN3&"Template desconto % Playboy nível conta"),BENEFICIOS!$A:$G,5,0))),"Criar",IF(DN3="","",VLOOKUP(($BC3&DN3&"Template desconto % Playboy nível conta"),BENEFICIOS!$A:$G,5,0)))) -> Criar | DP3: 29.9 | DQ3: =IF(DP3=0,"",IF(DP3=VLOOKUP("PCS-OzTL33",ARBOR!$A:$C,3,0),0.0001,IF(DP3>VLOOKUP("PCS-OzTL33",ARBOR!$A:$C,3,0),"Maior que CAP!",IF((DOLLAR(DP3+(VLOOKUP("PCS-OzTL33",ARBOR!$A:$C,3,0)*-TRUNC(DP3/VLOOKUP("PCS-OzTL33",ARBOR!$A:$C,3,0)-1,4)),6))<>(DOLLAR(VLOOKUP("PCS-OzTL33",ARBOR!$A:$C,3,0),6)),-TRUNC(DP3/VLOOKUP("PCS-OzTL33",ARBOR!$A:$C,3,0)-1,4)+0.0001,-TRUNC(DP3/VLOOKUP("PCS-OzTL33",ARBOR!$A:$C,3,0)-1,4))))) -> 0.0918 | DR3: =IF(DQ3="S/Desc","S/Desc",IF(ISERROR(IF(DQ3="","",VLOOKUP(($BC3&DQ3&"Template desconto % Sexy Hot + Playboy nível conta"),BENEFICIOS!$A:$G,5,0))),"Criar",IF(DQ3="","",VLOOKUP(($BC3&DQ3&"Template desconto % Sexy Hot + Playboy nível conta"),BENEFICIOS!$A:$G,5,0)))) -> Criar | DS3: 14.9 | DT3: =IF(DS3=0,"",IF(DS3=VLOOKUP("PCS-OzTL503",ARBOR!$A:$C,3,0),0.0001,IF(DS3>VLOOKUP("PCS-OzTL503",ARBOR!$A:$C,3,0),"Maior que CAP!",IF((DOLLAR(DS3+(VLOOKUP("PCS-OzTL503",ARBOR!$A:$C,3,0)*-TRUNC(DS3/VLOOKUP("PCS-OzTL503",ARBOR!$A:$C,3,0)-1,4)),6))<>(DOLLAR(VLOOKUP("PCS-OzTL503",ARBOR!$A:$C,3,0),6)),-TRUNC(DS3/VLOOKUP("PCS-OzTL503",ARBOR!$A:$C,3,0)-1,4)+0.0001,-TRUNC(DS3/VLOOKUP("PCS-OzTL503",ARBOR!$A:$C,3,0)-1,4))))) -> 0.0915 | DU3: =IF(DT3="S/Desc","S/Desc",IF(ISERROR(IF(DT3="","",VLOOKUP(($BC3&DT3&"Template desconto % SexPrivê nível conta"),BENEFICIOS!$A:$G,5,0))),"Criar",IF(DT3="","",VLOOKUP(($BC3&DT3&"Template desconto % SexPrivê nível conta"),BENEFICIOS!$A:$G,5,0)))) -> Criar | DV3: 10 | DW3: =IF(DV3=0,"",IF(DV3=VLOOKUP("PCS-OzTL500",ARBOR!$A:$C,3,0),0.0001,IF(DV3>VLOOKUP("PCS-OzTL500",ARBOR!$A:$C,3,0),"Maior que CAP!",IF((DOLLAR(DV3+(VLOOKUP("PCS-OzTL500",ARBOR!$A:$C,3,0)*-TRUNC(DV3/VLOOKUP("PCS-OzTL500",ARBOR!$A:$C,3,0)-1,4)),6))<>(DOLLAR(VLOOKUP("PCS-OzTL500",ARBOR!$A:$C,3,0),6)),-TRUNC(DV3/VLOOKUP("PCS-OzTL500",ARBOR!$A:$C,3,0)-1,4)+0.0001,-TRUNC(DV3/VLOOKUP("PCS-OzTL500",ARBOR!$A:$C,3,0)-1,4))))) -> 0.0918 | DX3: =IF(DW3="S/Desc","S/Desc",IF(ISERROR(IF(DW3="","",VLOOKUP(($BC3&DW3&"Template desconto % Étnico nível conta"),BENEFICIOS!$A:$G,5,0))),"Criar",IF(DW3="","",VLOOKUP(($BC3&DW3&"Template desconto % Étnico nível conta"),BENEFICIOS!$A:$G,5,0)))) -> Criar | DZ3: =IF(DY3=0,"",IF(DY3=VLOOKUP("PCS-OzTL50",ARBOR!$A:$C,3,0),0.0001,IF(DY3>VLOOKUP("PCS-OzTL50",ARBOR!$A:$C,3,0),"Maior que CAP!",IF((DOLLAR(DY3+(VLOOKUP("PCS-OzTL50",ARBOR!$A:$C,3,0)*-TRUNC(DY3/VLOOKUP("PCS-OzTL50",ARBOR!$A:$C,3,0)-1,4)),6))<>(DOLLAR(VLOOKUP("PCS-OzTL50",ARBOR!$A:$C,3,0),6)),-TRUNC(DY3/VLOOKUP("PCS-OzTL50",ARBOR!$A:$C,3,0)-1,4)+0.0001,-TRUNC(DY3/VLOOKUP("PCS-OzTL50",ARBOR!$A:$C,3,0)-1,4))))) | EC3: =IF(EB3=0,"",IF(EB3=VLOOKUP("PCS-OzTL51",ARBOR!$A:$C,3,0),0.0001,IF(EB3>VLOOKUP("PCS-OzTL51",ARBOR!$A:$C,3,0),"Maior que CAP!",IF((DOLLAR(EB3+(VLOOKUP("PCS-OzTL51",ARBOR!$A:$C,3,0)*-TRUNC(EB3/VLOOKUP("PCS-OzTL51",ARBOR!$A:$C,3,0)-1,4)),6))<>(DOLLAR(VLOOKUP("PCS-OzTL51",ARBOR!$A:$C,3,0),6)),-TRUNC(EB3/VLOOKUP("PCS-OzTL51",ARBOR!$A:$C,3,0)-1,4)+0.0001,-TRUNC(EB3/VLOOKUP("PCS-OzTL51",ARBOR!$A:$C,3,0)-1,4))))) | EF3: =IF(EE3=0,"",IF(EE3=VLOOKUP("PCS-OzTL52",ARBOR!$A:$C,3,0),0.0001,IF(EE3>VLOOKUP("PCS-OzTL52",ARBOR!$A:$C,3,0),"Maior que CAP!",IF((DOLLAR(EE3+(VLOOKUP("PCS-OzTL52",ARBOR!$A:$C,3,0)*-TRUNC(EE3/VLOOKUP("PCS-OzTL52",ARBOR!$A:$C,3,0)-1,4)),6))<>(DOLLAR(VLOOKUP("PCS-OzTL52",ARBOR!$A:$C,3,0),6)),-TRUNC(EE3/VLOOKUP("PCS-OzTL52",ARBOR!$A:$C,3,0)-1,4)+0.0001,-TRUNC(EE3/VLOOKUP("PCS-OzTL52",ARBOR!$A:$C,3,0)-1,4))))) | EI3: =IF(EH3=0,"",IF(EH3=VLOOKUP("PCS-OzTL53",ARBOR!$A:$C,3,0),0.0001,IF(EH3>VLOOKUP("PCS-OzTL53",ARBOR!$A:$C,3,0),"Maior que CAP!",IF((DOLLAR(EH3+(VLOOKUP("PCS-OzTL53",ARBOR!$A:$C,3,0)*-TRUNC(EH3/VLOOKUP("PCS-OzTL53",ARBOR!$A:$C,3,0)-1,4)),6))<>(DOLLAR(VLOOKUP("PCS-OzTL53",ARBOR!$A:$C,3,0),6)),-TRUNC(EH3/VLOOKUP("PCS-OzTL53",ARBOR!$A:$C,3,0)-1,4)+0.0001,-TRUNC(EH3/VLOOKUP("PCS-OzTL53",ARBOR!$A:$C,3,0)-1,4))))) | EL3: =IF(EK3=0,"",IF(EK3=VLOOKUP("PCS-OzTL54",ARBOR!$A:$C,3,0),0.0001,IF(EK3>VLOOKUP("PCS-OzTL54",ARBOR!$A:$C,3,0),"Maior que CAP!",IF((DOLLAR(EK3+(VLOOKUP("PCS-OzTL54",ARBOR!$A:$C,3,0)*-TRUNC(EK3/VLOOKUP("PCS-OzTL54",ARBOR!$A:$C,3,0)-1,4)),6))<>(DOLLAR(VLOOKUP("PCS-OzTL54",ARBOR!$A:$C,3,0),6)),-TRUNC(EK3/VLOOKUP("PCS-OzTL54",ARBOR!$A:$C,3,0)-1,4)+0.0001,-TRUNC(EK3/VLOOKUP("PCS-OzTL54",ARBOR!$A:$C,3,0)-1,4))))) | EN3: 24.9 | EO3: =IF(EN3=0,"",IF(EN3=VLOOKUP("PCS-OzTL99",ARBOR!$A:$C,3,0),0.0001,IF(EN3>VLOOKUP("PCS-OzTL99",ARBOR!$A:$C,3,0),"Maior que CAP!",IF((DOLLAR(EN3+(VLOOKUP("PCS-OzTL99",ARBOR!$A:$C,3,0)*-TRUNC(EN3/VLOOKUP("PCS-OzTL99",ARBOR!$A:$C,3,0)-1,4)),6))<>(DOLLAR(VLOOKUP("PCS-OzTL99",ARBOR!$A:$C,3,0),6)),-TRUNC(EN3/VLOOKUP("PCS-OzTL99",ARBOR!$A:$C,3,0)-1,4)+0.0001,-TRUNC(EN3/VLOOKUP("PCS-OzTL99",ARBOR!$A:$C,3,0)-1,4))))) -> 0.1673 | EP3: =IF(EO3="S/Desc","S/Desc",IF(ISERROR(IF(EO3="","",VLOOKUP(($BC3&EO3&"Template desconto % Ponto adicional nível conta"),BENEFICIOS!$A:$G,5,0))),"Criar",IF(EO3="","",VLOOKUP(($BC3&EO3&"Template desconto % Ponto adicional nível conta"),BENEFICIOS!$A:$G,5,0)))) -> Criar | ER3: =IF(EQ3="Sim","PCS-34704","") | ES3: Sim | ET3: Benefício | EU3: 499 | EV3: 12 | EW3: =IF(ET3="Benefício","Oi benefício fidelização Multiprodutos","") -> Oi benefício fidelização Multiprodutos | EX3: =IF(ET3="Benefício","PCS-Fk83324","") -> PCS-Fk83324 | EY3: =IF(ES3="Sim","PCS-SBL553142","") -> PCS-SBL553142 | EZ3: LD + VC Oi | FA3: 0T0T_FTV_MIN_LD_270000. | FG3: =IF($BH3="","",$BH3+$BE3) -> 134.9 | FH3: =IF($BK3="","",$BK3+$BE3) | FI3: =IF($BN3="","",$BN3+$BE3) | FJ3: =IF($BQ3="","",$BQ3+$BE3) | FK3: =IF($BT3="","",$BT3+$BE3) | FL3: =IF($BW3="","",$BW3+$BE3) | FM3: =IF($BZ3="","",$BZ3+$BE3) | FN3: =IF($CC3="","",$CC3+$BE3) | FO3: =IF($CF3="","",$CF3+$BE3) | FP3: =IF($CI3="","",$CI3+$BE3) | FQ3: =IF($CL3="","",$CL3+$BE3) | FR3: =IF($CO3="","",$CO3+$BE3) | FS3: =IF($CR3="","",$CR3+$BE3) | FT3: =IF($CU3="","",$CU3+$BE3) | FU3: =IF($CX3="","",$CX3+$BE3) | FV3: =IF($DA3="","",$DA3+$BE3) | FW3: =IF($DD3="","",$DD3+$BE3)
A4: Oi Total | B4: Migração | C4: Atuais | D4: Não | AM4: OT_ATV_JUL17_FID_DACC_2PTV_TV2_MI-TO_LD-VC_OF1 | AN4: Rentabilizar atuais clientes do plano | AO4: Produto Fixo + TV , Produto com fidelização | AP4: 42917 | AQ4: 43039 | AR4: 20. Oi Total | AS4: 20. Oi Total | AU4: Varejo | AV4: 20 | AW4: 10000 | AX4: Campanha Restrita | AY4: Sim | AZ4: Sim | BA4: Não | BB4: OT_ATV_JUL17_FID_DACC_2PTV_TV2_MI-TO_LD-VC_OF1 | BC4: Oi Total Fixo + TV 2 | BD4: =IF(BC4="Oi Total Fixo + TV 1","CFG-2Plowpi",IF(BC4="Oi Total Fixo + TV 2","PCS-2PMepi",IF(BC4="Oi Total Fixo + TV 3","PCS-2PHipi",""))) -> PCS-2PMepi | BE4: 60 | BF4: =IF(BE4=0,"",IF(BE4=VLOOKUP("FIXO",ARBOR!$A:$C,3,0),0.0001,IF(BE4>VLOOKUP("FIXO",ARBOR!$A:$C,3,0),"Maior que CAP!",IF((DOLLAR(BE4+(VLOOKUP("FIXO",ARBOR!$A:$C,3,0)*-TRUNC(BE4/VLOOKUP("FIXO",ARBOR!$A:$C,3,0)-1,4)),6))<>(DOLLAR(VLOOKUP("FIXO",ARBOR!$A:$C,3,0),6)),-TRUNC(BE4/VLOOKUP("FIXO",ARBOR!$A:$C,3,0)-1,4)+0.0001,-TRUNC(BE4/VLOOKUP("FIXO",ARBOR!$A:$C,3,0)-1,4))))) -> 0.2089 | BG4: =IF(ISERROR(IF(BF4="","",VLOOKUP(($BC4&BF4&"Template de desconto FLAT bundle - Fixo - Varejo - Ganho Tributário Cross"),BENEFICIOS!$A:$G,5,0))),"Criar",IF(BF4="","",VLOOKUP(($BC4&BF4&"Template de desconto FLAT bundle - Fixo - Varejo - Ganho Tributário Cross"),BENEFICIOS!$A:$G,5,0))) -> Criar | BI4: =IF(BH4=0,"",IF(BH4=VLOOKUP("PCS-OzTL40",ARBOR!$A:$C,3,0),0.0001,IF(BH4>VLOOKUP("PCS-OzTL40",ARBOR!$A:$C,3,0),"Maior que CAP!",IF((DOLLAR(BH4+(VLOOKUP("PCS-OzTL40",ARBOR!$A:$C,3,0)*-TRUNC(BH4/VLOOKUP("PCS-OzTL40",ARBOR!$A:$C,3,0)-1,4)),6))<>(DOLLAR(VLOOKUP("PCS-OzTL40",ARBOR!$A:$C,3,0),6)),-TRUNC(BH4/VLOOKUP("PCS-OzTL40",ARBOR!$A:$C,3,0)-1,4)+0.0001,-TRUNC(BH4/VLOOKUP("PCS-OzTL40",ARBOR!$A:$C,3,0)-1,4))))) | BJ4: =IF(ISERROR(IF(BI4="","",VLOOKUP((BC4&BI4&"Template desconto FLAT Plano Principal Oi TV nível conta"),BENEFICIOS!$A:$G,5,0))),"Criar",IF(BI4="","",VLOOKUP((BC4&BI4&"Template desconto FLAT Plano Principal Oi TV nível conta"),BENEFICIOS!$A:$G,5,0))) | BK4: 94.9 | BL4: =IF(BK4=0,"",IF(BK4=VLOOKUP("PCS-OzTL41",ARBOR!$A:$C,3,0),0.0001,IF(BK4>VLOOKUP("PCS-OzTL41",ARBOR!$A:$C,3,0),"Maior que CAP!",IF((DOLLAR(BK4+(VLOOKUP("PCS-OzTL41",ARBOR!$A:$C,3,0)*-TRUNC(BK4/VLOOKUP("PCS-OzTL41",ARBOR!$A:$C,3,0)-1,4)),6))<>(DOLLAR(VLOOKUP("PCS-OzTL41",ARBOR!$A:$C,3,0),6)),-TRUNC(BK4/VLOOKUP("PCS-OzTL41",ARBOR!$A:$C,3,0)-1,4)+0.0001,-TRUNC(BK4/VLOOKUP("PCS-OzTL41",ARBOR!$A:$C,3,0)-1,4))))) -> 0.2159 | BM4: =IF(ISERROR(IF(BL4="","",VLOOKUP((BC4&BL4&"Template desconto FLAT Plano Principal Oi TV nível conta"),BENEFICIOS!$A:$G,5,0))),"Criar",IF(BL4="","",VLOOKUP((BC4&BL4&"Template desconto FLAT Plano Principal Oi TV nível conta"),BENEFICIOS!$A:$G,5,0))) -> Criar | BO4: =IF(BN4=0,"",IF(BN4=VLOOKUP("PCS-OzTL44",ARBOR!$A:$C,3,0),0.0001,IF(BN4>VLOOKUP("PCS-OzTL44",ARBOR!$A:$C,3,0),"Maior que CAP!",IF((DOLLAR(BN4+(VLOOKUP("PCS-OzTL44",ARBOR!$A:$C,3,0)*-TRUNC(BN4/VLOOKUP("PCS-OzTL44",ARBOR!$A:$C,3,0)-1,4)),6))<>(DOLLAR(VLOOKUP("PCS-OzTL44",ARBOR!$A:$C,3,0),6)),-TRUNC(BN4/VLOOKUP("PCS-OzTL44",ARBOR!$A:$C,3,0)-1,4)+0.0001,-TRUNC(BN4/VLOOKUP("PCS-OzTL44",ARBOR!$A:$C,3,0)-1,4))))) | BP4: =IF(ISERROR(IF(BO4="","",VLOOKUP((BC4&BO4&"Template desconto FLAT Plano Principal Oi TV nível conta"),BENEFICIOS!$A:$G,5,0))),"Criar",IF(BO4="","",VLOOKUP((BC4&BO4&"Template desconto FLAT Plano Principal Oi TV nível conta"),BENEFICIOS!$A:$G,5,0))) | BR4: =IF(BQ4=0,"",IF(BQ4=VLOOKUP("PCS-OzTL43",ARBOR!$A:$C,3,0),0.0001,IF(BQ4>VLOOKUP("PCS-OzTL43",ARBOR!$A:$C,3,0),"Maior que CAP!",IF((DOLLAR(BQ4+(VLOOKUP("PCS-OzTL43",ARBOR!$A:$C,3,0)*-TRUNC(BQ4/VLOOKUP("PCS-OzTL43",ARBOR!$A:$C,3,0)-1,4)),6))<>(DOLLAR(VLOOKUP("PCS-OzTL43",ARBOR!$A:$C,3,0),6)),-TRUNC(BQ4/VLOOKUP("PCS-OzTL43",ARBOR!$A:$C,3,0)-1,4)+0.0001,-TRUNC(BQ4/VLOOKUP("PCS-OzTL43",ARBOR!$A:$C,3,0)-1,4))))) | BS4: =IF(ISERROR(IF(BR4="","",VLOOKUP((BC4&BR4&"Template desconto FLAT Plano Principal Oi TV nível conta"),BENEFICIOS!$A:$G,5,0))),"Criar",IF(BR4="","",VLOOKUP((BC4&BR4&"Template desconto FLAT Plano Principal Oi TV nível conta"),BENEFICIOS!$A:$G,5,0))) | BU4: =IF(BT4=0,"",IF(BT4=VLOOKUP("PCS-OzTL45",ARBOR!$A:$C,3,0),0.0001,IF(BT4>VLOOKUP("PCS-OzTL45",ARBOR!$A:$C,3,0),"Maior que CAP!",IF((DOLLAR(BT4+(VLOOKUP("PCS-OzTL45",ARBOR!$A:$C,3,0)*-TRUNC(BT4/VLOOKUP("PCS-OzTL45",ARBOR!$A:$C,3,0)-1,4)),6))<>(DOLLAR(VLOOKUP("PCS-OzTL45",ARBOR!$A:$C,3,0),6)),-TRUNC(BT4/VLOOKUP("PCS-OzTL45",ARBOR!$A:$C,3,0)-1,4)+0.0001,-TRUNC(BT4/VLOOKUP("PCS-OzTL45",ARBOR!$A:$C,3,0)-1,4))))) | BV4: =IF(ISERROR(IF(BU4="","",VLOOKUP((BC4&BU4&"Template desconto FLAT Plano Principal Oi TV nível conta"),BENEFICIOS!$A:$G,5,0))),"Criar",IF(BU4="","",VLOOKUP((BC4&BU4&"Template desconto FLAT Plano Principal Oi TV nível conta"),BENEFICIOS!$A:$G,5,0))) | BX4: =IF(BW4=0,"",IF(BW4=VLOOKUP("PCS-OzTL741",ARBOR!$A:$C,3,0),0.0001,IF(BW4>VLOOKUP("PCS-OzTL741",ARBOR!$A:$C,3,0),"Maior que CAP!",IF((DOLLAR(BW4+(VLOOKUP("PCS-OzTL741",ARBOR!$A:$C,3,0)*-TRUNC(BW4/VLOOKUP("PCS-OzTL741",ARBOR!$A:$C,3,0)-1,4)),6))<>(DOLLAR(VLOOKUP("PCS-OzTL741",ARBOR!$A:$C,3,0),6)),-TRUNC(BW4/VLOOKUP("PCS-OzTL741",ARBOR!$A:$C,3,0)-1,4)+0.0001,-TRUNC(BW4/VLOOKUP("PCS-OzTL741",ARBOR!$A:$C,3,0)-1,4))))) | BY4: =IF(ISERROR(IF(BX4="","",VLOOKUP((BC4&BX4&"Template desconto FLAT Plano Principal Oi TV nível conta"),BENEFICIOS!$A:$G,5,0))),"Criar",IF(BX4="","",VLOOKUP((BC4&BX4&"Template desconto FLAT Plano Principal Oi TV nível conta"),BENEFICIOS!$A:$G,5,0))) | CA4: =IF(BZ4=0,"",IF(BZ4=VLOOKUP("PCS-OzTL744",ARBOR!$A:$C,3,0),0.0001,IF(BZ4>VLOOKUP("PCS-OzTL744",ARBOR!$A:$C,3,0),"Maior que CAP!",IF((DOLLAR(BZ4+(VLOOKUP("PCS-OzTL744",ARBOR!$A:$C,3,0)*-TRUNC(BZ4/VLOOKUP("PCS-OzTL744",ARBOR!$A:$C,3,0)-1,4)),6))<>(DOLLAR(VLOOKUP("PCS-OzTL744",ARBOR!$A:$C,3,0),6)),-TRUNC(BZ4/VLOOKUP("PCS-OzTL744",ARBOR!$A:$C,3,0)-1,4)+0.0001,-TRUNC(BZ4/VLOOKUP("PCS-OzTL744",ARBOR!$A:$C,3,0)-1,4))))) | CB4: =IF(ISERROR(IF(CA4="","",VLOOKUP(($BC4&CA4&"Template desconto FLAT Plano Principal Oi TV nível conta"),BENEFICIOS!$A:$G,5,0))),"Criar",IF(CA4="","",VLOOKUP(($BC4&CA4&"Template desconto FLAT Plano Principal Oi TV nível conta"),BENEFICIOS!$A:$G,5,0))) | CD4: =IF(CC4=0,"",IF(CC4=VLOOKUP("PCS-OzTL743",ARBOR!$A:$C,3,0),0.0001,IF(CC4>VLOOKUP("PCS-OzTL743",ARBOR!$A:$C,3,0),"Maior que CAP!",IF((DOLLAR(CC4+(VLOOKUP("PCS-OzTL743",ARBOR!$A:$C,3,0)*-TRUNC(CC4/VLOOKUP("PCS-OzTL743",ARBOR!$A:$C,3,0)-1,4)),6))<>(DOLLAR(VLOOKUP("PCS-OzTL743",ARBOR!$A:$C,3,0),6)),-TRUNC(CC4/VLOOKUP("PCS-OzTL743",ARBOR!$A:$C,3,0)-1,4)+0.0001,-TRUNC(CC4/VLOOKUP("PCS-OzTL743",ARBOR!$A:$C,3,0)-1,4))))) | CE4: =IF(ISERROR(IF(CD4="","",VLOOKUP(($BC4&CD4&"Template desconto FLAT Plano Principal Oi TV nível conta"),BENEFICIOS!$A:$G,5,0))),"Criar",IF(CD4="","",VLOOKUP(($BC4&CD4&"Template desconto FLAT Plano Principal Oi TV nível conta"),BENEFICIOS!$A:$G,5,0))) | CG4: =IF(CF4=0,"",IF(CF4=VLOOKUP("PCS-OzTL745",ARBOR!$A:$C,3,0),0.0001,IF(CF4>VLOOKUP("PCS-OzTL745",ARBOR!$A:$C,3,0),"Maior que CAP!",IF((DOLLAR(CF4+(VLOOKUP("PCS-OzTL745",ARBOR!$A:$C,3,0)*-TRUNC(CF4/VLOOKUP("PCS-OzTL745",ARBOR!$A:$C,3,0)-1,4)),6))<>(DOLLAR(VLOOKUP("PCS-OzTL745",ARBOR!$A:$C,3,0),6)),-TRUNC(CF4/VLOOKUP("PCS-OzTL745",ARBOR!$A:$C,3,0)-1,4)+0.0001,-TRUNC(CF4/VLOOKUP("PCS-OzTL745",ARBOR!$A:$C,3,0)-1,4))))) | CH4: =IF(ISERROR(IF(CG4="","",VLOOKUP(($BC4&CG4&"Template desconto FLAT Plano Principal Oi TV nível conta"),BENEFICIOS!$A:$G,5,0))),"Criar",IF(CG4="","",VLOOKUP(($BC4&CG4&"Template desconto FLAT Plano Principal Oi TV nível conta"),BENEFICIOS!$A:$G,5,0))) | CI4: 104.9 | CJ4: =IF(CI4=0,"",IF(CI4=VLOOKUP("PCS-OzTL42",ARBOR!$A:$C,3,0),0.0001,IF(CI4>VLOOKUP("PCS-OzTL42",ARBOR!$A:$C,3,0),"Maior que CAP!",IF((DOLLAR(CI4+(VLOOKUP("PCS-OzTL42",ARBOR!$A:$C,3,0)*-TRUNC(CI4/VLOOKUP("PCS-OzTL42",ARBOR!$A:$C,3,0)-1,4)),6))<>(DOLLAR(VLOOKUP("PCS-OzTL42",ARBOR!$A:$C,3,0),6)),-TRUNC(CI4/VLOOKUP("PCS-OzTL42",ARBOR!$A:$C,3,0)-1,4)+0.0001,-TRUNC(CI4/VLOOKUP("PCS-OzTL42",ARBOR!$A:$C,3,0)-1,4))))) -> 0.3646 | CK4: =IF(ISERROR(IF(CJ4="","",VLOOKUP(($BC4&CJ4&"Template desconto FLAT Plano Principal Oi TV nível conta"),BENEFICIOS!$A:$G,5,0))),"Criar",IF(CJ4="","",VLOOKUP(($BC4&CJ4&"Template desconto FLAT Plano Principal Oi TV nível conta"),BENEFICIOS!$A:$G,5,0))) -> Criar | CM4: =IF(CL4=0,"",IF(CL4=VLOOKUP("PCS-OzTL47",ARBOR!$A:$C,3,0),0.0001,IF(CL4>VLOOKUP("PCS-OzTL47",ARBOR!$A:$C,3,0),"Maior que CAP!",IF((DOLLAR(CL4+(VLOOKUP("PCS-OzTL47",ARBOR!$A:$C,3,0)*-TRUNC(CL4/VLOOKUP("PCS-OzTL47",ARBOR!$A:$C,3,0)-1,4)),6))<>(DOLLAR(VLOOKUP("PCS-OzTL47",ARBOR!$A:$C,3,0),6)),-TRUNC(CL4/VLOOKUP("PCS-OzTL47",ARBOR!$A:$C,3,0)-1,4)+0.0001,-TRUNC(CL4/VLOOKUP("PCS-OzTL47",ARBOR!$A:$C,3,0)-1,4))))) | CN4: =IF(ISERROR(IF(CM4="","",VLOOKUP(($BC4&CM4&"Template desconto FLAT Plano Principal Oi TV nível conta"),BENEFICIOS!$A:$G,5,0))),"Criar",IF(CM4="","",VLOOKUP(($BC4&CM4&"Template desconto FLAT Plano Principal Oi TV nível conta"),BENEFICIOS!$A:$G,5,0))) | CP4: =IF(CO4=0,"",IF(CO4=VLOOKUP("PCS-OzTL46",ARBOR!$A:$C,3,0),0.0001,IF(CO4>VLOOKUP("PCS-OzTL46",ARBOR!$A:$C,3,0),"Maior que CAP!",IF((DOLLAR(CO4+(VLOOKUP("PCS-OzTL46",ARBOR!$A:$C,3,0)*-TRUNC(CO4/VLOOKUP("PCS-OzTL46",ARBOR!$A:$C,3,0)-1,4)),6))<>(DOLLAR(VLOOKUP("PCS-OzTL46",ARBOR!$A:$C,3,0),6)),-TRUNC(CO4/VLOOKUP("PCS-OzTL46",ARBOR!$A:$C,3,0)-1,4)+0.0001,-TRUNC(CO4/VLOOKUP("PCS-OzTL46",ARBOR!$A:$C,3,0)-1,4))))) | CQ4: =IF(ISERROR(IF(CP4="","",VLOOKUP(($BC4&CP4&"Template desconto FLAT Plano Principal Oi TV nível conta"),BENEFICIOS!$A:$G,5,0))),"Criar",IF(CP4="","",VLOOKUP(($BC4&CP4&"Template desconto FLAT Plano Principal Oi TV nível conta"),BENEFICIOS!$A:$G,5,0))) | CS4: =IF(CR4=0,"",IF(CR4=VLOOKUP("PCS-OzTL48",ARBOR!$A:$C,3,0),0.0001,IF(CR4>VLOOKUP("PCS-OzTL48",ARBOR!$A:$C,3,0),"Maior que CAP!",IF((DOLLAR(CR4+(VLOOKUP("PCS-OzTL48",ARBOR!$A:$C,3,0)*-TRUNC(CR4/VLOOKUP("PCS-OzTL48",ARBOR!$A:$C,3,0)-1,4)),6))<>(DOLLAR(VLOOKUP("PCS-OzTL48",ARBOR!$A:$C,3,0),6)),-TRUNC(CR4/VLOOKUP("PCS-OzTL48",ARBOR!$A:$C,3,0)-1,4)+0.0001,-TRUNC(CR4/VLOOKUP("PCS-OzTL48",ARBOR!$A:$C,3,0)-1,4))))) | CT4: =IF(ISERROR(IF(CS4="","",VLOOKUP(($BC4&CS4&"Template desconto FLAT Plano Principal Oi TV nível conta"),BENEFICIOS!$A:$G,5,0))),"Criar",IF(CS4="","",VLOOKUP(($BC4&CS4&"Template desconto FLAT Plano Principal Oi TV nível conta"),BENEFICIOS!$A:$G,5,0))) | CU4: 124.9 | CV4: =IF(CU4=0,"",IF(CU4=VLOOKUP("PCS-OzTL742",ARBOR!$A:$C,3,0),0.0001,IF(CU4>VLOOKUP("PCS-OzTL742",ARBOR!$A:$C,3,0),"Maior que CAP!",IF((DOLLAR(CU4+(VLOOKUP("PCS-OzTL742",ARBOR!$A:$C,3,0)*-TRUNC(CU4/VLOOKUP("PCS-OzTL742",ARBOR!$A:$C,3,0)-1,4)),6))<>(DOLLAR(VLOOKUP("PCS-OzTL742",ARBOR!$A:$C,3,0),6)),-TRUNC(CU4/VLOOKUP("PCS-OzTL742",ARBOR!$A:$C,3,0)-1,4)+0.0001,-TRUNC(CU4/VLOOKUP("PCS-OzTL742",ARBOR!$A:$C,3,0)-1,4))))) -> 0.4327 | CW4: =IF(ISERROR(IF(CV4="","",VLOOKUP(($BC4&CV4&"Template desconto FLAT Plano Principal Oi TV nível conta"),BENEFICIOS!$A:$G,5,0))),"Criar",IF(CV4="","",VLOOKUP(($BC4&CV4&"Template desconto FLAT Plano Principal Oi TV nível conta"),BENEFICIOS!$A:$G,5,0))) -> Criar | CY4: =IF(CX4=0,"",IF(CX4=VLOOKUP("PCS-OzTL747",ARBOR!$A:$C,3,0),0.0001,IF(CX4>VLOOKUP("PCS-OzTL747",ARBOR!$A:$C,3,0),"Maior que CAP!",IF((DOLLAR(CX4+(VLOOKUP("PCS-OzTL747",ARBOR!$A:$C,3,0)*-TRUNC(CX4/VLOOKUP("PCS-OzTL747",ARBOR!$A:$C,3,0)-1,4)),6))<>(DOLLAR(VLOOKUP("PCS-OzTL747",ARBOR!$A:$C,3,0),6)),-TRUNC(CX4/VLOOKUP("PCS-OzTL747",ARBOR!$A:$C,3,0)-1,4)+0.0001,-TRUNC(CX4/VLOOKUP("PCS-OzTL747",ARBOR!$A:$C,3,0)-1,4))))) | CZ4: =IF(ISERROR(IF(CY4="","",VLOOKUP(($BC4&CY4&"Template desconto FLAT Plano Principal Oi TV nível conta"),BENEFICIOS!$A:$G,5,0))),"Criar",IF(CY4="","",VLOOKUP(($BC4&CY4&"Template desconto FLAT Plano Principal Oi TV nível conta"),BENEFICIOS!$A:$G,5,0))) | DB4: =IF(DA4=0,"",IF(DA4=VLOOKUP("PCS-OzTL746",ARBOR!$A:$C,3,0),0.0001,IF(DA4>VLOOKUP("PCS-OzTL746",ARBOR!$A:$C,3,0),"Maior que CAP!",IF((DOLLAR(DA4+(VLOOKUP("PCS-OzTL746",ARBOR!$A:$C,3,0)*-TRUNC(DA4/VLOOKUP("PCS-OzTL746",ARBOR!$A:$C,3,0)-1,4)),6))<>(DOLLAR(VLOOKUP("PCS-OzTL746",ARBOR!$A:$C,3,0),6)),-TRUNC(DA4/VLOOKUP("PCS-OzTL746",ARBOR!$A:$C,3,0)-1,4)+0.0001,-TRUNC(DA4/VLOOKUP("PCS-OzTL746",ARBOR!$A:$C,3,0)-1,4))))) | DC4: =IF(ISERROR(IF(DB4="","",VLOOKUP(($BC4&DB4&"Template desconto FLAT Plano Principal Oi TV nível conta"),BENEFICIOS!$A:$G,5,0))),"Criar",IF(DB4="","",VLOOKUP(($BC4&DB4&"Template desconto FLAT Plano Principal Oi TV nível conta"),BENEFICIOS!$A:$G,5,0))) | DE4: =IF(DD4=0,"",IF(DD4=VLOOKUP("PCS-OzTL748",ARBOR!$A:$C,3,0),0.0001,IF(DD4>VLOOKUP("PCS-OzTL748",ARBOR!$A:$C,3,0),"Maior que CAP!",IF((DOLLAR(DD4+(VLOOKUP("PCS-OzTL748",ARBOR!$A:$C,3,0)*-TRUNC(DD4/VLOOKUP("PCS-OzTL748",ARBOR!$A:$C,3,0)-1,4)),6))<>(DOLLAR(VLOOKUP("PCS-OzTL748",ARBOR!$A:$C,3,0),6)),-TRUNC(DD4/VLOOKUP("PCS-OzTL748",ARBOR!$A:$C,3,0)-1,4)+0.0001,-TRUNC(DD4/VLOOKUP("PCS-OzTL748",ARBOR!$A:$C,3,0)-1,4))))) | DF4: =IF(ISERROR(IF(DE4="","",VLOOKUP(($BC4&DE4&"Template desconto FLAT Plano Principal Oi TV nível conta"),BENEFICIOS!$A:$G,5,0))),"Criar",IF(DE4="","",VLOOKUP(($BC4&DE4&"Template desconto FLAT Plano Principal Oi TV nível conta"),BENEFICIOS!$A:$G,5,0))) | DG4: 75 | DH4: =IF(DG4=0,"",IF(DG4=VLOOKUP("PCS-OzTL34",ARBOR!$A:$C,3,0),0.0001,IF(DG4>VLOOKUP("PCS-OzTL34",ARBOR!$A:$C,3,0),"Maior que CAP!",IF((DOLLAR(DG4+(VLOOKUP("PCS-OzTL34",ARBOR!$A:$C,3,0)*-TRUNC(DG4/VLOOKUP("PCS-OzTL34",ARBOR!$A:$C,3,0)-1,4)),6))<>(DOLLAR(VLOOKUP("PCS-OzTL34",ARBOR!$A:$C,3,0),6)),-TRUNC(DG4/VLOOKUP("PCS-OzTL34",ARBOR!$A:$C,3,0)-1,4)+0.0001,-TRUNC(DG4/VLOOKUP("PCS-OzTL34",ARBOR!$A:$C,3,0)-1,4))))) -> 0.319 | DI4: =IF(DH4="S/Desc","S/Desc",IF(ISERROR(IF(DH4="","",VLOOKUP(($BC4&DH4&"Template desconto % Combate nível conta"),BENEFICIOS!$A:$G,5,0))),"Criar",IF(DH4="","",VLOOKUP(($BC4&DH4&"Template desconto % Combate nível conta"),BENEFICIOS!$A:$G,5,0)))) -> Criar | DJ4: 19.9 | DK4: =IF(DJ4=0,"",IF(DJ4=VLOOKUP("PCS-OzTL31",ARBOR!$A:$C,3,0),0.0001,IF(DJ4>VLOOKUP("PCS-OzTL31",ARBOR!$A:$C,3,0),"Maior que CAP!",IF((DOLLAR(DJ4+(VLOOKUP("PCS-OzTL31",ARBOR!$A:$C,3,0)*-TRUNC(DJ4/VLOOKUP("PCS-OzTL31",ARBOR!$A:$C,3,0)-1,4)),6))<>(DOLLAR(VLOOKUP("PCS-OzTL31",ARBOR!$A:$C,3,0),6)),-TRUNC(DJ4/VLOOKUP("PCS-OzTL31",ARBOR!$A:$C,3,0)-1,4)+0.0001,-TRUNC(DJ4/VLOOKUP("PCS-OzTL31",ARBOR!$A:$C,3,0)-1,4))))) -> 0.0918 | DL4: =IF(DK4="S/Desc","S/Desc",IF(ISERROR(IF(DK4="","",VLOOKUP(($BC4&DK4&"Template desconto % Sexy Hot nível conta"),BENEFICIOS!$A:$G,5,0))),"Criar",IF(DK4="","",VLOOKUP(($BC4&DK4&"Template desconto % Sexy Hot nível conta"),BENEFICIOS!$A:$G,5,0)))) -> Criar | DM4: 19.9 | DN4: =IF(DM4=0,"",IF(DM4=VLOOKUP("PCS-OzTL32",ARBOR!$A:$C,3,0),0.0001,IF(DM4>VLOOKUP("PCS-OzTL32",ARBOR!$A:$C,3,0),"Maior que CAP!",IF((DOLLAR(DM4+(VLOOKUP("PCS-OzTL32",ARBOR!$A:$C,3,0)*-TRUNC(DM4/VLOOKUP("PCS-OzTL32",ARBOR!$A:$C,3,0)-1,4)),6))<>(DOLLAR(VLOOKUP("PCS-OzTL32",ARBOR!$A:$C,3,0),6)),-TRUNC(DM4/VLOOKUP("PCS-OzTL32",ARBOR!$A:$C,3,0)-1,4)+0.0001,-TRUNC(DM4/VLOOKUP("PCS-OzTL32",ARBOR!$A:$C,3,0)-1,4))))) -> 0.0918 | DO4: =IF(DN4="S/Desc","S/Desc",IF(ISERROR(IF(DN4="","",VLOOKUP(($BC4&DN4&"Template desconto % Playboy nível conta"),BENEFICIOS!$A:$G,5,0))),"Criar",IF(DN4="","",VLOOKUP(($BC4&DN4&"Template desconto % Playboy nível conta"),BENEFICIOS!$A:$G,5,0)))) -> Criar | DP4: 29.9 | DQ4: =IF(DP4=0,"",IF(DP4=VLOOKUP("PCS-OzTL33",ARBOR!$A:$C,3,0),0.0001,IF(DP4>VLOOKUP("PCS-OzTL33",ARBOR!$A:$C,3,0),"Maior que CAP!",IF((DOLLAR(DP4+(VLOOKUP("PCS-OzTL33",ARBOR!$A:$C,3,0)*-TRUNC(DP4/VLOOKUP("PCS-OzTL33",ARBOR!$A:$C,3,0)-1,4)),6))<>(DOLLAR(VLOOKUP("PCS-OzTL33",ARBOR!$A:$C,3,0),6)),-TRUNC(DP4/VLOOKUP("PCS-OzTL33",ARBOR!$A:$C,3,0)-1,4)+0.0001,-TRUNC(DP4/VLOOKUP("PCS-OzTL33",ARBOR!$A:$C,3,0)-1,4))))) -> 0.0918 | DR4: =IF(DQ4="S/Desc","S/Desc",IF(ISERROR(IF(DQ4="","",VLOOKUP(($BC4&DQ4&"Template desconto % Sexy Hot + Playboy nível conta"),BENEFICIOS!$A:$G,5,0))),"Criar",IF(DQ4="","",VLOOKUP(($BC4&DQ4&"Template desconto % Sexy Hot + Playboy nível conta"),BENEFICIOS!$A:$G,5,0)))) -> Criar | DS4: 14.9 | DT4: =IF(DS4=0,"",IF(DS4=VLOOKUP("PCS-OzTL503",ARBOR!$A:$C,3,0),0.0001,IF(DS4>VLOOKUP("PCS-OzTL503",ARBOR!$A:$C,3,0),"Maior que CAP!",IF((DOLLAR(DS4+(VLOOKUP("PCS-OzTL503",ARBOR!$A:$C,3,0)*-TRUNC(DS4/VLOOKUP("PCS-OzTL503",ARBOR!$A:$C,3,0)-1,4)),6))<>(DOLLAR(VLOOKUP("PCS-OzTL503",ARBOR!$A:$C,3,0),6)),-TRUNC(DS4/VLOOKUP("PCS-OzTL503",ARBOR!$A:$C,3,0)-1,4)+0.0001,-TRUNC(DS4/VLOOKUP("PCS-OzTL503",ARBOR!$A:$C,3,0)-1,4))))) -> 0.0915 | DU4: =IF(DT4="S/Desc","S/Desc",IF(ISERROR(IF(DT4="","",VLOOKUP(($BC4&DT4&"Template desconto % SexPrivê nível conta"),BENEFICIOS!$A:$G,5,0))),"Criar",IF(DT4="","",VLOOKUP(($BC4&DT4&"Template desconto % SexPrivê nível conta"),BENEFICIOS!$A:$G,5,0)))) -> Criar | DV4: 10 | DW4: =IF(DV4=0,"",IF(DV4=VLOOKUP("PCS-OzTL500",ARBOR!$A:$C,3,0),0.0001,IF(DV4>VLOOKUP("PCS-OzTL500",ARBOR!$A:$C,3,0),"Maior que CAP!",IF((DOLLAR(DV4+(VLOOKUP("PCS-OzTL500",ARBOR!$A:$C,3,0)*-TRUNC(DV4/VLOOKUP("PCS-OzTL500",ARBOR!$A:$C,3,0)-1,4)),6))<>(DOLLAR(VLOOKUP("PCS-OzTL500",ARBOR!$A:$C,3,0),6)),-TRUNC(DV4/VLOOKUP("PCS-OzTL500",ARBOR!$A:$C,3,0)-1,4)+0.0001,-TRUNC(DV4/VLOOKUP("PCS-OzTL500",ARBOR!$A:$C,3,0)-1,4))))) -> 0.0918 | DX4: =IF(DW4="S/Desc","S/Desc",IF(ISERROR(IF(DW4="","",VLOOKUP(($BC4&DW4&"Template desconto % Étnico nível conta"),BENEFICIOS!$A:$G,5,0))),"Criar",IF(DW4="","",VLOOKUP(($BC4&DW4&"Template desconto % Étnico nível conta"),BENEFICIOS!$A:$G,5,0)))) -> Criar | DZ4: =IF(DY4=0,"",IF(DY4=VLOOKUP("PCS-OzTL50",ARBOR!$A:$C,3,0),0.0001,IF(DY4>VLOOKUP("PCS-OzTL50",ARBOR!$A:$C,3,0),"Maior que CAP!",IF((DOLLAR(DY4+(VLOOKUP("PCS-OzTL50",ARBOR!$A:$C,3,0)*-TRUNC(DY4/VLOOKUP("PCS-OzTL50",ARBOR!$A:$C,3,0)-1,4)),6))<>(DOLLAR(VLOOKUP("PCS-OzTL50",ARBOR!$A:$C,3,0),6)),-TRUNC(DY4/VLOOKUP("PCS-OzTL50",ARBOR!$A:$C,3,0)-1,4)+0.0001,-TRUNC(DY4/VLOOKUP("PCS-OzTL50",ARBOR!$A:$C,3,0)-1,4))))) | EC4: =IF(EB4=0,"",IF(EB4=VLOOKUP("PCS-OzTL51",ARBOR!$A:$C,3,0),0.0001,IF(EB4>VLOOKUP("PCS-OzTL51",ARBOR!$A:$C,3,0),"Maior que CAP!",IF((DOLLAR(EB4+(VLOOKUP("PCS-OzTL51",ARBOR!$A:$C,3,0)*-TRUNC(EB4/VLOOKUP("PCS-OzTL51",ARBOR!$A:$C,3,0)-1,4)),6))<>(DOLLAR(VLOOKUP("PCS-OzTL51",ARBOR!$A:$C,3,0),6)),-TRUNC(EB4/VLOOKUP("PCS-OzTL51",ARBOR!$A:$C,3,0)-1,4)+0.0001,-TRUNC(EB4/VLOOKUP("PCS-OzTL51",ARBOR!$A:$C,3,0)-1,4))))) | EF4: =IF(EE4=0,"",IF(EE4=VLOOKUP("PCS-OzTL52",ARBOR!$A:$C,3,0),0.0001,IF(EE4>VLOOKUP("PCS-OzTL52",ARBOR!$A:$C,3,0),"Maior que CAP!",IF((DOLLAR(EE4+(VLOOKUP("PCS-OzTL52",ARBOR!$A:$C,3,0)*-TRUNC(EE4/VLOOKUP("PCS-OzTL52",ARBOR!$A:$C,3,0)-1,4)),6))<>(DOLLAR(VLOOKUP("PCS-OzTL52",ARBOR!$A:$C,3,0),6)),-TRUNC(EE4/VLOOKUP("PCS-OzTL52",ARBOR!$A:$C,3,0)-1,4)+0.0001,-TRUNC(EE4/VLOOKUP("PCS-OzTL52",ARBOR!$A:$C,3,0)-1,4))))) | EI4: =IF(EH4=0,"",IF(EH4=VLOOKUP("PCS-OzTL53",ARBOR!$A:$C,3,0),0.0001,IF(EH4>VLOOKUP("PCS-OzTL53",ARBOR!$A:$C,3,0),"Maior que CAP!",IF((DOLLAR(EH4+(VLOOKUP("PCS-OzTL53",ARBOR!$A:$C,3,0)*-TRUNC(EH4/VLOOKUP("PCS-OzTL53",ARBOR!$A:$C,3,0)-1,4)),6))<>(DOLLAR(VLOOKUP("PCS-OzTL53",ARBOR!$A:$C,3,0),6)),-TRUNC(EH4/VLOOKUP("PCS-OzTL53",ARBOR!$A:$C,3,0)-1,4)+0.0001,-TRUNC(EH4/VLOOKUP("PCS-OzTL53",ARBOR!$A:$C,3,0)-1,4))))) | EL4: =IF(EK4=0,"",IF(EK4=VLOOKUP("PCS-OzTL54",ARBOR!$A:$C,3,0),0.0001,IF(EK4>VLOOKUP("PCS-OzTL54",ARBOR!$A:$C,3,0),"Maior que CAP!",IF((DOLLAR(EK4+(VLOOKUP("PCS-OzTL54",ARBOR!$A:$C,3,0)*-TRUNC(EK4/VLOOKUP("PCS-OzTL54",ARBOR!$A:$C,3,0)-1,4)),6))<>(DOLLAR(VLOOKUP("PCS-OzTL54",ARBOR!$A:$C,3,0),6)),-TRUNC(EK4/VLOOKUP("PCS-OzTL54",ARBOR!$A:$C,3,0)-1,4)+0.0001,-TRUNC(EK4/VLOOKUP("PCS-OzTL54",ARBOR!$A:$C,3,0)-1,4))))) | EN4: 24.9 | EO4: =IF(EN4=0,"",IF(EN4=VLOOKUP("PCS-OzTL99",ARBOR!$A:$C,3,0),0.0001,IF(EN4>VLOOKUP("PCS-OzTL99",ARBOR!$A:$C,3,0),"Maior que CAP!",IF((DOLLAR(EN4+(VLOOKUP("PCS-OzTL99",ARBOR!$A:$C,3,0)*-TRUNC(EN4/VLOOKUP("PCS-OzTL99",ARBOR!$A:$C,3,0)-1,4)),6))<>(DOLLAR(VLOOKUP("PCS-OzTL99",ARBOR!$A:$C,3,0),6)),-TRUNC(EN4/VLOOKUP("PCS-OzTL99",ARBOR!$A:$C,3,0)-1,4)+0.0001,-TRUNC(EN4/VLOOKUP("PCS-OzTL99",ARBOR!$A:$C,3,0)-1,4))))) -> 0.1673 | EP4: =IF(EO4="S/Desc","S/Desc",IF(ISERROR(IF(EO4="","",VLOOKUP(($BC4&EO4&"Template desconto % Ponto adicional nível conta"),BENEFICIOS!$A:$G,5,0))),"Criar",IF(EO4="","",VLOOKUP(($BC4&EO4&"Template desconto % Ponto adicional nível conta"),BENEFICIOS!$A:$G,5,0)))) -> Criar | ER4: =IF(EQ4="Sim","PCS-34704","") | ES4: Sim | ET4: Benefício | EU4: 499 | EV4: 12 | EW4: =IF(ET4="Benefício","Oi benefício fidelização Multiprodutos","") -> Oi benefício fidelização Multiprodutos | EX4: =IF(ET4="Benefício","PCS-Fk83324","") -> PCS-Fk83324 | EY4: =IF(ES4="Sim","PCS-SBL553142","") -> PCS-SBL553142 | EZ4: LD + VC Oi | FA4: 0T0T_FTV_MIN_LD_270000. | FG4: =IF($BH4="","",$BH4+$BE4) | FH4: =IF($BK4="","",$BK4+$BE4) -> 154.9 | FI4: =IF($BN4="","",$BN4+$BE4) | FJ4: =IF($BQ4="","",$BQ4+$BE4) | FK4: =IF($BT4="","",$BT4+$BE4) | FL4: =IF($BW4="","",$BW4+$BE4) | FM4: =IF($BZ4="","",$BZ4+$BE4) | FN4: =IF($CC4="","",$CC4+$BE4) | FO4: =IF($CF4="","",$CF4+$BE4) | FP4: =IF($CI4="","",$CI4+$BE4) -> 164.9 | FQ4: =IF($CL4="","",$CL4+$BE4) | FR4: =IF($CO4="","",$CO4+$BE4) | FS4: =IF($CR4="","",$CR4+$BE4) | FT4: =IF($CU4="","",$CU4+$BE4) -> 184.9 | FU4: =IF($CX4="","",$CX4+$BE4) | FV4: =IF($DA4="","",$DA4+$BE4) | FW4: =IF($DD4="","",$DD4+$BE4)
A5: Oi Total | B5: Migração | C5: Atuais | D5: Não | AM5: OT_ATV_JUL17_FID_DACC_2PTV_TV3_MF-TF_LD-VC_OF1 | AN5: Rentabilizar atuais clientes do plano | AO5: Produto Fixo + TV , Produto com fidelização | AP5: 42917 | AQ5: 43039 | AR5: 20. Oi Total | AS5: 20. Oi Total | AU5: Varejo | AV5: 20 | AW5: 10000 | AX5: Campanha Restrita | AY5: Sim | AZ5: Sim | BA5: Não | BB5: OT_ATV_JUL17_FID_DACC_2PTV_TV3_MF-TF_LD-VC_OF1 | BC5: Oi Total Fixo + TV 3 | BD5: =IF(BC5="Oi Total Fixo + TV 1","CFG-2Plowpi",IF(BC5="Oi Total Fixo + TV 2","PCS-2PMepi",IF(BC5="Oi Total Fixo + TV 3","PCS-2PHipi",""))) -> PCS-2PHipi | BE5: 60 | BF5: =IF(BE5=0,"",IF(BE5=VLOOKUP("FIXO",ARBOR!$A:$C,3,0),0.0001,IF(BE5>VLOOKUP("FIXO",ARBOR!$A:$C,3,0),"Maior que CAP!",IF((DOLLAR(BE5+(VLOOKUP("FIXO",ARBOR!$A:$C,3,0)*-TRUNC(BE5/VLOOKUP("FIXO",ARBOR!$A:$C,3,0)-1,4)),6))<>(DOLLAR(VLOOKUP("FIXO",ARBOR!$A:$C,3,0),6)),-TRUNC(BE5/VLOOKUP("FIXO",ARBOR!$A:$C,3,0)-1,4)+0.0001,-TRUNC(BE5/VLOOKUP("FIXO",ARBOR!$A:$C,3,0)-1,4))))) -> 0.2089 | BG5: =IF(ISERROR(IF(BF5="","",VLOOKUP(($BC5&BF5&"Template de desconto FLAT bundle - Fixo - Varejo - Ganho Tributário Cross"),BENEFICIOS!$A:$G,5,0))),"Criar",IF(BF5="","",VLOOKUP(($BC5&BF5&"Template de desconto FLAT bundle - Fixo - Varejo - Ganho Tributário Cross"),BENEFICIOS!$A:$G,5,0))) -> Criar | BI5: =IF(BH5=0,"",IF(BH5=VLOOKUP("PCS-OzTL40",ARBOR!$A:$C,3,0),0.0001,IF(BH5>VLOOKUP("PCS-OzTL40",ARBOR!$A:$C,3,0),"Maior que CAP!",IF((DOLLAR(BH5+(VLOOKUP("PCS-OzTL40",ARBOR!$A:$C,3,0)*-TRUNC(BH5/VLOOKUP("PCS-OzTL40",ARBOR!$A:$C,3,0)-1,4)),6))<>(DOLLAR(VLOOKUP("PCS-OzTL40",ARBOR!$A:$C,3,0),6)),-TRUNC(BH5/VLOOKUP("PCS-OzTL40",ARBOR!$A:$C,3,0)-1,4)+0.0001,-TRUNC(BH5/VLOOKUP("PCS-OzTL40",ARBOR!$A:$C,3,0)-1,4))))) | BJ5: =IF(ISERROR(IF(BI5="","",VLOOKUP((BC5&BI5&"Template desconto FLAT Plano Principal Oi TV nível conta"),BENEFICIOS!$A:$G,5,0))),"Criar",IF(BI5="","",VLOOKUP((BC5&BI5&"Template desconto FLAT Plano Principal Oi TV nível conta"),BENEFICIOS!$A:$G,5,0))) | BL5: =IF(BK5=0,"",IF(BK5=VLOOKUP("PCS-OzTL41",ARBOR!$A:$C,3,0),0.0001,IF(BK5>VLOOKUP("PCS-OzTL41",ARBOR!$A:$C,3,0),"Maior que CAP!",IF((DOLLAR(BK5+(VLOOKUP("PCS-OzTL41",ARBOR!$A:$C,3,0)*-TRUNC(BK5/VLOOKUP("PCS-OzTL41",ARBOR!$A:$C,3,0)-1,4)),6))<>(DOLLAR(VLOOKUP("PCS-OzTL41",ARBOR!$A:$C,3,0),6)),-TRUNC(BK5/VLOOKUP("PCS-OzTL41",ARBOR!$A:$C,3,0)-1,4)+0.0001,-TRUNC(BK5/VLOOKUP("PCS-OzTL41",ARBOR!$A:$C,3,0)-1,4))))) | BM5: =IF(ISERROR(IF(BL5="","",VLOOKUP((BC5&BL5&"Template desconto FLAT Plano Principal Oi TV nível conta"),BENEFICIOS!$A:$G,5,0))),"Criar",IF(BL5="","",VLOOKUP((BC5&BL5&"Template desconto FLAT Plano Principal Oi TV nível conta"),BENEFICIOS!$A:$G,5,0))) | BN5: 124.9 | BO5: =IF(BN5=0,"",IF(BN5=VLOOKUP("PCS-OzTL44",ARBOR!$A:$C,3,0),0.0001,IF(BN5>VLOOKUP("PCS-OzTL44",ARBOR!$A:$C,3,0),"Maior que CAP!",IF((DOLLAR(BN5+(VLOOKUP("PCS-OzTL44",ARBOR!$A:$C,3,0)*-TRUNC(BN5/VLOOKUP("PCS-OzTL44",ARBOR!$A:$C,3,0)-1,4)),6))<>(DOLLAR(VLOOKUP("PCS-OzTL44",ARBOR!$A:$C,3,0),6)),-TRUNC(BN5/VLOOKUP("PCS-OzTL44",ARBOR!$A:$C,3,0)-1,4)+0.0001,-TRUNC(BN5/VLOOKUP("PCS-OzTL44",ARBOR!$A:$C,3,0)-1,4))))) -> 0.3516 | BP5: =IF(ISERROR(IF(BO5="","",VLOOKUP((BC5&BO5&"Template desconto FLAT Plano Principal Oi TV nível conta"),BENEFICIOS!$A:$G,5,0))),"Criar",IF(BO5="","",VLOOKUP((BC5&BO5&"Template desconto FLAT Plano Principal Oi TV nível conta"),BENEFICIOS!$A:$G,5,0))) -> Criar | BQ5: 124.9 | BR5: =IF(BQ5=0,"",IF(BQ5=VLOOKUP("PCS-OzTL43",ARBOR!$A:$C,3,0),0.0001,IF(BQ5>VLOOKUP("PCS-OzTL43",ARBOR!$A:$C,3,0),"Maior que CAP!",IF((DOLLAR(BQ5+(VLOOKUP("PCS-OzTL43",ARBOR!$A:$C,3,0)*-TRUNC(BQ5/VLOOKUP("PCS-OzTL43",ARBOR!$A:$C,3,0)-1,4)),6))<>(DOLLAR(VLOOKUP("PCS-OzTL43",ARBOR!$A:$C,3,0),6)),-TRUNC(BQ5/VLOOKUP("PCS-OzTL43",ARBOR!$A:$C,3,0)-1,4)+0.0001,-TRUNC(BQ5/VLOOKUP("PCS-OzTL43",ARBOR!$A:$C,3,0)-1,4))))) -> 0.3867 | BS5: =IF(ISERROR(IF(BR5="","",VLOOKUP((BC5&BR5&"Template desconto FLAT Plano Principal Oi TV nível conta"),BENEFICIOS!$A:$G,5,0))),"Criar",IF(BR5="","",VLOOKUP((BC5&BR5&"Template desconto FLAT Plano Principal Oi TV nível conta"),BENEFICIOS!$A:$G,5,0))) -> Criar | BT5: 154.9 | BU5: =IF(BT5=0,"",IF(BT5=VLOOKUP("PCS-OzTL45",ARBOR!$A:$C,3,0),0.0001,IF(BT5>VLOOKUP("PCS-OzTL45",ARBOR!$A:$C,3,0),"Maior que CAP!",IF((DOLLAR(BT5+(VLOOKUP("PCS-OzTL45",ARBOR!$A:$C,3,0)*-TRUNC(BT5/VLOOKUP("PCS-OzTL45",ARBOR!$A:$C,3,0)-1,4)),6))<>(DOLLAR(VLOOKUP("PCS-OzTL45",ARBOR!$A:$C,3,0),6)),-TRUNC(BT5/VLOOKUP("PCS-OzTL45",ARBOR!$A:$C,3,0)-1,4)+0.0001,-TRUNC(BT5/VLOOKUP("PCS-OzTL45",ARBOR!$A:$C,3,0)-1,4))))) -> 0.2594 | BV5: =IF(ISERROR(IF(BU5="","",VLOOKUP((BC5&BU5&"Template desconto FLAT Plano Principal Oi TV nível conta"),BENEFICIOS!$A:$G,5,0))),"Criar",IF(BU5="","",VLOOKUP((BC5&BU5&"Template desconto FLAT Plano Principal Oi TV nível conta"),BENEFICIOS!$A:$G,5,0))) -> Criar | BX5: =IF(BW5=0,"",IF(BW5=VLOOKUP("PCS-OzTL741",ARBOR!$A:$C,3,0),0.0001,IF(BW5>VLOOKUP("PCS-OzTL741",ARBOR!$A:$C,3,0),"Maior que CAP!",IF((DOLLAR(BW5+(VLOOKUP("PCS-OzTL741",ARBOR!$A:$C,3,0)*-TRUNC(BW5/VLOOKUP("PCS-OzTL741",ARBOR!$A:$C,3,0)-1,4)),6))<>(DOLLAR(VLOOKUP("PCS-OzTL741",ARBOR!$A:$C,3,0),6)),-TRUNC(BW5/VLOOKUP("PCS-OzTL741",ARBOR!$A:$C,3,0)-1,4)+0.0001,-TRUNC(BW5/VLOOKUP("PCS-OzTL741",ARBOR!$A:$C,3,0)-1,4))))) | BY5: =IF(ISERROR(IF(BX5="","",VLOOKUP((BC5&BX5&"Template desconto FLAT Plano Principal Oi TV nível conta"),BENEFICIOS!$A:$G,5,0))),"Criar",IF(BX5="","",VLOOKUP((BC5&BX5&"Template desconto FLAT Plano Principal Oi TV nível conta"),BENEFICIOS!$A:$G,5,0))) | CA5: =IF(BZ5=0,"",IF(BZ5=VLOOKUP("PCS-OzTL744",ARBOR!$A:$C,3,0),0.0001,IF(BZ5>VLOOKUP("PCS-OzTL744",ARBOR!$A:$C,3,0),"Maior que CAP!",IF((DOLLAR(BZ5+(VLOOKUP("PCS-OzTL744",ARBOR!$A:$C,3,0)*-TRUNC(BZ5/VLOOKUP("PCS-OzTL744",ARBOR!$A:$C,3,0)-1,4)),6))<>(DOLLAR(VLOOKUP("PCS-OzTL744",ARBOR!$A:$C,3,0),6)),-TRUNC(BZ5/VLOOKUP("PCS-OzTL744",ARBOR!$A:$C,3,0)-1,4)+0.0001,-TRUNC(BZ5/VLOOKUP("PCS-OzTL744",ARBOR!$A:$C,3,0)-1,4))))) | CB5: =IF(ISERROR(IF(CA5="","",VLOOKUP(($BC5&CA5&"Template desconto FLAT Plano Principal Oi TV nível conta"),BENEFICIOS!$A:$G,5,0))),"Criar",IF(CA5="","",VLOOKUP(($BC5&CA5&"Template desconto FLAT Plano Principal Oi TV nível conta"),BENEFICIOS!$A:$G,5,0))) | CD5: =IF(CC5=0,"",IF(CC5=VLOOKUP("PCS-OzTL743",ARBOR!$A:$C,3,0),0.0001,IF(CC5>VLOOKUP("PCS-OzTL743",ARBOR!$A:$C,3,0),"Maior que CAP!",IF((DOLLAR(CC5+(VLOOKUP("PCS-OzTL743",ARBOR!$A:$C,3,0)*-TRUNC(CC5/VLOOKUP("PCS-OzTL743",ARBOR!$A:$C,3,0)-1,4)),6))<>(DOLLAR(VLOOKUP("PCS-OzTL743",ARBOR!$A:$C,3,0),6)),-TRUNC(CC5/VLOOKUP("PCS-OzTL743",ARBOR!$A:$C,3,0)-1,4)+0.0001,-TRUNC(CC5/VLOOKUP("PCS-OzTL743",ARBOR!$A:$C,3,0)-1,4))))) | CE5: =IF(ISERROR(IF(CD5="","",VLOOKUP(($BC5&CD5&"Template desconto FLAT Plano Principal Oi TV nível conta"),BENEFICIOS!$A:$G,5,0))),"Criar",IF(CD5="","",VLOOKUP(($BC5&CD5&"Template desconto FLAT Plano Principal Oi TV nível conta"),BENEFICIOS!$A:$G,5,0))) | CG5: =IF(CF5=0,"",IF(CF5=VLOOKUP("PCS-OzTL745",ARBOR!$A:$C,3,0),0.0001,IF(CF5>VLOOKUP("PCS-OzTL745",ARBOR!$A:$C,3,0),"Maior que CAP!",IF((DOLLAR(CF5+(VLOOKUP("PCS-OzTL745",ARBOR!$A:$C,3,0)*-TRUNC(CF5/VLOOKUP("PCS-OzTL745",ARBOR!$A:$C,3,0)-1,4)),6))<>(DOLLAR(VLOOKUP("PCS-OzTL745",ARBOR!$A:$C,3,0),6)),-TRUNC(CF5/VLOOKUP("PCS-OzTL745",ARBOR!$A:$C,3,0)-1,4)+0.0001,-TRUNC(CF5/VLOOKUP("PCS-OzTL745",ARBOR!$A:$C,3,0)-1,4))))) | CH5: =IF(ISERROR(IF(CG5="","",VLOOKUP(($BC5&CG5&"Template desconto FLAT Plano Principal Oi TV nível conta"),BENEFICIOS!$A:$G,5,0))),"Criar",IF(CG5="","",VLOOKUP(($BC5&CG5&"Template desconto FLAT Plano Principal Oi TV nível conta"),BENEFICIOS!$A:$G,5,0))) | CJ5: =IF(CI5=0,"",IF(CI5=VLOOKUP("PCS-OzTL42",ARBOR!$A:$C,3,0),0.0001,IF(CI5>VLOOKUP("PCS-OzTL42",ARBOR!$A:$C,3,0),"Maior que CAP!",IF((DOLLAR(CI5+(VLOOKUP("PCS-OzTL42",ARBOR!$A:$C,3,0)*-TRUNC(CI5/VLOOKUP("PCS-OzTL42",ARBOR!$A:$C,3,0)-1,4)),6))<>(DOLLAR(VLOOKUP("PCS-OzTL42",ARBOR!$A:$C,3,0),6)),-TRUNC(CI5/VLOOKUP("PCS-OzTL42",ARBOR!$A:$C,3,0)-1,4)+0.0001,-TRUNC(CI5/VLOOKUP("PCS-OzTL42",ARBOR!$A:$C,3,0)-1,4))))) | CK5: =IF(ISERROR(IF(CJ5="","",VLOOKUP(($BC5&CJ5&"Template desconto FLAT Plano Principal Oi TV nível conta"),BENEFICIOS!$A:$G,5,0))),"Criar",IF(CJ5="","",VLOOKUP(($BC5&CJ5&"Template desconto FLAT Plano Principal Oi TV nível conta"),BENEFICIOS!$A:$G,5,0))) | CL5: 134.9 | CM5: =IF(CL5=0,"",IF(CL5=VLOOKUP("PCS-OzTL47",ARBOR!$A:$C,3,0),0.0001,IF(CL5>VLOOKUP("PCS-OzTL47",ARBOR!$A:$C,3,0),"Maior que CAP!",IF((DOLLAR(CL5+(VLOOKUP("PCS-OzTL47",ARBOR!$A:$C,3,0)*-TRUNC(CL5/VLOOKUP("PCS-OzTL47",ARBOR!$A:$C,3,0)-1,4)),6))<>(DOLLAR(VLOOKUP("PCS-OzTL47",ARBOR!$A:$C,3,0),6)),-TRUNC(CL5/VLOOKUP("PCS-OzTL47",ARBOR!$A:$C,3,0)-1,4)+0.0001,-TRUNC(CL5/VLOOKUP("PCS-OzTL47",ARBOR!$A:$C,3,0)-1,4))))) -> 0.3376 | CN5: =IF(ISERROR(IF(CM5="","",VLOOKUP(($BC5&CM5&"Template desconto FLAT Plano Principal Oi TV nível conta"),BENEFICIOS!$A:$G,5,0))),"Criar",IF(CM5="","",VLOOKUP(($BC5&CM5&"Template desconto FLAT Plano Principal Oi TV nível conta"),BENEFICIOS!$A:$G,5,0))) -> Criar | CO5: 134.9 | CP5: =IF(CO5=0,"",IF(CO5=VLOOKUP("PCS-OzTL46",ARBOR!$A:$C,3,0),0.0001,IF(CO5>VLOOKUP("PCS-OzTL46",ARBOR!$A:$C,3,0),"Maior que CAP!",IF((DOLLAR(CO5+(VLOOKUP("PCS-OzTL46",ARBOR!$A:$C,3,0)*-TRUNC(CO5/VLOOKUP("PCS-OzTL46",ARBOR!$A:$C,3,0)-1,4)),6))<>(DOLLAR(VLOOKUP("PCS-OzTL46",ARBOR!$A:$C,3,0),6)),-TRUNC(CO5/VLOOKUP("PCS-OzTL46",ARBOR!$A:$C,3,0)-1,4)+0.0001,-TRUNC(CO5/VLOOKUP("PCS-OzTL46",ARBOR!$A:$C,3,0)-1,4))))) -> 0.3716 | CQ5: =IF(ISERROR(IF(CP5="","",VLOOKUP(($BC5&CP5&"Template desconto FLAT Plano Principal Oi TV nível conta"),BENEFICIOS!$A:$G,5,0))),"Criar",IF(CP5="","",VLOOKUP(($BC5&CP5&"Template desconto FLAT Plano Principal Oi TV nível conta"),BENEFICIOS!$A:$G,5,0))) -> Criar | CR5: 164.9 | CS5: =IF(CR5=0,"",IF(CR5=VLOOKUP("PCS-OzTL48",ARBOR!$A:$C,3,0),0.0001,IF(CR5>VLOOKUP("PCS-OzTL48",ARBOR!$A:$C,3,0),"Maior que CAP!",IF((DOLLAR(CR5+(VLOOKUP("PCS-OzTL48",ARBOR!$A:$C,3,0)*-TRUNC(CR5/VLOOKUP("PCS-OzTL48",ARBOR!$A:$C,3,0)-1,4)),6))<>(DOLLAR(VLOOKUP("PCS-OzTL48",ARBOR!$A:$C,3,0),6)),-TRUNC(CR5/VLOOKUP("PCS-OzTL48",ARBOR!$A:$C,3,0)-1,4)+0.0001,-TRUNC(CR5/VLOOKUP("PCS-OzTL48",ARBOR!$A:$C,3,0)-1,4))))) -> 0.3487 | CT5: =IF(ISERROR(IF(CS5="","",VLOOKUP(($BC5&CS5&"Template desconto FLAT Plano Principal Oi TV nível conta"),BENEFICIOS!$A:$G,5,0))),"Criar",IF(CS5="","",VLOOKUP(($BC5&CS5&"Template desconto FLAT Plano Principal Oi TV nível conta"),BENEFICIOS!$A:$G,5,0))) -> Criar | CV5: =IF(CU5=0,"",IF(CU5=VLOOKUP("PCS-OzTL742",ARBOR!$A:$C,3,0),0.0001,IF(CU5>VLOOKUP("PCS-OzTL742",ARBOR!$A:$C,3,0),"Maior que CAP!",IF((DOLLAR(CU5+(VLOOKUP("PCS-OzTL742",ARBOR!$A:$C,3,0)*-TRUNC(CU5/VLOOKUP("PCS-OzTL742",ARBOR!$A:$C,3,0)-1,4)),6))<>(DOLLAR(VLOOKUP("PCS-OzTL742",ARBOR!$A:$C,3,0),6)),-TRUNC(CU5/VLOOKUP("PCS-OzTL742",ARBOR!$A:$C,3,0)-1,4)+0.0001,-TRUNC(CU5/VLOOKUP("PCS-OzTL742",ARBOR!$A:$C,3,0)-1,4))))) | CW5: =IF(ISERROR(IF(CV5="","",VLOOKUP(($BC5&CV5&"Template desconto FLAT Plano Principal Oi TV nível conta"),BENEFICIOS!$A:$G,5,0))),"Criar",IF(CV5="","",VLOOKUP(($BC5&CV5&"Template desconto FLAT Plano Principal Oi TV nível conta"),BENEFICIOS!$A:$G,5,0))) | CX5: 154.9 | CY5: =IF(CX5=0,"",IF(CX5=VLOOKUP("PCS-OzTL747",ARBOR!$A:$C,3,0),0.0001,IF(CX5>VLOOKUP("PCS-OzTL747",ARBOR!$A:$C,3,0),"Maior que CAP!",IF((DOLLAR(CX5+(VLOOKUP("PCS-OzTL747",ARBOR!$A:$C,3,0)*-TRUNC(CX5/VLOOKUP("PCS-OzTL747",ARBOR!$A:$C,3,0)-1,4)),6))<>(DOLLAR(VLOOKUP("PCS-OzTL747",ARBOR!$A:$C,3,0),6)),-TRUNC(CX5/VLOOKUP("PCS-OzTL747",ARBOR!$A:$C,3,0)-1,4)+0.0001,-TRUNC(CX5/VLOOKUP("PCS-OzTL747",ARBOR!$A:$C,3,0)-1,4))))) -> 0.4013 | CZ5: =IF(ISERROR(IF(CY5="","",VLOOKUP(($BC5&CY5&"Template desconto FLAT Plano Principal Oi TV nível conta"),BENEFICIOS!$A:$G,5,0))),"Criar",IF(CY5="","",VLOOKUP(($BC5&CY5&"Template desconto FLAT Plano Principal Oi TV nível conta"),BENEFICIOS!$A:$G,5,0))) -> Criar | DA5: 154.9 | DB5: =IF(DA5=0,"",IF(DA5=VLOOKUP("PCS-OzTL746",ARBOR!$A:$C,3,0),0.0001,IF(DA5>VLOOKUP("PCS-OzTL746",ARBOR!$A:$C,3,0),"Maior que CAP!",IF((DOLLAR(DA5+(VLOOKUP("PCS-OzTL746",ARBOR!$A:$C,3,0)*-TRUNC(DA5/VLOOKUP("PCS-OzTL746",ARBOR!$A:$C,3,0)-1,4)),6))<>(DOLLAR(VLOOKUP("PCS-OzTL746",ARBOR!$A:$C,3,0),6)),-TRUNC(DA5/VLOOKUP("PCS-OzTL746",ARBOR!$A:$C,3,0)-1,4)+0.0001,-TRUNC(DA5/VLOOKUP("PCS-OzTL746",ARBOR!$A:$C,3,0)-1,4))))) -> 0.4257 | DC5: =IF(ISERROR(IF(DB5="","",VLOOKUP(($BC5&DB5&"Template desconto FLAT Plano Principal Oi TV nível conta"),BENEFICIOS!$A:$G,5,0))),"Criar",IF(DB5="","",VLOOKUP(($BC5&DB5&"Template desconto FLAT Plano Principal Oi TV nível conta"),BENEFICIOS!$A:$G,5,0))) -> Criar | DD5: 184.9 | DE5: =IF(DD5=0,"",IF(DD5=VLOOKUP("PCS-OzTL748",ARBOR!$A:$C,3,0),0.0001,IF(DD5>VLOOKUP("PCS-OzTL748",ARBOR!$A:$C,3,0),"Maior que CAP!",IF((DOLLAR(DD5+(VLOOKUP("PCS-OzTL748",ARBOR!$A:$C,3,0)*-TRUNC(DD5/VLOOKUP("PCS-OzTL748",ARBOR!$A:$C,3,0)-1,4)),6))<>(DOLLAR(VLOOKUP("PCS-OzTL748",ARBOR!$A:$C,3,0),6)),-TRUNC(DD5/VLOOKUP("PCS-OzTL748",ARBOR!$A:$C,3,0)-1,4)+0.0001,-TRUNC(DD5/VLOOKUP("PCS-OzTL748",ARBOR!$A:$C,3,0)-1,4))))) -> 0.4002 | DF5: =IF(ISERROR(IF(DE5="","",VLOOKUP(($BC5&DE5&"Template desconto FLAT Plano Principal Oi TV nível conta"),BENEFICIOS!$A:$G,5,0))),"Criar",IF(DE5="","",VLOOKUP(($BC5&DE5&"Template desconto FLAT Plano Principal Oi TV nível conta"),BENEFICIOS!$A:$G,5,0))) -> Criar | DG5: 75 | DH5: =IF(DG5=0,"",IF(DG5=VLOOKUP("PCS-OzTL34",ARBOR!$A:$C,3,0),0.0001,IF(DG5>VLOOKUP("PCS-OzTL34",ARBOR!$A:$C,3,0),"Maior que CAP!",IF((DOLLAR(DG5+(VLOOKUP("PCS-OzTL34",ARBOR!$A:$C,3,0)*-TRUNC(DG5/VLOOKUP("PCS-OzTL34",ARBOR!$A:$C,3,0)-1,4)),6))<>(DOLLAR(VLOOKUP("PCS-OzTL34",ARBOR!$A:$C,3,0),6)),-TRUNC(DG5/VLOOKUP("PCS-OzTL34",ARBOR!$A:$C,3,0)-1,4)+0.0001,-TRUNC(DG5/VLOOKUP("PCS-OzTL34",ARBOR!$A:$C,3,0)-1,4))))) -> 0.319 | DI5: =IF(DH5="S/Desc","S/Desc",IF(ISERROR(IF(DH5="","",VLOOKUP(($BC5&DH5&"Template desconto % Combate nível conta"),BENEFICIOS!$A:$G,5,0))),"Criar",IF(DH5="","",VLOOKUP(($BC5&DH5&"Template desconto % Combate nível conta"),BENEFICIOS!$A:$G,5,0)))) -> Criar | DJ5: 19.9 | DK5: =IF(DJ5=0,"",IF(DJ5=VLOOKUP("PCS-OzTL31",ARBOR!$A:$C,3,0),0.0001,IF(DJ5>VLOOKUP("PCS-OzTL31",ARBOR!$A:$C,3,0),"Maior que CAP!",IF((DOLLAR(DJ5+(VLOOKUP("PCS-OzTL31",ARBOR!$A:$C,3,0)*-TRUNC(DJ5/VLOOKUP("PCS-OzTL31",ARBOR!$A:$C,3,0)-1,4)),6))<>(DOLLAR(VLOOKUP("PCS-OzTL31",ARBOR!$A:$C,3,0),6)),-TRUNC(DJ5/VLOOKUP("PCS-OzTL31",ARBOR!$A:$C,3,0)-1,4)+0.0001,-TRUNC(DJ5/VLOOKUP("PCS-OzTL31",ARBOR!$A:$C,3,0)-1,4))))) -> 0.0918 | DL5: =IF(DK5="S/Desc","S/Desc",IF(ISERROR(IF(DK5="","",VLOOKUP(($BC5&DK5&"Template desconto % Sexy Hot nível conta"),BENEFICIOS!$A:$G,5,0))),"Criar",IF(DK5="","",VLOOKUP(($BC5&DK5&"Template desconto % Sexy Hot nível conta"),BENEFICIOS!$A:$G,5,0)))) -> Criar | DM5: 19.9 | DN5: =IF(DM5=0,"",IF(DM5=VLOOKUP("PCS-OzTL32",ARBOR!$A:$C,3,0),0.0001,IF(DM5>VLOOKUP("PCS-OzTL32",ARBOR!$A:$C,3,0),"Maior que CAP!",IF((DOLLAR(DM5+(VLOOKUP("PCS-OzTL32",ARBOR!$A:$C,3,0)*-TRUNC(DM5/VLOOKUP("PCS-OzTL32",ARBOR!$A:$C,3,0)-1,4)),6))<>(DOLLAR(VLOOKUP("PCS-OzTL32",ARBOR!$A:$C,3,0),6)),-TRUNC(DM5/VLOOKUP("PCS-OzTL32",ARBOR!$A:$C,3,0)-1,4)+0.0001,-TRUNC(DM5/VLOOKUP("PCS-OzTL32",ARBOR!$A:$C,3,0)-1,4))))) -> 0.0918 | DO5: =IF(DN5="S/Desc","S/Desc",IF(ISERROR(IF(DN5="","",VLOOKUP(($BC5&DN5&"Template desconto % Playboy nível conta"),BENEFICIOS!$A:$G,5,0))),"Criar",IF(DN5="","",VLOOKUP(($BC5&DN5&"Template desconto % Playboy nível conta"),BENEFICIOS!$A:$G,5,0)))) -> Criar | DP5: 29.9 | DQ5: =IF(DP5=0,"",IF(DP5=VLOOKUP("PCS-OzTL33",ARBOR!$A:$C,3,0),0.0001,IF(DP5>VLOOKUP("PCS-OzTL33",ARBOR!$A:$C,3,0),"Maior que CAP!",IF((DOLLAR(DP5+(VLOOKUP("PCS-OzTL33",ARBOR!$A:$C,3,0)*-TRUNC(DP5/VLOOKUP("PCS-OzTL33",ARBOR!$A:$C,3,0)-1,4)),6))<>(DOLLAR(VLOOKUP("PCS-OzTL33",ARBOR!$A:$C,3,0),6)),-TRUNC(DP5/VLOOKUP("PCS-OzTL33",ARBOR!$A:$C,3,0)-1,4)+0.0001,-TRUNC(DP5/VLOOKUP("PCS-OzTL33",ARBOR!$A:$C,3,0)-1,4))))) -> 0.0918 | DR5: =IF(DQ5="S/Desc","S/Desc",IF(ISERROR(IF(DQ5="","",VLOOKUP(($BC5&DQ5&"Template desconto % Sexy Hot + Playboy nível conta"),BENEFICIOS!$A:$G,5,0))),"Criar",IF(DQ5="","",VLOOKUP(($BC5&DQ5&"Template desconto % Sexy Hot + Playboy nível conta"),BENEFICIOS!$A:$G,5,0)))) -> Criar | DS5: 14.9 | DT5: =IF(DS5=0,"",IF(DS5=VLOOKUP("PCS-OzTL503",ARBOR!$A:$C,3,0),0.0001,IF(DS5>VLOOKUP("PCS-OzTL503",ARBOR!$A:$C,3,0),"Maior que CAP!",IF((DOLLAR(DS5+(VLOOKUP("PCS-OzTL503",ARBOR!$A:$C,3,0)*-TRUNC(DS5/VLOOKUP("PCS-OzTL503",ARBOR!$A:$C,3,0)-1,4)),6))<>(DOLLAR(VLOOKUP("PCS-OzTL503",ARBOR!$A:$C,3,0),6)),-TRUNC(DS5/VLOOKUP("PCS-OzTL503",ARBOR!$A:$C,3,0)-1,4)+0.0001,-TRUNC(DS5/VLOOKUP("PCS-OzTL503",ARBOR!$A:$C,3,0)-1,4))))) -> 0.0915 | DU5: =IF(DT5="S/Desc","S/Desc",IF(ISERROR(IF(DT5="","",VLOOKUP(($BC5&DT5&"Template desconto % SexPrivê nível conta"),BENEFICIOS!$A:$G,5,0))),"Criar",IF(DT5="","",VLOOKUP(($BC5&DT5&"Template desconto % SexPrivê nível conta"),BENEFICIOS!$A:$G,5,0)))) -> Criar | DV5: 10 | DW5: =IF(DV5=0,"",IF(DV5=VLOOKUP("PCS-OzTL500",ARBOR!$A:$C,3,0),0.0001,IF(DV5>VLOOKUP("PCS-OzTL500",ARBOR!$A:$C,3,0),"Maior que CAP!",IF((DOLLAR(DV5+(VLOOKUP("PCS-OzTL500",ARBOR!$A:$C,3,0)*-TRUNC(DV5/VLOOKUP("PCS-OzTL500",ARBOR!$A:$C,3,0)-1,4)),6))<>(DOLLAR(VLOOKUP("PCS-OzTL500",ARBOR!$A:$C,3,0),6)),-TRUNC(DV5/VLOOKUP("PCS-OzTL500",ARBOR!$A:$C,3,0)-1,4)+0.0001,-TRUNC(DV5/VLOOKUP("PCS-OzTL500",ARBOR!$A:$C,3,0)-1,4))))) -> 0.0918 | DX5: =IF(DW5="S/Desc","S/Desc",IF(ISERROR(IF(DW5="","",VLOOKUP(($BC5&DW5&"Template desconto % Étnico nível conta"),BENEFICIOS!$A:$G,5,0))),"Criar",IF(DW5="","",VLOOKUP(($BC5&DW5&"Template desconto % Étnico nível conta"),BENEFICIOS!$A:$G,5,0)))) -> Criar | DZ5: =IF(DY5=0,"",IF(DY5=VLOOKUP("PCS-OzTL50",ARBOR!$A:$C,3,0),0.0001,IF(DY5>VLOOKUP("PCS-OzTL50",ARBOR!$A:$C,3,0),"Maior que CAP!",IF((DOLLAR(DY5+(VLOOKUP("PCS-OzTL50",ARBOR!$A:$C,3,0)*-TRUNC(DY5/VLOOKUP("PCS-OzTL50",ARBOR!$A:$C,3,0)-1,4)),6))<>(DOLLAR(VLOOKUP("PCS-OzTL50",ARBOR!$A:$C,3,0),6)),-TRUNC(DY5/VLOOKUP("PCS-OzTL50",ARBOR!$A:$C,3,0)-1,4)+0.0001,-TRUNC(DY5/VLOOKUP("PCS-OzTL50",ARBOR!$A:$C,3,0)-1,4))))) | EC5: =IF(EB5=0,"",IF(EB5=VLOOKUP("PCS-OzTL51",ARBOR!$A:$C,3,0),0.0001,IF(EB5>VLOOKUP("PCS-OzTL51",ARBOR!$A:$C,3,0),"Maior que CAP!",IF((DOLLAR(EB5+(VLOOKUP("PCS-OzTL51",ARBOR!$A:$C,3,0)*-TRUNC(EB5/VLOOKUP("PCS-OzTL51",ARBOR!$A:$C,3,0)-1,4)),6))<>(DOLLAR(VLOOKUP("PCS-OzTL51",ARBOR!$A:$C,3,0),6)),-TRUNC(EB5/VLOOKUP("PCS-OzTL51",ARBOR!$A:$C,3,0)-1,4)+0.0001,-TRUNC(EB5/VLOOKUP("PCS-OzTL51",ARBOR!$A:$C,3,0)-1,4))))) | EF5: =IF(EE5=0,"",IF(EE5=VLOOKUP("PCS-OzTL52",ARBOR!$A:$C,3,0),0.0001,IF(EE5>VLOOKUP("PCS-OzTL52",ARBOR!$A:$C,3,0),"Maior que CAP!",IF((DOLLAR(EE5+(VLOOKUP("PCS-OzTL52",ARBOR!$A:$C,3,0)*-TRUNC(EE5/VLOOKUP("PCS-OzTL52",ARBOR!$A:$C,3,0)-1,4)),6))<>(DOLLAR(VLOOKUP("PCS-OzTL52",ARBOR!$A:$C,3,0),6)),-TRUNC(EE5/VLOOKUP("PCS-OzTL52",ARBOR!$A:$C,3,0)-1,4)+0.0001,-TRUNC(EE5/VLOOKUP("PCS-OzTL52",ARBOR!$A:$C,3,0)-1,4))))) | EI5: =IF(EH5=0,"",IF(EH5=VLOOKUP("PCS-OzTL53",ARBOR!$A:$C,3,0),0.0001,IF(EH5>VLOOKUP("PCS-OzTL53",ARBOR!$A:$C,3,0),"Maior que CAP!",IF((DOLLAR(EH5+(VLOOKUP("PCS-OzTL53",ARBOR!$A:$C,3,0)*-TRUNC(EH5/VLOOKUP("PCS-OzTL53",ARBOR!$A:$C,3,0)-1,4)),6))<>(DOLLAR(VLOOKUP("PCS-OzTL53",ARBOR!$A:$C,3,0),6)),-TRUNC(EH5/VLOOKUP("PCS-OzTL53",ARBOR!$A:$C,3,0)-1,4)+0.0001,-TRUNC(EH5/VLOOKUP("PCS-OzTL53",ARBOR!$A:$C,3,0)-1,4))))) | EL5: =IF(EK5=0,"",IF(EK5=VLOOKUP("PCS-OzTL54",ARBOR!$A:$C,3,0),0.0001,IF(EK5>VLOOKUP("PCS-OzTL54",ARBOR!$A:$C,3,0),"Maior que CAP!",IF((DOLLAR(EK5+(VLOOKUP("PCS-OzTL54",ARBOR!$A:$C,3,0)*-TRUNC(EK5/VLOOKUP("PCS-OzTL54",ARBOR!$A:$C,3,0)-1,4)),6))<>(DOLLAR(VLOOKUP("PCS-OzTL54",ARBOR!$A:$C,3,0),6)),-TRUNC(EK5/VLOOKUP("PCS-OzTL54",ARBOR!$A:$C,3,0)-1,4)+0.0001,-TRUNC(EK5/VLOOKUP("PCS-OzTL54",ARBOR!$A:$C,3,0)-1,4))))) | EN5: 24.9 | EO5: =IF(EN5=0,"",IF(EN5=VLOOKUP("PCS-OzTL99",ARBOR!$A:$C,3,0),0.0001,IF(EN5>VLOOKUP("PCS-OzTL99",ARBOR!$A:$C,3,0),"Maior que CAP!",IF((DOLLAR(EN5+(VLOOKUP("PCS-OzTL99",ARBOR!$A:$C,3,0)*-TRUNC(EN5/VLOOKUP("PCS-OzTL99",ARBOR!$A:$C,3,0)-1,4)),6))<>(DOLLAR(VLOOKUP("PCS-OzTL99",ARBOR!$A:$C,3,0),6)),-TRUNC(EN5/VLOOKUP("PCS-OzTL99",ARBOR!$A:$C,3,0)-1,4)+0.0001,-TRUNC(EN5/VLOOKUP("PCS-OzTL99",ARBOR!$A:$C,3,0)-1,4))))) -> 0.1673 | EP5: =IF(EO5="S/Desc","S/Desc",IF(ISERROR(IF(EO5="","",VLOOKUP(($BC5&EO5&"Template desconto % Ponto adicional nível conta"),BENEFICIOS!$A:$G,5,0))),"Criar",IF(EO5="","",VLOOKUP(($BC5&EO5&"Template desconto % Ponto adicional nível conta"),BENEFICIOS!$A:$G,5,0)))) -> Criar | ER5: =IF(EQ5="Sim","PCS-34704","") | ES5: Sim | ET5: Benefício | EU5: 499 | EV5: 12 | EW5: =IF(ET5="Benefício","Oi benefício fidelização Multiprodutos","") -> Oi benefício fidelização Multiprodutos | EX5: =IF(ET5="Benefício","PCS-Fk83324","") -> PCS-Fk83324 | EY5: =IF(ES5="Sim","PCS-SBL553142","") -> PCS-SBL553142 | EZ5: LD + VC Oi | FA5: 0T0T_FTV_MIN_LD_270000. | FG5: =IF($BH5="","",$BH5+$BE5) | FH5: =IF($BK5="","",$BK5+$BE5) | FI5: =IF($BN5="","",$BN5+$BE5) -> 184.9 | FJ5: =IF($BQ5="","",$BQ5+$BE5) -> 184.9 | FK5: =IF($BT5="","",$BT5+$BE5) -> 214.9 | FL5: =IF($BW5="","",$BW5+$BE5) | FM5: =IF($BZ5="","",$BZ5+$BE5) | FN5: =IF($CC5="","",$CC5+$BE5) | FO5: =IF($CF5="","",$CF5+$BE5) | FP5: =IF($CI5="","",$CI5+$BE5) | FQ5: =IF($CL5="","",$CL5+$BE5) -> 194.9 | FR5: =IF($CO5="","",$CO5+$BE5) -> 194.9 | FS5: =IF($CR5="","",$CR5+$BE5) -> 224.9 | FT5: =IF($CU5="","",$CU5+$BE5) | FU5: =IF($CX5="","",$CX5+$BE5) -> 214.9 | FV5: =IF($DA5="","",$DA5+$BE5) -> 214.9 | FW5: =IF($DD5="","",$DD5+$BE5) -> 244.9
A6: Oi Total | B6: Migração | C6: Atuais | D6: Não | AM6: OT_ATV_JUL17_FID_DACC_2PTV_TV2_MI-TO_LD-VC_OF2 | AN6: Rentabilizar atuais clientes do plano | AO6: Produto Fixo + TV , Produto com fidelização | AP6: 42917 | AQ6: 43039 | AR6: 20. Oi Total | AS6: 20. Oi Total | AU6: Varejo | AV6: 20 | AW6: 10000 | AX6: Campanha Restrita | AY6: Sim | AZ6: Sim | BA6: Não | BB6: OT_ATV_JUL17_FID_DACC_2PTV_TV2_MI-TO_LD-VC_OF2 | BC6: Oi Total Fixo + TV 2 | BD6: =IF(BC6="Oi Total Fixo + TV 1","CFG-2Plowpi",IF(BC6="Oi Total Fixo + TV 2","PCS-2PMepi",IF(BC6="Oi Total Fixo + TV 3","PCS-2PHipi",""))) -> PCS-2PMepi | BE6: 45 | BF6: =IF(BE6=0,"",IF(BE6=VLOOKUP("FIXO",ARBOR!$A:$C,3,0),0.0001,IF(BE6>VLOOKUP("FIXO",ARBOR!$A:$C,3,0),"Maior que CAP!",IF((DOLLAR(BE6+(VLOOKUP("FIXO",ARBOR!$A:$C,3,0)*-TRUNC(BE6/VLOOKUP("FIXO",ARBOR!$A:$C,3,0)-1,4)),6))<>(DOLLAR(VLOOKUP("FIXO",ARBOR!$A:$C,3,0),6)),-TRUNC(BE6/VLOOKUP("FIXO",ARBOR!$A:$C,3,0)-1,4)+0.0001,-TRUNC(BE6/VLOOKUP("FIXO",ARBOR!$A:$C,3,0)-1,4))))) -> 0.4067 | BG6: =IF(ISERROR(IF(BF6="","",VLOOKUP(($BC6&BF6&"Template de desconto FLAT bundle - Fixo - Varejo - Ganho Tributário Cross"),BENEFICIOS!$A:$G,5,0))),"Criar",IF(BF6="","",VLOOKUP(($BC6&BF6&"Template de desconto FLAT bundle - Fixo - Varejo - Ganho Tributário Cross"),BENEFICIOS!$A:$G,5,0))) -> Criar | BI6: =IF(BH6=0,"",IF(BH6=VLOOKUP("PCS-OzTL40",ARBOR!$A:$C,3,0),0.0001,IF(BH6>VLOOKUP("PCS-OzTL40",ARBOR!$A:$C,3,0),"Maior que CAP!",IF((DOLLAR(BH6+(VLOOKUP("PCS-OzTL40",ARBOR!$A:$C,3,0)*-TRUNC(BH6/VLOOKUP("PCS-OzTL40",ARBOR!$A:$C,3,0)-1,4)),6))<>(DOLLAR(VLOOKUP("PCS-OzTL40",ARBOR!$A:$C,3,0),6)),-TRUNC(BH6/VLOOKUP("PCS-OzTL40",ARBOR!$A:$C,3,0)-1,4)+0.0001,-TRUNC(BH6/VLOOKUP("PCS-OzTL40",ARBOR!$A:$C,3,0)-1,4))))) | BJ6: =IF(ISERROR(IF(BI6="","",VLOOKUP((BC6&BI6&"Template desconto FLAT Plano Principal Oi TV nível conta"),BENEFICIOS!$A:$G,5,0))),"Criar",IF(BI6="","",VLOOKUP((BC6&BI6&"Template desconto FLAT Plano Principal Oi TV nível conta"),BENEFICIOS!$A:$G,5,0))) | BK6: 89.9 | BL6: =IF(BK6=0,"",IF(BK6=VLOOKUP("PCS-OzTL41",ARBOR!$A:$C,3,0),0.0001,IF(BK6>VLOOKUP("PCS-OzTL41",ARBOR!$A:$C,3,0),"Maior que CAP!",IF((DOLLAR(BK6+(VLOOKUP("PCS-OzTL41",ARBOR!$A:$C,3,0)*-TRUNC(BK6/VLOOKUP("PCS-OzTL41",ARBOR!$A:$C,3,0)-1,4)),6))<>(DOLLAR(VLOOKUP("PCS-OzTL41",ARBOR!$A:$C,3,0),6)),-TRUNC(BK6/VLOOKUP("PCS-OzTL41",ARBOR!$A:$C,3,0)-1,4)+0.0001,-TRUNC(BK6/VLOOKUP("PCS-OzTL41",ARBOR!$A:$C,3,0)-1,4))))) -> 0.2573 | BM6: =IF(ISERROR(IF(BL6="","",VLOOKUP((BC6&BL6&"Template desconto FLAT Plano Principal Oi TV nível conta"),BENEFICIOS!$A:$G,5,0))),"Criar",IF(BL6="","",VLOOKUP((BC6&BL6&"Template desconto FLAT Plano Principal Oi TV nível conta"),BENEFICIOS!$A:$G,5,0))) -> Criar | BO6: =IF(BN6=0,"",IF(BN6=VLOOKUP("PCS-OzTL44",ARBOR!$A:$C,3,0),0.0001,IF(BN6>VLOOKUP("PCS-OzTL44",ARBOR!$A:$C,3,0),"Maior que CAP!",IF((DOLLAR(BN6+(VLOOKUP("PCS-OzTL44",ARBOR!$A:$C,3,0)*-TRUNC(BN6/VLOOKUP("PCS-OzTL44",ARBOR!$A:$C,3,0)-1,4)),6))<>(DOLLAR(VLOOKUP("PCS-OzTL44",ARBOR!$A:$C,3,0),6)),-TRUNC(BN6/VLOOKUP("PCS-OzTL44",ARBOR!$A:$C,3,0)-1,4)+0.0001,-TRUNC(BN6/VLOOKUP("PCS-OzTL44",ARBOR!$A:$C,3,0)-1,4))))) | BP6: =IF(ISERROR(IF(BO6="","",VLOOKUP((BC6&BO6&"Template desconto FLAT Plano Principal Oi TV nível conta"),BENEFICIOS!$A:$G,5,0))),"Criar",IF(BO6="","",VLOOKUP((BC6&BO6&"Template desconto FLAT Plano Principal Oi TV nível conta"),BENEFICIOS!$A:$G,5,0))) | BR6: =IF(BQ6=0,"",IF(BQ6=VLOOKUP("PCS-OzTL43",ARBOR!$A:$C,3,0),0.0001,IF(BQ6>VLOOKUP("PCS-OzTL43",ARBOR!$A:$C,3,0),"Maior que CAP!",IF((DOLLAR(BQ6+(VLOOKUP("PCS-OzTL43",ARBOR!$A:$C,3,0)*-TRUNC(BQ6/VLOOKUP("PCS-OzTL43",ARBOR!$A:$C,3,0)-1,4)),6))<>(DOLLAR(VLOOKUP("PCS-OzTL43",ARBOR!$A:$C,3,0),6)),-TRUNC(BQ6/VLOOKUP("PCS-OzTL43",ARBOR!$A:$C,3,0)-1,4)+0.0001,-TRUNC(BQ6/VLOOKUP("PCS-OzTL43",ARBOR!$A:$C,3,0)-1,4))))) | BS6: =IF(ISERROR(IF(BR6="","",VLOOKUP((BC6&BR6&"Template desconto FLAT Plano Principal Oi TV nível conta"),BENEFICIOS!$A:$G,5,0))),"Criar",IF(BR6="","",VLOOKUP((BC6&BR6&"Template desconto FLAT Plano Principal Oi TV nível conta"),BENEFICIOS!$A:$G,5,0))) | BU6: =IF(BT6=0,"",IF(BT6=VLOOKUP("PCS-OzTL45",ARBOR!$A:$C,3,0),0.0001,IF(BT6>VLOOKUP("PCS-OzTL45",ARBOR!$A:$C,3,0),"Maior que CAP!",IF((DOLLAR(BT6+(VLOOKUP("PCS-OzTL45",ARBOR!$A:$C,3,0)*-TRUNC(BT6/VLOOKUP("PCS-OzTL45",ARBOR!$A:$C,3,0)-1,4)),6))<>(DOLLAR(VLOOKUP("PCS-OzTL45",ARBOR!$A:$C,3,0),6)),-TRUNC(BT6/VLOOKUP("PCS-OzTL45",ARBOR!$A:$C,3,0)-1,4)+0.0001,-TRUNC(BT6/VLOOKUP("PCS-OzTL45",ARBOR!$A:$C,3,0)-1,4))))) | BV6: =IF(ISERROR(IF(BU6="","",VLOOKUP((BC6&BU6&"Template desconto FLAT Plano Principal Oi TV nível conta"),BENEFICIOS!$A:$G,5,0))),"Criar",IF(BU6="","",VLOOKUP((BC6&BU6&"Template desconto FLAT Plano Principal Oi TV nível conta"),BENEFICIOS!$A:$G,5,0))) | BX6: =IF(BW6=0,"",IF(BW6=VLOOKUP("PCS-OzTL741",ARBOR!$A:$C,3,0),0.0001,IF(BW6>VLOOKUP("PCS-OzTL741",ARBOR!$A:$C,3,0),"Maior que CAP!",IF((DOLLAR(BW6+(VLOOKUP("PCS-OzTL741",ARBOR!$A:$C,3,0)*-TRUNC(BW6/VLOOKUP("PCS-OzTL741",ARBOR!$A:$C,3,0)-1,4)),6))<>(DOLLAR(VLOOKUP("PCS-OzTL741",ARBOR!$A:$C,3,0),6)),-TRUNC(BW6/VLOOKUP("PCS-OzTL741",ARBOR!$A:$C,3,0)-1,4)+0.0001,-TRUNC(BW6/VLOOKUP("PCS-OzTL741",ARBOR!$A:$C,3,0)-1,4))))) | BY6: =IF(ISERROR(IF(BX6="","",VLOOKUP((BC6&BX6&"Template desconto FLAT Plano Principal Oi TV nível conta"),BENEFICIOS!$A:$G,5,0))),"Criar",IF(BX6="","",VLOOKUP((BC6&BX6&"Template desconto FLAT Plano Principal Oi TV nível conta"),BENEFICIOS!$A:$G,5,0))) | CA6: =IF(BZ6=0,"",IF(BZ6=VLOOKUP("PCS-OzTL744",ARBOR!$A:$C,3,0),0.0001,IF(BZ6>VLOOKUP("PCS-OzTL744",ARBOR!$A:$C,3,0),"Maior que CAP!",IF((DOLLAR(BZ6+(VLOOKUP("PCS-OzTL744",ARBOR!$A:$C,3,0)*-TRUNC(BZ6/VLOOKUP("PCS-OzTL744",ARBOR!$A:$C,3,0)-1,4)),6))<>(DOLLAR(VLOOKUP("PCS-OzTL744",ARBOR!$A:$C,3,0),6)),-TRUNC(BZ6/VLOOKUP("PCS-OzTL744",ARBOR!$A:$C,3,0)-1,4)+0.0001,-TRUNC(BZ6/VLOOKUP("PCS-OzTL744",ARBOR!$A:$C,3,0)-1,4))))) | CB6: =IF(ISERROR(IF(CA6="","",VLOOKUP(($BC6&CA6&"Template desconto FLAT Plano Principal Oi TV nível conta"),BENEFICIOS!$A:$G,5,0))),"Criar",IF(CA6="","",VLOOKUP(($BC6&CA6&"Template desconto FLAT Plano Principal Oi TV nível conta"),BENEFICIOS!$A:$G,5,0))) | CD6: =IF(CC6=0,"",IF(CC6=VLOOKUP("PCS-OzTL743",ARBOR!$A:$C,3,0),0.0001,IF(CC6>VLOOKUP("PCS-OzTL743",ARBOR!$A:$C,3,0),"Maior que CAP!",IF((DOLLAR(CC6+(VLOOKUP("PCS-OzTL743",ARBOR!$A:$C,3,0)*-TRUNC(CC6/VLOOKUP("PCS-OzTL743",ARBOR!$A:$C,3,0)-1,4)),6))<>(DOLLAR(VLOOKUP("PCS-OzTL743",ARBOR!$A:$C,3,0),6)),-TRUNC(CC6/VLOOKUP("PCS-OzTL743",ARBOR!$A:$C,3,0)-1,4)+0.0001,-TRUNC(CC6/VLOOKUP("PCS-OzTL743",ARBOR!$A:$C,3,0)-1,4))))) | CE6: =IF(ISERROR(IF(CD6="","",VLOOKUP(($BC6&CD6&"Template desconto FLAT Plano Principal Oi TV nível conta"),BENEFICIOS!$A:$G,5,0))),"Criar",IF(CD6="","",VLOOKUP(($BC6&CD6&"Template desconto FLAT Plano Principal Oi TV nível conta"),BENEFICIOS!$A:$G,5,0))) | CG6: =IF(CF6=0,"",IF(CF6=VLOOKUP("PCS-OzTL745",ARBOR!$A:$C,3,0),0.0001,IF(CF6>VLOOKUP("PCS-OzTL745",ARBOR!$A:$C,3,0),"Maior que CAP!",IF((DOLLAR(CF6+(VLOOKUP("PCS-OzTL745",ARBOR!$A:$C,3,0)*-TRUNC(CF6/VLOOKUP("PCS-OzTL745",ARBOR!$A:$C,3,0)-1,4)),6))<>(DOLLAR(VLOOKUP("PCS-OzTL745",ARBOR!$A:$C,3,0),6)),-TRUNC(CF6/VLOOKUP("PCS-OzTL745",ARBOR!$A:$C,3,0)-1,4)+0.0001,-TRUNC(CF6/VLOOKUP("PCS-OzTL745",ARBOR!$A:$C,3,0)-1,4))))) | CH6: =IF(ISERROR(IF(CG6="","",VLOOKUP(($BC6&CG6&"Template desconto FLAT Plano Principal Oi TV nível conta"),BENEFICIOS!$A:$G,5,0))),"Criar",IF(CG6="","",VLOOKUP(($BC6&CG6&"Template desconto FLAT Plano Principal Oi TV nível conta"),BENEFICIOS!$A:$G,5,0))) | CI6: 99.9 | CJ6: =IF(CI6=0,"",IF(CI6=VLOOKUP("PCS-OzTL42",ARBOR!$A:$C,3,0),0.0001,IF(CI6>VLOOKUP("PCS-OzTL42",ARBOR!$A:$C,3,0),"Maior que CAP!",IF((DOLLAR(CI6+(VLOOKUP("PCS-OzTL42",ARBOR!$A:$C,3,0)*-TRUNC(CI6/VLOOKUP("PCS-OzTL42",ARBOR!$A:$C,3,0)-1,4)),6))<>(DOLLAR(VLOOKUP("PCS-OzTL42",ARBOR!$A:$C,3,0),6)),-TRUNC(CI6/VLOOKUP("PCS-OzTL42",ARBOR!$A:$C,3,0)-1,4)+0.0001,-TRUNC(CI6/VLOOKUP("PCS-OzTL42",ARBOR!$A:$C,3,0)-1,4))))) -> 0.3949 | CK6: =IF(ISERROR(IF(CJ6="","",VLOOKUP(($BC6&CJ6&"Template desconto FLAT Plano Principal Oi TV nível conta"),BENEFICIOS!$A:$G,5,0))),"Criar",IF(CJ6="","",VLOOKUP(($BC6&CJ6&"Template desconto FLAT Plano Principal Oi TV nível conta"),BENEFICIOS!$A:$G,5,0))) -> Criar | CM6: =IF(CL6=0,"",IF(CL6=VLOOKUP("PCS-OzTL47",ARBOR!$A:$C,3,0),0.0001,IF(CL6>VLOOKUP("PCS-OzTL47",ARBOR!$A:$C,3,0),"Maior que CAP!",IF((DOLLAR(CL6+(VLOOKUP("PCS-OzTL47",ARBOR!$A:$C,3,0)*-TRUNC(CL6/VLOOKUP("PCS-OzTL47",ARBOR!$A:$C,3,0)-1,4)),6))<>(DOLLAR(VLOOKUP("PCS-OzTL47",ARBOR!$A:$C,3,0),6)),-TRUNC(CL6/VLOOKUP("PCS-OzTL47",ARBOR!$A:$C,3,0)-1,4)+0.0001,-TRUNC(CL6/VLOOKUP("PCS-OzTL47",ARBOR!$A:$C,3,0)-1,4))))) | CN6: =IF(ISERROR(IF(CM6="","",VLOOKUP(($BC6&CM6&"Template desconto FLAT Plano Principal Oi TV nível conta"),BENEFICIOS!$A:$G,5,0))),"Criar",IF(CM6="","",VLOOKUP(($BC6&CM6&"Template desconto FLAT Plano Principal Oi TV nível conta"),BENEFICIOS!$A:$G,5,0))) | CP6: =IF(CO6=0,"",IF(CO6=VLOOKUP("PCS-OzTL46",ARBOR!$A:$C,3,0),0.0001,IF(CO6>VLOOKUP("PCS-OzTL46",ARBOR!$A:$C,3,0),"Maior que CAP!",IF((DOLLAR(CO6+(VLOOKUP("PCS-OzTL46",ARBOR!$A:$C,3,0)*-TRUNC(CO6/VLOOKUP("PCS-OzTL46",ARBOR!$A:$C,3,0)-1,4)),6))<>(DOLLAR(VLOOKUP("PCS-OzTL46",ARBOR!$A:$C,3,0),6)),-TRUNC(CO6/VLOOKUP("PCS-OzTL46",ARBOR!$A:$C,3,0)-1,4)+0.0001,-TRUNC(CO6/VLOOKUP("PCS-OzTL46",ARBOR!$A:$C,3,0)-1,4))))) | CQ6: =IF(ISERROR(IF(CP6="","",VLOOKUP(($BC6&CP6&"Template desconto FLAT Plano Principal Oi TV nível conta"),BENEFICIOS!$A:$G,5,0))),"Criar",IF(CP6="","",VLOOKUP(($BC6&CP6&"Template desconto FLAT Plano Principal Oi TV nível conta"),BENEFICIOS!$A:$G,5,0))) | CS6: =IF(CR6=0,"",IF(CR6=VLOOKUP("PCS-OzTL48",ARBOR!$A:$C,3,0),0.0001,IF(CR6>VLOOKUP("PCS-OzTL48",ARBOR!$A:$C,3,0),"Maior que CAP!",IF((DOLLAR(CR6+(VLOOKUP("PCS-OzTL48",ARBOR!$A:$C,3,0)*-TRUNC(CR6/VLOOKUP("PCS-OzTL48",ARBOR!$A:$C,3,0)-1,4)),6))<>(DOLLAR(VLOOKUP("PCS-OzTL48",ARBOR!$A:$C,3,0),6)),-TRUNC(CR6/VLOOKUP("PCS-OzTL48",ARBOR!$A:$C,3,0)-1,4)+0.0001,-TRUNC(CR6/VLOOKUP("PCS-OzTL48",ARBOR!$A:$C,3,0)-1,4))))) | CT6: =IF(ISERROR(IF(CS6="","",VLOOKUP(($BC6&CS6&"Template desconto FLAT Plano Principal Oi TV nível conta"),BENEFICIOS!$A:$G,5,0))),"Criar",IF(CS6="","",VLOOKUP(($BC6&CS6&"Template desconto FLAT Plano Principal Oi TV nível conta"),BENEFICIOS!$A:$G,5,0))) | CU6: 119.9 | CV6: =IF(CU6=0,"",IF(CU6=VLOOKUP("PCS-OzTL742",ARBOR!$A:$C,3,0),0.0001,IF(CU6>VLOOKUP("PCS-OzTL742",ARBOR!$A:$C,3,0),"Maior que CAP!",IF((DOLLAR(CU6+(VLOOKUP("PCS-OzTL742",ARBOR!$A:$C,3,0)*-TRUNC(CU6/VLOOKUP("PCS-OzTL742",ARBOR!$A:$C,3,0)-1,4)),6))<>(DOLLAR(VLOOKUP("PCS-OzTL742",ARBOR!$A:$C,3,0),6)),-TRUNC(CU6/VLOOKUP("PCS-OzTL742",ARBOR!$A:$C,3,0)-1,4)+0.0001,-TRUNC(CU6/VLOOKUP("PCS-OzTL742",ARBOR!$A:$C,3,0)-1,4))))) -> 0.4554 | CW6: =IF(ISERROR(IF(CV6="","",VLOOKUP(($BC6&CV6&"Template desconto FLAT Plano Principal Oi TV nível conta"),BENEFICIOS!$A:$G,5,0))),"Criar",IF(CV6="","",VLOOKUP(($BC6&CV6&"Template desconto FLAT Plano Principal Oi TV nível conta"),BENEFICIOS!$A:$G,5,0))) -> Criar | CY6: =IF(CX6=0,"",IF(CX6=VLOOKUP("PCS-OzTL747",ARBOR!$A:$C,3,0),0.0001,IF(CX6>VLOOKUP("PCS-OzTL747",ARBOR!$A:$C,3,0),"Maior que CAP!",IF((DOLLAR(CX6+(VLOOKUP("PCS-OzTL747",ARBOR!$A:$C,3,0)*-TRUNC(CX6/VLOOKUP("PCS-OzTL747",ARBOR!$A:$C,3,0)-1,4)),6))<>(DOLLAR(VLOOKUP("PCS-OzTL747",ARBOR!$A:$C,3,0),6)),-TRUNC(CX6/VLOOKUP("PCS-OzTL747",ARBOR!$A:$C,3,0)-1,4)+0.0001,-TRUNC(CX6/VLOOKUP("PCS-OzTL747",ARBOR!$A:$C,3,0)-1,4))))) | CZ6: =IF(ISERROR(IF(CY6="","",VLOOKUP(($BC6&CY6&"Template desconto FLAT Plano Principal Oi TV nível conta"),BENEFICIOS!$A:$G,5,0))),"Criar",IF(CY6="","",VLOOKUP(($BC6&CY6&"Template desconto FLAT Plano Principal Oi TV nível conta"),BENEFICIOS!$A:$G,5,0))) | DB6: =IF(DA6=0,"",IF(DA6=VLOOKUP("PCS-OzTL746",ARBOR!$A:$C,3,0),0.0001,IF(DA6>VLOOKUP("PCS-OzTL746",ARBOR!$A:$C,3,0),"Maior que CAP!",IF((DOLLAR(DA6+(VLOOKUP("PCS-OzTL746",ARBOR!$A:$C,3,0)*-TRUNC(DA6/VLOOKUP("PCS-OzTL746",ARBOR!$A:$C,3,0)-1,4)),6))<>(DOLLAR(VLOOKUP("PCS-OzTL746",ARBOR!$A:$C,3,0),6)),-TRUNC(DA6/VLOOKUP("PCS-OzTL746",ARBOR!$A:$C,3,0)-1,4)+0.0001,-TRUNC(DA6/VLOOKUP("PCS-OzTL746",ARBOR!$A:$C,3,0)-1,4))))) | DC6: =IF(ISERROR(IF(DB6="","",VLOOKUP(($BC6&DB6&"Template desconto FLAT Plano Principal Oi TV nível conta"),BENEFICIOS!$A:$G,5,0))),"Criar",IF(DB6="","",VLOOKUP(($BC6&DB6&"Template desconto FLAT Plano Principal Oi TV nível conta"),BENEFICIOS!$A:$G,5,0))) | DE6: =IF(DD6=0,"",IF(DD6=VLOOKUP("PCS-OzTL748",ARBOR!$A:$C,3,0),0.0001,IF(DD6>VLOOKUP("PCS-OzTL748",ARBOR!$A:$C,3,0),"Maior que CAP!",IF((DOLLAR(DD6+(VLOOKUP("PCS-OzTL748",ARBOR!$A:$C,3,0)*-TRUNC(DD6/VLOOKUP("PCS-OzTL748",ARBOR!$A:$C,3,0)-1,4)),6))<>(DOLLAR(VLOOKUP("PCS-OzTL748",ARBOR!$A:$C,3,0),6)),-TRUNC(DD6/VLOOKUP("PCS-OzTL748",ARBOR!$A:$C,3,0)-1,4)+0.0001,-TRUNC(DD6/VLOOKUP("PCS-OzTL748",ARBOR!$A:$C,3,0)-1,4))))) | DF6: =IF(ISERROR(IF(DE6="","",VLOOKUP(($BC6&DE6&"Template desconto FLAT Plano Principal Oi TV nível conta"),BENEFICIOS!$A:$G,5,0))),"Criar",IF(DE6="","",VLOOKUP(($BC6&DE6&"Template desconto FLAT Plano Principal Oi TV nível conta"),BENEFICIOS!$A:$G,5,0))) | DG6: 75 | DH6: =IF(DG6=0,"",IF(DG6=VLOOKUP("PCS-OzTL34",ARBOR!$A:$C,3,0),0.0001,IF(DG6>VLOOKUP("PCS-OzTL34",ARBOR!$A:$C,3,0),"Maior que CAP!",IF((DOLLAR(DG6+(VLOOKUP("PCS-OzTL34",ARBOR!$A:$C,3,0)*-TRUNC(DG6/VLOOKUP("PCS-OzTL34",ARBOR!$A:$C,3,0)-1,4)),6))<>(DOLLAR(VLOOKUP("PCS-OzTL34",ARBOR!$A:$C,3,0),6)),-TRUNC(DG6/VLOOKUP("PCS-OzTL34",ARBOR!$A:$C,3,0)-1,4)+0.0001,-TRUNC(DG6/VLOOKUP("PCS-OzTL34",ARBOR!$A:$C,3,0)-1,4))))) -> 0.319 | DI6: =IF(DH6="S/Desc","S/Desc",IF(ISERROR(IF(DH6="","",VLOOKUP(($BC6&DH6&"Template desconto % Combate nível conta"),BENEFICIOS!$A:$G,5,0))),"Criar",IF(DH6="","",VLOOKUP(($BC6&DH6&"Template desconto % Combate nível conta"),BENEFICIOS!$A:$G,5,0)))) -> Criar | DJ6: 19.9 | DK6: =IF(DJ6=0,"",IF(DJ6=VLOOKUP("PCS-OzTL31",ARBOR!$A:$C,3,0),0.0001,IF(DJ6>VLOOKUP("PCS-OzTL31",ARBOR!$A:$C,3,0),"Maior que CAP!",IF((DOLLAR(DJ6+(VLOOKUP("PCS-OzTL31",ARBOR!$A:$C,3,0)*-TRUNC(DJ6/VLOOKUP("PCS-OzTL31",ARBOR!$A:$C,3,0)-1,4)),6))<>(DOLLAR(VLOOKUP("PCS-OzTL31",ARBOR!$A:$C,3,0),6)),-TRUNC(DJ6/VLOOKUP("PCS-OzTL31",ARBOR!$A:$C,3,0)-1,4)+0.0001,-TRUNC(DJ6/VLOOKUP("PCS-OzTL31",ARBOR!$A:$C,3,0)-1,4))))) -> 0.0918 | DL6: =IF(DK6="S/Desc","S/Desc",IF(ISERROR(IF(DK6="","",VLOOKUP(($BC6&DK6&"Template desconto % Sexy Hot nível conta"),BENEFICIOS!$A:$G,5,0))),"Criar",IF(DK6="","",VLOOKUP(($BC6&DK6&"Template desconto % Sexy Hot nível conta"),BENEFICIOS!$A:$G,5,0)))) -> Criar | DM6: 19.9 | DN6: =IF(DM6=0,"",IF(DM6=VLOOKUP("PCS-OzTL32",ARBOR!$A:$C,3,0),0.0001,IF(DM6>VLOOKUP("PCS-OzTL32",ARBOR!$A:$C,3,0),"Maior que CAP!",IF((DOLLAR(DM6+(VLOOKUP("PCS-OzTL32",ARBOR!$A:$C,3,0)*-TRUNC(DM6/VLOOKUP("PCS-OzTL32",ARBOR!$A:$C,3,0)-1,4)),6))<>(DOLLAR(VLOOKUP("PCS-OzTL32",ARBOR!$A:$C,3,0),6)),-TRUNC(DM6/VLOOKUP("PCS-OzTL32",ARBOR!$A:$C,3,0)-1,4)+0.0001,-TRUNC(DM6/VLOOKUP("PCS-OzTL32",ARBOR!$A:$C,3,0)-1,4))))) -> 0.0918 | DO6: =IF(DN6="S/Desc","S/Desc",IF(ISERROR(IF(DN6="","",VLOOKUP(($BC6&DN6&"Template desconto % Playboy nível conta"),BENEFICIOS!$A:$G,5,0))),"Criar",IF(DN6="","",VLOOKUP(($BC6&DN6&"Template desconto % Playboy nível conta"),BENEFICIOS!$A:$G,5,0)))) -> Criar | DP6: 29.9 | DQ6: =IF(DP6=0,"",IF(DP6=VLOOKUP("PCS-OzTL33",ARBOR!$A:$C,3,0),0.0001,IF(DP6>VLOOKUP("PCS-OzTL33",ARBOR!$A:$C,3,0),"Maior que CAP!",IF((DOLLAR(DP6+(VLOOKUP("PCS-OzTL33",ARBOR!$A:$C,3,0)*-TRUNC(DP6/VLOOKUP("PCS-OzTL33",ARBOR!$A:$C,3,0)-1,4)),6))<>(DOLLAR(VLOOKUP("PCS-OzTL33",ARBOR!$A:$C,3,0),6)),-TRUNC(DP6/VLOOKUP("PCS-OzTL33",ARBOR!$A:$C,3,0)-1,4)+0.0001,-TRUNC(DP6/VLOOKUP("PCS-OzTL33",ARBOR!$A:$C,3,0)-1,4))))) -> 0.0918 | DR6: =IF(DQ6="S/Desc","S/Desc",IF(ISERROR(IF(DQ6="","",VLOOKUP(($BC6&DQ6&"Template desconto % Sexy Hot + Playboy nível conta"),BENEFICIOS!$A:$G,5,0))),"Criar",IF(DQ6="","",VLOOKUP(($BC6&DQ6&"Template desconto % Sexy Hot + Playboy nível conta"),BENEFICIOS!$A:$G,5,0)))) -> Criar | DS6: 14.9 | DT6: =IF(DS6=0,"",IF(DS6=VLOOKUP("PCS-OzTL503",ARBOR!$A:$C,3,0),0.0001,IF(DS6>VLOOKUP("PCS-OzTL503",ARBOR!$A:$C,3,0),"Maior que CAP!",IF((DOLLAR(DS6+(VLOOKUP("PCS-OzTL503",ARBOR!$A:$C,3,0)*-TRUNC(DS6/VLOOKUP("PCS-OzTL503",ARBOR!$A:$C,3,0)-1,4)),6))<>(DOLLAR(VLOOKUP("PCS-OzTL503",ARBOR!$A:$C,3,0),6)),-TRUNC(DS6/VLOOKUP("PCS-OzTL503",ARBOR!$A:$C,3,0)-1,4)+0.0001,-TRUNC(DS6/VLOOKUP("PCS-OzTL503",ARBOR!$A:$C,3,0)-1,4))))) -> 0.0915 | DU6: =IF(DT6="S/Desc","S/Desc",IF(ISERROR(IF(DT6="","",VLOOKUP(($BC6&DT6&"Template desconto % SexPrivê nível conta"),BENEFICIOS!$A:$G,5,0))),"Criar",IF(DT6="","",VLOOKUP(($BC6&DT6&"Template desconto % SexPrivê nível conta"),BENEFICIOS!$A:$G,5,0)))) -> Criar | DV6: 10 | DW6: =IF(DV6=0,"",IF(DV6=VLOOKUP("PCS-OzTL500",ARBOR!$A:$C,3,0),0.0001,IF(DV6>VLOOKUP("PCS-OzTL500",ARBOR!$A:$C,3,0),"Maior que CAP!",IF((DOLLAR(DV6+(VLOOKUP("PCS-OzTL500",ARBOR!$A:$C,3,0)*-TRUNC(DV6/VLOOKUP("PCS-OzTL500",ARBOR!$A:$C,3,0)-1,4)),6))<>(DOLLAR(VLOOKUP("PCS-OzTL500",ARBOR!$A:$C,3,0),6)),-TRUNC(DV6/VLOOKUP("PCS-OzTL500",ARBOR!$A:$C,3,0)-1,4)+0.0001,-TRUNC(DV6/VLOOKUP("PCS-OzTL500",ARBOR!$A:$C,3,0)-1,4))))) -> 0.0918 | DX6: =IF(DW6="S/Desc","S/Desc",IF(ISERROR(IF(DW6="","",VLOOKUP(($BC6&DW6&"Template desconto % Étnico nível conta"),BENEFICIOS!$A:$G,5,0))),"Criar",IF(DW6="","",VLOOKUP(($BC6&DW6&"Template desconto % Étnico nível conta"),BENEFICIOS!$A:$G,5,0)))) -> Criar | DZ6: =IF(DY6=0,"",IF(DY6=VLOOKUP("PCS-OzTL50",ARBOR!$A:$C,3,0),0.0001,IF(DY6>VLOOKUP("PCS-OzTL50",ARBOR!$A:$C,3,0),"Maior que CAP!",IF((DOLLAR(DY6+(VLOOKUP("PCS-OzTL50",ARBOR!$A:$C,3,0)*-TRUNC(DY6/VLOOKUP("PCS-OzTL50",ARBOR!$A:$C,3,0)-1,4)),6))<>(DOLLAR(VLOOKUP("PCS-OzTL50",ARBOR!$A:$C,3,0),6)),-TRUNC(DY6/VLOOKUP("PCS-OzTL50",ARBOR!$A:$C,3,0)-1,4)+0.0001,-TRUNC(DY6/VLOOKUP("PCS-OzTL50",ARBOR!$A:$C,3,0)-1,4))))) | EC6: =IF(EB6=0,"",IF(EB6=VLOOKUP("PCS-OzTL51",ARBOR!$A:$C,3,0),0.0001,IF(EB6>VLOOKUP("PCS-OzTL51",ARBOR!$A:$C,3,0),"Maior que CAP!",IF((DOLLAR(EB6+(VLOOKUP("PCS-OzTL51",ARBOR!$A:$C,3,0)*-TRUNC(EB6/VLOOKUP("PCS-OzTL51",ARBOR!$A:$C,3,0)-1,4)),6))<>(DOLLAR(VLOOKUP("PCS-OzTL51",ARBOR!$A:$C,3,0),6)),-TRUNC(EB6/VLOOKUP("PCS-OzTL51",ARBOR!$A:$C,3,0)-1,4)+0.0001,-TRUNC(EB6/VLOOKUP("PCS-OzTL51",ARBOR!$A:$C,3,0)-1,4))))) | EF6: =IF(EE6=0,"",IF(EE6=VLOOKUP("PCS-OzTL52",ARBOR!$A:$C,3,0),0.0001,IF(EE6>VLOOKUP("PCS-OzTL52",ARBOR!$A:$C,3,0),"Maior que CAP!",IF((DOLLAR(EE6+(VLOOKUP("PCS-OzTL52",ARBOR!$A:$C,3,0)*-TRUNC(EE6/VLOOKUP("PCS-OzTL52",ARBOR!$A:$C,3,0)-1,4)),6))<>(DOLLAR(VLOOKUP("PCS-OzTL52",ARBOR!$A:$C,3,0),6)),-TRUNC(EE6/VLOOKUP("PCS-OzTL52",ARBOR!$A:$C,3,0)-1,4)+0.0001,-TRUNC(EE6/VLOOKUP("PCS-OzTL52",ARBOR!$A:$C,3,0)-1,4))))) | EI6: =IF(EH6=0,"",IF(EH6=VLOOKUP("PCS-OzTL53",ARBOR!$A:$C,3,0),0.0001,IF(EH6>VLOOKUP("PCS-OzTL53",ARBOR!$A:$C,3,0),"Maior que CAP!",IF((DOLLAR(EH6+(VLOOKUP("PCS-OzTL53",ARBOR!$A:$C,3,0)*-TRUNC(EH6/VLOOKUP("PCS-OzTL53",ARBOR!$A:$C,3,0)-1,4)),6))<>(DOLLAR(VLOOKUP("PCS-OzTL53",ARBOR!$A:$C,3,0),6)),-TRUNC(EH6/VLOOKUP("PCS-OzTL53",ARBOR!$A:$C,3,0)-1,4)+0.0001,-TRUNC(EH6/VLOOKUP("PCS-OzTL53",ARBOR!$A:$C,3,0)-1,4))))) | EL6: =IF(EK6=0,"",IF(EK6=VLOOKUP("PCS-OzTL54",ARBOR!$A:$C,3,0),0.0001,IF(EK6>VLOOKUP("PCS-OzTL54",ARBOR!$A:$C,3,0),"Maior que CAP!",IF((DOLLAR(EK6+(VLOOKUP("PCS-OzTL54",ARBOR!$A:$C,3,0)*-TRUNC(EK6/VLOOKUP("PCS-OzTL54",ARBOR!$A:$C,3,0)-1,4)),6))<>(DOLLAR(VLOOKUP("PCS-OzTL54",ARBOR!$A:$C,3,0),6)),-TRUNC(EK6/VLOOKUP("PCS-OzTL54",ARBOR!$A:$C,3,0)-1,4)+0.0001,-TRUNC(EK6/VLOOKUP("PCS-OzTL54",ARBOR!$A:$C,3,0)-1,4))))) | EN6: 24.9 | EO6: =IF(EN6=0,"",IF(EN6=VLOOKUP("PCS-OzTL99",ARBOR!$A:$C,3,0),0.0001,IF(EN6>VLOOKUP("PCS-OzTL99",ARBOR!$A:$C,3,0),"Maior que CAP!",IF((DOLLAR(EN6+(VLOOKUP("PCS-OzTL99",ARBOR!$A:$C,3,0)*-TRUNC(EN6/VLOOKUP("PCS-OzTL99",ARBOR!$A:$C,3,0)-1,4)),6))<>(DOLLAR(VLOOKUP("PCS-OzTL99",ARBOR!$A:$C,3,0),6)),-TRUNC(EN6/VLOOKUP("PCS-OzTL99",ARBOR!$A:$C,3,0)-1,4)+0.0001,-TRUNC(EN6/VLOOKUP("PCS-OzTL99",ARBOR!$A:$C,3,0)-1,4))))) -> 0.1673 | EP6: =IF(EO6="S/Desc","S/Desc",IF(ISERROR(IF(EO6="","",VLOOKUP(($BC6&EO6&"Template desconto % Ponto adicional nível conta"),BENEFICIOS!$A:$G,5,0))),"Criar",IF(EO6="","",VLOOKUP(($BC6&EO6&"Template desconto % Ponto adicional nível conta"),BENEFICIOS!$A:$G,5,0)))) -> Criar | ER6: =IF(EQ6="Sim","PCS-34704","") | ES6: Sim | ET6: Benefício | EU6: 499 | EV6: 12 | EW6: =IF(ET6="Benefício","Oi benefício fidelização Multiprodutos","") -> Oi benefício fidelização Multiprodutos | EX6: =IF(ET6="Benefício","PCS-Fk83324","") -> PCS-Fk83324 | EY6: =IF(ES6="Sim","PCS-SBL553142","") -> PCS-SBL553142 | EZ6: LD + VC Oi | FA6: 0T0T_FTV_MIN_LD_270000. | FG6: =IF($BH6="","",$BH6+$BE6) | FH6: =IF($BK6="","",$BK6+$BE6) -> 134.9 | FI6: =IF($BN6="","",$BN6+$BE6) | FJ6: =IF($BQ6="","",$BQ6+$BE6) | FK6: =IF($BT6="","",$BT6+$BE6) | FL6: =IF($BW6="","",$BW6+$BE6) | FM6: =IF($BZ6="","",$BZ6+$BE6) | FN6: =IF($CC6="","",$CC6+$BE6) | FO6: =IF($CF6="","",$CF6+$BE6) | FP6: =IF($CI6="","",$CI6+$BE6) -> 144.9 | FQ6: =IF($CL6="","",$CL6+$BE6) | FR6: =IF($CO6="","",$CO6+$BE6) | FS6: =IF($CR6="","",$CR6+$BE6) | FT6: =IF($CU6="","",$CU6+$BE6) -> 164.9 | FU6: =IF($CX6="","",$CX6+$BE6) | FV6: =IF($DA6="","",$DA6+$BE6) | FW6: =IF($DD6="","",$DD6+$BE6)
A7: Oi Total | B7: Migração | C7: Atuais | D7: Não | AM7: OT_ATV_JUL17_FID_DACC_2PTV_TV3_MF-TF_LD-VC_OF2 | AN7: Rentabilizar atuais clientes do plano | AO7: Produto Fixo + TV , Produto com fidelização | AP7: 42917 | AQ7: 43039 | AR7: 20. Oi Total | AS7: 20. Oi Total | AU7: Varejo | AV7: 20 | AW7: 10000 | AX7: Campanha Restrita | AY7: Sim | AZ7: Sim | BA7: Não | BB7: OT_ATV_JUL17_FID_DACC_2PTV_TV3_MF-TF_LD-VC_OF2 | BC7: Oi Total Fixo + TV 3 | BD7: =IF(BC7="Oi Total Fixo + TV 1","CFG-2Plowpi",IF(BC7="Oi Total Fixo + TV 2","PCS-2PMepi",IF(BC7="Oi Total Fixo + TV 3","PCS-2PHipi",""))) -> PCS-2PHipi | BE7: 45 | BF7: =IF(BE7=0,"",IF(BE7=VLOOKUP("FIXO",ARBOR!$A:$C,3,0),0.0001,IF(BE7>VLOOKUP("FIXO",ARBOR!$A:$C,3,0),"Maior que CAP!",IF((DOLLAR(BE7+(VLOOKUP("FIXO",ARBOR!$A:$C,3,0)*-TRUNC(BE7/VLOOKUP("FIXO",ARBOR!$A:$C,3,0)-1,4)),6))<>(DOLLAR(VLOOKUP("FIXO",ARBOR!$A:$C,3,0),6)),-TRUNC(BE7/VLOOKUP("FIXO",ARBOR!$A:$C,3,0)-1,4)+0.0001,-TRUNC(BE7/VLOOKUP("FIXO",ARBOR!$A:$C,3,0)-1,4))))) -> 0.4067 | BG7: =IF(ISERROR(IF(BF7="","",VLOOKUP(($BC7&BF7&"Template de desconto FLAT bundle - Fixo - Varejo - Ganho Tributário Cross"),BENEFICIOS!$A:$G,5,0))),"Criar",IF(BF7="","",VLOOKUP(($BC7&BF7&"Template de desconto FLAT bundle - Fixo - Varejo - Ganho Tributário Cross"),BENEFICIOS!$A:$G,5,0))) -> Criar | BI7: =IF(BH7=0,"",IF(BH7=VLOOKUP("PCS-OzTL40",ARBOR!$A:$C,3,0),0.0001,IF(BH7>VLOOKUP("PCS-OzTL40",ARBOR!$A:$C,3,0),"Maior que CAP!",IF((DOLLAR(BH7+(VLOOKUP("PCS-OzTL40",ARBOR!$A:$C,3,0)*-TRUNC(BH7/VLOOKUP("PCS-OzTL40",ARBOR!$A:$C,3,0)-1,4)),6))<>(DOLLAR(VLOOKUP("PCS-OzTL40",ARBOR!$A:$C,3,0),6)),-TRUNC(BH7/VLOOKUP("PCS-OzTL40",ARBOR!$A:$C,3,0)-1,4)+0.0001,-TRUNC(BH7/VLOOKUP("PCS-OzTL40",ARBOR!$A:$C,3,0)-1,4))))) | BJ7: =IF(ISERROR(IF(BI7="","",VLOOKUP((BC7&BI7&"Template desconto FLAT Plano Principal Oi TV nível conta"),BENEFICIOS!$A:$G,5,0))),"Criar",IF(BI7="","",VLOOKUP((BC7&BI7&"Template desconto FLAT Plano Principal Oi TV nível conta"),BENEFICIOS!$A:$G,5,0))) | BL7: =IF(BK7=0,"",IF(BK7=VLOOKUP("PCS-OzTL41",ARBOR!$A:$C,3,0),0.0001,IF(BK7>VLOOKUP("PCS-OzTL41",ARBOR!$A:$C,3,0),"Maior que CAP!",IF((DOLLAR(BK7+(VLOOKUP("PCS-OzTL41",ARBOR!$A:$C,3,0)*-TRUNC(BK7/VLOOKUP("PCS-OzTL41",ARBOR!$A:$C,3,0)-1,4)),6))<>(DOLLAR(VLOOKUP("PCS-OzTL41",ARBOR!$A:$C,3,0),6)),-TRUNC(BK7/VLOOKUP("PCS-OzTL41",ARBOR!$A:$C,3,0)-1,4)+0.0001,-TRUNC(BK7/VLOOKUP("PCS-OzTL41",ARBOR!$A:$C,3,0)-1,4))))) | BM7: =IF(ISERROR(IF(BL7="","",VLOOKUP((BC7&BL7&"Template desconto FLAT Plano Principal Oi TV nível conta"),BENEFICIOS!$A:$G,5,0))),"Criar",IF(BL7="","",VLOOKUP((BC7&BL7&"Template desconto FLAT Plano Principal Oi TV nível conta"),BENEFICIOS!$A:$G,5,0))) | BN7: 119.9 | BO7: =IF(BN7=0,"",IF(BN7=VLOOKUP("PCS-OzTL44",ARBOR!$A:$C,3,0),0.0001,IF(BN7>VLOOKUP("PCS-OzTL44",ARBOR!$A:$C,3,0),"Maior que CAP!",IF((DOLLAR(BN7+(VLOOKUP("PCS-OzTL44",ARBOR!$A:$C,3,0)*-TRUNC(BN7/VLOOKUP("PCS-OzTL44",ARBOR!$A:$C,3,0)-1,4)),6))<>(DOLLAR(VLOOKUP("PCS-OzTL44",ARBOR!$A:$C,3,0),6)),-TRUNC(BN7/VLOOKUP("PCS-OzTL44",ARBOR!$A:$C,3,0)-1,4)+0.0001,-TRUNC(BN7/VLOOKUP("PCS-OzTL44",ARBOR!$A:$C,3,0)-1,4))))) -> 0.3775 | BP7: =IF(ISERROR(IF(BO7="","",VLOOKUP((BC7&BO7&"Template desconto FLAT Plano Principal Oi TV nível conta"),BENEFICIOS!$A:$G,5,0))),"Criar",IF(BO7="","",VLOOKUP((BC7&BO7&"Template desconto FLAT Plano Principal Oi TV nível conta"),BENEFICIOS!$A:$G,5,0))) -> Criar | BQ7: 119.9 | BR7: =IF(BQ7=0,"",IF(BQ7=VLOOKUP("PCS-OzTL43",ARBOR!$A:$C,3,0),0.0001,IF(BQ7>VLOOKUP("PCS-OzTL43",ARBOR!$A:$C,3,0),"Maior que CAP!",IF((DOLLAR(BQ7+(VLOOKUP("PCS-OzTL43",ARBOR!$A:$C,3,0)*-TRUNC(BQ7/VLOOKUP("PCS-OzTL43",ARBOR!$A:$C,3,0)-1,4)),6))<>(DOLLAR(VLOOKUP("PCS-OzTL43",ARBOR!$A:$C,3,0),6)),-TRUNC(BQ7/VLOOKUP("PCS-OzTL43",ARBOR!$A:$C,3,0)-1,4)+0.0001,-TRUNC(BQ7/VLOOKUP("PCS-OzTL43",ARBOR!$A:$C,3,0)-1,4))))) -> 0.4112 | BS7: =IF(ISERROR(IF(BR7="","",VLOOKUP((BC7&BR7&"Template desconto FLAT Plano Principal Oi TV nível conta"),BENEFICIOS!$A:$G,5,0))),"Criar",IF(BR7="","",VLOOKUP((BC7&BR7&"Template desconto FLAT Plano Principal Oi TV nível conta"),BENEFICIOS!$A:$G,5,0))) -> Criar | BT7: 149.9 | BU7: =IF(BT7=0,"",IF(BT7=VLOOKUP("PCS-OzTL45",ARBOR!$A:$C,3,0),0.0001,IF(BT7>VLOOKUP("PCS-OzTL45",ARBOR!$A:$C,3,0),"Maior que CAP!",IF((DOLLAR(BT7+(VLOOKUP("PCS-OzTL45",ARBOR!$A:$C,3,0)*-TRUNC(BT7/VLOOKUP("PCS-OzTL45",ARBOR!$A:$C,3,0)-1,4)),6))<>(DOLLAR(VLOOKUP("PCS-OzTL45",ARBOR!$A:$C,3,0),6)),-TRUNC(BT7/VLOOKUP("PCS-OzTL45",ARBOR!$A:$C,3,0)-1,4)+0.0001,-TRUNC(BT7/VLOOKUP("PCS-OzTL45",ARBOR!$A:$C,3,0)-1,4))))) -> 0.2833 | BV7: =IF(ISERROR(IF(BU7="","",VLOOKUP((BC7&BU7&"Template desconto FLAT Plano Principal Oi TV nível conta"),BENEFICIOS!$A:$G,5,0))),"Criar",IF(BU7="","",VLOOKUP((BC7&BU7&"Template desconto FLAT Plano Principal Oi TV nível conta"),BENEFICIOS!$A:$G,5,0))) -> Criar | BX7: =IF(BW7=0,"",IF(BW7=VLOOKUP("PCS-OzTL741",ARBOR!$A:$C,3,0),0.0001,IF(BW7>VLOOKUP("PCS-OzTL741",ARBOR!$A:$C,3,0),"Maior que CAP!",IF((DOLLAR(BW7+(VLOOKUP("PCS-OzTL741",ARBOR!$A:$C,3,0)*-TRUNC(BW7/VLOOKUP("PCS-OzTL741",ARBOR!$A:$C,3,0)-1,4)),6))<>(DOLLAR(VLOOKUP("PCS-OzTL741",ARBOR!$A:$C,3,0),6)),-TRUNC(BW7/VLOOKUP("PCS-OzTL741",ARBOR!$A:$C,3,0)-1,4)+0.0001,-TRUNC(BW7/VLOOKUP("PCS-OzTL741",ARBOR!$A:$C,3,0)-1,4))))) | BY7: =IF(ISERROR(IF(BX7="","",VLOOKUP((BC7&BX7&"Template desconto FLAT Plano Principal Oi TV nível conta"),BENEFICIOS!$A:$G,5,0))),"Criar",IF(BX7="","",VLOOKUP((BC7&BX7&"Template desconto FLAT Plano Principal Oi TV nível conta"),BENEFICIOS!$A:$G,5,0))) | CA7: =IF(BZ7=0,"",IF(BZ7=VLOOKUP("PCS-OzTL744",ARBOR!$A:$C,3,0),0.0001,IF(BZ7>VLOOKUP("PCS-OzTL744",ARBOR!$A:$C,3,0),"Maior que CAP!",IF((DOLLAR(BZ7+(VLOOKUP("PCS-OzTL744",ARBOR!$A:$C,3,0)*-TRUNC(BZ7/VLOOKUP("PCS-OzTL744",ARBOR!$A:$C,3,0)-1,4)),6))<>(DOLLAR(VLOOKUP("PCS-OzTL744",ARBOR!$A:$C,3,0),6)),-TRUNC(BZ7/VLOOKUP("PCS-OzTL744",ARBOR!$A:$C,3,0)-1,4)+0.0001,-TRUNC(BZ7/VLOOKUP("PCS-OzTL744",ARBOR!$A:$C,3,0)-1,4))))) | CB7: =IF(ISERROR(IF(CA7="","",VLOOKUP(($BC7&CA7&"Template desconto FLAT Plano Principal Oi TV nível conta"),BENEFICIOS!$A:$G,5,0))),"Criar",IF(CA7="","",VLOOKUP(($BC7&CA7&"Template desconto FLAT Plano Principal Oi TV nível conta"),BENEFICIOS!$A:$G,5,0))) | CD7: =IF(CC7=0,"",IF(CC7=VLOOKUP("PCS-OzTL743",ARBOR!$A:$C,3,0),0.0001,IF(CC7>VLOOKUP("PCS-OzTL743",ARBOR!$A:$C,3,0),"Maior que CAP!",IF((DOLLAR(CC7+(VLOOKUP("PCS-OzTL743",ARBOR!$A:$C,3,0)*-TRUNC(CC7/VLOOKUP("PCS-OzTL743",ARBOR!$A:$C,3,0)-1,4)),6))<>(DOLLAR(VLOOKUP("PCS-OzTL743",ARBOR!$A:$C,3,0),6)),-TRUNC(CC7/VLOOKUP("PCS-OzTL743",ARBOR!$A:$C,3,0)-1,4)+0.0001,-TRUNC(CC7/VLOOKUP("PCS-OzTL743",ARBOR!$A:$C,3,0)-1,4))))) | CE7: =IF(ISERROR(IF(CD7="","",VLOOKUP(($BC7&CD7&"Template desconto FLAT Plano Principal Oi TV nível conta"),BENEFICIOS!$A:$G,5,0))),"Criar",IF(CD7="","",VLOOKUP(($BC7&CD7&"Template desconto FLAT Plano Principal Oi TV nível conta"),BENEFICIOS!$A:$G,5,0))) | CG7: =IF(CF7=0,"",IF(CF7=VLOOKUP("PCS-OzTL745",ARBOR!$A:$C,3,0),0.0001,IF(CF7>VLOOKUP("PCS-OzTL745",ARBOR!$A:$C,3,0),"Maior que CAP!",IF((DOLLAR(CF7+(VLOOKUP("PCS-OzTL745",ARBOR!$A:$C,3,0)*-TRUNC(CF7/VLOOKUP("PCS-OzTL745",ARBOR!$A:$C,3,0)-1,4)),6))<>(DOLLAR(VLOOKUP("PCS-OzTL745",ARBOR!$A:$C,3,0),6)),-TRUNC(CF7/VLOOKUP("PCS-OzTL745",ARBOR!$A:$C,3,0)-1,4)+0.0001,-TRUNC(CF7/VLOOKUP("PCS-OzTL745",ARBOR!$A:$C,3,0)-1,4))))) | CH7: =IF(ISERROR(IF(CG7="","",VLOOKUP(($BC7&CG7&"Template desconto FLAT Plano Principal Oi TV nível conta"),BENEFICIOS!$A:$G,5,0))),"Criar",IF(CG7="","",VLOOKUP(($BC7&CG7&"Template desconto FLAT Plano Principal Oi TV nível conta"),BENEFICIOS!$A:$G,5,0))) | CJ7: =IF(CI7=0,"",IF(CI7=VLOOKUP("PCS-OzTL42",ARBOR!$A:$C,3,0),0.0001,IF(CI7>VLOOKUP("PCS-OzTL42",ARBOR!$A:$C,3,0),"Maior que CAP!",IF((DOLLAR(CI7+(VLOOKUP("PCS-OzTL42",ARBOR!$A:$C,3,0)*-TRUNC(CI7/VLOOKUP("PCS-OzTL42",ARBOR!$A:$C,3,0)-1,4)),6))<>(DOLLAR(VLOOKUP("PCS-OzTL42",ARBOR!$A:$C,3,0),6)),-TRUNC(CI7/VLOOKUP("PCS-OzTL42",ARBOR!$A:$C,3,0)-1,4)+0.0001,-TRUNC(CI7/VLOOKUP("PCS-OzTL42",ARBOR!$A:$C,3,0)-1,4))))) | CK7: =IF(ISERROR(IF(CJ7="","",VLOOKUP(($BC7&CJ7&"Template desconto FLAT Plano Principal Oi TV nível conta"),BENEFICIOS!$A:$G,5,0))),"Criar",IF(CJ7="","",VLOOKUP(($BC7&CJ7&"Template desconto FLAT Plano Principal Oi TV nível conta"),BENEFICIOS!$A:$G,5,0))) | CL7: 129.9 | CM7: =IF(CL7=0,"",IF(CL7=VLOOKUP("PCS-OzTL47",ARBOR!$A:$C,3,0),0.0001,IF(CL7>VLOOKUP("PCS-OzTL47",ARBOR!$A:$C,3,0),"Maior que CAP!",IF((DOLLAR(CL7+(VLOOKUP("PCS-OzTL47",ARBOR!$A:$C,3,0)*-TRUNC(CL7/VLOOKUP("PCS-OzTL47",ARBOR!$A:$C,3,0)-1,4)),6))<>(DOLLAR(VLOOKUP("PCS-OzTL47",ARBOR!$A:$C,3,0),6)),-TRUNC(CL7/VLOOKUP("PCS-OzTL47",ARBOR!$A:$C,3,0)-1,4)+0.0001,-TRUNC(CL7/VLOOKUP("PCS-OzTL47",ARBOR!$A:$C,3,0)-1,4))))) -> 0.3621 | CN7: =IF(ISERROR(IF(CM7="","",VLOOKUP(($BC7&CM7&"Template desconto FLAT Plano Principal Oi TV nível conta"),BENEFICIOS!$A:$G,5,0))),"Criar",IF(CM7="","",VLOOKUP(($BC7&CM7&"Template desconto FLAT Plano Principal Oi TV nível conta"),BENEFICIOS!$A:$G,5,0))) -> Criar | CO7: 129.9 | CP7: =IF(CO7=0,"",IF(CO7=VLOOKUP("PCS-OzTL46",ARBOR!$A:$C,3,0),0.0001,IF(CO7>VLOOKUP("PCS-OzTL46",ARBOR!$A:$C,3,0),"Maior que CAP!",IF((DOLLAR(CO7+(VLOOKUP("PCS-OzTL46",ARBOR!$A:$C,3,0)*-TRUNC(CO7/VLOOKUP("PCS-OzTL46",ARBOR!$A:$C,3,0)-1,4)),6))<>(DOLLAR(VLOOKUP("PCS-OzTL46",ARBOR!$A:$C,3,0),6)),-TRUNC(CO7/VLOOKUP("PCS-OzTL46",ARBOR!$A:$C,3,0)-1,4)+0.0001,-TRUNC(CO7/VLOOKUP("PCS-OzTL46",ARBOR!$A:$C,3,0)-1,4))))) -> 0.3949 | CQ7: =IF(ISERROR(IF(CP7="","",VLOOKUP(($BC7&CP7&"Template desconto FLAT Plano Principal Oi TV nível conta"),BENEFICIOS!$A:$G,5,0))),"Criar",IF(CP7="","",VLOOKUP(($BC7&CP7&"Template desconto FLAT Plano Principal Oi TV nível conta"),BENEFICIOS!$A:$G,5,0))) -> Criar | CR7: 159.9 | CS7: =IF(CR7=0,"",IF(CR7=VLOOKUP("PCS-OzTL48",ARBOR!$A:$C,3,0),0.0001,IF(CR7>VLOOKUP("PCS-OzTL48",ARBOR!$A:$C,3,0),"Maior que CAP!",IF((DOLLAR(CR7+(VLOOKUP("PCS-OzTL48",ARBOR!$A:$C,3,0)*-TRUNC(CR7/VLOOKUP("PCS-OzTL48",ARBOR!$A:$C,3,0)-1,4)),6))<>(DOLLAR(VLOOKUP("PCS-OzTL48",ARBOR!$A:$C,3,0),6)),-TRUNC(CR7/VLOOKUP("PCS-OzTL48",ARBOR!$A:$C,3,0)-1,4)+0.0001,-TRUNC(CR7/VLOOKUP("PCS-OzTL48",ARBOR!$A:$C,3,0)-1,4))))) -> 0.3685 | CT7: =IF(ISERROR(IF(CS7="","",VLOOKUP(($BC7&CS7&"Template desconto FLAT Plano Principal Oi TV nível conta"),BENEFICIOS!$A:$G,5,0))),"Criar",IF(CS7="","",VLOOKUP(($BC7&CS7&"Template desconto FLAT Plano Principal Oi TV nível conta"),BENEFICIOS!$A:$G,5,0))) -> Criar | CV7: =IF(CU7=0,"",IF(CU7=VLOOKUP("PCS-OzTL742",ARBOR!$A:$C,3,0),0.0001,IF(CU7>VLOOKUP("PCS-OzTL742",ARBOR!$A:$C,3,0),"Maior que CAP!",IF((DOLLAR(CU7+(VLOOKUP("PCS-OzTL742",ARBOR!$A:$C,3,0)*-TRUNC(CU7/VLOOKUP("PCS-OzTL742",ARBOR!$A:$C,3,0)-1,4)),6))<>(DOLLAR(VLOOKUP("PCS-OzTL742",ARBOR!$A:$C,3,0),6)),-TRUNC(CU7/VLOOKUP("PCS-OzTL742",ARBOR!$A:$C,3,0)-1,4)+0.0001,-TRUNC(CU7/VLOOKUP("PCS-OzTL742",ARBOR!$A:$C,3,0)-1,4))))) | CW7: =IF(ISERROR(IF(CV7="","",VLOOKUP(($BC7&CV7&"Template desconto FLAT Plano Principal Oi TV nível conta"),BENEFICIOS!$A:$G,5,0))),"Criar",IF(CV7="","",VLOOKUP(($BC7&CV7&"Template desconto FLAT Plano Principal Oi TV nível conta"),BENEFICIOS!$A:$G,5,0))) | CY7: =IF(CX7=0,"",IF(CX7=VLOOKUP("PCS-OzTL747",ARBOR!$A:$C,3,0),0.0001,IF(CX7>VLOOKUP("PCS-OzTL747",ARBOR!$A:$C,3,0),"Maior que CAP!",IF((DOLLAR(CX7+(VLOOKUP("PCS-OzTL747",ARBOR!$A:$C,3,0)*-TRUNC(CX7/VLOOKUP("PCS-OzTL747",ARBOR!$A:$C,3,0)-1,4)),6))<>(DOLLAR(VLOOKUP("PCS-OzTL747",ARBOR!$A:$C,3,0),6)),-TRUNC(CX7/VLOOKUP("PCS-OzTL747",ARBOR!$A:$C,3,0)-1,4)+0.0001,-TRUNC(CX7/VLOOKUP("PCS-OzTL747",ARBOR!$A:$C,3,0)-1,4))))) | CZ7: =IF(ISERROR(IF(CY7="","",VLOOKUP(($BC7&CY7&"Template desconto FLAT Plano Principal Oi TV nível conta"),BENEFICIOS!$A:$G,5,0))),"Criar",IF(CY7="","",VLOOKUP(($BC7&CY7&"Template desconto FLAT Plano Principal Oi TV nível conta"),BENEFICIOS!$A:$G,5,0))) | DB7: =IF(DA7=0,"",IF(DA7=VLOOKUP("PCS-OzTL746",ARBOR!$A:$C,3,0),0.0001,IF(DA7>VLOOKUP("PCS-OzTL746",ARBOR!$A:$C,3,0),"Maior que CAP!",IF((DOLLAR(DA7+(VLOOKUP("PCS-OzTL746",ARBOR!$A:$C,3,0)*-TRUNC(DA7/VLOOKUP("PCS-OzTL746",ARBOR!$A:$C,3,0)-1,4)),6))<>(DOLLAR(VLOOKUP("PCS-OzTL746",ARBOR!$A:$C,3,0),6)),-TRUNC(DA7/VLOOKUP("PCS-OzTL746",ARBOR!$A:$C,3,0)-1,4)+0.0001,-TRUNC(DA7/VLOOKUP("PCS-OzTL746",ARBOR!$A:$C,3,0)-1,4))))) | DC7: =IF(ISERROR(IF(DB7="","",VLOOKUP(($BC7&DB7&"Template desconto FLAT Plano Principal Oi TV nível conta"),BENEFICIOS!$A:$G,5,0))),"Criar",IF(DB7="","",VLOOKUP(($BC7&DB7&"Template desconto FLAT Plano Principal Oi TV nível conta"),BENEFICIOS!$A:$G,5,0))) | DE7: =IF(DD7=0,"",IF(DD7=VLOOKUP("PCS-OzTL748",ARBOR!$A:$C,3,0),0.0001,IF(DD7>VLOOKUP("PCS-OzTL748",ARBOR!$A:$C,3,0),"Maior que CAP!",IF((DOLLAR(DD7+(VLOOKUP("PCS-OzTL748",ARBOR!$A:$C,3,0)*-TRUNC(DD7/VLOOKUP("PCS-OzTL748",ARBOR!$A:$C,3,0)-1,4)),6))<>(DOLLAR(VLOOKUP("PCS-OzTL748",ARBOR!$A:$C,3,0),6)),-TRUNC(DD7/VLOOKUP("PCS-OzTL748",ARBOR!$A:$C,3,0)-1,4)+0.0001,-TRUNC(DD7/VLOOKUP("PCS-OzTL748",ARBOR!$A:$C,3,0)-1,4))))) | DF7: =IF(ISERROR(IF(DE7="","",VLOOKUP(($BC7&DE7&"Template desconto FLAT Plano Principal Oi TV nível conta"),BENEFICIOS!$A:$G,5,0))),"Criar",IF(DE7="","",VLOOKUP(($BC7&DE7&"Template desconto FLAT Plano Principal Oi TV nível conta"),BENEFICIOS!$A:$G,5,0))) | DG7: 75 | DH7: =IF(DG7=0,"",IF(DG7=VLOOKUP("PCS-OzTL34",ARBOR!$A:$C,3,0),0.0001,IF(DG7>VLOOKUP("PCS-OzTL34",ARBOR!$A:$C,3,0),"Maior que CAP!",IF((DOLLAR(DG7+(VLOOKUP("PCS-OzTL34",ARBOR!$A:$C,3,0)*-TRUNC(DG7/VLOOKUP("PCS-OzTL34",ARBOR!$A:$C,3,0)-1,4)),6))<>(DOLLAR(VLOOKUP("PCS-OzTL34",ARBOR!$A:$C,3,0),6)),-TRUNC(DG7/VLOOKUP("PCS-OzTL34",ARBOR!$A:$C,3,0)-1,4)+0.0001,-TRUNC(DG7/VLOOKUP("PCS-OzTL34",ARBOR!$A:$C,3,0)-1,4))))) -> 0.319 | DI7: =IF(DH7="S/Desc","S/Desc",IF(ISERROR(IF(DH7="","",VLOOKUP(($BC7&DH7&"Template desconto % Combate nível conta"),BENEFICIOS!$A:$G,5,0))),"Criar",IF(DH7="","",VLOOKUP(($BC7&DH7&"Template desconto % Combate nível conta"),BENEFICIOS!$A:$G,5,0)))) -> Criar | DJ7: 19.9 | DK7: =IF(DJ7=0,"",IF(DJ7=VLOOKUP("PCS-OzTL31",ARBOR!$A:$C,3,0),0.0001,IF(DJ7>VLOOKUP("PCS-OzTL31",ARBOR!$A:$C,3,0),"Maior que CAP!",IF((DOLLAR(DJ7+(VLOOKUP("PCS-OzTL31",ARBOR!$A:$C,3,0)*-TRUNC(DJ7/VLOOKUP("PCS-OzTL31",ARBOR!$A:$C,3,0)-1,4)),6))<>(DOLLAR(VLOOKUP("PCS-OzTL31",ARBOR!$A:$C,3,0),6)),-TRUNC(DJ7/VLOOKUP("PCS-OzTL31",ARBOR!$A:$C,3,0)-1,4)+0.0001,-TRUNC(DJ7/VLOOKUP("PCS-OzTL31",ARBOR!$A:$C,3,0)-1,4))))) -> 0.0918 | DL7: =IF(DK7="S/Desc","S/Desc",IF(ISERROR(IF(DK7="","",VLOOKUP(($BC7&DK7&"Template desconto % Sexy Hot nível conta"),BENEFICIOS!$A:$G,5,0))),"Criar",IF(DK7="","",VLOOKUP(($BC7&DK7&"Template desconto % Sexy Hot nível conta"),BENEFICIOS!$A:$G,5,0)))) -> Criar | DM7: 19.9 | DN7: =IF(DM7=0,"",IF(DM7=VLOOKUP("PCS-OzTL32",ARBOR!$A:$C,3,0),0.0001,IF(DM7>VLOOKUP("PCS-OzTL32",ARBOR!$A:$C,3,0),"Maior que CAP!",IF((DOLLAR(DM7+(VLOOKUP("PCS-OzTL32",ARBOR!$A:$C,3,0)*-TRUNC(DM7/VLOOKUP("PCS-OzTL32",ARBOR!$A:$C,3,0)-1,4)),6))<>(DOLLAR(VLOOKUP("PCS-OzTL32",ARBOR!$A:$C,3,0),6)),-TRUNC(DM7/VLOOKUP("PCS-OzTL32",ARBOR!$A:$C,3,0)-1,4)+0.0001,-TRUNC(DM7/VLOOKUP("PCS-OzTL32",ARBOR!$A:$C,3,0)-1,4))))) -> 0.0918 | DO7: =IF(DN7="S/Desc","S/Desc",IF(ISERROR(IF(DN7="","",VLOOKUP(($BC7&DN7&"Template desconto % Playboy nível conta"),BENEFICIOS!$A:$G,5,0))),"Criar",IF(DN7="","",VLOOKUP(($BC7&DN7&"Template desconto % Playboy nível conta"),BENEFICIOS!$A:$G,5,0)))) -> Criar | DP7: 29.9 | DQ7: =IF(DP7=0,"",IF(DP7=VLOOKUP("PCS-OzTL33",ARBOR!$A:$C,3,0),0.0001,IF(DP7>VLOOKUP("PCS-OzTL33",ARBOR!$A:$C,3,0),"Maior que CAP!",IF((DOLLAR(DP7+(VLOOKUP("PCS-OzTL33",ARBOR!$A:$C,3,0)*-TRUNC(DP7/VLOOKUP("PCS-OzTL33",ARBOR!$A:$C,3,0)-1,4)),6))<>(DOLLAR(VLOOKUP("PCS-OzTL33",ARBOR!$A:$C,3,0),6)),-TRUNC(DP7/VLOOKUP("PCS-OzTL33",ARBOR!$A:$C,3,0)-1,4)+0.0001,-TRUNC(DP7/VLOOKUP("PCS-OzTL33",ARBOR!$A:$C,3,0)-1,4))))) -> 0.0918 | DR7: =IF(DQ7="S/Desc","S/Desc",IF(ISERROR(IF(DQ7="","",VLOOKUP(($BC7&DQ7&"Template desconto % Sexy Hot + Playboy nível conta"),BENEFICIOS!$A:$G,5,0))),"Criar",IF(DQ7="","",VLOOKUP(($BC7&DQ7&"Template desconto % Sexy Hot + Playboy nível conta"),BENEFICIOS!$A:$G,5,0)))) -> Criar | DS7: 14.9 | DT7: =IF(DS7=0,"",IF(DS7=VLOOKUP("PCS-OzTL503",ARBOR!$A:$C,3,0),0.0001,IF(DS7>VLOOKUP("PCS-OzTL503",ARBOR!$A:$C,3,0),"Maior que CAP!",IF((DOLLAR(DS7+(VLOOKUP("PCS-OzTL503",ARBOR!$A:$C,3,0)*-TRUNC(DS7/VLOOKUP("PCS-OzTL503",ARBOR!$A:$C,3,0)-1,4)),6))<>(DOLLAR(VLOOKUP("PCS-OzTL503",ARBOR!$A:$C,3,0),6)),-TRUNC(DS7/VLOOKUP("PCS-OzTL503",ARBOR!$A:$C,3,0)-1,4)+0.0001,-TRUNC(DS7/VLOOKUP("PCS-OzTL503",ARBOR!$A:$C,3,0)-1,4))))) -> 0.0915 | DU7: =IF(DT7="S/Desc","S/Desc",IF(ISERROR(IF(DT7="","",VLOOKUP(($BC7&DT7&"Template desconto % SexPrivê nível conta"),BENEFICIOS!$A:$G,5,0))),"Criar",IF(DT7="","",VLOOKUP(($BC7&DT7&"Template desconto % SexPrivê nível conta"),BENEFICIOS!$A:$G,5,0)))) -> Criar | DV7: 10 | DW7: =IF(DV7=0,"",IF(DV7=VLOOKUP("PCS-OzTL500",ARBOR!$A:$C,3,0),0.0001,IF(DV7>VLOOKUP("PCS-OzTL500",ARBOR!$A:$C,3,0),"Maior que CAP!",IF((DOLLAR(DV7+(VLOOKUP("PCS-OzTL500",ARBOR!$A:$C,3,0)*-TRUNC(DV7/VLOOKUP("PCS-OzTL500",ARBOR!$A:$C,3,0)-1,4)),6))<>(DOLLAR(VLOOKUP("PCS-OzTL500",ARBOR!$A:$C,3,0),6)),-TRUNC(DV7/VLOOKUP("PCS-OzTL500",ARBOR!$A:$C,3,0)-1,4)+0.0001,-TRUNC(DV7/VLOOKUP("PCS-OzTL500",ARBOR!$A:$C,3,0)-1,4))))) -> 0.0918 | DX7: =IF(DW7="S/Desc","S/Desc",IF(ISERROR(IF(DW7="","",VLOOKUP(($BC7&DW7&"Template desconto % Étnico nível conta"),BENEFICIOS!$A:$G,5,0))),"Criar",IF(DW7="","",VLOOKUP(($BC7&DW7&"Template desconto % Étnico nível conta"),BENEFICIOS!$A:$G,5,0)))) -> Criar | DZ7: =IF(DY7=0,"",IF(DY7=VLOOKUP("PCS-OzTL50",ARBOR!$A:$C,3,0),0.0001,IF(DY7>VLOOKUP("PCS-OzTL50",ARBOR!$A:$C,3,0),"Maior que CAP!",IF((DOLLAR(DY7+(VLOOKUP("PCS-OzTL50",ARBOR!$A:$C,3,0)*-TRUNC(DY7/VLOOKUP("PCS-OzTL50",ARBOR!$A:$C,3,0)-1,4)),6))<>(DOLLAR(VLOOKUP("PCS-OzTL50",ARBOR!$A:$C,3,0),6)),-TRUNC(DY7/VLOOKUP("PCS-OzTL50",ARBOR!$A:$C,3,0)-1,4)+0.0001,-TRUNC(DY7/VLOOKUP("PCS-OzTL50",ARBOR!$A:$C,3,0)-1,4))))) | EC7: =IF(EB7=0,"",IF(EB7=VLOOKUP("PCS-OzTL51",ARBOR!$A:$C,3,0),0.0001,IF(EB7>VLOOKUP("PCS-OzTL51",ARBOR!$A:$C,3,0),"Maior que CAP!",IF((DOLLAR(EB7+(VLOOKUP("PCS-OzTL51",ARBOR!$A:$C,3,0)*-TRUNC(EB7/VLOOKUP("PCS-OzTL51",ARBOR!$A:$C,3,0)-1,4)),6))<>(DOLLAR(VLOOKUP("PCS-OzTL51",ARBOR!$A:$C,3,0),6)),-TRUNC(EB7/VLOOKUP("PCS-OzTL51",ARBOR!$A:$C,3,0)-1,4)+0.0001,-TRUNC(EB7/VLOOKUP("PCS-OzTL51",ARBOR!$A:$C,3,0)-1,4))))) | EF7: =IF(EE7=0,"",IF(EE7=VLOOKUP("PCS-OzTL52",ARBOR!$A:$C,3,0),0.0001,IF(EE7>VLOOKUP("PCS-OzTL52",ARBOR!$A:$C,3,0),"Maior que CAP!",IF((DOLLAR(EE7+(VLOOKUP("PCS-OzTL52",ARBOR!$A:$C,3,0)*-TRUNC(EE7/VLOOKUP("PCS-OzTL52",ARBOR!$A:$C,3,0)-1,4)),6))<>(DOLLAR(VLOOKUP("PCS-OzTL52",ARBOR!$A:$C,3,0),6)),-TRUNC(EE7/VLOOKUP("PCS-OzTL52",ARBOR!$A:$C,3,0)-1,4)+0.0001,-TRUNC(EE7/VLOOKUP("PCS-OzTL52",ARBOR!$A:$C,3,0)-1,4))))) | EI7: =IF(EH7=0,"",IF(EH7=VLOOKUP("PCS-OzTL53",ARBOR!$A:$C,3,0),0.0001,IF(EH7>VLOOKUP("PCS-OzTL53",ARBOR!$A:$C,3,0),"Maior que CAP!",IF((DOLLAR(EH7+(VLOOKUP("PCS-OzTL53",ARBOR!$A:$C,3,0)*-TRUNC(EH7/VLOOKUP("PCS-OzTL53",ARBOR!$A:$C,3,0)-1,4)),6))<>(DOLLAR(VLOOKUP("PCS-OzTL53",ARBOR!$A:$C,3,0),6)),-TRUNC(EH7/VLOOKUP("PCS-OzTL53",ARBOR!$A:$C,3,0)-1,4)+0.0001,-TRUNC(EH7/VLOOKUP("PCS-OzTL53",ARBOR!$A:$C,3,0)-1,4))))) | EL7: =IF(EK7=0,"",IF(EK7=VLOOKUP("PCS-OzTL54",ARBOR!$A:$C,3,0),0.0001,IF(EK7>VLOOKUP("PCS-OzTL54",ARBOR!$A:$C,3,0),"Maior que CAP!",IF((DOLLAR(EK7+(VLOOKUP("PCS-OzTL54",ARBOR!$A:$C,3,0)*-TRUNC(EK7/VLOOKUP("PCS-OzTL54",ARBOR!$A:$C,3,0)-1,4)),6))<>(DOLLAR(VLOOKUP("PCS-OzTL54",ARBOR!$A:$C,3,0),6)),-TRUNC(EK7/VLOOKUP("PCS-OzTL54",ARBOR!$A:$C,3,0)-1,4)+0.0001,-TRUNC(EK7/VLOOKUP("PCS-OzTL54",ARBOR!$A:$C,3,0)-1,4))))) | EN7: 24.9 | EO7: =IF(EN7=0,"",IF(EN7=VLOOKUP("PCS-OzTL99",ARBOR!$A:$C,3,0),0.0001,IF(EN7>VLOOKUP("PCS-OzTL99",ARBOR!$A:$C,3,0),"Maior que CAP!",IF((DOLLAR(EN7+(VLOOKUP("PCS-OzTL99",ARBOR!$A:$C,3,0)*-TRUNC(EN7/VLOOKUP("PCS-OzTL99",ARBOR!$A:$C,3,0)-1,4)),6))<>(DOLLAR(VLOOKUP("PCS-OzTL99",ARBOR!$A:$C,3,0),6)),-TRUNC(EN7/VLOOKUP("PCS-OzTL99",ARBOR!$A:$C,3,0)-1,4)+0.0001,-TRUNC(EN7/VLOOKUP("PCS-OzTL99",ARBOR!$A:$C,3,0)-1,4))))) -> 0.1673 | EP7: =IF(EO7="S/Desc","S/Desc",IF(ISERROR(IF(EO7="","",VLOOKUP(($BC7&EO7&"Template desconto % Ponto adicional nível conta"),BENEFICIOS!$A:$G,5,0))),"Criar",IF(EO7="","",VLOOKUP(($BC7&EO7&"Template desconto % Ponto adicional nível conta"),BENEFICIOS!$A:$G,5,0)))) -> Criar | ER7: =IF(EQ7="Sim","PCS-34704","") | ES7: Sim | ET7: Benefício | EU7: 499 | EV7: 12 | EW7: =IF(ET7="Benefício","Oi benefício fidelização Multiprodutos","") -> Oi benefício fidelização Multiprodutos | EX7: =IF(ET7="Benefício","PCS-Fk83324","") -> PCS-Fk83324 | EY7: =IF(ES7="Sim","PCS-SBL553142","") -> PCS-SBL553142 | EZ7: LD + VC Oi | FA7: 0T0T_FTV_MIN_LD_270000. | FG7: =IF($BH7="","",$BH7+$BE7) | FH7: =IF($BK7="","",$BK7+$BE7) | FI7: =IF($BN7="","",$BN7+$BE7) -> 164.9 | FJ7: =IF($BQ7="","",$BQ7+$BE7) -> 164.9 | FK7: =IF($BT7="","",$BT7+$BE7) -> 194.9 | FL7: =IF($BW7="","",$BW7+$BE7) | FM7: =IF($BZ7="","",$BZ7+$BE7) | FN7: =IF($CC7="","",$CC7+$BE7) | FO7: =IF($CF7="","",$CF7+$BE7) | FP7: =IF($CI7="","",$CI7+$BE7) | FQ7: =IF($CL7="","",$CL7+$BE7) -> 174.9 | FR7: =IF($CO7="","",$CO7+$BE7) -> 174.9 | FS7: =IF($CR7="","",$CR7+$BE7) -> 204.9 | FT7: =IF($CU7="","",$CU7+$BE7) | FU7: =IF($CX7="","",$CX7+$BE7) | FV7: =IF($DA7="","",$DA7+$BE7) | FW7: =IF($DD7="","",$DD7+$BE7)
A8: Oi Total | B8: Migração | C8: Atuais | D8: Não | AM8: OT_ATV_JUL17_FID_DACC_2PTV_TV2_MI-TO_LD-VC_OF3 | AN8: Rentabilizar atuais clientes do plano | AO8: Produto Fixo + TV , Produto com fidelização | AP8: 42917 | AQ8: 43039 | AR8: 20. Oi Total | AS8: 20. Oi Total | AU8: Varejo | AV8: 20 | AW8: 10000 | AX8: Campanha Restrita | AY8: Sim | AZ8: Sim | BA8: Não | BB8: OT_ATV_JUL17_FID_DACC_2PTV_TV2_MI-TO_LD-VC_OF3 | BC8: Oi Total Fixo + TV 2 | BD8: =IF(BC8="Oi Total Fixo + TV 1","CFG-2Plowpi",IF(BC8="Oi Total Fixo + TV 2","PCS-2PMepi",IF(BC8="Oi Total Fixo + TV 3","PCS-2PHipi",""))) -> PCS-2PMepi | BE8: 35 | BF8: =IF(BE8=0,"",IF(BE8=VLOOKUP("FIXO",ARBOR!$A:$C,3,0),0.0001,IF(BE8>VLOOKUP("FIXO",ARBOR!$A:$C,3,0),"Maior que CAP!",IF((DOLLAR(BE8+(VLOOKUP("FIXO",ARBOR!$A:$C,3,0)*-TRUNC(BE8/VLOOKUP("FIXO",ARBOR!$A:$C,3,0)-1,4)),6))<>(DOLLAR(VLOOKUP("FIXO",ARBOR!$A:$C,3,0),6)),-TRUNC(BE8/VLOOKUP("FIXO",ARBOR!$A:$C,3,0)-1,4)+0.0001,-TRUNC(BE8/VLOOKUP("FIXO",ARBOR!$A:$C,3,0)-1,4))))) -> 0.5386 | BG8: =IF(ISERROR(IF(BF8="","",VLOOKUP(($BC8&BF8&"Template de desconto FLAT bundle - Fixo - Varejo - Ganho Tributário Cross"),BENEFICIOS!$A:$G,5,0))),"Criar",IF(BF8="","",VLOOKUP(($BC8&BF8&"Template de desconto FLAT bundle - Fixo - Varejo - Ganho Tributário Cross"),BENEFICIOS!$A:$G,5,0))) -> Criar | BI8: =IF(BH8=0,"",IF(BH8=VLOOKUP("PCS-OzTL40",ARBOR!$A:$C,3,0),0.0001,IF(BH8>VLOOKUP("PCS-OzTL40",ARBOR!$A:$C,3,0),"Maior que CAP!",IF((DOLLAR(BH8+(VLOOKUP("PCS-OzTL40",ARBOR!$A:$C,3,0)*-TRUNC(BH8/VLOOKUP("PCS-OzTL40",ARBOR!$A:$C,3,0)-1,4)),6))<>(DOLLAR(VLOOKUP("PCS-OzTL40",ARBOR!$A:$C,3,0),6)),-TRUNC(BH8/VLOOKUP("PCS-OzTL40",ARBOR!$A:$C,3,0)-1,4)+0.0001,-TRUNC(BH8/VLOOKUP("PCS-OzTL40",ARBOR!$A:$C,3,0)-1,4))))) | BJ8: =IF(ISERROR(IF(BI8="","",VLOOKUP((BC8&BI8&"Template desconto FLAT Plano Principal Oi TV nível conta"),BENEFICIOS!$A:$G,5,0))),"Criar",IF(BI8="","",VLOOKUP((BC8&BI8&"Template desconto FLAT Plano Principal Oi TV nível conta"),BENEFICIOS!$A:$G,5,0))) | BK8: 79.9 | BL8: =IF(BK8=0,"",IF(BK8=VLOOKUP("PCS-OzTL41",ARBOR!$A:$C,3,0),0.0001,IF(BK8>VLOOKUP("PCS-OzTL41",ARBOR!$A:$C,3,0),"Maior que CAP!",IF((DOLLAR(BK8+(VLOOKUP("PCS-OzTL41",ARBOR!$A:$C,3,0)*-TRUNC(BK8/VLOOKUP("PCS-OzTL41",ARBOR!$A:$C,3,0)-1,4)),6))<>(DOLLAR(VLOOKUP("PCS-OzTL41",ARBOR!$A:$C,3,0),6)),-TRUNC(BK8/VLOOKUP("PCS-OzTL41",ARBOR!$A:$C,3,0)-1,4)+0.0001,-TRUNC(BK8/VLOOKUP("PCS-OzTL41",ARBOR!$A:$C,3,0)-1,4))))) -> 0.3399 | BM8: =IF(ISERROR(IF(BL8="","",VLOOKUP((BC8&BL8&"Template desconto FLAT Plano Principal Oi TV nível conta"),BENEFICIOS!$A:$G,5,0))),"Criar",IF(BL8="","",VLOOKUP((BC8&BL8&"Template desconto FLAT Plano Principal Oi TV nível conta"),BENEFICIOS!$A:$G,5,0))) -> Criar | BO8: =IF(BN8=0,"",IF(BN8=VLOOKUP("PCS-OzTL44",ARBOR!$A:$C,3,0),0.0001,IF(BN8>VLOOKUP("PCS-OzTL44",ARBOR!$A:$C,3,0),"Maior que CAP!",IF((DOLLAR(BN8+(VLOOKUP("PCS-OzTL44",ARBOR!$A:$C,3,0)*-TRUNC(BN8/VLOOKUP("PCS-OzTL44",ARBOR!$A:$C,3,0)-1,4)),6))<>(DOLLAR(VLOOKUP("PCS-OzTL44",ARBOR!$A:$C,3,0),6)),-TRUNC(BN8/VLOOKUP("PCS-OzTL44",ARBOR!$A:$C,3,0)-1,4)+0.0001,-TRUNC(BN8/VLOOKUP("PCS-OzTL44",ARBOR!$A:$C,3,0)-1,4))))) | BP8: =IF(ISERROR(IF(BO8="","",VLOOKUP((BC8&BO8&"Template desconto FLAT Plano Principal Oi TV nível conta"),BENEFICIOS!$A:$G,5,0))),"Criar",IF(BO8="","",VLOOKUP((BC8&BO8&"Template desconto FLAT Plano Principal Oi TV nível conta"),BENEFICIOS!$A:$G,5,0))) | BR8: =IF(BQ8=0,"",IF(BQ8=VLOOKUP("PCS-OzTL43",ARBOR!$A:$C,3,0),0.0001,IF(BQ8>VLOOKUP("PCS-OzTL43",ARBOR!$A:$C,3,0),"Maior que CAP!",IF((DOLLAR(BQ8+(VLOOKUP("PCS-OzTL43",ARBOR!$A:$C,3,0)*-TRUNC(BQ8/VLOOKUP("PCS-OzTL43",ARBOR!$A:$C,3,0)-1,4)),6))<>(DOLLAR(VLOOKUP("PCS-OzTL43",ARBOR!$A:$C,3,0),6)),-TRUNC(BQ8/VLOOKUP("PCS-OzTL43",ARBOR!$A:$C,3,0)-1,4)+0.0001,-TRUNC(BQ8/VLOOKUP("PCS-OzTL43",ARBOR!$A:$C,3,0)-1,4))))) | BS8: =IF(ISERROR(IF(BR8="","",VLOOKUP((BC8&BR8&"Template desconto FLAT Plano Principal Oi TV nível conta"),BENEFICIOS!$A:$G,5,0))),"Criar",IF(BR8="","",VLOOKUP((BC8&BR8&"Template desconto FLAT Plano Principal Oi TV nível conta"),BENEFICIOS!$A:$G,5,0))) | BU8: =IF(BT8=0,"",IF(BT8=VLOOKUP("PCS-OzTL45",ARBOR!$A:$C,3,0),0.0001,IF(BT8>VLOOKUP("PCS-OzTL45",ARBOR!$A:$C,3,0),"Maior que CAP!",IF((DOLLAR(BT8+(VLOOKUP("PCS-OzTL45",ARBOR!$A:$C,3,0)*-TRUNC(BT8/VLOOKUP("PCS-OzTL45",ARBOR!$A:$C,3,0)-1,4)),6))<>(DOLLAR(VLOOKUP("PCS-OzTL45",ARBOR!$A:$C,3,0),6)),-TRUNC(BT8/VLOOKUP("PCS-OzTL45",ARBOR!$A:$C,3,0)-1,4)+0.0001,-TRUNC(BT8/VLOOKUP("PCS-OzTL45",ARBOR!$A:$C,3,0)-1,4))))) | BV8: =IF(ISERROR(IF(BU8="","",VLOOKUP((BC8&BU8&"Template desconto FLAT Plano Principal Oi TV nível conta"),BENEFICIOS!$A:$G,5,0))),"Criar",IF(BU8="","",VLOOKUP((BC8&BU8&"Template desconto FLAT Plano Principal Oi TV nível conta"),BENEFICIOS!$A:$G,5,0))) | BX8: =IF(BW8=0,"",IF(BW8=VLOOKUP("PCS-OzTL741",ARBOR!$A:$C,3,0),0.0001,IF(BW8>VLOOKUP("PCS-OzTL741",ARBOR!$A:$C,3,0),"Maior que CAP!",IF((DOLLAR(BW8+(VLOOKUP("PCS-OzTL741",ARBOR!$A:$C,3,0)*-TRUNC(BW8/VLOOKUP("PCS-OzTL741",ARBOR!$A:$C,3,0)-1,4)),6))<>(DOLLAR(VLOOKUP("PCS-OzTL741",ARBOR!$A:$C,3,0),6)),-TRUNC(BW8/VLOOKUP("PCS-OzTL741",ARBOR!$A:$C,3,0)-1,4)+0.0001,-TRUNC(BW8/VLOOKUP("PCS-OzTL741",ARBOR!$A:$C,3,0)-1,4))))) | BY8: =IF(ISERROR(IF(BX8="","",VLOOKUP((BC8&BX8&"Template desconto FLAT Plano Principal Oi TV nível conta"),BENEFICIOS!$A:$G,5,0))),"Criar",IF(BX8="","",VLOOKUP((BC8&BX8&"Template desconto FLAT Plano Principal Oi TV nível conta"),BENEFICIOS!$A:$G,5,0))) | CA8: =IF(BZ8=0,"",IF(BZ8=VLOOKUP("PCS-OzTL744",ARBOR!$A:$C,3,0),0.0001,IF(BZ8>VLOOKUP("PCS-OzTL744",ARBOR!$A:$C,3,0),"Maior que CAP!",IF((DOLLAR(BZ8+(VLOOKUP("PCS-OzTL744",ARBOR!$A:$C,3,0)*-TRUNC(BZ8/VLOOKUP("PCS-OzTL744",ARBOR!$A:$C,3,0)-1,4)),6))<>(DOLLAR(VLOOKUP("PCS-OzTL744",ARBOR!$A:$C,3,0),6)),-TRUNC(BZ8/VLOOKUP("PCS-OzTL744",ARBOR!$A:$C,3,0)-1,4)+0.0001,-TRUNC(BZ8/VLOOKUP("PCS-OzTL744",ARBOR!$A:$C,3,0)-1,4))))) | CB8: =IF(ISERROR(IF(CA8="","",VLOOKUP(($BC8&CA8&"Template desconto FLAT Plano Principal Oi TV nível conta"),BENEFICIOS!$A:$G,5,0))),"Criar",IF(CA8="","",VLOOKUP(($BC8&CA8&"Template desconto FLAT Plano Principal Oi TV nível conta"),BENEFICIOS!$A:$G,5,0))) | CD8: =IF(CC8=0,"",IF(CC8=VLOOKUP("PCS-OzTL743",ARBOR!$A:$C,3,0),0.0001,IF(CC8>VLOOKUP("PCS-OzTL743",ARBOR!$A:$C,3,0),"Maior que CAP!",IF((DOLLAR(CC8+(VLOOKUP("PCS-OzTL743",ARBOR!$A:$C,3,0)*-TRUNC(CC8/VLOOKUP("PCS-OzTL743",ARBOR!$A:$C,3,0)-1,4)),6))<>(DOLLAR(VLOOKUP("PCS-OzTL743",ARBOR!$A:$C,3,0),6)),-TRUNC(CC8/VLOOKUP("PCS-OzTL743",ARBOR!$A:$C,3,0)-1,4)+0.0001,-TRUNC(CC8/VLOOKUP("PCS-OzTL743",ARBOR!$A:$C,3,0)-1,4))))) | CE8: =IF(ISERROR(IF(CD8="","",VLOOKUP(($BC8&CD8&"Template desconto FLAT Plano Principal Oi TV nível conta"),BENEFICIOS!$A:$G,5,0))),"Criar",IF(CD8="","",VLOOKUP(($BC8&CD8&"Template desconto FLAT Plano Principal Oi TV nível conta"),BENEFICIOS!$A:$G,5,0))) | CG8: =IF(CF8=0,"",IF(CF8=VLOOKUP("PCS-OzTL745",ARBOR!$A:$C,3,0),0.0001,IF(CF8>VLOOKUP("PCS-OzTL745",ARBOR!$A:$C,3,0),"Maior que CAP!",IF((DOLLAR(CF8+(VLOOKUP("PCS-OzTL745",ARBOR!$A:$C,3,0)*-TRUNC(CF8/VLOOKUP("PCS-OzTL745",ARBOR!$A:$C,3,0)-1,4)),6))<>(DOLLAR(VLOOKUP("PCS-OzTL745",ARBOR!$A:$C,3,0),6)),-TRUNC(CF8/VLOOKUP("PCS-OzTL745",ARBOR!$A:$C,3,0)-1,4)+0.0001,-TRUNC(CF8/VLOOKUP("PCS-OzTL745",ARBOR!$A:$C,3,0)-1,4))))) | CH8: =IF(ISERROR(IF(CG8="","",VLOOKUP(($BC8&CG8&"Template desconto FLAT Plano Principal Oi TV nível conta"),BENEFICIOS!$A:$G,5,0))),"Criar",IF(CG8="","",VLOOKUP(($BC8&CG8&"Template desconto FLAT Plano Principal Oi TV nível conta"),BENEFICIOS!$A:$G,5,0))) | CI8: 89.9 | CJ8: =IF(CI8=0,"",IF(CI8=VLOOKUP("PCS-OzTL42",ARBOR!$A:$C,3,0),0.0001,IF(CI8>VLOOKUP("PCS-OzTL42",ARBOR!$A:$C,3,0),"Maior que CAP!",IF((DOLLAR(CI8+(VLOOKUP("PCS-OzTL42",ARBOR!$A:$C,3,0)*-TRUNC(CI8/VLOOKUP("PCS-OzTL42",ARBOR!$A:$C,3,0)-1,4)),6))<>(DOLLAR(VLOOKUP("PCS-OzTL42",ARBOR!$A:$C,3,0),6)),-TRUNC(CI8/VLOOKUP("PCS-OzTL42",ARBOR!$A:$C,3,0)-1,4)+0.0001,-TRUNC(CI8/VLOOKUP("PCS-OzTL42",ARBOR!$A:$C,3,0)-1,4))))) -> 0.4555 | CK8: =IF(ISERROR(IF(CJ8="","",VLOOKUP(($BC8&CJ8&"Template desconto FLAT Plano Principal Oi TV nível conta"),BENEFICIOS!$A:$G,5,0))),"Criar",IF(CJ8="","",VLOOKUP(($BC8&CJ8&"Template desconto FLAT Plano Principal Oi TV nível conta"),BENEFICIOS!$A:$G,5,0))) -> Criar | CM8: =IF(CL8=0,"",IF(CL8=VLOOKUP("PCS-OzTL47",ARBOR!$A:$C,3,0),0.0001,IF(CL8>VLOOKUP("PCS-OzTL47",ARBOR!$A:$C,3,0),"Maior que CAP!",IF((DOLLAR(CL8+(VLOOKUP("PCS-OzTL47",ARBOR!$A:$C,3,0)*-TRUNC(CL8/VLOOKUP("PCS-OzTL47",ARBOR!$A:$C,3,0)-1,4)),6))<>(DOLLAR(VLOOKUP("PCS-OzTL47",ARBOR!$A:$C,3,0),6)),-TRUNC(CL8/VLOOKUP("PCS-OzTL47",ARBOR!$A:$C,3,0)-1,4)+0.0001,-TRUNC(CL8/VLOOKUP("PCS-OzTL47",ARBOR!$A:$C,3,0)-1,4))))) | CN8: =IF(ISERROR(IF(CM8="","",VLOOKUP(($BC8&CM8&"Template desconto FLAT Plano Principal Oi TV nível conta"),BENEFICIOS!$A:$G,5,0))),"Criar",IF(CM8="","",VLOOKUP(($BC8&CM8&"Template desconto FLAT Plano Principal Oi TV nível conta"),BENEFICIOS!$A:$G,5,0))) | CP8: =IF(CO8=0,"",IF(CO8=VLOOKUP("PCS-OzTL46",ARBOR!$A:$C,3,0),0.0001,IF(CO8>VLOOKUP("PCS-OzTL46",ARBOR!$A:$C,3,0),"Maior que CAP!",IF((DOLLAR(CO8+(VLOOKUP("PCS-OzTL46",ARBOR!$A:$C,3,0)*-TRUNC(CO8/VLOOKUP("PCS-OzTL46",ARBOR!$A:$C,3,0)-1,4)),6))<>(DOLLAR(VLOOKUP("PCS-OzTL46",ARBOR!$A:$C,3,0),6)),-TRUNC(CO8/VLOOKUP("PCS-OzTL46",ARBOR!$A:$C,3,0)-1,4)+0.0001,-TRUNC(CO8/VLOOKUP("PCS-OzTL46",ARBOR!$A:$C,3,0)-1,4))))) | CQ8: =IF(ISERROR(IF(CP8="","",VLOOKUP(($BC8&CP8&"Template desconto FLAT Plano Principal Oi TV nível conta"),BENEFICIOS!$A:$G,5,0))),"Criar",IF(CP8="","",VLOOKUP(($BC8&CP8&"Template desconto FLAT Plano Principal Oi TV nível conta"),BENEFICIOS!$A:$G,5,0))) | CS8: =IF(CR8=0,"",IF(CR8=VLOOKUP("PCS-OzTL48",ARBOR!$A:$C,3,0),0.0001,IF(CR8>VLOOKUP("PCS-OzTL48",ARBOR!$A:$C,3,0),"Maior que CAP!",IF((DOLLAR(CR8+(VLOOKUP("PCS-OzTL48",ARBOR!$A:$C,3,0)*-TRUNC(CR8/VLOOKUP("PCS-OzTL48",ARBOR!$A:$C,3,0)-1,4)),6))<>(DOLLAR(VLOOKUP("PCS-OzTL48",ARBOR!$A:$C,3,0),6)),-TRUNC(CR8/VLOOKUP("PCS-OzTL48",ARBOR!$A:$C,3,0)-1,4)+0.0001,-TRUNC(CR8/VLOOKUP("PCS-OzTL48",ARBOR!$A:$C,3,0)-1,4))))) | CT8: =IF(ISERROR(IF(CS8="","",VLOOKUP(($BC8&CS8&"Template desconto FLAT Plano Principal Oi TV nível conta"),BENEFICIOS!$A:$G,5,0))),"Criar",IF(CS8="","",VLOOKUP(($BC8&CS8&"Template desconto FLAT Plano Principal Oi TV nível conta"),BENEFICIOS!$A:$G,5,0))) | CU8: 109.9 | CV8: =IF(CU8=0,"",IF(CU8=VLOOKUP("PCS-OzTL742",ARBOR!$A:$C,3,0),0.0001,IF(CU8>VLOOKUP("PCS-OzTL742",ARBOR!$A:$C,3,0),"Maior que CAP!",IF((DOLLAR(CU8+(VLOOKUP("PCS-OzTL742",ARBOR!$A:$C,3,0)*-TRUNC(CU8/VLOOKUP("PCS-OzTL742",ARBOR!$A:$C,3,0)-1,4)),6))<>(DOLLAR(VLOOKUP("PCS-OzTL742",ARBOR!$A:$C,3,0),6)),-TRUNC(CU8/VLOOKUP("PCS-OzTL742",ARBOR!$A:$C,3,0)-1,4)+0.0001,-TRUNC(CU8/VLOOKUP("PCS-OzTL742",ARBOR!$A:$C,3,0)-1,4))))) -> 0.5008 | CW8: =IF(ISERROR(IF(CV8="","",VLOOKUP(($BC8&CV8&"Template desconto FLAT Plano Principal Oi TV nível conta"),BENEFICIOS!$A:$G,5,0))),"Criar",IF(CV8="","",VLOOKUP(($BC8&CV8&"Template desconto FLAT Plano Principal Oi TV nível conta"),BENEFICIOS!$A:$G,5,0))) -> Criar | CY8: =IF(CX8=0,"",IF(CX8=VLOOKUP("PCS-OzTL747",ARBOR!$A:$C,3,0),0.0001,IF(CX8>VLOOKUP("PCS-OzTL747",ARBOR!$A:$C,3,0),"Maior que CAP!",IF((DOLLAR(CX8+(VLOOKUP("PCS-OzTL747",ARBOR!$A:$C,3,0)*-TRUNC(CX8/VLOOKUP("PCS-OzTL747",ARBOR!$A:$C,3,0)-1,4)),6))<>(DOLLAR(VLOOKUP("PCS-OzTL747",ARBOR!$A:$C,3,0),6)),-TRUNC(CX8/VLOOKUP("PCS-OzTL747",ARBOR!$A:$C,3,0)-1,4)+0.0001,-TRUNC(CX8/VLOOKUP("PCS-OzTL747",ARBOR!$A:$C,3,0)-1,4))))) | CZ8: =IF(ISERROR(IF(CY8="","",VLOOKUP(($BC8&CY8&"Template desconto FLAT Plano Principal Oi TV nível conta"),BENEFICIOS!$A:$G,5,0))),"Criar",IF(CY8="","",VLOOKUP(($BC8&CY8&"Template desconto FLAT Plano Principal Oi TV nível conta"),BENEFICIOS!$A:$G,5,0))) | DB8: =IF(DA8=0,"",IF(DA8=VLOOKUP("PCS-OzTL746",ARBOR!$A:$C,3,0),0.0001,IF(DA8>VLOOKUP("PCS-OzTL746",ARBOR!$A:$C,3,0),"Maior que CAP!",IF((DOLLAR(DA8+(VLOOKUP("PCS-OzTL746",ARBOR!$A:$C,3,0)*-TRUNC(DA8/VLOOKUP("PCS-OzTL746",ARBOR!$A:$C,3,0)-1,4)),6))<>(DOLLAR(VLOOKUP("PCS-OzTL746",ARBOR!$A:$C,3,0),6)),-TRUNC(DA8/VLOOKUP("PCS-OzTL746",ARBOR!$A:$C,3,0)-1,4)+0.0001,-TRUNC(DA8/VLOOKUP("PCS-OzTL746",ARBOR!$A:$C,3,0)-1,4))))) | DC8: =IF(ISERROR(IF(DB8="","",VLOOKUP(($BC8&DB8&"Template desconto FLAT Plano Principal Oi TV nível conta"),BENEFICIOS!$A:$G,5,0))),"Criar",IF(DB8="","",VLOOKUP(($BC8&DB8&"Template desconto FLAT Plano Principal Oi TV nível conta"),BENEFICIOS!$A:$G,5,0))) | DE8: =IF(DD8=0,"",IF(DD8=VLOOKUP("PCS-OzTL748",ARBOR!$A:$C,3,0),0.0001,IF(DD8>VLOOKUP("PCS-OzTL748",ARBOR!$A:$C,3,0),"Maior que CAP!",IF((DOLLAR(DD8+(VLOOKUP("PCS-OzTL748",ARBOR!$A:$C,3,0)*-TRUNC(DD8/VLOOKUP("PCS-OzTL748",ARBOR!$A:$C,3,0)-1,4)),6))<>(DOLLAR(VLOOKUP("PCS-OzTL748",ARBOR!$A:$C,3,0),6)),-TRUNC(DD8/VLOOKUP("PCS-OzTL748",ARBOR!$A:$C,3,0)-1,4)+0.0001,-TRUNC(DD8/VLOOKUP("PCS-OzTL748",ARBOR!$A:$C,3,0)-1,4))))) | DF8: =IF(ISERROR(IF(DE8="","",VLOOKUP(($BC8&DE8&"Template desconto FLAT Plano Principal Oi TV nível conta"),BENEFICIOS!$A:$G,5,0))),"Criar",IF(DE8="","",VLOOKUP(($BC8&DE8&"Template desconto FLAT Plano Principal Oi TV nível conta"),BENEFICIOS!$A:$G,5,0))) | DG8: 75 | DH8: =IF(DG8=0,"",IF(DG8=VLOOKUP("PCS-OzTL34",ARBOR!$A:$C,3,0),0.0001,IF(DG8>VLOOKUP("PCS-OzTL34",ARBOR!$A:$C,3,0),"Maior que CAP!",IF((DOLLAR(DG8+(VLOOKUP("PCS-OzTL34",ARBOR!$A:$C,3,0)*-TRUNC(DG8/VLOOKUP("PCS-OzTL34",ARBOR!$A:$C,3,0)-1,4)),6))<>(DOLLAR(VLOOKUP("PCS-OzTL34",ARBOR!$A:$C,3,0),6)),-TRUNC(DG8/VLOOKUP("PCS-OzTL34",ARBOR!$A:$C,3,0)-1,4)+0.0001,-TRUNC(DG8/VLOOKUP("PCS-OzTL34",ARBOR!$A:$C,3,0)-1,4))))) -> 0.319 | DI8: =IF(DH8="S/Desc","S/Desc",IF(ISERROR(IF(DH8="","",VLOOKUP(($BC8&DH8&"Template desconto % Combate nível conta"),BENEFICIOS!$A:$G,5,0))),"Criar",IF(DH8="","",VLOOKUP(($BC8&DH8&"Template desconto % Combate nível conta"),BENEFICIOS!$A:$G,5,0)))) -> Criar | DJ8: 19.9 | DK8: =IF(DJ8=0,"",IF(DJ8=VLOOKUP("PCS-OzTL31",ARBOR!$A:$C,3,0),0.0001,IF(DJ8>VLOOKUP("PCS-OzTL31",ARBOR!$A:$C,3,0),"Maior que CAP!",IF((DOLLAR(DJ8+(VLOOKUP("PCS-OzTL31",ARBOR!$A:$C,3,0)*-TRUNC(DJ8/VLOOKUP("PCS-OzTL31",ARBOR!$A:$C,3,0)-1,4)),6))<>(DOLLAR(VLOOKUP("PCS-OzTL31",ARBOR!$A:$C,3,0),6)),-TRUNC(DJ8/VLOOKUP("PCS-OzTL31",ARBOR!$A:$C,3,0)-1,4)+0.0001,-TRUNC(DJ8/VLOOKUP("PCS-OzTL31",ARBOR!$A:$C,3,0)-1,4))))) -> 0.0918 | DL8: =IF(DK8="S/Desc","S/Desc",IF(ISERROR(IF(DK8="","",VLOOKUP(($BC8&DK8&"Template desconto % Sexy Hot nível conta"),BENEFICIOS!$A:$G,5,0))),"Criar",IF(DK8="","",VLOOKUP(($BC8&DK8&"Template desconto % Sexy Hot nível conta"),BENEFICIOS!$A:$G,5,0)))) -> Criar | DM8: 19.9 | DN8: =IF(DM8=0,"",IF(DM8=VLOOKUP("PCS-OzTL32",ARBOR!$A:$C,3,0),0.0001,IF(DM8>VLOOKUP("PCS-OzTL32",ARBOR!$A:$C,3,0),"Maior que CAP!",IF((DOLLAR(DM8+(VLOOKUP("PCS-OzTL32",ARBOR!$A:$C,3,0)*-TRUNC(DM8/VLOOKUP("PCS-OzTL32",ARBOR!$A:$C,3,0)-1,4)),6))<>(DOLLAR(VLOOKUP("PCS-OzTL32",ARBOR!$A:$C,3,0),6)),-TRUNC(DM8/VLOOKUP("PCS-OzTL32",ARBOR!$A:$C,3,0)-1,4)+0.0001,-TRUNC(DM8/VLOOKUP("PCS-OzTL32",ARBOR!$A:$C,3,0)-1,4))))) -> 0.0918 | DO8: =IF(DN8="S/Desc","S/Desc",IF(ISERROR(IF(DN8="","",VLOOKUP(($BC8&DN8&"Template desconto % Playboy nível conta"),BENEFICIOS!$A:$G,5,0))),"Criar",IF(DN8="","",VLOOKUP(($BC8&DN8&"Template desconto % Playboy nível conta"),BENEFICIOS!$A:$G,5,0)))) -> Criar | DP8: 29.9 | DQ8: =IF(DP8=0,"",IF(DP8=VLOOKUP("PCS-OzTL33",ARBOR!$A:$C,3,0),0.0001,IF(DP8>VLOOKUP("PCS-OzTL33",ARBOR!$A:$C,3,0),"Maior que CAP!",IF((DOLLAR(DP8+(VLOOKUP("PCS-OzTL33",ARBOR!$A:$C,3,0)*-TRUNC(DP8/VLOOKUP("PCS-OzTL33",ARBOR!$A:$C,3,0)-1,4)),6))<>(DOLLAR(VLOOKUP("PCS-OzTL33",ARBOR!$A:$C,3,0),6)),-TRUNC(DP8/VLOOKUP("PCS-OzTL33",ARBOR!$A:$C,3,0)-1,4)+0.0001,-TRUNC(DP8/VLOOKUP("PCS-OzTL33",ARBOR!$A:$C,3,0)-1,4))))) -> 0.0918 | DR8: =IF(DQ8="S/Desc","S/Desc",IF(ISERROR(IF(DQ8="","",VLOOKUP(($BC8&DQ8&"Template desconto % Sexy Hot + Playboy nível conta"),BENEFICIOS!$A:$G,5,0))),"Criar",IF(DQ8="","",VLOOKUP(($BC8&DQ8&"Template desconto % Sexy Hot + Playboy nível conta"),BENEFICIOS!$A:$G,5,0)))) -> Criar | DS8: 14.9 | DT8: =IF(DS8=0,"",IF(DS8=VLOOKUP("PCS-OzTL503",ARBOR!$A:$C,3,0),0.0001,IF(DS8>VLOOKUP("PCS-OzTL503",ARBOR!$A:$C,3,0),"Maior que CAP!",IF((DOLLAR(DS8+(VLOOKUP("PCS-OzTL503",ARBOR!$A:$C,3,0)*-TRUNC(DS8/VLOOKUP("PCS-OzTL503",ARBOR!$A:$C,3,0)-1,4)),6))<>(DOLLAR(VLOOKUP("PCS-OzTL503",ARBOR!$A:$C,3,0),6)),-TRUNC(DS8/VLOOKUP("PCS-OzTL503",ARBOR!$A:$C,3,0)-1,4)+0.0001,-TRUNC(DS8/VLOOKUP("PCS-OzTL503",ARBOR!$A:$C,3,0)-1,4))))) -> 0.0915 | DU8: =IF(DT8="S/Desc","S/Desc",IF(ISERROR(IF(DT8="","",VLOOKUP(($BC8&DT8&"Template desconto % SexPrivê nível conta"),BENEFICIOS!$A:$G,5,0))),"Criar",IF(DT8="","",VLOOKUP(($BC8&DT8&"Template desconto % SexPrivê nível conta"),BENEFICIOS!$A:$G,5,0)))) -> Criar | DV8: 10 | DW8: =IF(DV8=0,"",IF(DV8=VLOOKUP("PCS-OzTL500",ARBOR!$A:$C,3,0),0.0001,IF(DV8>VLOOKUP("PCS-OzTL500",ARBOR!$A:$C,3,0),"Maior que CAP!",IF((DOLLAR(DV8+(VLOOKUP("PCS-OzTL500",ARBOR!$A:$C,3,0)*-TRUNC(DV8/VLOOKUP("PCS-OzTL500",ARBOR!$A:$C,3,0)-1,4)),6))<>(DOLLAR(VLOOKUP("PCS-OzTL500",ARBOR!$A:$C,3,0),6)),-TRUNC(DV8/VLOOKUP("PCS-OzTL500",ARBOR!$A:$C,3,0)-1,4)+0.0001,-TRUNC(DV8/VLOOKUP("PCS-OzTL500",ARBOR!$A:$C,3,0)-1,4))))) -> 0.0918 | DX8: =IF(DW8="S/Desc","S/Desc",IF(ISERROR(IF(DW8="","",VLOOKUP(($BC8&DW8&"Template desconto % Étnico nível conta"),BENEFICIOS!$A:$G,5,0))),"Criar",IF(DW8="","",VLOOKUP(($BC8&DW8&"Template desconto % Étnico nível conta"),BENEFICIOS!$A:$G,5,0)))) -> Criar | DZ8: =IF(DY8=0,"",IF(DY8=VLOOKUP("PCS-OzTL50",ARBOR!$A:$C,3,0),0.0001,IF(DY8>VLOOKUP("PCS-OzTL50",ARBOR!$A:$C,3,0),"Maior que CAP!",IF((DOLLAR(DY8+(VLOOKUP("PCS-OzTL50",ARBOR!$A:$C,3,0)*-TRUNC(DY8/VLOOKUP("PCS-OzTL50",ARBOR!$A:$C,3,0)-1,4)),6))<>(DOLLAR(VLOOKUP("PCS-OzTL50",ARBOR!$A:$C,3,0),6)),-TRUNC(DY8/VLOOKUP("PCS-OzTL50",ARBOR!$A:$C,3,0)-1,4)+0.0001,-TRUNC(DY8/VLOOKUP("PCS-OzTL50",ARBOR!$A:$C,3,0)-1,4))))) | EC8: =IF(EB8=0,"",IF(EB8=VLOOKUP("PCS-OzTL51",ARBOR!$A:$C,3,0),0.0001,IF(EB8>VLOOKUP("PCS-OzTL51",ARBOR!$A:$C,3,0),"Maior que CAP!",IF((DOLLAR(EB8+(VLOOKUP("PCS-OzTL51",ARBOR!$A:$C,3,0)*-TRUNC(EB8/VLOOKUP("PCS-OzTL51",ARBOR!$A:$C,3,0)-1,4)),6))<>(DOLLAR(VLOOKUP("PCS-OzTL51",ARBOR!$A:$C,3,0),6)),-TRUNC(EB8/VLOOKUP("PCS-OzTL51",ARBOR!$A:$C,3,0)-1,4)+0.0001,-TRUNC(EB8/VLOOKUP("PCS-OzTL51",ARBOR!$A:$C,3,0)-1,4))))) | EF8: =IF(EE8=0,"",IF(EE8=VLOOKUP("PCS-OzTL52",ARBOR!$A:$C,3,0),0.0001,IF(EE8>VLOOKUP("PCS-OzTL52",ARBOR!$A:$C,3,0),"Maior que CAP!",IF((DOLLAR(EE8+(VLOOKUP("PCS-OzTL52",ARBOR!$A:$C,3,0)*-TRUNC(EE8/VLOOKUP("PCS-OzTL52",ARBOR!$A:$C,3,0)-1,4)),6))<>(DOLLAR(VLOOKUP("PCS-OzTL52",ARBOR!$A:$C,3,0),6)),-TRUNC(EE8/VLOOKUP("PCS-OzTL52",ARBOR!$A:$C,3,0)-1,4)+0.0001,-TRUNC(EE8/VLOOKUP("PCS-OzTL52",ARBOR!$A:$C,3,0)-1,4))))) | EI8: =IF(EH8=0,"",IF(EH8=VLOOKUP("PCS-OzTL53",ARBOR!$A:$C,3,0),0.0001,IF(EH8>VLOOKUP("PCS-OzTL53",ARBOR!$A:$C,3,0),"Maior que CAP!",IF((DOLLAR(EH8+(VLOOKUP("PCS-OzTL53",ARBOR!$A:$C,3,0)*-TRUNC(EH8/VLOOKUP("PCS-OzTL53",ARBOR!$A:$C,3,0)-1,4)),6))<>(DOLLAR(VLOOKUP("PCS-OzTL53",ARBOR!$A:$C,3,0),6)),-TRUNC(EH8/VLOOKUP("PCS-OzTL53",ARBOR!$A:$C,3,0)-1,4)+0.0001,-TRUNC(EH8/VLOOKUP("PCS-OzTL53",ARBOR!$A:$C,3,0)-1,4))))) | EL8: =IF(EK8=0,"",IF(EK8=VLOOKUP("PCS-OzTL54",ARBOR!$A:$C,3,0),0.0001,IF(EK8>VLOOKUP("PCS-OzTL54",ARBOR!$A:$C,3,0),"Maior que CAP!",IF((DOLLAR(EK8+(VLOOKUP("PCS-OzTL54",ARBOR!$A:$C,3,0)*-TRUNC(EK8/VLOOKUP("PCS-OzTL54",ARBOR!$A:$C,3,0)-1,4)),6))<>(DOLLAR(VLOOKUP("PCS-OzTL54",ARBOR!$A:$C,3,0),6)),-TRUNC(EK8/VLOOKUP("PCS-OzTL54",ARBOR!$A:$C,3,0)-1,4)+0.0001,-TRUNC(EK8/VLOOKUP("PCS-OzTL54",ARBOR!$A:$C,3,0)-1,4))))) | EN8: 24.9 | EO8: =IF(EN8=0,"",IF(EN8=VLOOKUP("PCS-OzTL99",ARBOR!$A:$C,3,0),0.0001,IF(EN8>VLOOKUP("PCS-OzTL99",ARBOR!$A:$C,3,0),"Maior que CAP!",IF((DOLLAR(EN8+(VLOOKUP("PCS-OzTL99",ARBOR!$A:$C,3,0)*-TRUNC(EN8/VLOOKUP("PCS-OzTL99",ARBOR!$A:$C,3,0)-1,4)),6))<>(DOLLAR(VLOOKUP("PCS-OzTL99",ARBOR!$A:$C,3,0),6)),-TRUNC(EN8/VLOOKUP("PCS-OzTL99",ARBOR!$A:$C,3,0)-1,4)+0.0001,-TRUNC(EN8/VLOOKUP("PCS-OzTL99",ARBOR!$A:$C,3,0)-1,4))))) -> 0.1673 | EP8: =IF(EO8="S/Desc","S/Desc",IF(ISERROR(IF(EO8="","",VLOOKUP(($BC8&EO8&"Template desconto % Ponto adicional nível conta"),BENEFICIOS!$A:$G,5,0))),"Criar",IF(EO8="","",VLOOKUP(($BC8&EO8&"Template desconto % Ponto adicional nível conta"),BENEFICIOS!$A:$G,5,0)))) -> Criar | ER8: =IF(EQ8="Sim","PCS-34704","") | ES8: Sim | ET8: Benefício | EU8: 499 | EV8: 12 | EW8: =IF(ET8="Benefício","Oi benefício fidelização Multiprodutos","") -> Oi benefício fidelização Multiprodutos | EX8: =IF(ET8="Benefício","PCS-Fk83324","") -> PCS-Fk83324 | EY8: =IF(ES8="Sim","PCS-SBL553142","") -> PCS-SBL553142 | EZ8: LD + VC Oi | FA8: 0T0T_FTV_MIN_LD_270000. | FG8: =IF($BH8="","",$BH8+$BE8) | FH8: =IF($BK8="","",$BK8+$BE8) -> 114.9 | FI8: =IF($BN8="","",$BN8+$BE8) | FJ8: =IF($BQ8="","",$BQ8+$BE8) | FK8: =IF($BT8="","",$BT8+$BE8) | FL8: =IF($BW8="","",$BW8+$BE8) | FM8: =IF($BZ8="","",$BZ8+$BE8) | FN8: =IF($CC8="","",$CC8+$BE8) | FO8: =IF($CF8="","",$CF8+$BE8) | FP8: =IF($CI8="","",$CI8+$BE8) -> 124.9 | FQ8: =IF($CL8="","",$CL8+$BE8) | FR8: =IF($CO8="","",$CO8+$BE8) | FS8: =IF($CR8="","",$CR8+$BE8) | FT8: =IF($CU8="","",$CU8+$BE8) -> 144.9 | FU8: =IF($CX8="","",$CX8+$BE8) | FV8: =IF($DA8="","",$DA8+$BE8) | FW8: =IF($DD8="","",$DD8+$BE8)
A9: Oi Total | B9: Migração | C9: Atuais | D9: Não | AM9: OT_ATV_JUL17_FID_DACC_2PTV_TV3_MF-TF_LD-VC_OF3 | AN9: Rentabilizar atuais clientes do plano | AO9: Produto Fixo + TV , Produto com fidelização | AP9: 42917 | AQ9: 43039 | AR9: 20. Oi Total | AS9: 20. Oi Total | AU9: Varejo | AV9: 20 | AW9: 10000 | AX9: Campanha Restrita | AY9: Sim | AZ9: Sim | BA9: Não | BB9: OT_ATV_JUL17_FID_DACC_2PTV_TV3_MF-TF_LD-VC_OF3 | BC9: Oi Total Fixo + TV 3 | BD9: =IF(BC9="Oi Total Fixo + TV 1","CFG-2Plowpi",IF(BC9="Oi Total Fixo + TV 2","PCS-2PMepi",IF(BC9="Oi Total Fixo + TV 3","PCS-2PHipi",""))) -> PCS-2PHipi | BE9: 35 | BF9: =IF(BE9=0,"",IF(BE9=VLOOKUP("FIXO",ARBOR!$A:$C,3,0),0.0001,IF(BE9>VLOOKUP("FIXO",ARBOR!$A:$C,3,0),"Maior que CAP!",IF((DOLLAR(BE9+(VLOOKUP("FIXO",ARBOR!$A:$C,3,0)*-TRUNC(BE9/VLOOKUP("FIXO",ARBOR!$A:$C,3,0)-1,4)),6))<>(DOLLAR(VLOOKUP("FIXO",ARBOR!$A:$C,3,0),6)),-TRUNC(BE9/VLOOKUP("FIXO",ARBOR!$A:$C,3,0)-1,4)+0.0001,-TRUNC(BE9/VLOOKUP("FIXO",ARBOR!$A:$C,3,0)-1,4))))) -> 0.5386 | BG9: =IF(ISERROR(IF(BF9="","",VLOOKUP(($BC9&BF9&"Template de desconto FLAT bundle - Fixo - Varejo - Ganho Tributário Cross"),BENEFICIOS!$A:$G,5,0))),"Criar",IF(BF9="","",VLOOKUP(($BC9&BF9&"Template de desconto FLAT bundle - Fixo - Varejo - Ganho Tributário Cross"),BENEFICIOS!$A:$G,5,0))) -> Criar | BI9: =IF(BH9=0,"",IF(BH9=VLOOKUP("PCS-OzTL40",ARBOR!$A:$C,3,0),0.0001,IF(BH9>VLOOKUP("PCS-OzTL40",ARBOR!$A:$C,3,0),"Maior que CAP!",IF((DOLLAR(BH9+(VLOOKUP("PCS-OzTL40",ARBOR!$A:$C,3,0)*-TRUNC(BH9/VLOOKUP("PCS-OzTL40",ARBOR!$A:$C,3,0)-1,4)),6))<>(DOLLAR(VLOOKUP("PCS-OzTL40",ARBOR!$A:$C,3,0),6)),-TRUNC(BH9/VLOOKUP("PCS-OzTL40",ARBOR!$A:$C,3,0)-1,4)+0.0001,-TRUNC(BH9/VLOOKUP("PCS-OzTL40",ARBOR!$A:$C,3,0)-1,4))))) | BJ9: =IF(ISERROR(IF(BI9="","",VLOOKUP((BC9&BI9&"Template desconto FLAT Plano Principal Oi TV nível conta"),BENEFICIOS!$A:$G,5,0))),"Criar",IF(BI9="","",VLOOKUP((BC9&BI9&"Template desconto FLAT Plano Principal Oi TV nível conta"),BENEFICIOS!$A:$G,5,0))) | BL9: =IF(BK9=0,"",IF(BK9=VLOOKUP("PCS-OzTL41",ARBOR!$A:$C,3,0),0.0001,IF(BK9>VLOOKUP("PCS-OzTL41",ARBOR!$A:$C,3,0),"Maior que CAP!",IF((DOLLAR(BK9+(VLOOKUP("PCS-OzTL41",ARBOR!$A:$C,3,0)*-TRUNC(BK9/VLOOKUP("PCS-OzTL41",ARBOR!$A:$C,3,0)-1,4)),6))<>(DOLLAR(VLOOKUP("PCS-OzTL41",ARBOR!$A:$C,3,0),6)),-TRUNC(BK9/VLOOKUP("PCS-OzTL41",ARBOR!$A:$C,3,0)-1,4)+0.0001,-TRUNC(BK9/VLOOKUP("PCS-OzTL41",ARBOR!$A:$C,3,0)-1,4))))) | BM9: =IF(ISERROR(IF(BL9="","",VLOOKUP((BC9&BL9&"Template desconto FLAT Plano Principal Oi TV nível conta"),BENEFICIOS!$A:$G,5,0))),"Criar",IF(BL9="","",VLOOKUP((BC9&BL9&"Template desconto FLAT Plano Principal Oi TV nível conta"),BENEFICIOS!$A:$G,5,0))) | BN9: 109.9 | BO9: =IF(BN9=0,"",IF(BN9=VLOOKUP("PCS-OzTL44",ARBOR!$A:$C,3,0),0.0001,IF(BN9>VLOOKUP("PCS-OzTL44",ARBOR!$A:$C,3,0),"Maior que CAP!",IF((DOLLAR(BN9+(VLOOKUP("PCS-OzTL44",ARBOR!$A:$C,3,0)*-TRUNC(BN9/VLOOKUP("PCS-OzTL44",ARBOR!$A:$C,3,0)-1,4)),6))<>(DOLLAR(VLOOKUP("PCS-OzTL44",ARBOR!$A:$C,3,0),6)),-TRUNC(BN9/VLOOKUP("PCS-OzTL44",ARBOR!$A:$C,3,0)-1,4)+0.0001,-TRUNC(BN9/VLOOKUP("PCS-OzTL44",ARBOR!$A:$C,3,0)-1,4))))) -> 0.4295 | BP9: =IF(ISERROR(IF(BO9="","",VLOOKUP((BC9&BO9&"Template desconto FLAT Plano Principal Oi TV nível conta"),BENEFICIOS!$A:$G,5,0))),"Criar",IF(BO9="","",VLOOKUP((BC9&BO9&"Template desconto FLAT Plano Principal Oi TV nível conta"),BENEFICIOS!$A:$G,5,0))) -> Criar | BQ9: 109.9 | BR9: =IF(BQ9=0,"",IF(BQ9=VLOOKUP("PCS-OzTL43",ARBOR!$A:$C,3,0),0.0001,IF(BQ9>VLOOKUP("PCS-OzTL43",ARBOR!$A:$C,3,0),"Maior que CAP!",IF((DOLLAR(BQ9+(VLOOKUP("PCS-OzTL43",ARBOR!$A:$C,3,0)*-TRUNC(BQ9/VLOOKUP("PCS-OzTL43",ARBOR!$A:$C,3,0)-1,4)),6))<>(DOLLAR(VLOOKUP("PCS-OzTL43",ARBOR!$A:$C,3,0),6)),-TRUNC(BQ9/VLOOKUP("PCS-OzTL43",ARBOR!$A:$C,3,0)-1,4)+0.0001,-TRUNC(BQ9/VLOOKUP("PCS-OzTL43",ARBOR!$A:$C,3,0)-1,4))))) -> 0.4603 | BS9: =IF(ISERROR(IF(BR9="","",VLOOKUP((BC9&BR9&"Template desconto FLAT Plano Principal Oi TV nível conta"),BENEFICIOS!$A:$G,5,0))),"Criar",IF(BR9="","",VLOOKUP((BC9&BR9&"Template desconto FLAT Plano Principal Oi TV nível conta"),BENEFICIOS!$A:$G,5,0))) -> Criar | BT9: 139.9 | BU9: =IF(BT9=0,"",IF(BT9=VLOOKUP("PCS-OzTL45",ARBOR!$A:$C,3,0),0.0001,IF(BT9>VLOOKUP("PCS-OzTL45",ARBOR!$A:$C,3,0),"Maior que CAP!",IF((DOLLAR(BT9+(VLOOKUP("PCS-OzTL45",ARBOR!$A:$C,3,0)*-TRUNC(BT9/VLOOKUP("PCS-OzTL45",ARBOR!$A:$C,3,0)-1,4)),6))<>(DOLLAR(VLOOKUP("PCS-OzTL45",ARBOR!$A:$C,3,0),6)),-TRUNC(BT9/VLOOKUP("PCS-OzTL45",ARBOR!$A:$C,3,0)-1,4)+0.0001,-TRUNC(BT9/VLOOKUP("PCS-OzTL45",ARBOR!$A:$C,3,0)-1,4))))) -> 0.3311 | BV9: =IF(ISERROR(IF(BU9="","",VLOOKUP((BC9&BU9&"Template desconto FLAT Plano Principal Oi TV nível conta"),BENEFICIOS!$A:$G,5,0))),"Criar",IF(BU9="","",VLOOKUP((BC9&BU9&"Template desconto FLAT Plano Principal Oi TV nível conta"),BENEFICIOS!$A:$G,5,0))) -> Criar | BX9: =IF(BW9=0,"",IF(BW9=VLOOKUP("PCS-OzTL741",ARBOR!$A:$C,3,0),0.0001,IF(BW9>VLOOKUP("PCS-OzTL741",ARBOR!$A:$C,3,0),"Maior que CAP!",IF((DOLLAR(BW9+(VLOOKUP("PCS-OzTL741",ARBOR!$A:$C,3,0)*-TRUNC(BW9/VLOOKUP("PCS-OzTL741",ARBOR!$A:$C,3,0)-1,4)),6))<>(DOLLAR(VLOOKUP("PCS-OzTL741",ARBOR!$A:$C,3,0),6)),-TRUNC(BW9/VLOOKUP("PCS-OzTL741",ARBOR!$A:$C,3,0)-1,4)+0.0001,-TRUNC(BW9/VLOOKUP("PCS-OzTL741",ARBOR!$A:$C,3,0)-1,4))))) | BY9: =IF(ISERROR(IF(BX9="","",VLOOKUP((BC9&BX9&"Template desconto FLAT Plano Principal Oi TV nível conta"),BENEFICIOS!$A:$G,5,0))),"Criar",IF(BX9="","",VLOOKUP((BC9&BX9&"Template desconto FLAT Plano Principal Oi TV nível conta"),BENEFICIOS!$A:$G,5,0))) | CA9: =IF(BZ9=0,"",IF(BZ9=VLOOKUP("PCS-OzTL744",ARBOR!$A:$C,3,0),0.0001,IF(BZ9>VLOOKUP("PCS-OzTL744",ARBOR!$A:$C,3,0),"Maior que CAP!",IF((DOLLAR(BZ9+(VLOOKUP("PCS-OzTL744",ARBOR!$A:$C,3,0)*-TRUNC(BZ9/VLOOKUP("PCS-OzTL744",ARBOR!$A:$C,3,0)-1,4)),6))<>(DOLLAR(VLOOKUP("PCS-OzTL744",ARBOR!$A:$C,3,0),6)),-TRUNC(BZ9/VLOOKUP("PCS-OzTL744",ARBOR!$A:$C,3,0)-1,4)+0.0001,-TRUNC(BZ9/VLOOKUP("PCS-OzTL744",ARBOR!$A:$C,3,0)-1,4))))) | CB9: =IF(ISERROR(IF(CA9="","",VLOOKUP(($BC9&CA9&"Template desconto FLAT Plano Principal Oi TV nível conta"),BENEFICIOS!$A:$G,5,0))),"Criar",IF(CA9="","",VLOOKUP(($BC9&CA9&"Template desconto FLAT Plano Principal Oi TV nível conta"),BENEFICIOS!$A:$G,5,0))) | CD9: =IF(CC9=0,"",IF(CC9=VLOOKUP("PCS-OzTL743",ARBOR!$A:$C,3,0),0.0001,IF(CC9>VLOOKUP("PCS-OzTL743",ARBOR!$A:$C,3,0),"Maior que CAP!",IF((DOLLAR(CC9+(VLOOKUP("PCS-OzTL743",ARBOR!$A:$C,3,0)*-TRUNC(CC9/VLOOKUP("PCS-OzTL743",ARBOR!$A:$C,3,0)-1,4)),6))<>(DOLLAR(VLOOKUP("PCS-OzTL743",ARBOR!$A:$C,3,0),6)),-TRUNC(CC9/VLOOKUP("PCS-OzTL743",ARBOR!$A:$C,3,0)-1,4)+0.0001,-TRUNC(CC9/VLOOKUP("PCS-OzTL743",ARBOR!$A:$C,3,0)-1,4))))) | CE9: =IF(ISERROR(IF(CD9="","",VLOOKUP(($BC9&CD9&"Template desconto FLAT Plano Principal Oi TV nível conta"),BENEFICIOS!$A:$G,5,0))),"Criar",IF(CD9="","",VLOOKUP(($BC9&CD9&"Template desconto FLAT Plano Principal Oi TV nível conta"),BENEFICIOS!$A:$G,5,0))) | CG9: =IF(CF9=0,"",IF(CF9=VLOOKUP("PCS-OzTL745",ARBOR!$A:$C,3,0),0.0001,IF(CF9>VLOOKUP("PCS-OzTL745",ARBOR!$A:$C,3,0),"Maior que CAP!",IF((DOLLAR(CF9+(VLOOKUP("PCS-OzTL745",ARBOR!$A:$C,3,0)*-TRUNC(CF9/VLOOKUP("PCS-OzTL745",ARBOR!$A:$C,3,0)-1,4)),6))<>(DOLLAR(VLOOKUP("PCS-OzTL745",ARBOR!$A:$C,3,0),6)),-TRUNC(CF9/VLOOKUP("PCS-OzTL745",ARBOR!$A:$C,3,0)-1,4)+0.0001,-TRUNC(CF9/VLOOKUP("PCS-OzTL745",ARBOR!$A:$C,3,0)-1,4))))) | CH9: =IF(ISERROR(IF(CG9="","",VLOOKUP(($BC9&CG9&"Template desconto FLAT Plano Principal Oi TV nível conta"),BENEFICIOS!$A:$G,5,0))),"Criar",IF(CG9="","",VLOOKUP(($BC9&CG9&"Template desconto FLAT Plano Principal Oi TV nível conta"),BENEFICIOS!$A:$G,5,0))) | CJ9: =IF(CI9=0,"",IF(CI9=VLOOKUP("PCS-OzTL42",ARBOR!$A:$C,3,0),0.0001,IF(CI9>VLOOKUP("PCS-OzTL42",ARBOR!$A:$C,3,0),"Maior que CAP!",IF((DOLLAR(CI9+(VLOOKUP("PCS-OzTL42",ARBOR!$A:$C,3,0)*-TRUNC(CI9/VLOOKUP("PCS-OzTL42",ARBOR!$A:$C,3,0)-1,4)),6))<>(DOLLAR(VLOOKUP("PCS-OzTL42",ARBOR!$A:$C,3,0),6)),-TRUNC(CI9/VLOOKUP("PCS-OzTL42",ARBOR!$A:$C,3,0)-1,4)+0.0001,-TRUNC(CI9/VLOOKUP("PCS-OzTL42",ARBOR!$A:$C,3,0)-1,4))))) | CK9: =IF(ISERROR(IF(CJ9="","",VLOOKUP(($BC9&CJ9&"Template desconto FLAT Plano Principal Oi TV nível conta"),BENEFICIOS!$A:$G,5,0))),"Criar",IF(CJ9="","",VLOOKUP(($BC9&CJ9&"Template desconto FLAT Plano Principal Oi TV nível conta"),BENEFICIOS!$A:$G,5,0))) | CL9: 119.9 | CM9: =IF(CL9=0,"",IF(CL9=VLOOKUP("PCS-OzTL47",ARBOR!$A:$C,3,0),0.0001,IF(CL9>VLOOKUP("PCS-OzTL47",ARBOR!$A:$C,3,0),"Maior que CAP!",IF((DOLLAR(CL9+(VLOOKUP("PCS-OzTL47",ARBOR!$A:$C,3,0)*-TRUNC(CL9/VLOOKUP("PCS-OzTL47",ARBOR!$A:$C,3,0)-1,4)),6))<>(DOLLAR(VLOOKUP("PCS-OzTL47",ARBOR!$A:$C,3,0),6)),-TRUNC(CL9/VLOOKUP("PCS-OzTL47",ARBOR!$A:$C,3,0)-1,4)+0.0001,-TRUNC(CL9/VLOOKUP("PCS-OzTL47",ARBOR!$A:$C,3,0)-1,4))))) -> 0.4112 | CN9: =IF(ISERROR(IF(CM9="","",VLOOKUP(($BC9&CM9&"Template desconto FLAT Plano Principal Oi TV nível conta"),BENEFICIOS!$A:$G,5,0))),"Criar",IF(CM9="","",VLOOKUP(($BC9&CM9&"Template desconto FLAT Plano Principal Oi TV nível conta"),BENEFICIOS!$A:$G,5,0))) -> Criar | CO9: 119.9 | CP9: =IF(CO9=0,"",IF(CO9=VLOOKUP("PCS-OzTL46",ARBOR!$A:$C,3,0),0.0001,IF(CO9>VLOOKUP("PCS-OzTL46",ARBOR!$A:$C,3,0),"Maior que CAP!",IF((DOLLAR(CO9+(VLOOKUP("PCS-OzTL46",ARBOR!$A:$C,3,0)*-TRUNC(CO9/VLOOKUP("PCS-OzTL46",ARBOR!$A:$C,3,0)-1,4)),6))<>(DOLLAR(VLOOKUP("PCS-OzTL46",ARBOR!$A:$C,3,0),6)),-TRUNC(CO9/VLOOKUP("PCS-OzTL46",ARBOR!$A:$C,3,0)-1,4)+0.0001,-TRUNC(CO9/VLOOKUP("PCS-OzTL46",ARBOR!$A:$C,3,0)-1,4))))) -> 0.4414 | CQ9: =IF(ISERROR(IF(CP9="","",VLOOKUP(($BC9&CP9&"Template desconto FLAT Plano Principal Oi TV nível conta"),BENEFICIOS!$A:$G,5,0))),"Criar",IF(CP9="","",VLOOKUP(($BC9&CP9&"Template desconto FLAT Plano Principal Oi TV nível conta"),BENEFICIOS!$A:$G,5,0))) -> Criar | CR9: 149.9 | CS9: =IF(CR9=0,"",IF(CR9=VLOOKUP("PCS-OzTL48",ARBOR!$A:$C,3,0),0.0001,IF(CR9>VLOOKUP("PCS-OzTL48",ARBOR!$A:$C,3,0),"Maior que CAP!",IF((DOLLAR(CR9+(VLOOKUP("PCS-OzTL48",ARBOR!$A:$C,3,0)*-TRUNC(CR9/VLOOKUP("PCS-OzTL48",ARBOR!$A:$C,3,0)-1,4)),6))<>(DOLLAR(VLOOKUP("PCS-OzTL48",ARBOR!$A:$C,3,0),6)),-TRUNC(CR9/VLOOKUP("PCS-OzTL48",ARBOR!$A:$C,3,0)-1,4)+0.0001,-TRUNC(CR9/VLOOKUP("PCS-OzTL48",ARBOR!$A:$C,3,0)-1,4))))) -> 0.408 | CT9: =IF(ISERROR(IF(CS9="","",VLOOKUP(($BC9&CS9&"Template desconto FLAT Plano Principal Oi TV nível conta"),BENEFICIOS!$A:$G,5,0))),"Criar",IF(CS9="","",VLOOKUP(($BC9&CS9&"Template desconto FLAT Plano Principal Oi TV nível conta"),BENEFICIOS!$A:$G,5,0))) -> Criar | CV9: =IF(CU9=0,"",IF(CU9=VLOOKUP("PCS-OzTL742",ARBOR!$A:$C,3,0),0.0001,IF(CU9>VLOOKUP("PCS-OzTL742",ARBOR!$A:$C,3,0),"Maior que CAP!",IF((DOLLAR(CU9+(VLOOKUP("PCS-OzTL742",ARBOR!$A:$C,3,0)*-TRUNC(CU9/VLOOKUP("PCS-OzTL742",ARBOR!$A:$C,3,0)-1,4)),6))<>(DOLLAR(VLOOKUP("PCS-OzTL742",ARBOR!$A:$C,3,0),6)),-TRUNC(CU9/VLOOKUP("PCS-OzTL742",ARBOR!$A:$C,3,0)-1,4)+0.0001,-TRUNC(CU9/VLOOKUP("PCS-OzTL742",ARBOR!$A:$C,3,0)-1,4))))) | CW9: =IF(ISERROR(IF(CV9="","",VLOOKUP(($BC9&CV9&"Template desconto FLAT Plano Principal Oi TV nível conta"),BENEFICIOS!$A:$G,5,0))),"Criar",IF(CV9="","",VLOOKUP(($BC9&CV9&"Template desconto FLAT Plano Principal Oi TV nível conta"),BENEFICIOS!$A:$G,5,0))) | CY9: =IF(CX9=0,"",IF(CX9=VLOOKUP("PCS-OzTL747",ARBOR!$A:$C,3,0),0.0001,IF(CX9>VLOOKUP("PCS-OzTL747",ARBOR!$A:$C,3,0),"Maior que CAP!",IF((DOLLAR(CX9+(VLOOKUP("PCS-OzTL747",ARBOR!$A:$C,3,0)*-TRUNC(CX9/VLOOKUP("PCS-OzTL747",ARBOR!$A:$C,3,0)-1,4)),6))<>(DOLLAR(VLOOKUP("PCS-OzTL747",ARBOR!$A:$C,3,0),6)),-TRUNC(CX9/VLOOKUP("PCS-OzTL747",ARBOR!$A:$C,3,0)-1,4)+0.0001,-TRUNC(CX9/VLOOKUP("PCS-OzTL747",ARBOR!$A:$C,3,0)-1,4))))) | CZ9: =IF(ISERROR(IF(CY9="","",VLOOKUP(($BC9&CY9&"Template desconto FLAT Plano Principal Oi TV nível conta"),BENEFICIOS!$A:$G,5,0))),"Criar",IF(CY9="","",VLOOKUP(($BC9&CY9&"Template desconto FLAT Plano Principal Oi TV nível conta"),BENEFICIOS!$A:$G,5,0))) | DB9: =IF(DA9=0,"",IF(DA9=VLOOKUP("PCS-OzTL746",ARBOR!$A:$C,3,0),0.0001,IF(DA9>VLOOKUP("PCS-OzTL746",ARBOR!$A:$C,3,0),"Maior que CAP!",IF((DOLLAR(DA9+(VLOOKUP("PCS-OzTL746",ARBOR!$A:$C,3,0)*-TRUNC(DA9/VLOOKUP("PCS-OzTL746",ARBOR!$A:$C,3,0)-1,4)),6))<>(DOLLAR(VLOOKUP("PCS-OzTL746",ARBOR!$A:$C,3,0),6)),-TRUNC(DA9/VLOOKUP("PCS-OzTL746",ARBOR!$A:$C,3,0)-1,4)+0.0001,-TRUNC(DA9/VLOOKUP("PCS-OzTL746",ARBOR!$A:$C,3,0)-1,4))))) | DC9: =IF(ISERROR(IF(DB9="","",VLOOKUP(($BC9&DB9&"Template desconto FLAT Plano Principal Oi TV nível conta"),BENEFICIOS!$A:$G,5,0))),"Criar",IF(DB9="","",VLOOKUP(($BC9&DB9&"Template desconto FLAT Plano Principal Oi TV nível conta"),BENEFICIOS!$A:$G,5,0))) | DE9: =IF(DD9=0,"",IF(DD9=VLOOKUP("PCS-OzTL748",ARBOR!$A:$C,3,0),0.0001,IF(DD9>VLOOKUP("PCS-OzTL748",ARBOR!$A:$C,3,0),"Maior que CAP!",IF((DOLLAR(DD9+(VLOOKUP("PCS-OzTL748",ARBOR!$A:$C,3,0)*-TRUNC(DD9/VLOOKUP("PCS-OzTL748",ARBOR!$A:$C,3,0)-1,4)),6))<>(DOLLAR(VLOOKUP("PCS-OzTL748",ARBOR!$A:$C,3,0),6)),-TRUNC(DD9/VLOOKUP("PCS-OzTL748",ARBOR!$A:$C,3,0)-1,4)+0.0001,-TRUNC(DD9/VLOOKUP("PCS-OzTL748",ARBOR!$A:$C,3,0)-1,4))))) | DF9: =IF(ISERROR(IF(DE9="","",VLOOKUP(($BC9&DE9&"Template desconto FLAT Plano Principal Oi TV nível conta"),BENEFICIOS!$A:$G,5,0))),"Criar",IF(DE9="","",VLOOKUP(($BC9&DE9&"Template desconto FLAT Plano Principal Oi TV nível conta"),BENEFICIOS!$A:$G,5,0))) | DG9: 75 | DH9: =IF(DG9=0,"",IF(DG9=VLOOKUP("PCS-OzTL34",ARBOR!$A:$C,3,0),0.0001,IF(DG9>VLOOKUP("PCS-OzTL34",ARBOR!$A:$C,3,0),"Maior que CAP!",IF((DOLLAR(DG9+(VLOOKUP("PCS-OzTL34",ARBOR!$A:$C,3,0)*-TRUNC(DG9/VLOOKUP("PCS-OzTL34",ARBOR!$A:$C,3,0)-1,4)),6))<>(DOLLAR(VLOOKUP("PCS-OzTL34",ARBOR!$A:$C,3,0),6)),-TRUNC(DG9/VLOOKUP("PCS-OzTL34",ARBOR!$A:$C,3,0)-1,4)+0.0001,-TRUNC(DG9/VLOOKUP("PCS-OzTL34",ARBOR!$A:$C,3,0)-1,4))))) -> 0.319 | DI9: =IF(DH9="S/Desc","S/Desc",IF(ISERROR(IF(DH9="","",VLOOKUP(($BC9&DH9&"Template desconto % Combate nível conta"),BENEFICIOS!$A:$G,5,0))),"Criar",IF(DH9="","",VLOOKUP(($BC9&DH9&"Template desconto % Combate nível conta"),BENEFICIOS!$A:$G,5,0)))) -> Criar | DJ9: 19.9 | DK9: =IF(DJ9=0,"",IF(DJ9=VLOOKUP("PCS-OzTL31",ARBOR!$A:$C,3,0),0.0001,IF(DJ9>VLOOKUP("PCS-OzTL31",ARBOR!$A:$C,3,0),"Maior que CAP!",IF((DOLLAR(DJ9+(VLOOKUP("PCS-OzTL31",ARBOR!$A:$C,3,0)*-TRUNC(DJ9/VLOOKUP("PCS-OzTL31",ARBOR!$A:$C,3,0)-1,4)),6))<>(DOLLAR(VLOOKUP("PCS-OzTL31",ARBOR!$A:$C,3,0),6)),-TRUNC(DJ9/VLOOKUP("PCS-OzTL31",ARBOR!$A:$C,3,0)-1,4)+0.0001,-TRUNC(DJ9/VLOOKUP("PCS-OzTL31",ARBOR!$A:$C,3,0)-1,4))))) -> 0.0918 | DL9: =IF(DK9="S/Desc","S/Desc",IF(ISERROR(IF(DK9="","",VLOOKUP(($BC9&DK9&"Template desconto % Sexy Hot nível conta"),BENEFICIOS!$A:$G,5,0))),"Criar",IF(DK9="","",VLOOKUP(($BC9&DK9&"Template desconto % Sexy Hot nível conta"),BENEFICIOS!$A:$G,5,0)))) -> Criar | DM9: 19.9 | DN9: =IF(DM9=0,"",IF(DM9=VLOOKUP("PCS-OzTL32",ARBOR!$A:$C,3,0),0.0001,IF(DM9>VLOOKUP("PCS-OzTL32",ARBOR!$A:$C,3,0),"Maior que CAP!",IF((DOLLAR(DM9+(VLOOKUP("PCS-OzTL32",ARBOR!$A:$C,3,0)*-TRUNC(DM9/VLOOKUP("PCS-OzTL32",ARBOR!$A:$C,3,0)-1,4)),6))<>(DOLLAR(VLOOKUP("PCS-OzTL32",ARBOR!$A:$C,3,0),6)),-TRUNC(DM9/VLOOKUP("PCS-OzTL32",ARBOR!$A:$C,3,0)-1,4)+0.0001,-TRUNC(DM9/VLOOKUP("PCS-OzTL32",ARBOR!$A:$C,3,0)-1,4))))) -> 0.0918 | DO9: =IF(DN9="S/Desc","S/Desc",IF(ISERROR(IF(DN9="","",VLOOKUP(($BC9&DN9&"Template desconto % Playboy nível conta"),BENEFICIOS!$A:$G,5,0))),"Criar",IF(DN9="","",VLOOKUP(($BC9&DN9&"Template desconto % Playboy nível conta"),BENEFICIOS!$A:$G,5,0)))) -> Criar | DP9: 29.9 | DQ9: =IF(DP9=0,"",IF(DP9=VLOOKUP("PCS-OzTL33",ARBOR!$A:$C,3,0),0.0001,IF(DP9>VLOOKUP("PCS-OzTL33",ARBOR!$A:$C,3,0),"Maior que CAP!",IF((DOLLAR(DP9+(VLOOKUP("PCS-OzTL33",ARBOR!$A:$C,3,0)*-TRUNC(DP9/VLOOKUP("PCS-OzTL33",ARBOR!$A:$C,3,0)-1,4)),6))<>(DOLLAR(VLOOKUP("PCS-OzTL33",ARBOR!$A:$C,3,0),6)),-TRUNC(DP9/VLOOKUP("PCS-OzTL33",ARBOR!$A:$C,3,0)-1,4)+0.0001,-TRUNC(DP9/VLOOKUP("PCS-OzTL33",ARBOR!$A:$C,3,0)-1,4))))) -> 0.0918 | DR9: =IF(DQ9="S/Desc","S/Desc",IF(ISERROR(IF(DQ9="","",VLOOKUP(($BC9&DQ9&"Template desconto % Sexy Hot + Playboy nível conta"),BENEFICIOS!$A:$G,5,0))),"Criar",IF(DQ9="","",VLOOKUP(($BC9&DQ9&"Template desconto % Sexy Hot + Playboy nível conta"),BENEFICIOS!$A:$G,5,0)))) -> Criar | DS9: 14.9 | DT9: =IF(DS9=0,"",IF(DS9=VLOOKUP("PCS-OzTL503",ARBOR!$A:$C,3,0),0.0001,IF(DS9>VLOOKUP("PCS-OzTL503",ARBOR!$A:$C,3,0),"Maior que CAP!",IF((DOLLAR(DS9+(VLOOKUP("PCS-OzTL503",ARBOR!$A:$C,3,0)*-TRUNC(DS9/VLOOKUP("PCS-OzTL503",ARBOR!$A:$C,3,0)-1,4)),6))<>(DOLLAR(VLOOKUP("PCS-OzTL503",ARBOR!$A:$C,3,0),6)),-TRUNC(DS9/VLOOKUP("PCS-OzTL503",ARBOR!$A:$C,3,0)-1,4)+0.0001,-TRUNC(DS9/VLOOKUP("PCS-OzTL503",ARBOR!$A:$C,3,0)-1,4))))) -> 0.0915 | DU9: =IF(DT9="S/Desc","S/Desc",IF(ISERROR(IF(DT9="","",VLOOKUP(($BC9&DT9&"Template desconto % SexPrivê nível conta"),BENEFICIOS!$A:$G,5,0))),"Criar",IF(DT9="","",VLOOKUP(($BC9&DT9&"Template desconto % SexPrivê nível conta"),BENEFICIOS!$A:$G,5,0)))) -> Criar | DV9: 10 | DW9: =IF(DV9=0,"",IF(DV9=VLOOKUP("PCS-OzTL500",ARBOR!$A:$C,3,0),0.0001,IF(DV9>VLOOKUP("PCS-OzTL500",ARBOR!$A:$C,3,0),"Maior que CAP!",IF((DOLLAR(DV9+(VLOOKUP("PCS-OzTL500",ARBOR!$A:$C,3,0)*-TRUNC(DV9/VLOOKUP("PCS-OzTL500",ARBOR!$A:$C,3,0)-1,4)),6))<>(DOLLAR(VLOOKUP("PCS-OzTL500",ARBOR!$A:$C,3,0),6)),-TRUNC(DV9/VLOOKUP("PCS-OzTL500",ARBOR!$A:$C,3,0)-1,4)+0.0001,-TRUNC(DV9/VLOOKUP("PCS-OzTL500",ARBOR!$A:$C,3,0)-1,4))))) -> 0.0918 | DX9: =IF(DW9="S/Desc","S/Desc",IF(ISERROR(IF(DW9="","",VLOOKUP(($BC9&DW9&"Template desconto % Étnico nível conta"),BENEFICIOS!$A:$G,5,0))),"Criar",IF(DW9="","",VLOOKUP(($BC9&DW9&"Template desconto % Étnico nível conta"),BENEFICIOS!$A:$G,5,0)))) -> Criar | DZ9: =IF(DY9=0,"",IF(DY9=VLOOKUP("PCS-OzTL50",ARBOR!$A:$C,3,0),0.0001,IF(DY9>VLOOKUP("PCS-OzTL50",ARBOR!$A:$C,3,0),"Maior que CAP!",IF((DOLLAR(DY9+(VLOOKUP("PCS-OzTL50",ARBOR!$A:$C,3,0)*-TRUNC(DY9/VLOOKUP("PCS-OzTL50",ARBOR!$A:$C,3,0)-1,4)),6))<>(DOLLAR(VLOOKUP("PCS-OzTL50",ARBOR!$A:$C,3,0),6)),-TRUNC(DY9/VLOOKUP("PCS-OzTL50",ARBOR!$A:$C,3,0)-1,4)+0.0001,-TRUNC(DY9/VLOOKUP("PCS-OzTL50",ARBOR!$A:$C,3,0)-1,4))))) | EC9: =IF(EB9=0,"",IF(EB9=VLOOKUP("PCS-OzTL51",ARBOR!$A:$C,3,0),0.0001,IF(EB9>VLOOKUP("PCS-OzTL51",ARBOR!$A:$C,3,0),"Maior que CAP!",IF((DOLLAR(EB9+(VLOOKUP("PCS-OzTL51",ARBOR!$A:$C,3,0)*-TRUNC(EB9/VLOOKUP("PCS-OzTL51",ARBOR!$A:$C,3,0)-1,4)),6))<>(DOLLAR(VLOOKUP("PCS-OzTL51",ARBOR!$A:$C,3,0),6)),-TRUNC(EB9/VLOOKUP("PCS-OzTL51",ARBOR!$A:$C,3,0)-1,4)+0.0001,-TRUNC(EB9/VLOOKUP("PCS-OzTL51",ARBOR!$A:$C,3,0)-1,4))))) | EF9: =IF(EE9=0,"",IF(EE9=VLOOKUP("PCS-OzTL52",ARBOR!$A:$C,3,0),0.0001,IF(EE9>VLOOKUP("PCS-OzTL52",ARBOR!$A:$C,3,0),"Maior que CAP!",IF((DOLLAR(EE9+(VLOOKUP("PCS-OzTL52",ARBOR!$A:$C,3,0)*-TRUNC(EE9/VLOOKUP("PCS-OzTL52",ARBOR!$A:$C,3,0)-1,4)),6))<>(DOLLAR(VLOOKUP("PCS-OzTL52",ARBOR!$A:$C,3,0),6)),-TRUNC(EE9/VLOOKUP("PCS-OzTL52",ARBOR!$A:$C,3,0)-1,4)+0.0001,-TRUNC(EE9/VLOOKUP("PCS-OzTL52",ARBOR!$A:$C,3,0)-1,4))))) | EI9: =IF(EH9=0,"",IF(EH9=VLOOKUP("PCS-OzTL53",ARBOR!$A:$C,3,0),0.0001,IF(EH9>VLOOKUP("PCS-OzTL53",ARBOR!$A:$C,3,0),"Maior que CAP!",IF((DOLLAR(EH9+(VLOOKUP("PCS-OzTL53",ARBOR!$A:$C,3,0)*-TRUNC(EH9/VLOOKUP("PCS-OzTL53",ARBOR!$A:$C,3,0)-1,4)),6))<>(DOLLAR(VLOOKUP("PCS-OzTL53",ARBOR!$A:$C,3,0),6)),-TRUNC(EH9/VLOOKUP("PCS-OzTL53",ARBOR!$A:$C,3,0)-1,4)+0.0001,-TRUNC(EH9/VLOOKUP("PCS-OzTL53",ARBOR!$A:$C,3,0)-1,4))))) | EL9: =IF(EK9=0,"",IF(EK9=VLOOKUP("PCS-OzTL54",ARBOR!$A:$C,3,0),0.0001,IF(EK9>VLOOKUP("PCS-OzTL54",ARBOR!$A:$C,3,0),"Maior que CAP!",IF((DOLLAR(EK9+(VLOOKUP("PCS-OzTL54",ARBOR!$A:$C,3,0)*-TRUNC(EK9/VLOOKUP("PCS-OzTL54",ARBOR!$A:$C,3,0)-1,4)),6))<>(DOLLAR(VLOOKUP("PCS-OzTL54",ARBOR!$A:$C,3,0),6)),-TRUNC(EK9/VLOOKUP("PCS-OzTL54",ARBOR!$A:$C,3,0)-1,4)+0.0001,-TRUNC(EK9/VLOOKUP("PCS-OzTL54",ARBOR!$A:$C,3,0)-1,4))))) | EN9: 24.9 | EO9: =IF(EN9=0,"",IF(EN9=VLOOKUP("PCS-OzTL99",ARBOR!$A:$C,3,0),0.0001,IF(EN9>VLOOKUP("PCS-OzTL99",ARBOR!$A:$C,3,0),"Maior que CAP!",IF((DOLLAR(EN9+(VLOOKUP("PCS-OzTL99",ARBOR!$A:$C,3,0)*-TRUNC(EN9/VLOOKUP("PCS-OzTL99",ARBOR!$A:$C,3,0)-1,4)),6))<>(DOLLAR(VLOOKUP("PCS-OzTL99",ARBOR!$A:$C,3,0),6)),-TRUNC(EN9/VLOOKUP("PCS-OzTL99",ARBOR!$A:$C,3,0)-1,4)+0.0001,-TRUNC(EN9/VLOOKUP("PCS-OzTL99",ARBOR!$A:$C,3,0)-1,4))))) -> 0.1673 | EP9: =IF(EO9="S/Desc","S/Desc",IF(ISERROR(IF(EO9="","",VLOOKUP(($BC9&EO9&"Template desconto % Ponto adicional nível conta"),BENEFICIOS!$A:$G,5,0))),"Criar",IF(EO9="","",VLOOKUP(($BC9&EO9&"Template desconto % Ponto adicional nível conta"),BENEFICIOS!$A:$G,5,0)))) -> Criar | ER9: =IF(EQ9="Sim","PCS-34704","") | ES9: Sim | ET9: Benefício | EU9: 499 | EV9: 12 | EW9: =IF(ET9="Benefício","Oi benefício fidelização Multiprodutos","") -> Oi benefício fidelização Multiprodutos | EX9: =IF(ET9="Benefício","PCS-Fk83324","") -> PCS-Fk83324 | EY9: =IF(ES9="Sim","PCS-SBL553142","") -> PCS-SBL553142 | EZ9: LD + VC Oi | FA9: 0T0T_FTV_MIN_LD_270000. | FG9: =IF($BH9="","",$BH9+$BE9) | FH9: =IF($BK9="","",$BK9+$BE9) | FI9: =IF($BN9="","",$BN9+$BE9) -> 144.9 | FJ9: =IF($BQ9="","",$BQ9+$BE9) -> 144.9 | FK9: =IF($BT9="","",$BT9+$BE9) -> 174.9 | FL9: =IF($BW9="","",$BW9+$BE9) | FM9: =IF($BZ9="","",$BZ9+$BE9) | FN9: =IF($CC9="","",$CC9+$BE9) | FO9: =IF($CF9="","",$CF9+$BE9) | FP9: =IF($CI9="","",$CI9+$BE9) | FQ9: =IF($CL9="","",$CL9+$BE9) -> 154.9 | FR9: =IF($CO9="","",$CO9+$BE9) -> 154.9 | FS9: =IF($CR9="","",$CR9+$BE9) -> 184.9 | FT9: =IF($CU9="","",$CU9+$BE9) | FU9: =IF($CX9="","",$CX9+$BE9) | FV9: =IF($DA9="","",$DA9+$BE9) | FW9: =IF($DD9="","",$DD9+$BE9)
BD10: =IF(BC10="Oi Total Fixo + TV 1","CFG-2Plowpi",IF(BC10="Oi Total Fixo + TV 2","PCS-2PMepi",IF(BC10="Oi Total Fixo + TV 3","PCS-2PHipi",""))) | BF10: =IF(BE10=0,"",IF(BE10=VLOOKUP("FIXO",ARBOR!$A:$C,3,0),0.0001,IF(BE10>VLOOKUP("FIXO",ARBOR!$A:$C,3,0),"Maior que CAP!",IF((DOLLAR(BE10+(VLOOKUP("FIXO",ARBOR!$A:$C,3,0)*-TRUNC(BE10/VLOOKUP("FIXO",ARBOR!$A:$C,3,0)-1,4)),6))<>(DOLLAR(VLOOKUP("FIXO",ARBOR!$A:$C,3,0),6)),-TRUNC(BE10/VLOOKUP("FIXO",ARBOR!$A:$C,3,0)-1,4)+0.0001,-TRUNC(BE10/VLOOKUP("FIXO",ARBOR!$A:$C,3,0)-1,4))))) | BG10: =IF(ISERROR(IF(BF10="","",VLOOKUP(($BC10&BF10&"Template de desconto FLAT bundle - Fixo - Varejo - Ganho Tributário Cross"),BENEFICIOS!$A:$G,5,0))),"Criar",IF(BF10="","",VLOOKUP(($BC10&BF10&"Template de desconto FLAT bundle - Fixo - Varejo - Ganho Tributário Cross"),BENEFICIOS!$A:$G,5,0))) | BI10: =IF(BH10=0,"",IF(BH10=VLOOKUP("PCS-OzTL40",ARBOR!$A:$C,3,0),0.0001,IF(BH10>VLOOKUP("PCS-OzTL40",ARBOR!$A:$C,3,0),"Maior que CAP!",IF((DOLLAR(BH10+(VLOOKUP("PCS-OzTL40",ARBOR!$A:$C,3,0)*-TRUNC(BH10/VLOOKUP("PCS-OzTL40",ARBOR!$A:$C,3,0)-1,4)),6))<>(DOLLAR(VLOOKUP("PCS-OzTL40",ARBOR!$A:$C,3,0),6)),-TRUNC(BH10/VLOOKUP("PCS-OzTL40",ARBOR!$A:$C,3,0)-1,4)+0.0001,-TRUNC(BH10/VLOOKUP("PCS-OzTL40",ARBOR!$A:$C,3,0)-1,4))))) | BJ10: =IF(ISERROR(IF(BI10="","",VLOOKUP((BC10&BI10&"Template desconto FLAT Plano Principal Oi TV nível conta"),BENEFICIOS!$A:$G,5,0))),"Criar",IF(BI10="","",VLOOKUP((BC10&BI10&"Template desconto FLAT Plano Principal Oi TV nível conta"),BENEFICIOS!$A:$G,5,0))) | BL10: =IF(BK10=0,"",IF(BK10=VLOOKUP("PCS-OzTL41",ARBOR!$A:$C,3,0),0.0001,IF(BK10>VLOOKUP("PCS-OzTL41",ARBOR!$A:$C,3,0),"Maior que CAP!",IF((DOLLAR(BK10+(VLOOKUP("PCS-OzTL41",ARBOR!$A:$C,3,0)*-TRUNC(BK10/VLOOKUP("PCS-OzTL41",ARBOR!$A:$C,3,0)-1,4)),6))<>(DOLLAR(VLOOKUP("PCS-OzTL41",ARBOR!$A:$C,3,0),6)),-TRUNC(BK10/VLOOKUP("PCS-OzTL41",ARBOR!$A:$C,3,0)-1,4)+0.0001,-TRUNC(BK10/VLOOKUP("PCS-OzTL41",ARBOR!$A:$C,3,0)-1,4))))) | BM10: =IF(ISERROR(IF(BL10="","",VLOOKUP((BC10&BL10&"Template desconto FLAT Plano Principal Oi TV nível conta"),BENEFICIOS!$A:$G,5,0))),"Criar",IF(BL10="","",VLOOKUP((BC10&BL10&"Template desconto FLAT Plano Principal Oi TV nível conta"),BENEFICIOS!$A:$G,5,0))) | BO10: =IF(BN10=0,"",IF(BN10=VLOOKUP("PCS-OzTL44",ARBOR!$A:$C,3,0),0.0001,IF(BN10>VLOOKUP("PCS-OzTL44",ARBOR!$A:$C,3,0),"Maior que CAP!",IF((DOLLAR(BN10+(VLOOKUP("PCS-OzTL44",ARBOR!$A:$C,3,0)*-TRUNC(BN10/VLOOKUP("PCS-OzTL44",ARBOR!$A:$C,3,0)-1,4)),6))<>(DOLLAR(VLOOKUP("PCS-OzTL44",ARBOR!$A:$C,3,0),6)),-TRUNC(BN10/VLOOKUP("PCS-OzTL44",ARBOR!$A:$C,3,0)-1,4)+0.0001,-TRUNC(BN10/VLOOKUP("PCS-OzTL44",ARBOR!$A:$C,3,0)-1,4))))) | BP10: =IF(ISERROR(IF(BO10="","",VLOOKUP((BC10&BO10&"Template desconto FLAT Plano Principal Oi TV nível conta"),BENEFICIOS!$A:$G,5,0))),"Criar",IF(BO10="","",VLOOKUP((BC10&BO10&"Template desconto FLAT Plano Principal Oi TV nível conta"),BENEFICIOS!$A:$G,5,0))) | BR10: =IF(BQ10=0,"",IF(BQ10=VLOOKUP("PCS-OzTL43",ARBOR!$A:$C,3,0),0.0001,IF(BQ10>VLOOKUP("PCS-OzTL43",ARBOR!$A:$C,3,0),"Maior que CAP!",IF((DOLLAR(BQ10+(VLOOKUP("PCS-OzTL43",ARBOR!$A:$C,3,0)*-TRUNC(BQ10/VLOOKUP("PCS-OzTL43",ARBOR!$A:$C,3,0)-1,4)),6))<>(DOLLAR(VLOOKUP("PCS-OzTL43",ARBOR!$A:$C,3,0),6)),-TRUNC(BQ10/VLOOKUP("PCS-OzTL43",ARBOR!$A:$C,3,0)-1,4)+0.0001,-TRUNC(BQ10/VLOOKUP("PCS-OzTL43",ARBOR!$A:$C,3,0)-1,4))))) | BS10: =IF(ISERROR(IF(BR10="","",VLOOKUP((BC10&BR10&"Template desconto FLAT Plano Principal Oi TV nível conta"),BENEFICIOS!$A:$G,5,0))),"Criar",IF(BR10="","",VLOOKUP((BC10&BR10&"Template desconto FLAT Plano Principal Oi TV nível conta"),BENEFICIOS!$A:$G,5,0))) | BU10: =IF(BT10=0,"",IF(BT10=VLOOKUP("PCS-OzTL45",ARBOR!$A:$C,3,0),0.0001,IF(BT10>VLOOKUP("PCS-OzTL45",ARBOR!$A:$C,3,0),"Maior que CAP!",IF((DOLLAR(BT10+(VLOOKUP("PCS-OzTL45",ARBOR!$A:$C,3,0)*-TRUNC(BT10/VLOOKUP("PCS-OzTL45",ARBOR!$A:$C,3,0)-1,4)),6))<>(DOLLAR(VLOOKUP("PCS-OzTL45",ARBOR!$A:$C,3,0),6)),-TRUNC(BT10/VLOOKUP("PCS-OzTL45",ARBOR!$A:$C,3,0)-1,4)+0.0001,-TRUNC(BT10/VLOOKUP("PCS-OzTL45",ARBOR!$A:$C,3,0)-1,4))))) | BV10: =IF(ISERROR(IF(BU10="","",VLOOKUP((BC10&BU10&"Template desconto FLAT Plano Principal Oi TV nível conta"),BENEFICIOS!$A:$G,5,0))),"Criar",IF(BU10="","",VLOOKUP((BC10&BU10&"Template desconto FLAT Plano Principal Oi TV nível conta"),BENEFICIOS!$A:$G,5,0))) | BX10: =IF(BW10=0,"",IF(BW10=VLOOKUP("PCS-OzTL741",ARBOR!$A:$C,3,0),0.0001,IF(BW10>VLOOKUP("PCS-OzTL741",ARBOR!$A:$C,3,0),"Maior que CAP!",IF((DOLLAR(BW10+(VLOOKUP("PCS-OzTL741",ARBOR!$A:$C,3,0)*-TRUNC(BW10/VLOOKUP("PCS-OzTL741",ARBOR!$A:$C,3,0)-1,4)),6))<>(DOLLAR(VLOOKUP("PCS-OzTL741",ARBOR!$A:$C,3,0),6)),-TRUNC(BW10/VLOOKUP("PCS-OzTL741",ARBOR!$A:$C,3,0)-1,4)+0.0001,-TRUNC(BW10/VLOOKUP("PCS-OzTL741",ARBOR!$A:$C,3,0)-1,4))))) | BY10: =IF(ISERROR(IF(BX10="","",VLOOKUP((BC10&BX10&"Template desconto FLAT Plano Principal Oi TV nível conta"),BENEFICIOS!$A:$G,5,0))),"Criar",IF(BX10="","",VLOOKUP((BC10&BX10&"Template desconto FLAT Plano Principal Oi TV nível conta"),BENEFICIOS!$A:$G,5,0))) | CA10: =IF(BZ10=0,"",IF(BZ10=VLOOKUP("PCS-OzTL744",ARBOR!$A:$C,3,0),0.0001,IF(BZ10>VLOOKUP("PCS-OzTL744",ARBOR!$A:$C,3,0),"Maior que CAP!",IF((DOLLAR(BZ10+(VLOOKUP("PCS-OzTL744",ARBOR!$A:$C,3,0)*-TRUNC(BZ10/VLOOKUP("PCS-OzTL744",ARBOR!$A:$C,3,0)-1,4)),6))<>(DOLLAR(VLOOKUP("PCS-OzTL744",ARBOR!$A:$C,3,0),6)),-TRUNC(BZ10/VLOOKUP("PCS-OzTL744",ARBOR!$A:$C,3,0)-1,4)+0.0001,-TRUNC(BZ10/VLOOKUP("PCS-OzTL744",ARBOR!$A:$C,3,0)-1,4))))) | CB10: =IF(ISERROR(IF(CA10="","",VLOOKUP(($BC10&CA10&"Template desconto FLAT Plano Principal Oi TV nível conta"),BENEFICIOS!$A:$G,5,0))),"Criar",IF(CA10="","",VLOOKUP(($BC10&CA10&"Template desconto FLAT Plano Principal Oi TV nível conta"),BENEFICIOS!$A:$G,5,0))) | CD10: =IF(CC10=0,"",IF(CC10=VLOOKUP("PCS-OzTL743",ARBOR!$A:$C,3,0),0.0001,IF(CC10>VLOOKUP("PCS-OzTL743",ARBOR!$A:$C,3,0),"Maior que CAP!",IF((DOLLAR(CC10+(VLOOKUP("PCS-OzTL743",ARBOR!$A:$C,3,0)*-TRUNC(CC10/VLOOKUP("PCS-OzTL743",ARBOR!$A:$C,3,0)-1,4)),6))<>(DOLLAR(VLOOKUP("PCS-OzTL743",ARBOR!$A:$C,3,0),6)),-TRUNC(CC10/VLOOKUP("PCS-OzTL743",ARBOR!$A:$C,3,0)-1,4)+0.0001,-TRUNC(CC10/VLOOKUP("PCS-OzTL743",ARBOR!$A:$C,3,0)-1,4))))) | CE10: =IF(ISERROR(IF(CD10="","",VLOOKUP(($BC10&CD10&"Template desconto FLAT Plano Principal Oi TV nível conta"),BENEFICIOS!$A:$G,5,0))),"Criar",IF(CD10="","",VLOOKUP(($BC10&CD10&"Template desconto FLAT Plano Principal Oi TV nível conta"),BENEFICIOS!$A:$G,5,0))) | CG10: =IF(CF10=0,"",IF(CF10=VLOOKUP("PCS-OzTL745",ARBOR!$A:$C,3,0),0.0001,IF(CF10>VLOOKUP("PCS-OzTL745",ARBOR!$A:$C,3,0),"Maior que CAP!",IF((DOLLAR(CF10+(VLOOKUP("PCS-OzTL745",ARBOR!$A:$C,3,0)*-TRUNC(CF10/VLOOKUP("PCS-OzTL745",ARBOR!$A:$C,3,0)-1,4)),6))<>(DOLLAR(VLOOKUP("PCS-OzTL745",ARBOR!$A:$C,3,0),6)),-TRUNC(CF10/VLOOKUP("PCS-OzTL745",ARBOR!$A:$C,3,0)-1,4)+0.0001,-TRUNC(CF10/VLOOKUP("PCS-OzTL745",ARBOR!$A:$C,3,0)-1,4))))) | CH10: =IF(ISERROR(IF(CG10="","",VLOOKUP(($BC10&CG10&"Template desconto FLAT Plano Principal Oi TV nível conta"),BENEFICIOS!$A:$G,5,0))),"Criar",IF(CG10="","",VLOOKUP(($BC10&CG10&"Template desconto FLAT Plano Principal Oi TV nível conta"),BENEFICIOS!$A:$G,5,0))) | CJ10: =IF(CI10=0,"",IF(CI10=VLOOKUP("PCS-OzTL42",ARBOR!$A:$C,3,0),0.0001,IF(CI10>VLOOKUP("PCS-OzTL42",ARBOR!$A:$C,3,0),"Maior que CAP!",IF((DOLLAR(CI10+(VLOOKUP("PCS-OzTL42",ARBOR!$A:$C,3,0)*-TRUNC(CI10/VLOOKUP("PCS-OzTL42",ARBOR!$A:$C,3,0)-1,4)),6))<>(DOLLAR(VLOOKUP("PCS-OzTL42",ARBOR!$A:$C,3,0),6)),-TRUNC(CI10/VLOOKUP("PCS-OzTL42",ARBOR!$A:$C,3,0)-1,4)+0.0001,-TRUNC(CI10/VLOOKUP("PCS-OzTL42",ARBOR!$A:$C,3,0)-1,4))))) | CK10: =IF(ISERROR(IF(CJ10="","",VLOOKUP(($BC10&CJ10&"Template desconto FLAT Plano Principal Oi TV nível conta"),BENEFICIOS!$A:$G,5,0))),"Criar",IF(CJ10="","",VLOOKUP(($BC10&CJ10&"Template desconto FLAT Plano Principal Oi TV nível conta"),BENEFICIOS!$A:$G,5,0))) | CM10: =IF(CL10=0,"",IF(CL10=VLOOKUP("PCS-OzTL47",ARBOR!$A:$C,3,0),0.0001,IF(CL10>VLOOKUP("PCS-OzTL47",ARBOR!$A:$C,3,0),"Maior que CAP!",IF((DOLLAR(CL10+(VLOOKUP("PCS-OzTL47",ARBOR!$A:$C,3,0)*-TRUNC(CL10/VLOOKUP("PCS-OzTL47",ARBOR!$A:$C,3,0)-1,4)),6))<>(DOLLAR(VLOOKUP("PCS-OzTL47",ARBOR!$A:$C,3,0),6)),-TRUNC(CL10/VLOOKUP("PCS-OzTL47",ARBOR!$A:$C,3,0)-1,4)+0.0001,-TRUNC(CL10/VLOOKUP("PCS-OzTL47",ARBOR!$A:$C,3,0)-1,4))))) | CN10: =IF(ISERROR(IF(CM10="","",VLOOKUP(($BC10&CM10&"Template desconto FLAT Plano Principal Oi TV nível conta"),BENEFICIOS!$A:$G,5,0))),"Criar",IF(CM10="","",VLOOKUP(($BC10&CM10&"Template desconto FLAT Plano Principal Oi TV nível conta"),BENEFICIOS!$A:$G,5,0))) | CP10: =IF(CO10=0,"",IF(CO10=VLOOKUP("PCS-OzTL46",ARBOR!$A:$C,3,0),0.0001,IF(CO10>VLOOKUP("PCS-OzTL46",ARBOR!$A:$C,3,0),"Maior que CAP!",IF((DOLLAR(CO10+(VLOOKUP("PCS-OzTL46",ARBOR!$A:$C,3,0)*-TRUNC(CO10/VLOOKUP("PCS-OzTL46",ARBOR!$A:$C,3,0)-1,4)),6))<>(DOLLAR(VLOOKUP("PCS-OzTL46",ARBOR!$A:$C,3,0),6)),-TRUNC(CO10/VLOOKUP("PCS-OzTL46",ARBOR!$A:$C,3,0)-1,4)+0.0001,-TRUNC(CO10/VLOOKUP("PCS-OzTL46",ARBOR!$A:$C,3,0)-1,4))))) | CQ10: =IF(ISERROR(IF(CP10="","",VLOOKUP(($BC10&CP10&"Template desconto FLAT Plano Principal Oi TV nível conta"),BENEFICIOS!$A:$G,5,0))),"Criar",IF(CP10="","",VLOOKUP(($BC10&CP10&"Template desconto FLAT Plano Principal Oi TV nível conta"),BENEFICIOS!$A:$G,5,0))) | CS10: =IF(CR10=0,"",IF(CR10=VLOOKUP("PCS-OzTL48",ARBOR!$A:$C,3,0),0.0001,IF(CR10>VLOOKUP("PCS-OzTL48",ARBOR!$A:$C,3,0),"Maior que CAP!",IF((DOLLAR(CR10+(VLOOKUP("PCS-OzTL48",ARBOR!$A:$C,3,0)*-TRUNC(CR10/VLOOKUP("PCS-OzTL48",ARBOR!$A:$C,3,0)-1,4)),6))<>(DOLLAR(VLOOKUP("PCS-OzTL48",ARBOR!$A:$C,3,0),6)),-TRUNC(CR10/VLOOKUP("PCS-OzTL48",ARBOR!$A:$C,3,0)-1,4)+0.0001,-TRUNC(CR10/VLOOKUP("PCS-OzTL48",ARBOR!$A:$C,3,0)-1,4))))) | CT10: =IF(ISERROR(IF(CS10="","",VLOOKUP(($BC10&CS10&"Template desconto FLAT Plano Principal Oi TV nível conta"),BENEFICIOS!$A:$G,5,0))),"Criar",IF(CS10="","",VLOOKUP(($BC10&CS10&"Template desconto FLAT Plano Principal Oi TV nível conta"),BENEFICIOS!$A:$G,5,0))) | CV10: =IF(CU10=0,"",IF(CU10=VLOOKUP("PCS-OzTL742",ARBOR!$A:$C,3,0),0.0001,IF(CU10>VLOOKUP("PCS-OzTL742",ARBOR!$A:$C,3,0),"Maior que CAP!",IF((DOLLAR(CU10+(VLOOKUP("PCS-OzTL742",ARBOR!$A:$C,3,0)*-TRUNC(CU10/VLOOKUP("PCS-OzTL742",ARBOR!$A:$C,3,0)-1,4)),6))<>(DOLLAR(VLOOKUP("PCS-OzTL742",ARBOR!$A:$C,3,0),6)),-TRUNC(CU10/VLOOKUP("PCS-OzTL742",ARBOR!$A:$C,3,0)-1,4)+0.0001,-TRUNC(CU10/VLOOKUP("PCS-OzTL742",ARBOR!$A:$C,3,0)-1,4))))) | CW10: =IF(ISERROR(IF(CV10="","",VLOOKUP(($BC10&CV10&"Template desconto FLAT Plano Principal Oi TV nível conta"),BENEFICIOS!$A:$G,5,0))),"Criar",IF(CV10="","",VLOOKUP(($BC10&CV10&"Template desconto FLAT Plano Principal Oi TV nível conta"),BENEFICIOS!$A:$G,5,0))) | CY10: =IF(CX10=0,"",IF(CX10=VLOOKUP("PCS-OzTL747",ARBOR!$A:$C,3,0),0.0001,IF(CX10>VLOOKUP("PCS-OzTL747",ARBOR!$A:$C,3,0),"Maior que CAP!",IF((DOLLAR(CX10+(VLOOKUP("PCS-OzTL747",ARBOR!$A:$C,3,0)*-TRUNC(CX10/VLOOKUP("PCS-OzTL747",ARBOR!$A:$C,3,0)-1,4)),6))<>(DOLLAR(VLOOKUP("PCS-OzTL747",ARBOR!$A:$C,3,0),6)),-TRUNC(CX10/VLOOKUP("PCS-OzTL747",ARBOR!$A:$C,3,0)-1,4)+0.0001,-TRUNC(CX10/VLOOKUP("PCS-OzTL747",ARBOR!$A:$C,3,0)-1,4))))) | CZ10: =IF(ISERROR(IF(CY10="","",VLOOKUP(($BC10&CY10&"Template desconto FLAT Plano Principal Oi TV nível conta"),BENEFICIOS!$A:$G,5,0))),"Criar",IF(CY10="","",VLOOKUP(($BC10&CY10&"Template desconto FLAT Plano Principal Oi TV nível conta"),BENEFICIOS!$A:$G,5,0))) | DB10: =IF(DA10=0,"",IF(DA10=VLOOKUP("PCS-OzTL746",ARBOR!$A:$C,3,0),0.0001,IF(DA10>VLOOKUP("PCS-OzTL746",ARBOR!$A:$C,3,0),"Maior que CAP!",IF((DOLLAR(DA10+(VLOOKUP("PCS-OzTL746",ARBOR!$A:$C,3,0)*-TRUNC(DA10/VLOOKUP("PCS-OzTL746",ARBOR!$A:$C,3,0)-1,4)),6))<>(DOLLAR(VLOOKUP("PCS-OzTL746",ARBOR!$A:$C,3,0),6)),-TRUNC(DA10/VLOOKUP("PCS-OzTL746",ARBOR!$A:$C,3,0)-1,4)+0.0001,-TRUNC(DA10/VLOOKUP("PCS-OzTL746",ARBOR!$A:$C,3,0)-1,4))))) | DC10: =IF(ISERROR(IF(DB10="","",VLOOKUP(($BC10&DB10&"Template desconto FLAT Plano Principal Oi TV nível conta"),BENEFICIOS!$A:$G,5,0))),"Criar",IF(DB10="","",VLOOKUP(($BC10&DB10&"Template desconto FLAT Plano Principal Oi TV nível conta"),BENEFICIOS!$A:$G,5,0))) | DE10: =IF(DD10=0,"",IF(DD10=VLOOKUP("PCS-OzTL748",ARBOR!$A:$C,3,0),0.0001,IF(DD10>VLOOKUP("PCS-OzTL748",ARBOR!$A:$C,3,0),"Maior que CAP!",IF((DOLLAR(DD10+(VLOOKUP("PCS-OzTL748",ARBOR!$A:$C,3,0)*-TRUNC(DD10/VLOOKUP("PCS-OzTL748",ARBOR!$A:$C,3,0)-1,4)),6))<>(DOLLAR(VLOOKUP("PCS-OzTL748",ARBOR!$A:$C,3,0),6)),-TRUNC(DD10/VLOOKUP("PCS-OzTL748",ARBOR!$A:$C,3,0)-1,4)+0.0001,-TRUNC(DD10/VLOOKUP("PCS-OzTL748",ARBOR!$A:$C,3,0)-1,4))))) | DF10: =IF(ISERROR(IF(DE10="","",VLOOKUP(($BC10&DE10&"Template desconto FLAT Plano Principal Oi TV nível conta"),BENEFICIOS!$A:$G,5,0))),"Criar",IF(DE10="","",VLOOKUP(($BC10&DE10&"Template desconto FLAT Plano Principal Oi TV nível conta"),BENEFICIOS!$A:$G,5,0))) | DH10: =IF(DG10=0,"",IF(DG10=VLOOKUP("PCS-OzTL34",ARBOR!$A:$C,3,0),0.0001,IF(DG10>VLOOKUP("PCS-OzTL34",ARBOR!$A:$C,3,0),"Maior que CAP!",IF((DOLLAR(DG10+(VLOOKUP("PCS-OzTL34",ARBOR!$A:$C,3,0)*-TRUNC(DG10/VLOOKUP("PCS-OzTL34",ARBOR!$A:$C,3,0)-1,4)),6))<>(DOLLAR(VLOOKUP("PCS-OzTL34",ARBOR!$A:$C,3,0),6)),-TRUNC(DG10/VLOOKUP("PCS-OzTL34",ARBOR!$A:$C,3,0)-1,4)+0.0001,-TRUNC(DG10/VLOOKUP("PCS-OzTL34",ARBOR!$A:$C,3,0)-1,4))))) | DI10: =IF(DH10="S/Desc","S/Desc",IF(ISERROR(IF(DH10="","",VLOOKUP(($BC10&DH10&"Template desconto % Combate nível conta"),BENEFICIOS!$A:$G,5,0))),"Criar",IF(DH10="","",VLOOKUP(($BC10&DH10&"Template desconto % Combate nível conta"),BENEFICIOS!$A:$G,5,0)))) | DK10: =IF(DJ10=0,"",IF(DJ10=VLOOKUP("PCS-OzTL31",ARBOR!$A:$C,3,0),0.0001,IF(DJ10>VLOOKUP("PCS-OzTL31",ARBOR!$A:$C,3,0),"Maior que CAP!",IF((DOLLAR(DJ10+(VLOOKUP("PCS-OzTL31",ARBOR!$A:$C,3,0)*-TRUNC(DJ10/VLOOKUP("PCS-OzTL31",ARBOR!$A:$C,3,0)-1,4)),6))<>(DOLLAR(VLOOKUP("PCS-OzTL31",ARBOR!$A:$C,3,0),6)),-TRUNC(DJ10/VLOOKUP("PCS-OzTL31",ARBOR!$A:$C,3,0)-1,4)+0.0001,-TRUNC(DJ10/VLOOKUP("PCS-OzTL31",ARBOR!$A:$C,3,0)-1,4))))) | DL10: =IF(DK10="S/Desc","S/Desc",IF(ISERROR(IF(DK10="","",VLOOKUP(($BC10&DK10&"Template desconto % Sexy Hot nível conta"),BENEFICIOS!$A:$G,5,0))),"Criar",IF(DK10="","",VLOOKUP(($BC10&DK10&"Template desconto % Sexy Hot nível conta"),BENEFICIOS!$A:$G,5,0)))) | DN10: =IF(DM10=0,"",IF(DM10=VLOOKUP("PCS-OzTL32",ARBOR!$A:$C,3,0),0.0001,IF(DM10>VLOOKUP("PCS-OzTL32",ARBOR!$A:$C,3,0),"Maior que CAP!",IF((DOLLAR(DM10+(VLOOKUP("PCS-OzTL32",ARBOR!$A:$C,3,0)*-TRUNC(DM10/VLOOKUP("PCS-OzTL32",ARBOR!$A:$C,3,0)-1,4)),6))<>(DOLLAR(VLOOKUP("PCS-OzTL32",ARBOR!$A:$C,3,0),6)),-TRUNC(DM10/VLOOKUP("PCS-OzTL32",ARBOR!$A:$C,3,0)-1,4)+0.0001,-TRUNC(DM10/VLOOKUP("PCS-OzTL32",ARBOR!$A:$C,3,0)-1,4))))) | DO10: =IF(DN10="S/Desc","S/Desc",IF(ISERROR(IF(DN10="","",VLOOKUP(($BC10&DN10&"Template desconto % Playboy nível conta"),BENEFICIOS!$A:$G,5,0))),"Criar",IF(DN10="","",VLOOKUP(($BC10&DN10&"Template desconto % Playboy nível conta"),BENEFICIOS!$A:$G,5,0)))) | DQ10: =IF(DP10=0,"",IF(DP10=VLOOKUP("PCS-OzTL33",ARBOR!$A:$C,3,0),0.0001,IF(DP10>VLOOKUP("PCS-OzTL33",ARBOR!$A:$C,3,0),"Maior que CAP!",IF((DOLLAR(DP10+(VLOOKUP("PCS-OzTL33",ARBOR!$A:$C,3,0)*-TRUNC(DP10/VLOOKUP("PCS-OzTL33",ARBOR!$A:$C,3,0)-1,4)),6))<>(DOLLAR(VLOOKUP("PCS-OzTL33",ARBOR!$A:$C,3,0),6)),-TRUNC(DP10/VLOOKUP("PCS-OzTL33",ARBOR!$A:$C,3,0)-1,4)+0.0001,-TRUNC(DP10/VLOOKUP("PCS-OzTL33",ARBOR!$A:$C,3,0)-1,4))))) | DR10: =IF(DQ10="S/Desc","S/Desc",IF(ISERROR(IF(DQ10="","",VLOOKUP(($BC10&DQ10&"Template desconto % Sexy Hot + Playboy nível conta"),BENEFICIOS!$A:$G,5,0))),"Criar",IF(DQ10="","",VLOOKUP(($BC10&DQ10&"Template desconto % Sexy Hot + Playboy nível conta"),BENEFICIOS!$A:$G,5,0)))) | DT10: =IF(DS10=0,"",IF(DS10=VLOOKUP("PCS-OzTL503",ARBOR!$A:$C,3,0),0.0001,IF(DS10>VLOOKUP("PCS-OzTL503",ARBOR!$A:$C,3,0),"Maior que CAP!",IF((DOLLAR(DS10+(VLOOKUP("PCS-OzTL503",ARBOR!$A:$C,3,0)*-TRUNC(DS10/VLOOKUP("PCS-OzTL503",ARBOR!$A:$C,3,0)-1,4)),6))<>(DOLLAR(VLOOKUP("PCS-OzTL503",ARBOR!$A:$C,3,0),6)),-TRUNC(DS10/VLOOKUP("PCS-OzTL503",ARBOR!$A:$C,3,0)-1,4)+0.0001,-TRUNC(DS10/VLOOKUP("PCS-OzTL503",ARBOR!$A:$C,3,0)-1,4))))) | DU10: =IF(DT10="S/Desc","S/Desc",IF(ISERROR(IF(DT10="","",VLOOKUP(($BC10&DT10&"Template desconto % SexPrivê nível conta"),BENEFICIOS!$A:$G,5,0))),"Criar",IF(DT10="","",VLOOKUP(($BC10&DT10&"Template desconto % SexPrivê nível conta"),BENEFICIOS!$A:$G,5,0)))) | DW10: =IF(DV10=0,"",IF(DV10=VLOOKUP("PCS-OzTL500",ARBOR!$A:$C,3,0),0.0001,IF(DV10>VLOOKUP("PCS-OzTL500",ARBOR!$A:$C,3,0),"Maior que CAP!",IF((DOLLAR(DV10+(VLOOKUP("PCS-OzTL500",ARBOR!$A:$C,3,0)*-TRUNC(DV10/VLOOKUP("PCS-OzTL500",ARBOR!$A:$C,3,0)-1,4)),6))<>(DOLLAR(VLOOKUP("PCS-OzTL500",ARBOR!$A:$C,3,0),6)),-TRUNC(DV10/VLOOKUP("PCS-OzTL500",ARBOR!$A:$C,3,0)-1,4)+0.0001,-TRUNC(DV10/VLOOKUP("PCS-OzTL500",ARBOR!$A:$C,3,0)-1,4))))) | DX10: =IF(DW10="S/Desc","S/Desc",IF(ISERROR(IF(DW10="","",VLOOKUP(($BC10&DW10&"Template desconto % Étnico nível conta"),BENEFICIOS!$A:$G,5,0))),"Criar",IF(DW10="","",VLOOKUP(($BC10&DW10&"Template desconto % Étnico nível conta"),BENEFICIOS!$A:$G,5,0)))) | DZ10: =IF(DY10=0,"",IF(DY10=VLOOKUP("PCS-OzTL50",ARBOR!$A:$C,3,0),0.0001,IF(DY10>VLOOKUP("PCS-OzTL50",ARBOR!$A:$C,3,0),"Maior que CAP!",IF((DOLLAR(DY10+(VLOOKUP("PCS-OzTL50",ARBOR!$A:$C,3,0)*-TRUNC(DY10/VLOOKUP("PCS-OzTL50",ARBOR!$A:$C,3,0)-1,4)),6))<>(DOLLAR(VLOOKUP("PCS-OzTL50",ARBOR!$A:$C,3,0),6)),-TRUNC(DY10/VLOOKUP("PCS-OzTL50",ARBOR!$A:$C,3,0)-1,4)+0.0001,-TRUNC(DY10/VLOOKUP("PCS-OzTL50",ARBOR!$A:$C,3,0)-1,4))))) | EC10: =IF(EB10=0,"",IF(EB10=VLOOKUP("PCS-OzTL51",ARBOR!$A:$C,3,0),0.0001,IF(EB10>VLOOKUP("PCS-OzTL51",ARBOR!$A:$C,3,0),"Maior que CAP!",IF((DOLLAR(EB10+(VLOOKUP("PCS-OzTL51",ARBOR!$A:$C,3,0)*-TRUNC(EB10/VLOOKUP("PCS-OzTL51",ARBOR!$A:$C,3,0)-1,4)),6))<>(DOLLAR(VLOOKUP("PCS-OzTL51",ARBOR!$A:$C,3,0),6)),-TRUNC(EB10/VLOOKUP("PCS-OzTL51",ARBOR!$A:$C,3,0)-1,4)+0.0001,-TRUNC(EB10/VLOOKUP("PCS-OzTL51",ARBOR!$A:$C,3,0)-1,4))))) | EF10: =IF(EE10=0,"",IF(EE10=VLOOKUP("PCS-OzTL52",ARBOR!$A:$C,3,0),0.0001,IF(EE10>VLOOKUP("PCS-OzTL52",ARBOR!$A:$C,3,0),"Maior que CAP!",IF((DOLLAR(EE10+(VLOOKUP("PCS-OzTL52",ARBOR!$A:$C,3,0)*-TRUNC(EE10/VLOOKUP("PCS-OzTL52",ARBOR!$A:$C,3,0)-1,4)),6))<>(DOLLAR(VLOOKUP("PCS-OzTL52",ARBOR!$A:$C,3,0),6)),-TRUNC(EE10/VLOOKUP("PCS-OzTL52",ARBOR!$A:$C,3,0)-1,4)+0.0001,-TRUNC(EE10/VLOOKUP("PCS-OzTL52",ARBOR!$A:$C,3,0)-1,4))))) | EI10: =IF(EH10=0,"",IF(EH10=VLOOKUP("PCS-OzTL53",ARBOR!$A:$C,3,0),0.0001,IF(EH10>VLOOKUP("PCS-OzTL53",ARBOR!$A:$C,3,0),"Maior que CAP!",IF((DOLLAR(EH10+(VLOOKUP("PCS-OzTL53",ARBOR!$A:$C,3,0)*-TRUNC(EH10/VLOOKUP("PCS-OzTL53",ARBOR!$A:$C,3,0)-1,4)),6))<>(DOLLAR(VLOOKUP("PCS-OzTL53",ARBOR!$A:$C,3,0),6)),-TRUNC(EH10/VLOOKUP("PCS-OzTL53",ARBOR!$A:$C,3,0)-1,4)+0.0001,-TRUNC(EH10/VLOOKUP("PCS-OzTL53",ARBOR!$A:$C,3,0)-1,4))))) | EL10: =IF(EK10=0,"",IF(EK10=VLOOKUP("PCS-OzTL54",ARBOR!$A:$C,3,0),0.0001,IF(EK10>VLOOKUP("PCS-OzTL54",ARBOR!$A:$C,3,0),"Maior que CAP!",IF((DOLLAR(EK10+(VLOOKUP("PCS-OzTL54",ARBOR!$A:$C,3,0)*-TRUNC(EK10/VLOOKUP("PCS-OzTL54",ARBOR!$A:$C,3,0)-1,4)),6))<>(DOLLAR(VLOOKUP("PCS-OzTL54",ARBOR!$A:$C,3,0),6)),-TRUNC(EK10/VLOOKUP("PCS-OzTL54",ARBOR!$A:$C,3,0)-1,4)+0.0001,-TRUNC(EK10/VLOOKUP("PCS-OzTL54",ARBOR!$A:$C,3,0)-1,4))))) | EO10: =IF(EN10=0,"",IF(EN10=VLOOKUP("PCS-OzTL99",ARBOR!$A:$C,3,0),0.0001,IF(EN10>VLOOKUP("PCS-OzTL99",ARBOR!$A:$C,3,0),"Maior que CAP!",IF((DOLLAR(EN10+(VLOOKUP("PCS-OzTL99",ARBOR!$A:$C,3,0)*-TRUNC(EN10/VLOOKUP("PCS-OzTL99",ARBOR!$A:$C,3,0)-1,4)),6))<>(DOLLAR(VLOOKUP("PCS-OzTL99",ARBOR!$A:$C,3,0),6)),-TRUNC(EN10/VLOOKUP("PCS-OzTL99",ARBOR!$A:$C,3,0)-1,4)+0.0001,-TRUNC(EN10/VLOOKUP("PCS-OzTL99",ARBOR!$A:$C,3,0)-1,4))))) | EP10: =IF(EO10="S/Desc","S/Desc",IF(ISERROR(IF(EO10="","",VLOOKUP(($BC10&EO10&"Template desconto % Ponto adicional nível conta"),BENEFICIOS!$A:$G,5,0))),"Criar",IF(EO10="","",VLOOKUP(($BC10&EO10&"Template desconto % Ponto adicional nível conta"),BENEFICIOS!$A:$G,5,0)))) | ER10: =IF(EQ10="Sim","PCS-34704","") | EW10: =IF(ET10="Benefício","Oi benefício fidelização Multiprodutos","") | EX10: =IF(ET10="Benefício","PCS-Fk83324","") | EY10: =IF(ES10="Sim","PCS-SBL553142","") | FG10: =IF($BH10="","",$BH10+$BE10) | FH10: =IF($BK10="","",$BK10+$BE10) | FI10: =IF($BN10="","",$BN10+$BE10) | FJ10: =IF($BQ10="","",$BQ10+$BE10) | FK10: =IF($BT10="","",$BT10+$BE10) | FL10: =IF($BW10="","",$BW10+$BE10) | FM10: =IF($BZ10="","",$BZ10+$BE10) | FN10: =IF($CC10="","",$CC10+$BE10) | FO10: =IF($CF10="","",$CF10+$BE10) | FP10: =IF($CI10="","",$CI10+$BE10) | FQ10: =IF($CL10="","",$CL10+$BE10) | FR10: =IF($CO10="","",$CO10+$BE10) | FS10: =IF($CR10="","",$CR10+$BE10) | FT10: =IF($CU10="","",$CU10+$BE10) | FU10: =IF($CX10="","",$CX10+$BE10) | FV10: =IF($DA10="","",$DA10+$BE10) | FW10: =IF($DD10="","",$DD10+$BE10)
BD11: =IF(BC11="Oi Total Fixo + TV 1","CFG-2Plowpi",IF(BC11="Oi Total Fixo + TV 2","PCS-2PMepi",IF(BC11="Oi Total Fixo + TV 3","PCS-2PHipi",""))) | BF11: =IF(BE11=0,"",IF(BE11=VLOOKUP("FIXO",ARBOR!$A:$C,3,0),0.0001,IF(BE11>VLOOKUP("FIXO",ARBOR!$A:$C,3,0),"Maior que CAP!",IF((DOLLAR(BE11+(VLOOKUP("FIXO",ARBOR!$A:$C,3,0)*-TRUNC(BE11/VLOOKUP("FIXO",ARBOR!$A:$C,3,0)-1,4)),6))<>(DOLLAR(VLOOKUP("FIXO",ARBOR!$A:$C,3,0),6)),-TRUNC(BE11/VLOOKUP("FIXO",ARBOR!$A:$C,3,0)-1,4)+0.0001,-TRUNC(BE11/VLOOKUP("FIXO",ARBOR!$A:$C,3,0)-1,4))))) | BG11: =IF(ISERROR(IF(BF11="","",VLOOKUP(($BC11&BF11&"Template de desconto FLAT bundle - Fixo - Varejo - Ganho Tributário Cross"),BENEFICIOS!$A:$G,5,0))),"Criar",IF(BF11="","",VLOOKUP(($BC11&BF11&"Template de desconto FLAT bundle - Fixo - Varejo - Ganho Tributário Cross"),BENEFICIOS!$A:$G,5,0))) | BI11: =IF(BH11=0,"",IF(BH11=VLOOKUP("PCS-OzTL40",ARBOR!$A:$C,3,0),0.0001,IF(BH11>VLOOKUP("PCS-OzTL40",ARBOR!$A:$C,3,0),"Maior que CAP!",IF((DOLLAR(BH11+(VLOOKUP("PCS-OzTL40",ARBOR!$A:$C,3,0)*-TRUNC(BH11/VLOOKUP("PCS-OzTL40",ARBOR!$A:$C,3,0)-1,4)),6))<>(DOLLAR(VLOOKUP("PCS-OzTL40",ARBOR!$A:$C,3,0),6)),-TRUNC(BH11/VLOOKUP("PCS-OzTL40",ARBOR!$A:$C,3,0)-1,4)+0.0001,-TRUNC(BH11/VLOOKUP("PCS-OzTL40",ARBOR!$A:$C,3,0)-1,4))))) | BJ11: =IF(ISERROR(IF(BI11="","",VLOOKUP((BC11&BI11&"Template desconto FLAT Plano Principal Oi TV nível conta"),BENEFICIOS!$A:$G,5,0))),"Criar",IF(BI11="","",VLOOKUP((BC11&BI11&"Template desconto FLAT Plano Principal Oi TV nível conta"),BENEFICIOS!$A:$G,5,0))) | BL11: =IF(BK11=0,"",IF(BK11=VLOOKUP("PCS-OzTL41",ARBOR!$A:$C,3,0),0.0001,IF(BK11>VLOOKUP("PCS-OzTL41",ARBOR!$A:$C,3,0),"Maior que CAP!",IF((DOLLAR(BK11+(VLOOKUP("PCS-OzTL41",ARBOR!$A:$C,3,0)*-TRUNC(BK11/VLOOKUP("PCS-OzTL41",ARBOR!$A:$C,3,0)-1,4)),6))<>(DOLLAR(VLOOKUP("PCS-OzTL41",ARBOR!$A:$C,3,0),6)),-TRUNC(BK11/VLOOKUP("PCS-OzTL41",ARBOR!$A:$C,3,0)-1,4)+0.0001,-TRUNC(BK11/VLOOKUP("PCS-OzTL41",ARBOR!$A:$C,3,0)-1,4))))) | BM11: =IF(ISERROR(IF(BL11="","",VLOOKUP((BC11&BL11&"Template desconto FLAT Plano Principal Oi TV nível conta"),BENEFICIOS!$A:$G,5,0))),"Criar",IF(BL11="","",VLOOKUP((BC11&BL11&"Template desconto FLAT Plano Principal Oi TV nível conta"),BENEFICIOS!$A:$G,5,0))) | BO11: =IF(BN11=0,"",IF(BN11=VLOOKUP("PCS-OzTL44",ARBOR!$A:$C,3,0),0.0001,IF(BN11>VLOOKUP("PCS-OzTL44",ARBOR!$A:$C,3,0),"Maior que CAP!",IF((DOLLAR(BN11+(VLOOKUP("PCS-OzTL44",ARBOR!$A:$C,3,0)*-TRUNC(BN11/VLOOKUP("PCS-OzTL44",ARBOR!$A:$C,3,0)-1,4)),6))<>(DOLLAR(VLOOKUP("PCS-OzTL44",ARBOR!$A:$C,3,0),6)),-TRUNC(BN11/VLOOKUP("PCS-OzTL44",ARBOR!$A:$C,3,0)-1,4)+0.0001,-TRUNC(BN11/VLOOKUP("PCS-OzTL44",ARBOR!$A:$C,3,0)-1,4))))) | BP11: =IF(ISERROR(IF(BO11="","",VLOOKUP((BC11&BO11&"Template desconto FLAT Plano Principal Oi TV nível conta"),BENEFICIOS!$A:$G,5,0))),"Criar",IF(BO11="","",VLOOKUP((BC11&BO11&"Template desconto FLAT Plano Principal Oi TV nível conta"),BENEFICIOS!$A:$G,5,0))) | BR11: =IF(BQ11=0,"",IF(BQ11=VLOOKUP("PCS-OzTL43",ARBOR!$A:$C,3,0),0.0001,IF(BQ11>VLOOKUP("PCS-OzTL43",ARBOR!$A:$C,3,0),"Maior que CAP!",IF((DOLLAR(BQ11+(VLOOKUP("PCS-OzTL43",ARBOR!$A:$C,3,0)*-TRUNC(BQ11/VLOOKUP("PCS-OzTL43",ARBOR!$A:$C,3,0)-1,4)),6))<>(DOLLAR(VLOOKUP("PCS-OzTL43",ARBOR!$A:$C,3,0),6)),-TRUNC(BQ11/VLOOKUP("PCS-OzTL43",ARBOR!$A:$C,3,0)-1,4)+0.0001,-TRUNC(BQ11/VLOOKUP("PCS-OzTL43",ARBOR!$A:$C,3,0)-1,4))))) | BS11: =IF(ISERROR(IF(BR11="","",VLOOKUP((BC11&BR11&"Template desconto FLAT Plano Principal Oi TV nível conta"),BENEFICIOS!$A:$G,5,0))),"Criar",IF(BR11="","",VLOOKUP((BC11&BR11&"Template desconto FLAT Plano Principal Oi TV nível conta"),BENEFICIOS!$A:$G,5,0))) | BU11: =IF(BT11=0,"",IF(BT11=VLOOKUP("PCS-OzTL45",ARBOR!$A:$C,3,0),0.0001,IF(BT11>VLOOKUP("PCS-OzTL45",ARBOR!$A:$C,3,0),"Maior que CAP!",IF((DOLLAR(BT11+(VLOOKUP("PCS-OzTL45",ARBOR!$A:$C,3,0)*-TRUNC(BT11/VLOOKUP("PCS-OzTL45",ARBOR!$A:$C,3,0)-1,4)),6))<>(DOLLAR(VLOOKUP("PCS-OzTL45",ARBOR!$A:$C,3,0),6)),-TRUNC(BT11/VLOOKUP("PCS-OzTL45",ARBOR!$A:$C,3,0)-1,4)+0.0001,-TRUNC(BT11/VLOOKUP("PCS-OzTL45",ARBOR!$A:$C,3,0)-1,4))))) | BV11: =IF(ISERROR(IF(BU11="","",VLOOKUP((BC11&BU11&"Template desconto FLAT Plano Principal Oi TV nível conta"),BENEFICIOS!$A:$G,5,0))),"Criar",IF(BU11="","",VLOOKUP((BC11&BU11&"Template desconto FLAT Plano Principal Oi TV nível conta"),BENEFICIOS!$A:$G,5,0))) | BX11: =IF(BW11=0,"",IF(BW11=VLOOKUP("PCS-OzTL741",ARBOR!$A:$C,3,0),0.0001,IF(BW11>VLOOKUP("PCS-OzTL741",ARBOR!$A:$C,3,0),"Maior que CAP!",IF((DOLLAR(BW11+(VLOOKUP("PCS-OzTL741",ARBOR!$A:$C,3,0)*-TRUNC(BW11/VLOOKUP("PCS-OzTL741",ARBOR!$A:$C,3,0)-1,4)),6))<>(DOLLAR(VLOOKUP("PCS-OzTL741",ARBOR!$A:$C,3,0),6)),-TRUNC(BW11/VLOOKUP("PCS-OzTL741",ARBOR!$A:$C,3,0)-1,4)+0.0001,-TRUNC(BW11/VLOOKUP("PCS-OzTL741",ARBOR!$A:$C,3,0)-1,4))))) | BY11: =IF(ISERROR(IF(BX11="","",VLOOKUP((BC11&BX11&"Template desconto FLAT Plano Principal Oi TV nível conta"),BENEFICIOS!$A:$G,5,0))),"Criar",IF(BX11="","",VLOOKUP((BC11&BX11&"Template desconto FLAT Plano Principal Oi TV nível conta"),BENEFICIOS!$A:$G,5,0))) | CA11: =IF(BZ11=0,"",IF(BZ11=VLOOKUP("PCS-OzTL744",ARBOR!$A:$C,3,0),0.0001,IF(BZ11>VLOOKUP("PCS-OzTL744",ARBOR!$A:$C,3,0),"Maior que CAP!",IF((DOLLAR(BZ11+(VLOOKUP("PCS-OzTL744",ARBOR!$A:$C,3,0)*-TRUNC(BZ11/VLOOKUP("PCS-OzTL744",ARBOR!$A:$C,3,0)-1,4)),6))<>(DOLLAR(VLOOKUP("PCS-OzTL744",ARBOR!$A:$C,3,0),6)),-TRUNC(BZ11/VLOOKUP("PCS-OzTL744",ARBOR!$A:$C,3,0)-1,4)+0.0001,-TRUNC(BZ11/VLOOKUP("PCS-OzTL744",ARBOR!$A:$C,3,0)-1,4))))) | CB11: =IF(ISERROR(IF(CA11="","",VLOOKUP(($BC11&CA11&"Template desconto FLAT Plano Principal Oi TV nível conta"),BENEFICIOS!$A:$G,5,0))),"Criar",IF(CA11="","",VLOOKUP(($BC11&CA11&"Template desconto FLAT Plano Principal Oi TV nível conta"),BENEFICIOS!$A:$G,5,0))) | CD11: =IF(CC11=0,"",IF(CC11=VLOOKUP("PCS-OzTL743",ARBOR!$A:$C,3,0),0.0001,IF(CC11>VLOOKUP("PCS-OzTL743",ARBOR!$A:$C,3,0),"Maior que CAP!",IF((DOLLAR(CC11+(VLOOKUP("PCS-OzTL743",ARBOR!$A:$C,3,0)*-TRUNC(CC11/VLOOKUP("PCS-OzTL743",ARBOR!$A:$C,3,0)-1,4)),6))<>(DOLLAR(VLOOKUP("PCS-OzTL743",ARBOR!$A:$C,3,0),6)),-TRUNC(CC11/VLOOKUP("PCS-OzTL743",ARBOR!$A:$C,3,0)-1,4)+0.0001,-TRUNC(CC11/VLOOKUP("PCS-OzTL743",ARBOR!$A:$C,3,0)-1,4))))) | CE11: =IF(ISERROR(IF(CD11="","",VLOOKUP(($BC11&CD11&"Template desconto FLAT Plano Principal Oi TV nível conta"),BENEFICIOS!$A:$G,5,0))),"Criar",IF(CD11="","",VLOOKUP(($BC11&CD11&"Template desconto FLAT Plano Principal Oi TV nível conta"),BENEFICIOS!$A:$G,5,0))) | CG11: =IF(CF11=0,"",IF(CF11=VLOOKUP("PCS-OzTL745",ARBOR!$A:$C,3,0),0.0001,IF(CF11>VLOOKUP("PCS-OzTL745",ARBOR!$A:$C,3,0),"Maior que CAP!",IF((DOLLAR(CF11+(VLOOKUP("PCS-OzTL745",ARBOR!$A:$C,3,0)*-TRUNC(CF11/VLOOKUP("PCS-OzTL745",ARBOR!$A:$C,3,0)-1,4)),6))<>(DOLLAR(VLOOKUP("PCS-OzTL745",ARBOR!$A:$C,3,0),6)),-TRUNC(CF11/VLOOKUP("PCS-OzTL745",ARBOR!$A:$C,3,0)-1,4)+0.0001,-TRUNC(CF11/VLOOKUP("PCS-OzTL745",ARBOR!$A:$C,3,0)-1,4))))) | CH11: =IF(ISERROR(IF(CG11="","",VLOOKUP(($BC11&CG11&"Template desconto FLAT Plano Principal Oi TV nível conta"),BENEFICIOS!$A:$G,5,0))),"Criar",IF(CG11="","",VLOOKUP(($BC11&CG11&"Template desconto FLAT Plano Principal Oi TV nível conta"),BENEFICIOS!$A:$G,5,0))) | CJ11: =IF(CI11=0,"",IF(CI11=VLOOKUP("PCS-OzTL42",ARBOR!$A:$C,3,0),0.0001,IF(CI11>VLOOKUP("PCS-OzTL42",ARBOR!$A:$C,3,0),"Maior que CAP!",IF((DOLLAR(CI11+(VLOOKUP("PCS-OzTL42",ARBOR!$A:$C,3,0)*-TRUNC(CI11/VLOOKUP("PCS-OzTL42",ARBOR!$A:$C,3,0)-1,4)),6))<>(DOLLAR(VLOOKUP("PCS-OzTL42",ARBOR!$A:$C,3,0),6)),-TRUNC(CI11/VLOOKUP("PCS-OzTL42",ARBOR!$A:$C,3,0)-1,4)+0.0001,-TRUNC(CI11/VLOOKUP("PCS-OzTL42",ARBOR!$A:$C,3,0)-1,4))))) | CK11: =IF(ISERROR(IF(CJ11="","",VLOOKUP(($BC11&CJ11&"Template desconto FLAT Plano Principal Oi TV nível conta"),BENEFICIOS!$A:$G,5,0))),"Criar",IF(CJ11="","",VLOOKUP(($BC11&CJ11&"Template desconto FLAT Plano Principal Oi TV nível conta"),BENEFICIOS!$A:$G,5,0))) | CM11: =IF(CL11=0,"",IF(CL11=VLOOKUP("PCS-OzTL47",ARBOR!$A:$C,3,0),0.0001,IF(CL11>VLOOKUP("PCS-OzTL47",ARBOR!$A:$C,3,0),"Maior que CAP!",IF((DOLLAR(CL11+(VLOOKUP("PCS-OzTL47",ARBOR!$A:$C,3,0)*-TRUNC(CL11/VLOOKUP("PCS-OzTL47",ARBOR!$A:$C,3,0)-1,4)),6))<>(DOLLAR(VLOOKUP("PCS-OzTL47",ARBOR!$A:$C,3,0),6)),-TRUNC(CL11/VLOOKUP("PCS-OzTL47",ARBOR!$A:$C,3,0)-1,4)+0.0001,-TRUNC(CL11/VLOOKUP("PCS-OzTL47",ARBOR!$A:$C,3,0)-1,4))))) | CN11: =IF(ISERROR(IF(CM11="","",VLOOKUP(($BC11&CM11&"Template desconto FLAT Plano Principal Oi TV nível conta"),BENEFICIOS!$A:$G,5,0))),"Criar",IF(CM11="","",VLOOKUP(($BC11&CM11&"Template desconto FLAT Plano Principal Oi TV nível conta"),BENEFICIOS!$A:$G,5,0))) | CP11: =IF(CO11=0,"",IF(CO11=VLOOKUP("PCS-OzTL46",ARBOR!$A:$C,3,0),0.0001,IF(CO11>VLOOKUP("PCS-OzTL46",ARBOR!$A:$C,3,0),"Maior que CAP!",IF((DOLLAR(CO11+(VLOOKUP("PCS-OzTL46",ARBOR!$A:$C,3,0)*-TRUNC(CO11/VLOOKUP("PCS-OzTL46",ARBOR!$A:$C,3,0)-1,4)),6))<>(DOLLAR(VLOOKUP("PCS-OzTL46",ARBOR!$A:$C,3,0),6)),-TRUNC(CO11/VLOOKUP("PCS-OzTL46",ARBOR!$A:$C,3,0)-1,4)+0.0001,-TRUNC(CO11/VLOOKUP("PCS-OzTL46",ARBOR!$A:$C,3,0)-1,4))))) | CQ11: =IF(ISERROR(IF(CP11="","",VLOOKUP(($BC11&CP11&"Template desconto FLAT Plano Principal Oi TV nível conta"),BENEFICIOS!$A:$G,5,0))),"Criar",IF(CP11="","",VLOOKUP(($BC11&CP11&"Template desconto FLAT Plano Principal Oi TV nível conta"),BENEFICIOS!$A:$G,5,0))) | CS11: =IF(CR11=0,"",IF(CR11=VLOOKUP("PCS-OzTL48",ARBOR!$A:$C,3,0),0.0001,IF(CR11>VLOOKUP("PCS-OzTL48",ARBOR!$A:$C,3,0),"Maior que CAP!",IF((DOLLAR(CR11+(VLOOKUP("PCS-OzTL48",ARBOR!$A:$C,3,0)*-TRUNC(CR11/VLOOKUP("PCS-OzTL48",ARBOR!$A:$C,3,0)-1,4)),6))<>(DOLLAR(VLOOKUP("PCS-OzTL48",ARBOR!$A:$C,3,0),6)),-TRUNC(CR11/VLOOKUP("PCS-OzTL48",ARBOR!$A:$C,3,0)-1,4)+0.0001,-TRUNC(CR11/VLOOKUP("PCS-OzTL48",ARBOR!$A:$C,3,0)-1,4))))) | CT11: =IF(ISERROR(IF(CS11="","",VLOOKUP(($BC11&CS11&"Template desconto FLAT Plano Principal Oi TV nível conta"),BENEFICIOS!$A:$G,5,0))),"Criar",IF(CS11="","",VLOOKUP(($BC11&CS11&"Template desconto FLAT Plano Principal Oi TV nível conta"),BENEFICIOS!$A:$G,5,0))) | CV11: =IF(CU11=0,"",IF(CU11=VLOOKUP("PCS-OzTL742",ARBOR!$A:$C,3,0),0.0001,IF(CU11>VLOOKUP("PCS-OzTL742",ARBOR!$A:$C,3,0),"Maior que CAP!",IF((DOLLAR(CU11+(VLOOKUP("PCS-OzTL742",ARBOR!$A:$C,3,0)*-TRUNC(CU11/VLOOKUP("PCS-OzTL742",ARBOR!$A:$C,3,0)-1,4)),6))<>(DOLLAR(VLOOKUP("PCS-OzTL742",ARBOR!$A:$C,3,0),6)),-TRUNC(CU11/VLOOKUP("PCS-OzTL742",ARBOR!$A:$C,3,0)-1,4)+0.0001,-TRUNC(CU11/VLOOKUP("PCS-OzTL742",ARBOR!$A:$C,3,0)-1,4))))) | CW11: =IF(ISERROR(IF(CV11="","",VLOOKUP(($BC11&CV11&"Template desconto FLAT Plano Principal Oi TV nível conta"),BENEFICIOS!$A:$G,5,0))),"Criar",IF(CV11="","",VLOOKUP(($BC11&CV11&"Template desconto FLAT Plano Principal Oi TV nível conta"),BENEFICIOS!$A:$G,5,0))) | CY11: =IF(CX11=0,"",IF(CX11=VLOOKUP("PCS-OzTL747",ARBOR!$A:$C,3,0),0.0001,IF(CX11>VLOOKUP("PCS-OzTL747",ARBOR!$A:$C,3,0),"Maior que CAP!",IF((DOLLAR(CX11+(VLOOKUP("PCS-OzTL747",ARBOR!$A:$C,3,0)*-TRUNC(CX11/VLOOKUP("PCS-OzTL747",ARBOR!$A:$C,3,0)-1,4)),6))<>(DOLLAR(VLOOKUP("PCS-OzTL747",ARBOR!$A:$C,3,0),6)),-TRUNC(CX11/VLOOKUP("PCS-OzTL747",ARBOR!$A:$C,3,0)-1,4)+0.0001,-TRUNC(CX11/VLOOKUP("PCS-OzTL747",ARBOR!$A:$C,3,0)-1,4))))) | CZ11: =IF(ISERROR(IF(CY11="","",VLOOKUP(($BC11&CY11&"Template desconto FLAT Plano Principal Oi TV nível conta"),BENEFICIOS!$A:$G,5,0))),"Criar",IF(CY11="","",VLOOKUP(($BC11&CY11&"Template desconto FLAT Plano Principal Oi TV nível conta"),BENEFICIOS!$A:$G,5,0))) | DB11: =IF(DA11=0,"",IF(DA11=VLOOKUP("PCS-OzTL746",ARBOR!$A:$C,3,0),0.0001,IF(DA11>VLOOKUP("PCS-OzTL746",ARBOR!$A:$C,3,0),"Maior que CAP!",IF((DOLLAR(DA11+(VLOOKUP("PCS-OzTL746",ARBOR!$A:$C,3,0)*-TRUNC(DA11/VLOOKUP("PCS-OzTL746",ARBOR!$A:$C,3,0)-1,4)),6))<>(DOLLAR(VLOOKUP("PCS-OzTL746",ARBOR!$A:$C,3,0),6)),-TRUNC(DA11/VLOOKUP("PCS-OzTL746",ARBOR!$A:$C,3,0)-1,4)+0.0001,-TRUNC(DA11/VLOOKUP("PCS-OzTL746",ARBOR!$A:$C,3,0)-1,4))))) | DC11: =IF(ISERROR(IF(DB11="","",VLOOKUP(($BC11&DB11&"Template desconto FLAT Plano Principal Oi TV nível conta"),BENEFICIOS!$A:$G,5,0))),"Criar",IF(DB11="","",VLOOKUP(($BC11&DB11&"Template desconto FLAT Plano Principal Oi TV nível conta"),BENEFICIOS!$A:$G,5,0))) | DE11: =IF(DD11=0,"",IF(DD11=VLOOKUP("PCS-OzTL748",ARBOR!$A:$C,3,0),0.0001,IF(DD11>VLOOKUP("PCS-OzTL748",ARBOR!$A:$C,3,0),"Maior que CAP!",IF((DOLLAR(DD11+(VLOOKUP("PCS-OzTL748",ARBOR!$A:$C,3,0)*-TRUNC(DD11/VLOOKUP("PCS-OzTL748",ARBOR!$A:$C,3,0)-1,4)),6))<>(DOLLAR(VLOOKUP("PCS-OzTL748",ARBOR!$A:$C,3,0),6)),-TRUNC(DD11/VLOOKUP("PCS-OzTL748",ARBOR!$A:$C,3,0)-1,4)+0.0001,-TRUNC(DD11/VLOOKUP("PCS-OzTL748",ARBOR!$A:$C,3,0)-1,4))))) | DF11: =IF(ISERROR(IF(DE11="","",VLOOKUP(($BC11&DE11&"Template desconto FLAT Plano Principal Oi TV nível conta"),BENEFICIOS!$A:$G,5,0))),"Criar",IF(DE11="","",VLOOKUP(($BC11&DE11&"Template desconto FLAT Plano Principal Oi TV nível conta"),BENEFICIOS!$A:$G,5,0))) | DH11: =IF(DG11=0,"",IF(DG11=VLOOKUP("PCS-OzTL34",ARBOR!$A:$C,3,0),0.0001,IF(DG11>VLOOKUP("PCS-OzTL34",ARBOR!$A:$C,3,0),"Maior que CAP!",IF((DOLLAR(DG11+(VLOOKUP("PCS-OzTL34",ARBOR!$A:$C,3,0)*-TRUNC(DG11/VLOOKUP("PCS-OzTL34",ARBOR!$A:$C,3,0)-1,4)),6))<>(DOLLAR(VLOOKUP("PCS-OzTL34",ARBOR!$A:$C,3,0),6)),-TRUNC(DG11/VLOOKUP("PCS-OzTL34",ARBOR!$A:$C,3,0)-1,4)+0.0001,-TRUNC(DG11/VLOOKUP("PCS-OzTL34",ARBOR!$A:$C,3,0)-1,4))))) | DI11: =IF(DH11="S/Desc","S/Desc",IF(ISERROR(IF(DH11="","",VLOOKUP(($BC11&DH11&"Template desconto % Combate nível conta"),BENEFICIOS!$A:$G,5,0))),"Criar",IF(DH11="","",VLOOKUP(($BC11&DH11&"Template desconto % Combate nível conta"),BENEFICIOS!$A:$G,5,0)))) | DK11: =IF(DJ11=0,"",IF(DJ11=VLOOKUP("PCS-OzTL31",ARBOR!$A:$C,3,0),0.0001,IF(DJ11>VLOOKUP("PCS-OzTL31",ARBOR!$A:$C,3,0),"Maior que CAP!",IF((DOLLAR(DJ11+(VLOOKUP("PCS-OzTL31",ARBOR!$A:$C,3,0)*-TRUNC(DJ11/VLOOKUP("PCS-OzTL31",ARBOR!$A:$C,3,0)-1,4)),6))<>(DOLLAR(VLOOKUP("PCS-OzTL31",ARBOR!$A:$C,3,0),6)),-TRUNC(DJ11/VLOOKUP("PCS-OzTL31",ARBOR!$A:$C,3,0)-1,4)+0.0001,-TRUNC(DJ11/VLOOKUP("PCS-OzTL31",ARBOR!$A:$C,3,0)-1,4))))) | DL11: =IF(DK11="S/Desc","S/Desc",IF(ISERROR(IF(DK11="","",VLOOKUP(($BC11&DK11&"Template desconto % Sexy Hot nível conta"),BENEFICIOS!$A:$G,5,0))),"Criar",IF(DK11="","",VLOOKUP(($BC11&DK11&"Template desconto % Sexy Hot nível conta"),BENEFICIOS!$A:$G,5,0)))) | DN11: =IF(DM11=0,"",IF(DM11=VLOOKUP("PCS-OzTL32",ARBOR!$A:$C,3,0),0.0001,IF(DM11>VLOOKUP("PCS-OzTL32",ARBOR!$A:$C,3,0),"Maior que CAP!",IF((DOLLAR(DM11+(VLOOKUP("PCS-OzTL32",ARBOR!$A:$C,3,0)*-TRUNC(DM11/VLOOKUP("PCS-OzTL32",ARBOR!$A:$C,3,0)-1,4)),6))<>(DOLLAR(VLOOKUP("PCS-OzTL32",ARBOR!$A:$C,3,0),6)),-TRUNC(DM11/VLOOKUP("PCS-OzTL32",ARBOR!$A:$C,3,0)-1,4)+0.0001,-TRUNC(DM11/VLOOKUP("PCS-OzTL32",ARBOR!$A:$C,3,0)-1,4))))) | DO11: =IF(DN11="S/Desc","S/Desc",IF(ISERROR(IF(DN11="","",VLOOKUP(($BC11&DN11&"Template desconto % Playboy nível conta"),BENEFICIOS!$A:$G,5,0))),"Criar",IF(DN11="","",VLOOKUP(($BC11&DN11&"Template desconto % Playboy nível conta"),BENEFICIOS!$A:$G,5,0)))) | DQ11: =IF(DP11=0,"",IF(DP11=VLOOKUP("PCS-OzTL33",ARBOR!$A:$C,3,0),0.0001,IF(DP11>VLOOKUP("PCS-OzTL33",ARBOR!$A:$C,3,0),"Maior que CAP!",IF((DOLLAR(DP11+(VLOOKUP("PCS-OzTL33",ARBOR!$A:$C,3,0)*-TRUNC(DP11/VLOOKUP("PCS-OzTL33",ARBOR!$A:$C,3,0)-1,4)),6))<>(DOLLAR(VLOOKUP("PCS-OzTL33",ARBOR!$A:$C,3,0),6)),-TRUNC(DP11/VLOOKUP("PCS-OzTL33",ARBOR!$A:$C,3,0)-1,4)+0.0001,-TRUNC(DP11/VLOOKUP("PCS-OzTL33",ARBOR!$A:$C,3,0)-1,4))))) | DR11: =IF(DQ11="S/Desc","S/Desc",IF(ISERROR(IF(DQ11="","",VLOOKUP(($BC11&DQ11&"Template desconto % Sexy Hot + Playboy nível conta"),BENEFICIOS!$A:$G,5,0))),"Criar",IF(DQ11="","",VLOOKUP(($BC11&DQ11&"Template desconto % Sexy Hot + Playboy nível conta"),BENEFICIOS!$A:$G,5,0)))) | DT11: =IF(DS11=0,"",IF(DS11=VLOOKUP("PCS-OzTL503",ARBOR!$A:$C,3,0),0.0001,IF(DS11>VLOOKUP("PCS-OzTL503",ARBOR!$A:$C,3,0),"Maior que CAP!",IF((DOLLAR(DS11+(VLOOKUP("PCS-OzTL503",ARBOR!$A:$C,3,0)*-TRUNC(DS11/VLOOKUP("PCS-OzTL503",ARBOR!$A:$C,3,0)-1,4)),6))<>(DOLLAR(VLOOKUP("PCS-OzTL503",ARBOR!$A:$C,3,0),6)),-TRUNC(DS11/VLOOKUP("PCS-OzTL503",ARBOR!$A:$C,3,0)-1,4)+0.0001,-TRUNC(DS11/VLOOKUP("PCS-OzTL503",ARBOR!$A:$C,3,0)-1,4))))) | DU11: =IF(DT11="S/Desc","S/Desc",IF(ISERROR(IF(DT11="","",VLOOKUP(($BC11&DT11&"Template desconto % SexPrivê nível conta"),BENEFICIOS!$A:$G,5,0))),"Criar",IF(DT11="","",VLOOKUP(($BC11&DT11&"Template desconto % SexPrivê nível conta"),BENEFICIOS!$A:$G,5,0)))) | DW11: =IF(DV11=0,"",IF(DV11=VLOOKUP("PCS-OzTL500",ARBOR!$A:$C,3,0),0.0001,IF(DV11>VLOOKUP("PCS-OzTL500",ARBOR!$A:$C,3,0),"Maior que CAP!",IF((DOLLAR(DV11+(VLOOKUP("PCS-OzTL500",ARBOR!$A:$C,3,0)*-TRUNC(DV11/VLOOKUP("PCS-OzTL500",ARBOR!$A:$C,3,0)-1,4)),6))<>(DOLLAR(VLOOKUP("PCS-OzTL500",ARBOR!$A:$C,3,0),6)),-TRUNC(DV11/VLOOKUP("PCS-OzTL500",ARBOR!$A:$C,3,0)-1,4)+0.0001,-TRUNC(DV11/VLOOKUP("PCS-OzTL500",ARBOR!$A:$C,3,0)-1,4))))) | DX11: =IF(DW11="S/Desc","S/Desc",IF(ISERROR(IF(DW11="","",VLOOKUP(($BC11&DW11&"Template desconto % Étnico nível conta"),BENEFICIOS!$A:$G,5,0))),"Criar",IF(DW11="","",VLOOKUP(($BC11&DW11&"Template desconto % Étnico nível conta"),BENEFICIOS!$A:$G,5,0)))) | DZ11: =IF(DY11=0,"",IF(DY11=VLOOKUP("PCS-OzTL50",ARBOR!$A:$C,3,0),0.0001,IF(DY11>VLOOKUP("PCS-OzTL50",ARBOR!$A:$C,3,0),"Maior que CAP!",IF((DOLLAR(DY11+(VLOOKUP("PCS-OzTL50",ARBOR!$A:$C,3,0)*-TRUNC(DY11/VLOOKUP("PCS-OzTL50",ARBOR!$A:$C,3,0)-1,4)),6))<>(DOLLAR(VLOOKUP("PCS-OzTL50",ARBOR!$A:$C,3,0),6)),-TRUNC(DY11/VLOOKUP("PCS-OzTL50",ARBOR!$A:$C,3,0)-1,4)+0.0001,-TRUNC(DY11/VLOOKUP("PCS-OzTL50",ARBOR!$A:$C,3,0)-1,4))))) | EC11: =IF(EB11=0,"",IF(EB11=VLOOKUP("PCS-OzTL51",ARBOR!$A:$C,3,0),0.0001,IF(EB11>VLOOKUP("PCS-OzTL51",ARBOR!$A:$C,3,0),"Maior que CAP!",IF((DOLLAR(EB11+(VLOOKUP("PCS-OzTL51",ARBOR!$A:$C,3,0)*-TRUNC(EB11/VLOOKUP("PCS-OzTL51",ARBOR!$A:$C,3,0)-1,4)),6))<>(DOLLAR(VLOOKUP("PCS-OzTL51",ARBOR!$A:$C,3,0),6)),-TRUNC(EB11/VLOOKUP("PCS-OzTL51",ARBOR!$A:$C,3,0)-1,4)+0.0001,-TRUNC(EB11/VLOOKUP("PCS-OzTL51",ARBOR!$A:$C,3,0)-1,4))))) | EF11: =IF(EE11=0,"",IF(EE11=VLOOKUP("PCS-OzTL52",ARBOR!$A:$C,3,0),0.0001,IF(EE11>VLOOKUP("PCS-OzTL52",ARBOR!$A:$C,3,0),"Maior que CAP!",IF((DOLLAR(EE11+(VLOOKUP("PCS-OzTL52",ARBOR!$A:$C,3,0)*-TRUNC(EE11/VLOOKUP("PCS-OzTL52",ARBOR!$A:$C,3,0)-1,4)),6))<>(DOLLAR(VLOOKUP("PCS-OzTL52",ARBOR!$A:$C,3,0),6)),-TRUNC(EE11/VLOOKUP("PCS-OzTL52",ARBOR!$A:$C,3,0)-1,4)+0.0001,-TRUNC(EE11/VLOOKUP("PCS-OzTL52",ARBOR!$A:$C,3,0)-1,4))))) | EI11: =IF(EH11=0,"",IF(EH11=VLOOKUP("PCS-OzTL53",ARBOR!$A:$C,3,0),0.0001,IF(EH11>VLOOKUP("PCS-OzTL53",ARBOR!$A:$C,3,0),"Maior que CAP!",IF((DOLLAR(EH11+(VLOOKUP("PCS-OzTL53",ARBOR!$A:$C,3,0)*-TRUNC(EH11/VLOOKUP("PCS-OzTL53",ARBOR!$A:$C,3,0)-1,4)),6))<>(DOLLAR(VLOOKUP("PCS-OzTL53",ARBOR!$A:$C,3,0),6)),-TRUNC(EH11/VLOOKUP("PCS-OzTL53",ARBOR!$A:$C,3,0)-1,4)+0.0001,-TRUNC(EH11/VLOOKUP("PCS-OzTL53",ARBOR!$A:$C,3,0)-1,4))))) | EL11: =IF(EK11=0,"",IF(EK11=VLOOKUP("PCS-OzTL54",ARBOR!$A:$C,3,0),0.0001,IF(EK11>VLOOKUP("PCS-OzTL54",ARBOR!$A:$C,3,0),"Maior que CAP!",IF((DOLLAR(EK11+(VLOOKUP("PCS-OzTL54",ARBOR!$A:$C,3,0)*-TRUNC(EK11/VLOOKUP("PCS-OzTL54",ARBOR!$A:$C,3,0)-1,4)),6))<>(DOLLAR(VLOOKUP("PCS-OzTL54",ARBOR!$A:$C,3,0),6)),-TRUNC(EK11/VLOOKUP("PCS-OzTL54",ARBOR!$A:$C,3,0)-1,4)+0.0001,-TRUNC(EK11/VLOOKUP("PCS-OzTL54",ARBOR!$A:$C,3,0)-1,4))))) | EO11: =IF(EN11=0,"",IF(EN11=VLOOKUP("PCS-OzTL99",ARBOR!$A:$C,3,0),0.0001,IF(EN11>VLOOKUP("PCS-OzTL99",ARBOR!$A:$C,3,0),"Maior que CAP!",IF((DOLLAR(EN11+(VLOOKUP("PCS-OzTL99",ARBOR!$A:$C,3,0)*-TRUNC(EN11/VLOOKUP("PCS-OzTL99",ARBOR!$A:$C,3,0)-1,4)),6))<>(DOLLAR(VLOOKUP("PCS-OzTL99",ARBOR!$A:$C,3,0),6)),-TRUNC(EN11/VLOOKUP("PCS-OzTL99",ARBOR!$A:$C,3,0)-1,4)+0.0001,-TRUNC(EN11/VLOOKUP("PCS-OzTL99",ARBOR!$A:$C,3,0)-1,4))))) | EP11: =IF(EO11="S/Desc","S/Desc",IF(ISERROR(IF(EO11="","",VLOOKUP(($BC11&EO11&"Template desconto % Ponto adicional nível conta"),BENEFICIOS!$A:$G,5,0))),"Criar",IF(EO11="","",VLOOKUP(($BC11&EO11&"Template desconto % Ponto adicional nível conta"),BENEFICIOS!$A:$G,5,0)))) | ER11: =IF(EQ11="Sim","PCS-34704","") | EW11: =IF(ET11="Benefício","Oi benefício fidelização Multiprodutos","") | EX11: =IF(ET11="Benefício","PCS-Fk83324","") | EY11: =IF(ES11="Sim","PCS-SBL553142","") | FG11: =IF($BH11="","",$BH11+$BE11) | FH11: =IF($BK11="","",$BK11+$BE11) | FI11: =IF($BN11="","",$BN11+$BE11) | FJ11: =IF($BQ11="","",$BQ11+$BE11) | FK11: =IF($BT11="","",$BT11+$BE11) | FL11: =IF($BW11="","",$BW11+$BE11) | FM11: =IF($BZ11="","",$BZ11+$BE11) | FN11: =IF($CC11="","",$CC11+$BE11) | FO11: =IF($CF11="","",$CF11+$BE11) | FP11: =IF($CI11="","",$CI11+$BE11) | FQ11: =IF($CL11="","",$CL11+$BE11) | FR11: =IF($CO11="","",$CO11+$BE11) | FS11: =IF($CR11="","",$CR11+$BE11) | FT11: =IF($CU11="","",$CU11+$BE11) | FU11: =IF($CX11="","",$CX11+$BE11) | FV11: =IF($DA11="","",$DA11+$BE11) | FW11: =IF($DD11="","",$DD11+$BE11)
