Workbook

Sheet DDD
B2: UF | C2: LOCALIDADE | D2: MUNICÍPIO | E2: Chave | F2: DDD | G2: UF
B3: AC | C3: ACRELÂNDIA | D3: ACRELANDIA | E3: =B3&D3 -> ACACRELANDIA | F3: 68 | G3: AC
B4: AC | C4: ASSIS BRASIL | D4: ASSIS BRASIL | E4: =B4&D4 -> ACASSIS BRASIL | F4: 68 | G4: AC
B5: AC | C5: BRASILÉIA | D5: BRASILEIA | E5: =B5&D5 -> ACBRASILEIA | F5: 68 | G5: AC
B6: AC | C6: BUJARI | D6: BUJARI | E6: =B6&D6 -> ACBUJARI | F6: 68 | G6: AC
B7: AC | C7: CAPIXABA | D7: CAPIXABA | E7: =B7&D7 -> ACCAPIXABA | F7: 68 | G7: AC
B8: AC | C8: ASSIS BRASIL | D8: CRUZEIRO DO SUL | E8: =B8&D8 -> ACCRUZEIRO DO SUL | F8: 68 | G8: AC
B9: AC | C9: CRUZEIRO DO SUL | D9: CRUZEIRO DO SUL | E9: =B9&D9 -> ACCRUZEIRO DO SUL | F9: 68 | G9: AC
B10: AC | C10: SANTA ROSA DO JURUA | D10: CRUZEIRO DO SUL | E10: =B10&D10 -> ACCRUZEIRO DO SUL | F10: 68 | G10: AC
B11: AC | C11: FEIJÓ | D11: FEIJO | E11: =B11&D11 -> ACFEIJO | F11: 68 | G11: AC
B12: AC | C12: JORDÃO | D12: JORDAO | E12: =B12&D12 -> ACJORDAO | F12: 68 | G12: AC
B13: AC | C13: MÂNCIO LIMA | D13: MANCIO LIMA | E13: =B13&D13 -> ACMANCIO LIMA | F13: 68 | G13: AC
B14: AC | C14: MANOEL URBANO | D14: MANOEL URBANO | E14: =B14&D14 -> ACMANOEL URBANO | F14: 68 | G14: AC
... B9183: TO | C9183: XAMBIOÁ | D9183: XAMBIOA | E9183: =B9183&D9183 -> TOXAMBIOA | F9183: 63 | G9183: TO

Sheet Exportar Planilha Final
A1: UF | B1: NO_MUNICIPIO | C1: GRUPO_OFERTA | D1: GRUPO_PORTA_OCIOSAS | E1: DT_CRIACAO | F1: Num_DDD
A2: AC | B2: Acrelandia | C2: CONEC LIGHT | D2: PO | E2: 08/10/2019 | F2: 68 | H2: INSERT INTO PEGARULES.TB_MUNICIPIOS_OFERTAS VALUES( | I2: =_xlfn.CONCAT("'",A2,"'",",") -> 'AC', | J2: =_xlfn.CONCAT("'",B2,"'",",") -> 'Acrelandia', | K2: =_xlfn.CONCAT("'",C2,"'",",") -> 'CONEC LIGHT', | L2: =_xlfn.CONCAT("'",D2,"'",",") -> 'PO', | M2: =_xlfn.CONCAT("to_date('",E2,"','dd/mm/yyyy')",",") -> to_date('08/10/2019','dd/mm/yyyy'), | N2: =_xlfn.CONCAT(F2,");") -> 68); | P2: =_xlfn.CONCAT(H2:N2) -> INSERT INTO PEGARULES.TB_MUNICIPIOS_OFERTAS VALUES('AC','Acrelandia','CONEC LIGHT','PO',to_date('08/10/2019','dd/mm/yyyy'),68);
A3: AC | B3: Assis Brasil | C3: CONEC LIGHT | D3: PO | E3: 08/10/2019 | F3: 68 | H3: INSERT INTO PEGARULES.TB_MUNICIPIOS_OFERTAS VALUES( | I3: =_xlfn.CONCAT("'",A3,"'",",") -> 'AC', | J3: =_xlfn.CONCAT("'",B3,"'",",") -> 'Assis Brasil', | K3: =_xlfn.CONCAT("'",C3,"'",",") -> 'CONEC LIGHT', | L3: =_xlfn.CONCAT("'",D3,"'",",") -> 'PO', | M3: =_xlfn.CONCAT("to_date('",E3,"','dd/mm/yyyy')",",") -> to_date('08/10/2019','dd/mm/yyyy'), | N3: =_xlfn.CONCAT(F3,");") -> 68); | P3: =_xlfn.CONCAT(H3:N3) -> INSERT INTO PEGARULES.TB_MUNICIPIOS_OFERTAS VALUES('AC','Assis Brasil','CONEC LIGHT','PO',to_date('08/10/2019','dd/mm/yyyy'),68);
A4: AC | B4: Brasileia | C4: CONEC LIGHT | D4: PO | E4: 08/10/2019 | F4: 68 | H4: INSERT INTO PEGARULES.TB_MUNICIPIOS_OFERTAS VALUES( | I4: =_xlfn.CONCAT("'",A4,"'",",") -> 'AC', | J4: =_xlfn.CONCAT("'",B4,"'",",") -> 'Brasileia', | K4: =_xlfn.CONCAT("'",C4,"'",",") -> 'CONEC LIGHT', | L4: =_xlfn.CONCAT("'",D4,"'",",") -> 'PO', | M4: =_xlfn.CONCAT("to_date('",E4,"','dd/mm/yyyy')",",") -> to_date('08/10/2019','dd/mm/yyyy'), | N4: =_xlfn.CONCAT(F4,");") -> 68); | P4: =_xlfn.CONCAT(H4:N4) -> INSERT INTO PEGARULES.TB_MUNICIPIOS_OFERTAS VALUES('AC','Brasileia','CONEC LIGHT','PO',to_date('08/10/2019','dd/mm/yyyy'),68);
A5: AC | B5: Bujari | C5: CONEC LIGHT | D5: PO | E5: 08/10/2019 | F5: 68 | H5: INSERT INTO PEGARULES.TB_MUNICIPIOS_OFERTAS VALUES( | I5: =_xlfn.CONCAT("'",A5,"'",",") -> 'AC', | J5: =_xlfn.CONCAT("'",B5,"'",",") -> 'Bujari', | K5: =_xlfn.CONCAT("'",C5,"'",",") -> 'CONEC LIGHT', | L5: =_xlfn.CONCAT("'",D5,"'",",") -> 'PO', | M5: =_xlfn.CONCAT("to_date('",E5,"','dd/mm/yyyy')",",") -> to_date('08/10/2019','dd/mm/yyyy'), | N5: =_xlfn.CONCAT(F5,");") -> 68); | P5: =_xlfn.CONCAT(H5:N5) -> INSERT INTO PEGARULES.TB_MUNICIPIOS_OFERTAS VALUES('AC','Bujari','CONEC LIGHT','PO',to_date('08/10/2019','dd/mm/yyyy'),68);
A6: AC | B6: Capixaba | C6: CONEC LIGHT | D6: PO | E6: 08/10/2019 | F6: 68 | H6: INSERT INTO PEGARULES.TB_MUNICIPIOS_OFERTAS VALUES( | I6: =_xlfn.CONCAT("'",A6,"'",",") -> 'AC', | J6: =_xlfn.CONCAT("'",B6,"'",",") -> 'Capixaba', | K6: =_xlfn.CONCAT("'",C6,"'",",") -> 'CONEC LIGHT', | L6: =_xlfn.CONCAT("'",D6,"'",",") -> 'PO', | M6: =_xlfn.CONCAT("to_date('",E6,"','dd/mm/yyyy')",",") -> to_date('08/10/2019','dd/mm/yyyy'), | N6: =_xlfn.CONCAT(F6,");") -> 68); | P6: =_xlfn.CONCAT(H6:N6) -> INSERT INTO PEGARULES.TB_MUNICIPIOS_OFERTAS VALUES('AC','Capixaba','CONEC LIGHT','PO',to_date('08/10/2019','dd/mm/yyyy'),68);
A7: AC | B7: Cruzeiro do Sul | C7: CONEC LIGHT | D7: PO | E7: 08/10/2019 | F7: 68 | H7: INSERT INTO PEGARULES.TB_MUNICIPIOS_OFERTAS VALUES( | I7: =_xlfn.CONCAT("'",A7,"'",",") -> 'AC', | J7: =_xlfn.CONCAT("'",B7,"'",",") -> 'Cruzeiro do Sul', | K7: =_xlfn.CONCAT("'",C7,"'",",") -> 'CONEC LIGHT', | L7: =_xlfn.CONCAT("'",D7,"'",",") -> 'PO', | M7: =_xlfn.CONCAT("to_date('",E7,"','dd/mm/yyyy')",",") -> to_date('08/10/2019','dd/mm/yyyy'), | N7: =_xlfn.CONCAT(F7,");") -> 68); | P7: =_xlfn.CONCAT(H7:N7) -> INSERT INTO PEGARULES.TB_MUNICIPIOS_OFERTAS VALUES('AC','Cruzeiro do Sul','CONEC LIGHT','PO',to_date('08/10/2019','dd/mm/yyyy'),68);
A8: AC | B8: Epitaciolandia | D8: PO | E8: 08/10/2019 | F8: 68 | H8: INSERT INTO PEGARULES.TB_MUNICIPIOS_OFERTAS VALUES( | I8: =_xlfn.CONCAT("'",A8,"'",",") -> 'AC', | J8: =_xlfn.CONCAT("'",B8,"'",",") -> 'Epitaciolandia', | K8: =_xlfn.CONCAT("'",C8,"'",",") -> '', | L8: =_xlfn.CONCAT("'",D8,"'",",") -> 'PO', | M8: =_xlfn.CONCAT("to_date('",E8,"','dd/mm/yyyy')",",") -> to_date('08/10/2019','dd/mm/yyyy'), | N8: =_xlfn.CONCAT(F8,");") -> 68); | P8: =_xlfn.CONCAT(H8:N8) -> INSERT INTO PEGARULES.TB_MUNICIPIOS_OFERTAS VALUES('AC','Epitaciolandia','','PO',to_date('08/10/2019','dd/mm/yyyy'),68);
A9: AC | B9: Feijo | C9: CONEC LIGHT | D9: PO | E9: 08/10/2019 | F9: 68 | H9: INSERT INTO PEGARULES.TB_MUNICIPIOS_OFERTAS VALUES( | I9: =_xlfn.CONCAT("'",A9,"'",",") -> 'AC', | J9: =_xlfn.CONCAT("'",B9,"'",",") -> 'Feijo', | K9: =_xlfn.CONCAT("'",C9,"'",",") -> 'CONEC LIGHT', | L9: =_xlfn.CONCAT("'",D9,"'",",") -> 'PO', | M9: =_xlfn.CONCAT("to_date('",E9,"','dd/mm/yyyy')",",") -> to_date('08/10/2019','dd/mm/yyyy'), | N9: =_xlfn.CONCAT(F9,");") -> 68); | P9: =_xlfn.CONCAT(H9:N9) -> INSERT INTO PEGARULES.TB_MUNICIPIOS_OFERTAS VALUES('AC','Feijo','CONEC LIGHT','PO',to_date('08/10/2019','dd/mm/yyyy'),68);
A10: AC | B10: Jordao | C10: CONEC LIGHT | D10: PO | E10: 08/10/2019 | F10: 68 | H10: INSERT INTO PEGARULES.TB_MUNICIPIOS_OFERTAS VALUES( | I10: =_xlfn.CONCAT("'",A10,"'",",") -> 'AC', | J10: =_xlfn.CONCAT("'",B10,"'",",") -> 'Jordao', | K10: =_xlfn.CONCAT("'",C10,"'",",") -> 'CONEC LIGHT', | L10: =_xlfn.CONCAT("'",D10,"'",",") -> 'PO', | M10: =_xlfn.CONCAT("to_date('",E10,"','dd/mm/yyyy')",",") -> to_date('08/10/2019','dd/mm/yyyy'), | N10: =_xlfn.CONCAT(F10,");") -> 68); | P10: =_xlfn.CONCAT(H10:N10) -> INSERT INTO PEGARULES.TB_MUNICIPIOS_OFERTAS VALUES('AC','Jordao','CONEC LIGHT','PO',to_date('08/10/2019','dd/mm/yyyy'),68);
A11: AC | B11: Mancio Lima | C11: CONEC LIGHT | D11: PO | E11: 08/10/2019 | F11: 68 | H11: INSERT INTO PEGARULES.TB_MUNICIPIOS_OFERTAS VALUES( | I11: =_xlfn.CONCAT("'",A11,"'",",") -> 'AC', | J11: =_xlfn.CONCAT("'",B11,"'",",") -> 'Mancio Lima', | K11: =_xlfn.CONCAT("'",C11,"'",",") -> 'CONEC LIGHT', | L11: =_xlfn.CONCAT("'",D11,"'",",") -> 'PO', | M11: =_xlfn.CONCAT("to_date('",E11,"','dd/mm/yyyy')",",") -> to_date('08/10/2019','dd/mm/yyyy'), | N11: =_xlfn.CONCAT(F11,");") -> 68); | P11: =_xlfn.CONCAT(H11:N11) -> INSERT INTO PEGARULES.TB_MUNICIPIOS_OFERTAS VALUES('AC','Mancio Lima','CONEC LIGHT','PO',to_date('08/10/2019','dd/mm/yyyy'),68);
A12: AC | B12: Manoel Urbano | C12: CONEC LIGHT | D12: PO | E12: 08/10/2019 | F12: 68 | H12: INSERT INTO PEGARULES.TB_MUNICIPIOS_OFERTAS VALUES( | I12: =_xlfn.CONCAT("'",A12,"'",",") -> 'AC', | J12: =_xlfn.CONCAT("'",B12,"'",",") -> 'Manoel Urbano', | K12: =_xlfn.CONCAT("'",C12,"'",",") -> 'CONEC LIGHT', | L12: =_xlfn.CONCAT("'",D12,"'",",") -> 'PO', | M12: =_xlfn.CONCAT("to_date('",E12,"','dd/mm/yyyy')",",") -> to_date('08/10/2019','dd/mm/yyyy'), | N12: =_xlfn.CONCAT(F12,");") -> 68); | P12: =_xlfn.CONCAT(H12:N12) -> INSERT INTO PEGARULES.TB_MUNICIPIOS_OFERTAS VALUES('AC','Manoel Urbano','CONEC LIGHT','PO',to_date('08/10/2019','dd/mm/yyyy'),68);
A13: AC | B13: Marechal Thaumaturgo | C13: CONEC LIGHT | D13: PO | E13: 08/10/2019 | F13: 68 | H13: INSERT INTO PEGARULES.TB_MUNICIPIOS_OFERTAS VALUES( | I13: =_xlfn.CONCAT("'",A13,"'",",") -> 'AC', | J13: =_xlfn.CONCAT("'",B13,"'",",") -> 'Marechal Thaumaturgo', | K13: =_xlfn.CONCAT("'",C13,"'",",") -> 'CONEC LIGHT', | L13: =_xlfn.CONCAT("'",D13,"'",",") -> 'PO', | M13: =_xlfn.CONCAT("to_date('",E13,"','dd/mm/yyyy')",",") -> to_date('08/10/2019','dd/mm/yyyy'), | N13: =_xlfn.CONCAT(F13,");") -> 68); | P13: =_xlfn.CONCAT(H13:N13) -> INSERT INTO PEGARULES.TB_MUNICIPIOS_OFERTAS VALUES('AC','Marechal Thaumaturgo','CONEC LIGHT','PO',to_date('08/10/2019','dd/mm/yyyy'),68);
A14: AC | B14: Placido de Castro | C14: CONEC LIGHT | D14: PO | E14: 08/10/2019 | F14: 68 | H14: INSERT INTO PEGARULES.TB_MUNICIPIOS_OFERTAS VALUES( | I14: =_xlfn.CONCAT("'",A14,"'",",") -> 'AC', | J14: =_xlfn.CONCAT("'",B14,"'",",") -> 'Placido de Castro', | K14: =_xlfn.CONCAT("'",C14,"'",",") -> 'CONEC LIGHT', | L14: =_xlfn.CONCAT("'",D14,"'",",") -> 'PO', | M14: =_xlfn.CONCAT("to_date('",E14,"','dd/mm/yyyy')",",") -> to_date('08/10/2019','dd/mm/yyyy'), | N14: =_xlfn.CONCAT(F14,");") -> 68); | P14: =_xlfn.CONCAT(H14:N14) -> INSERT INTO PEGARULES.TB_MUNICIPIOS_OFERTAS VALUES('AC','Placido de Castro','CONEC LIGHT','PO',to_date('08/10/2019','dd/mm/yyyy'),68);
A15: AC | B15: Porto Acre | C15: CONEC LIGHT | D15: PO | E15: 08/10/2019 | F15: 68 | H15: INSERT INTO PEGARULES.TB_MUNICIPIOS_OFERTAS VALUES( | I15: =_xlfn.CONCAT("'",A15,"'",",") -> 'AC', | J15: =_xlfn.CONCAT("'",B15,"'",",") -> 'Porto Acre', | K15: =_xlfn.CONCAT("'",C15,"'",",") -> 'CONEC LIGHT', | L15: =_xlfn.CONCAT("'",D15,"'",",") -> 'PO', | M15: =_xlfn.CONCAT("to_date('",E15,"','dd/mm/yyyy')",",") -> to_date('08/10/2019','dd/mm/yyyy'), | N15: =_xlfn.CONCAT(F15,");") -> 68); | P15: =_xlfn.CONCAT(H15:N15) -> INSERT INTO PEGARULES.TB_MUNICIPIOS_OFERTAS VALUES('AC','Porto Acre','CONEC LIGHT','PO',to_date('08/10/2019','dd/mm/yyyy'),68);
A16: AC | B16: Porto Walter | C16: CONEC LIGHT | D16: PO | E16: 08/10/2019 | F16: 68 | H16: INSERT INTO PEGARULES.TB_MUNICIPIOS_OFERTAS VALUES( | I16: =_xlfn.CONCAT("'",A16,"'",",") -> 'AC', | J16: =_xlfn.CONCAT("'",B16,"'",",") -> 'Porto Walter', | K16: =_xlfn.CONCAT("'",C16,"'",",") -> 'CONEC LIGHT', | L16: =_xlfn.CONCAT("'",D16,"'",",") -> 'PO', | M16: =_xlfn.CONCAT("to_date('",E16,"','dd/mm/yyyy')",",") -> to_date('08/10/2019','dd/mm/yyyy'), | N16: =_xlfn.CONCAT(F16,");") -> 68); | P16: =_xlfn.CONCAT(H16:N16) -> INSERT INTO PEGARULES.TB_MUNICIPIOS_OFERTAS VALUES('AC','Porto Walter','CONEC LIGHT','PO',to_date('08/10/2019','dd/mm/yyyy'),68);
A17: AC | B17: Rio Branco | C17: CONEC LIGHT | E17: 08/10/2019 | F17: 68 | H17: INSERT INTO PEGARULES.TB_MUNICIPIOS_OFERTAS VALUES( | I17: =_xlfn.CONCAT("'",A17,"'",",") -> 'AC', | J17: =_xlfn.CONCAT("'",B17,"'",",") -> 'Rio Branco', | K17: =_xlfn.CONCAT("'",C17,"'",",") -> 'CONEC LIGHT', | L17: =_xlfn.CONCAT("'",D17,"'",",") -> '', | M17: =_xlfn.CONCAT("to_date('",E17,"','dd/mm/yyyy')",",") -> to_date('08/10/2019','dd/mm/yyyy'), | N17: =_xlfn.CONCAT(F17,");") -> 68); | P17: =_xlfn.CONCAT(H17:N17) -> INSERT INTO PEGARULES.TB_MUNICIPIOS_OFERTAS VALUES('AC','Rio Branco','CONEC LIGHT','',to_date('08/10/2019','dd/mm/yyyy'),68);
A18: AC | B18: Rodrigues Alves | C18: CONEC LIGHT | D18: PO | E18: 08/10/2019 | F18: 68 | H18: INSERT INTO PEGARULES.TB_MUNICIPIOS_OFERTAS VALUES( | I18: =_xlfn.CONCAT("'",A18,"'",",") -> 'AC', | J18: =_xlfn.CONCAT("'",B18,"'",",") -> 'Rodrigues Alves', | K18: =_xlfn.CONCAT("'",C18,"'",",") -> 'CONEC LIGHT', | L18: =_xlfn.CONCAT("'",D18,"'",",") -> 'PO', | M18: =_xlfn.CONCAT("to_date('",E18,"','dd/mm/yyyy')",",") -> to_date('08/10/2019','dd/mm/yyyy'), | N18: =_xlfn.CONCAT(F18,");") -> 68); | P18: =_xlfn.CONCAT(H18:N18) -> INSERT INTO PEGARULES.TB_MUNICIPIOS_OFERTAS VALUES('AC','Rodrigues Alves','CONEC LIGHT','PO',to_date('08/10/2019','dd/mm/yyyy'),68);
A19: AC | B19: Santa Rosa do Purus | C19: CONEC LIGHT | D19: PO | E19: 08/10/2019 | F19: 68 | H19: INSERT INTO PEGARULES.TB_MUNICIPIOS_OFERTAS VALUES( | I19: =_xlfn.CONCAT("'",A19,"'",",") -> 'AC', | J19: =_xlfn.CONCAT("'",B19,"'",",") -> 'Santa Rosa do Purus', | K19: =_xlfn.CONCAT("'",C19,"'",",") -> 'CONEC LIGHT', | L19: =_xlfn.CONCAT("'",D19,"'",",") -> 'PO', | M19: =_xlfn.CONCAT("to_date('",E19,"','dd/mm/yyyy')",",") -> to_date('08/10/2019','dd/mm/yyyy'), | N19: =_xlfn.CONCAT(F19,");") -> 68); | P19: =_xlfn.CONCAT(H19:N19) -> INSERT INTO PEGARULES.TB_MUNICIPIOS_OFERTAS VALUES('AC','Santa Rosa do Purus','CONEC LIGHT','PO',to_date('08/10/2019','dd/mm/yyyy'),68);
A20: AC | B20: Sena Madureira | C20: CONEC LIGHT | D20: PO | E20: 08/10/2019 | F20: 68 | H20: INSERT INTO PEGARULES.TB_MUNICIPIOS_OFERTAS VALUES( | I20: =_xlfn.CONCAT("'",A20,"'",",") -> 'AC', | J20: =_xlfn.CONCAT("'",B20,"'",",") -> 'Sena Madureira', | K20: =_xlfn.CONCAT("'",C20,"'",",") -> 'CONEC LIGHT', | L20: =_xlfn.CONCAT("'",D20,"'",",") -> 'PO', | M20: =_xlfn.CONCAT("to_date('",E20,"','dd/mm/yyyy')",",") -> to_date('08/10/2019','dd/mm/yyyy'), | N20: =_xlfn.CONCAT(F20,");") -> 68); | P20: =_xlfn.CONCAT(H20:N20) -> INSERT INTO PEGARULES.TB_MUNICIPIOS_OFERTAS VALUES('AC','Sena Madureira','CONEC LIGHT','PO',to_date('08/10/2019','dd/mm/yyyy'),68);
A21: AC | B21: Senador Guiomard | C21: CONEC LIGHT | D21: PO | E21: 08/10/2019 | F21: 68 | H21: INSERT INTO PEGARULES.TB_MUNICIPIOS_OFERTAS VALUES( | I21: =_xlfn.CONCAT("'",A21,"'",",") -> 'AC', | J21: =_xlfn.CONCAT("'",B21,"'",",") -> 'Senador Guiomard', | K21: =_xlfn.CONCAT("'",C21,"'",",") -> 'CONEC LIGHT', | L21: =_xlfn.CONCAT("'",D21,"'",",") -> 'PO', | M21: =_xlfn.CONCAT("to_date('",E21,"','dd/mm/yyyy')",",") -> to_date('08/10/2019','dd/mm/yyyy'), | N21: =_xlfn.CONCAT(F21,");") -> 68); | P21: =_xlfn.CONCAT(H21:N21) -> INSERT INTO PEGARULES.TB_MUNICIPIOS_OFERTAS VALUES('AC','Senador Guiomard','CONEC LIGHT','PO',to_date('08/10/2019','dd/mm/yyyy'),68);
A22: AC | B22: Tarauaca | C22: CONEC LIGHT | D22: PO | E22: 08/10/2019 | F22: 68 | H22: INSERT INTO PEGARULES.TB_MUNICIPIOS_OFERTAS VALUES( | I22: =_xlfn.CONCAT("'",A22,"'",",") -> 'AC', | J22: =_xlfn.CONCAT("'",B22,"'",",") -> 'Tarauaca', | K22: =_xlfn.CONCAT("'",C22,"'",",") -> 'CONEC LIGHT', | L22: =_xlfn.CONCAT("'",D22,"'",",") -> 'PO', | M22: =_xlfn.CONCAT("to_date('",E22,"','dd/mm/yyyy')",",") -> to_date('08/10/2019','dd/mm/yyyy'), | N22: =_xlfn.CONCAT(F22,");") -> 68); | P22: =_xlfn.CONCAT(H22:N22) -> INSERT INTO PEGARULES.TB_MUNICIPIOS_OFERTAS VALUES('AC','Tarauaca','CONEC LIGHT','PO',to_date('08/10/2019','dd/mm/yyyy'),68);
A23: AC | B23: Xapuri | C23: CONEC LIGHT | D23: PO | E23: 08/10/2019 | F23: 68 | H23: INSERT INTO PEGARULES.TB_MUNICIPIOS_OFERTAS VALUES( | I23: =_xlfn.CONCAT("'",A23,"'",",") -> 'AC', | J23: =_xlfn.CONCAT("'",B23,"'",",") -> 'Xapuri', | K23: =_xlfn.CONCAT("'",C23,"'",",") -> 'CONEC LIGHT', | L23: =_xlfn.CONCAT("'",D23,"'",",") -> 'PO', | M23: =_xlfn.CONCAT("to_date('",E23,"','dd/mm/yyyy')",",") -> to_date('08/10/2019','dd/mm/yyyy'), | N23: =_xlfn.CONCAT(F23,");") -> 68); | P23: =_xlfn.CONCAT(H23:N23) -> INSERT INTO PEGARULES.TB_MUNICIPIOS_OFERTAS VALUES('AC','Xapuri','CONEC LIGHT','PO',to_date('08/10/2019','dd/mm/yyyy'),68);
A24: AL | B24: agua Branca | D24: PO | E24: 08/10/2019 | F24: 82 | H24: INSERT INTO PEGARULES.TB_MUNICIPIOS_OFERTAS VALUES( | I24: =_xlfn.CONCAT("'",A24,"'",",") -> 'AL', | J24: =_xlfn.CONCAT("'",B24,"'",",") -> 'agua Branca', | K24: =_xlfn.CONCAT("'",C24,"'",",") -> '', | L24: =_xlfn.CONCAT("'",D24,"'",",") -> 'PO', | M24: =_xlfn.CONCAT("to_date('",E24,"','dd/mm/yyyy')",",") -> to_date('08/10/2019','dd/mm/yyyy'), | N24: =_xlfn.CONCAT(F24,");") -> 82); | P24: =_xlfn.CONCAT(H24:N24) -> INSERT INTO PEGARULES.TB_MUNICIPIOS_OFERTAS VALUES('AL','agua Branca','','PO',to_date('08/10/2019','dd/mm/yyyy'),82);
A25: AL | B25: Anadia | D25: PO | E25: 08/10/2019 | F25: 82 | H25: INSERT INTO PEGARULES.TB_MUNICIPIOS_OFERTAS VALUES( | I25: =_xlfn.CONCAT("'",A25,"'",",") -> 'AL', | J25: =_xlfn.CONCAT("'",B25,"'",",") -> 'Anadia', | K25: =_xlfn.CONCAT("'",C25,"'",",") -> '', | L25: =_xlfn.CONCAT("'",D25,"'",",") -> 'PO', | M25: =_xlfn.CONCAT("to_date('",E25,"','dd/mm/yyyy')",",") -> to_date('08/10/2019','dd/mm/yyyy'), | N25: =_xlfn.CONCAT(F25,");") -> 82); | P25: =_xlfn.CONCAT(H25:N25) -> INSERT INTO PEGARULES.TB_MUNICIPIOS_OFERTAS VALUES('AL','Anadia','','PO',to_date('08/10/2019','dd/mm/yyyy'),82);
A26: AL | B26: Arapiraca | C26: BL | D26: PO | E26: 08/10/2019 | F26: 82 | H26: INSERT INTO PEGARULES.TB_MUNICIPIOS_OFERTAS VALUES( | I26: =_xlfn.CONCAT("'",A26,"'",",") -> 'AL', | J26: =_xlfn.CONCAT("'",B26,"'",",") -> 'Arapiraca', | K26: =_xlfn.CONCAT("'",C26,"'",",") -> 'BL', | L26: =_xlfn.CONCAT("'",D26,"'",",") -> 'PO', | M26: =_xlfn.CONCAT("to_date('",E26,"','dd/mm/yyyy')",",") -> to_date('08/10/2019','dd/mm/yyyy'), | N26: =_xlfn.CONCAT(F26,");") -> 82); | P26: =_xlfn.CONCAT(H26:N26) -> INSERT INTO PEGARULES.TB_MUNICIPIOS_OFERTAS VALUES('AL','Arapiraca','BL','PO',to_date('08/10/2019','dd/mm/yyyy'),82);
A27: AL | B27: Atalaia | D27: PO | E27: 08/10/2019 | F27: 82 | H27: INSERT INTO PEGARULES.TB_MUNICIPIOS_OFERTAS VALUES( | I27: =_xlfn.CONCAT("'",A27,"'",",") -> 'AL', | J27: =_xlfn.CONCAT("'",B27,"'",",") -> 'Atalaia', | K27: =_xlfn.CONCAT("'",C27,"'",",") -> '', | L27: =_xlfn.CONCAT("'",D27,"'",",") -> 'PO', | M27: =_xlfn.CONCAT("to_date('",E27,"','dd/mm/yyyy')",",") -> to_date('08/10/2019','dd/mm/yyyy'), | N27: =_xlfn.CONCAT(F27,");") -> 82); | P27: =_xlfn.CONCAT(H27:N27) -> INSERT INTO PEGARULES.TB_MUNICIPIOS_OFERTAS VALUES('AL','Atalaia','','PO',to_date('08/10/2019','dd/mm/yyyy'),82);
A28: AL | B28: Barra de Santo Antonio | D28: PO | E28: 08/10/2019 | F28: 82 | H28: INSERT INTO PEGARULES.TB_MUNICIPIOS_OFERTAS VALUES( | I28: =_xlfn.CONCAT("'",A28,"'",",") -> 'AL', | J28: =_xlfn.CONCAT("'",B28,"'",",") -> 'Barra de Santo Antonio', | K28: =_xlfn.CONCAT("'",C28,"'",",") -> '', | L28: =_xlfn.CONCAT("'",D28,"'",",") -> 'PO', | M28: =_xlfn.CONCAT("to_date('",E28,"','dd/mm/yyyy')",",") -> to_date('08/10/2019','dd/mm/yyyy'), | N28: =_xlfn.CONCAT(F28,");") -> 82); | P28: =_xlfn.CONCAT(H28:N28) -> INSERT INTO PEGARULES.TB_MUNICIPIOS_OFERTAS VALUES('AL','Barra de Santo Antonio','','PO',to_date('08/10/2019','dd/mm/yyyy'),82);
A29: AL | B29: Barra de Sao Miguel | D29: PO | E29: 08/10/2019 | F29: 82 | H29: INSERT INTO PEGARULES.TB_MUNICIPIOS_OFERTAS VALUES( | I29: =_xlfn.CONCAT("'",A29,"'",",") -> 'AL', | J29: =_xlfn.CONCAT("'",B29,"'",",") -> 'Barra de Sao Miguel', | K29: =_xlfn.CONCAT("'",C29,"'",",") -> '', | L29: =_xlfn.CONCAT("'",D29,"'",",") -> 'PO', | M29: =_xlfn.CONCAT("to_date('",E29,"','dd/mm/yyyy')",",") -> to_date('08/10/2019','dd/mm/yyyy'), | N29: =_xlfn.CONCAT(F29,");") -> 82); | P29: =_xlfn.CONCAT(H29:N29) -> INSERT INTO PEGARULES.TB_MUNICIPIOS_OFERTAS VALUES('AL','Barra de Sao Miguel','','PO',to_date('08/10/2019','dd/mm/yyyy'),82);
A30: AL | B30: Batalha | D30: PO | E30: 08/10/2019 | F30: 82 | H30: INSERT INTO PEGARULES.TB_MUNICIPIOS_OFERTAS VALUES( | I30: =_xlfn.CONCAT("'",A30,"'",",") -> 'AL', | J30: =_xlfn.CONCAT("'",B30,"'",",") -> 'Batalha', | K30: =_xlfn.CONCAT("'",C30,"'",",") -> '', | L30: =_xlfn.CONCAT("'",D30,"'",",") -> 'PO', | M30: =_xlfn.CONCAT("to_date('",E30,"','dd/mm/yyyy')",",") -> to_date('08/10/2019','dd/mm/yyyy'), | N30: =_xlfn.CONCAT(F30,");") -> 82); | P30: =_xlfn.CONCAT(H30:N30) -> INSERT INTO PEGARULES.TB_MUNICIPIOS_OFERTAS VALUES('AL','Batalha','','PO',to_date('08/10/2019','dd/mm/yyyy'),82);
A31: AL | B31: Belem | D31: PO | E31: 08/10/2019 | F31: 82 | H31: INSERT INTO PEGARULES.TB_MUNICIPIOS_OFERTAS VALUES( | I31: =_xlfn.CONCAT("'",A31,"'",",") -> 'AL', | J31: =_xlfn.CONCAT("'",B31,"'",",") -> 'Belem', | K31: =_xlfn.CONCAT("'",C31,"'",",") -> '', | L31: =_xlfn.CONCAT("'",D31,"'",",") -> 'PO', | M31: =_xlfn.CONCAT("to_date('",E31,"','dd/mm/yyyy')",",") -> to_date('08/10/2019','dd/mm/yyyy'), | N31: =_xlfn.CONCAT(F31,");") -> 82); | P31: =_xlfn.CONCAT(H31:N31) -> INSERT INTO PEGARULES.TB_MUNICIPIOS_OFERTAS VALUES('AL','Belem','','PO',to_date('08/10/2019','dd/mm/yyyy'),82);
A32: AL | B32: Belo Monte | D32: PO | E32: 08/10/2019 | F32: 82 | H32: INSERT INTO PEGARULES.TB_MUNICIPIOS_OFERTAS VALUES( | I32: =_xlfn.CONCAT("'",A32,"'",",") -> 'AL', | J32: =_xlfn.CONCAT("'",B32,"'",",") -> 'Belo Monte', | K32: =_xlfn.CONCAT("'",C32,"'",",") -> '', | L32: =_xlfn.CONCAT("'",D32,"'",",") -> 'PO', | M32: =_xlfn.CONCAT("to_date('",E32,"','dd/mm/yyyy')",",") -> to_date('08/10/2019','dd/mm/yyyy'), | N32: =_xlfn.CONCAT(F32,");") -> 82); | P32: =_xlfn.CONCAT(H32:N32) -> INSERT INTO PEGARULES.TB_MUNICIPIOS_OFERTAS VALUES('AL','Belo Monte','','PO',to_date('08/10/2019','dd/mm/yyyy'),82);
A33: AL | B33: Boca da Mata | D33: PO | E33: 08/10/2019 | F33: 82 | H33: INSERT INTO PEGARULES.TB_MUNICIPIOS_OFERTAS VALUES( | I33: =_xlfn.CONCAT("'",A33,"'",",") -> 'AL', | J33: =_xlfn.CONCAT("'",B33,"'",",") -> 'Boca da Mata', | K33: =_xlfn.CONCAT("'",C33,"'",",") -> '', | L33: =_xlfn.CONCAT("'",D33,"'",",") -> 'PO', | M33: =_xlfn.CONCAT("to_date('",E33,"','dd/mm/yyyy')",",") -> to_date('08/10/2019','dd/mm/yyyy'), | N33: =_xlfn.CONCAT(F33,");") -> 82); | P33: =_xlfn.CONCAT(H33:N33) -> INSERT INTO PEGARULES.TB_MUNICIPIOS_OFERTAS VALUES('AL','Boca da Mata','','PO',to_date('08/10/2019','dd/mm/yyyy'),82);
A34: AL | B34: Branquinha | D34: PO | E34: 08/10/2019 | F34: 82 | H34: INSERT INTO PEGARULES.TB_MUNICIPIOS_OFERTAS VALUES( | I34: =_xlfn.CONCAT("'",A34,"'",",") -> 'AL', | J34: =_xlfn.CONCAT("'",B34,"'",",") -> 'Branquinha', | K34: =_xlfn.CONCAT("'",C34,"'",",") -> '', | L34: =_xlfn.CONCAT("'",D34,"'",",") -> 'PO', | M34: =_xlfn.CONCAT("to_date('",E34,"','dd/mm/yyyy')",",") -> to_date('08/10/2019','dd/mm/yyyy'), | N34: =_xlfn.CONCAT(F34,");") -> 82); | P34: =_xlfn.CONCAT(H34:N34) -> INSERT INTO PEGARULES.TB_MUNICIPIOS_OFERTAS VALUES('AL','Branquinha','','PO',to_date('08/10/2019','dd/mm/yyyy'),82);
A35: AL | B35: Cacimbinhas | D35: PO | E35: 08/10/2019 | F35: 82 | H35: INSERT INTO PEGARULES.TB_MUNICIPIOS_OFERTAS VALUES( | I35: =_xlfn.CONCAT("'",A35,"'",",") -> 'AL', | J35: =_xlfn.CONCAT("'",B35,"'",",") -> 'Cacimbinhas', | K35: =_xlfn.CONCAT("'",C35,"'",",") -> '', | L35: =_xlfn.CONCAT("'",D35,"'",",") -> 'PO', | M35: =_xlfn.CONCAT("to_date('",E35,"','dd/mm/yyyy')",",") -> to_date('08/10/2019','dd/mm/yyyy'), | N35: =_xlfn.CONCAT(F35,");") -> 82); | P35: =_xlfn.CONCAT(H35:N35) -> INSERT INTO PEGARULES.TB_MUNICIPIOS_OFERTAS VALUES('AL','Cacimbinhas','','PO',to_date('08/10/2019','dd/mm/yyyy'),82);
A36: AL | B36: Cajueiro | D36: PO | E36: 08/10/2019 | F36: 82 | H36: INSERT INTO PEGARULES.TB_MUNICIPIOS_OFERTAS VALUES( | I36: =_xlfn.CONCAT("'",A36,"'",",") -> 'AL', | J36: =_xlfn.CONCAT("'",B36,"'",",") -> 'Cajueiro', | K36: =_xlfn.CONCAT("'",C36,"'",",") -> '', | L36: =_xlfn.CONCAT("'",D36,"'",",") -> 'PO', | M36: =_xlfn.CONCAT("to_date('",E36,"','dd/mm/yyyy')",",") -> to_date('08/10/2019','dd/mm/yyyy'), | N36: =_xlfn.CONCAT(F36,");") -> 82); | P36: =_xlfn.CONCAT(H36:N36) -> INSERT INTO PEGARULES.TB_MUNICIPIOS_OFERTAS VALUES('AL','Cajueiro','','PO',to_date('08/10/2019','dd/mm/yyyy'),82);
A37: AL | B37: Campestre | D37: PO | E37: 08/10/2019 | F37: 82 | H37: INSERT INTO PEGARULES.TB_MUNICIPIOS_OFERTAS VALUES( | I37: =_xlfn.CONCAT("'",A37,"'",",") -> 'AL', | J37: =_xlfn.CONCAT("'",B37,"'",",") -> 'Campestre', | K37: =_xlfn.CONCAT("'",C37,"'",",") -> '', | L37: =_xlfn.CONCAT("'",D37,"'",",") -> 'PO', | M37: =_xlfn.CONCAT("to_date('",E37,"','dd/mm/yyyy')",",") -> to_date('08/10/2019','dd/mm/yyyy'), | N37: =_xlfn.CONCAT(F37,");") -> 82); | P37: =_xlfn.CONCAT(H37:N37) -> INSERT INTO PEGARULES.TB_MUNICIPIOS_OFERTAS VALUES('AL','Campestre','','PO',to_date('08/10/2019','dd/mm/yyyy'),82);
A38: AL | B38: Campo Alegre | D38: PO | E38: 08/10/2019 | F38: 82 | H38: INSERT INTO PEGARULES.TB_MUNICIPIOS_OFERTAS VALUES( | I38: =_xlfn.CONCAT("'",A38,"'",",") -> 'AL', | J38: =_xlfn.CONCAT("'",B38,"'",",") -> 'Campo Alegre', | K38: =_xlfn.CONCAT("'",C38,"'",",") -> '', | L38: =_xlfn.CONCAT("'",D38,"'",",") -> 'PO', | M38: =_xlfn.CONCAT("to_date('",E38,"','dd/mm/yyyy')",",") -> to_date('08/10/2019','dd/mm/yyyy'), | N38: =_xlfn.CONCAT(F38,");") -> 82); | P38: =_xlfn.CONCAT(H38:N38) -> INSERT INTO PEGARULES.TB_MUNICIPIOS_OFERTAS VALUES('AL','Campo Alegre','','PO',to_date('08/10/2019','dd/mm/yyyy'),82);
... A48: AL | B48: Craibas | D48: PO | E48: 08/10/2019 | F48: 82 | H48: INSERT INTO PEGARULES.TB_MUNICIPIOS_OFERTAS VALUES( | I48: =_xlfn.CONCAT("'",A48,"'",",") -> 'AL', | J48: =_xlfn.CONCAT("'",B48,"'",",") -> 'Craibas', | K48: =_xlfn.CONCAT("'",C48,"'",",") -> '', | L48: =_xlfn.CONCAT("'",D48,"'",",") -> 'PO', | M48: =_xlfn.CONCAT("to_date('",E48,"','dd/mm/yyyy')",",") -> to_date('08/10/2019','dd/mm/yyyy'), | N48: =_xlfn.CONCAT(F48,");") -> 82); | P48: =_xlfn.CONCAT(H48:N48) -> INSERT INTO PEGARULES.TB_MUNICIPIOS_OFERTAS VALUES('AL','Craibas','','PO',to_date('08/10/2019','dd/mm/yyyy'),82);
A49: AL | B49: Delmiro Gouveia | C49: BL | D49: PO | E49: 08/10/2019 | F49: 82 | H49: INSERT INTO PEGARULES.TB_MUNICIPIOS_OFERTAS VALUES( | I49: =_xlfn.CONCAT("'",A49,"'",",") -> 'AL', | J49: =_xlfn.CONCAT("'",B49,"'",",") -> 'Delmiro Gouveia', | K49: =_xlfn.CONCAT("'",C49,"'",",") -> 'BL', | L49: =_xlfn.CONCAT("'",D49,"'",",") -> 'PO', | M49: =_xlfn.CONCAT("to_date('",E49,"','dd/mm/yyyy')",",") -> to_date('08/10/2019','dd/mm/yyyy'), | N49: =_xlfn.CONCAT(F49,");") -> 82); | P49: =_xlfn.CONCAT(H49:N49) -> INSERT INTO PEGARULES.TB_MUNICIPIOS_OFERTAS VALUES('AL','Delmiro Gouveia','BL','PO',to_date('08/10/2019','dd/mm/yyyy'),82);
A50: AL | B50: Dois Riachos | D50: PO | E50: 08/10/2019 | F50: 82 | H50: INSERT INTO PEGARULES.TB_MUNICIPIOS_OFERTAS VALUES( | I50: =_xlfn.CONCAT("'",A50,"'",",") -> 'AL', | J50: =_xlfn.CONCAT("'",B50,"'",",") -> 'Dois Riachos', | K50: =_xlfn.CONCAT("'",C50,"'",",") -> '', | L50: =_xlfn.CONCAT("'",D50,"'",",") -> 'PO', | M50: =_xlfn.CONCAT("to_date('",E50,"','dd/mm/yyyy')",",") -> to_date('08/10/2019','dd/mm/yyyy'), | N50: =_xlfn.CONCAT(F50,");") -> 82); | P50: =_xlfn.CONCAT(H50:N50) -> INSERT INTO PEGARULES.TB_MUNICIPIOS_OFERTAS VALUES('AL','Dois Riachos','','PO',to_date('08/10/2019','dd/mm/yyyy'),82);
A51: AL | B51: Estrela de Alagoas | D51: PO | E51: 08/10/2019 | F51: 82 | H51: INSERT INTO PEGARULES.TB_MUNICIPIOS_OFERTAS VALUES( | I51: =_xlfn.CONCAT("'",A51,"'",",") -> 'AL', | J51: =_xlfn.CONCAT("'",B51,"'",",") -> 'Estrela de Alagoas', | K51: =_xlfn.CONCAT("'",C51,"'",",") -> '', | L51: =_xlfn.CONCAT("'",D51,"'",",") -> 'PO', | M51: =_xlfn.CONCAT("to_date('",E51,"','dd/mm/yyyy')",",") -> to_date('08/10/2019','dd/mm/yyyy'), | N51: =_xlfn.CONCAT(F51,");") -> 82); | P51: =_xlfn.CONCAT(H51:N51) -> INSERT INTO PEGARULES.TB_MUNICIPIOS_OFERTAS VALUES('AL','Estrela de Alagoas','','PO',to_date('08/10/2019','dd/mm/yyyy'),82);
A52: AL | B52: Feira Grande | D52: PO | E52: 08/10/2019 | F52: 82 | H52: INSERT INTO PEGARULES.TB_MUNICIPIOS_OFERTAS VALUES( | I52: =_xlfn.CONCAT("'",A52,"'",",") -> 'AL', | J52: =_xlfn.CONCAT("'",B52,"'",",") -> 'Feira Grande', | K52: =_xlfn.CONCAT("'",C52,"'",",") -> '', | L52: =_xlfn.CONCAT("'",D52,"'",",") -> 'PO', | M52: =_xlfn.CONCAT("to_date('",E52,"','dd/mm/yyyy')",",") -> to_date('08/10/2019','dd/mm/yyyy'), | N52: =_xlfn.CONCAT(F52,");") -> 82); | P52: =_xlfn.CONCAT(H52:N52) -> INSERT INTO PEGARULES.TB_MUNICIPIOS_OFERTAS VALUES('AL','Feira Grande','','PO',to_date('08/10/2019','dd/mm/yyyy'),82);
A53: AL | B53: Feliz Deserto | D53: PO | E53: 08/10/2019 | F53: 82 | H53: INSERT INTO PEGARULES.TB_MUNICIPIOS_OFERTAS VALUES( | I53: =_xlfn.CONCAT("'",A53,"'",",") -> 'AL', | J53: =_xlfn.CONCAT("'",B53,"'",",") -> 'Feliz Deserto', | K53: =_xlfn.CONCAT("'",C53,"'",",") -> '', | L53: =_xlfn.CONCAT("'",D53,"'",",") -> 'PO', | M53: =_xlfn.CONCAT("to_date('",E53,"','dd/mm/yyyy')",",") -> to_date('08/10/2019','dd/mm/yyyy'), | N53: =_xlfn.CONCAT(F53,");") -> 82); | P53: =_xlfn.CONCAT(H53:N53) -> INSERT INTO PEGARULES.TB_MUNICIPIOS_OFERTAS VALUES('AL','Feliz Deserto','','PO',to_date('08/10/2019','dd/mm/yyyy'),82);
A54: AL | B54: Flexeiras | D54: PO | E54: 08/10/2019 | F54: 82 | H54: INSERT INTO PEGARULES.TB_MUNICIPIOS_OFERTAS VALUES( | I54: =_xlfn.CONCAT("'",A54,"'",",") -> 'AL', | J54: =_xlfn.CONCAT("'",B54,"'",",") -> 'Flexeiras', | K54: =_xlfn.CONCAT("'",C54,"'",",") -> '', | L54: =_xlfn.CONCAT("'",D54,"'",",") -> 'PO', | M54: =_xlfn.CONCAT("to_date('",E54,"','dd/mm/yyyy')",",") -> to_date('08/10/2019','dd/mm/yyyy'), | N54: =_xlfn.CONCAT(F54,");") -> 82); | P54: =_xlfn.CONCAT(H54:N54) -> INSERT INTO PEGARULES.TB_MUNICIPIOS_OFERTAS VALUES('AL','Flexeiras','','PO',to_date('08/10/2019','dd/mm/yyyy'),82);
A55: AL | B55: Girau do Ponciano | D55: PO | E55: 08/10/2019 | F55: 82 | H55: INSERT INTO PEGARULES.TB_MUNICIPIOS_OFERTAS VALUES( | I55: =_xlfn.CONCAT("'",A55,"'",",") -> 'AL', | J55: =_xlfn.CONCAT("'",B55,"'",",") -> 'Girau do Ponciano', | K55: =_xlfn.CONCAT("'",C55,"'",",") -> '', | L55: =_xlfn.CONCAT("'",D55,"'",",") -> 'PO', | M55: =_xlfn.CONCAT("to_date('",E55,"','dd/mm/yyyy')",",") -> to_date('08/10/2019','dd/mm/yyyy'), | N55: =_xlfn.CONCAT(F55,");") -> 82); | P55: =_xlfn.CONCAT(H55:N55) -> INSERT INTO PEGARULES.TB_MUNICIPIOS_OFERTAS VALUES('AL','Girau do Ponciano','','PO',to_date('08/10/2019','dd/mm/yyyy'),82);
A56: AL | B56: Ibateguara | D56: PO | E56: 08/10/2019 | F56: 82 | H56: INSERT INTO PEGARULES.TB_MUNICIPIOS_OFERTAS VALUES( | I56: =_xlfn.CONCAT("'",A56,"'",",") -> 'AL', | J56: =_xlfn.CONCAT("'",B56,"'",",") -> 'Ibateguara', | K56: =_xlfn.CONCAT("'",C56,"'",",") -> '', | L56: =_xlfn.CONCAT("'",D56,"'",",") -> 'PO', | M56: =_xlfn.CONCAT("to_date('",E56,"','dd/mm/yyyy')",",") -> to_date('08/10/2019','dd/mm/yyyy'), | N56: =_xlfn.CONCAT(F56,");") -> 82); | P56: =_xlfn.CONCAT(H56:N56) -> INSERT INTO PEGARULES.TB_MUNICIPIOS_OFERTAS VALUES('AL','Ibateguara','','PO',to_date('08/10/2019','dd/mm/yyyy'),82);
A57: AL | B57: Igaci | D57: PO | E57: 08/10/2019 | F57: 82 | H57: INSERT INTO PEGARULES.TB_MUNICIPIOS_OFERTAS VALUES( | I57: =_xlfn.CONCAT("'",A57,"'",",") -> 'AL', | J57: =_xlfn.CONCAT("'",B57,"'",",") -> 'Igaci', | K57: =_xlfn.CONCAT("'",C57,"'",",") -> '', | L57: =_xlfn.CONCAT("'",D57,"'",",") -> 'PO', | M57: =_xlfn.CONCAT("to_date('",E57,"','dd/mm/yyyy')",",") -> to_date('08/10/2019','dd/mm/yyyy'), | N57: =_xlfn.CONCAT(F57,");") -> 82); | P57: =_xlfn.CONCAT(H57:N57) -> INSERT INTO PEGARULES.TB_MUNICIPIOS_OFERTAS VALUES('AL','Igaci','','PO',to_date('08/10/2019','dd/mm/yyyy'),82);
A58: AL | B58: Igreja Nova | D58: PO | E58: 08/10/2019 | F58: 82 | H58: INSERT INTO PEGARULES.TB_MUNICIPIOS_OFERTAS VALUES( | I58: =_xlfn.CONCAT("'",A58,"'",",") -> 'AL', | J58: =_xlfn.CONCAT("'",B58,"'",",") -> 'Igreja Nova', | K58: =_xlfn.CONCAT("'",C58,"'",",") -> '', | L58: =_xlfn.CONCAT("'",D58,"'",",") -> 'PO', | M58: =_xlfn.CONCAT("to_date('",E58,"','dd/mm/yyyy')",",") -> to_date('08/10/2019','dd/mm/yyyy'), | N58: =_xlfn.CONCAT(F58,");") -> 82); | P58: =_xlfn.CONCAT(H58:N58) -> INSERT INTO PEGARULES.TB_MUNICIPIOS_OFERTAS VALUES('AL','Igreja Nova','','PO',to_date('08/10/2019','dd/mm/yyyy'),82);
A59: AL | B59: Inhapi | D59: PO | E59: 08/10/2019 | F59: 82 | H59: INSERT INTO PEGARULES.TB_MUNICIPIOS_OFERTAS VALUES( | I59: =_xlfn.CONCAT("'",A59,"'",",") -> 'AL', | J59: =_xlfn.CONCAT("'",B59,"'",",") -> 'Inhapi', | K59: =_xlfn.CONCAT("'",C59,"'",",") -> '', | L59: =_xlfn.CONCAT("'",D59,"'",",") -> 'PO', | M59: =_xlfn.CONCAT("to_date('",E59,"','dd/mm/yyyy')",",") -> to_date('08/10/2019','dd/mm/yyyy'), | N59: =_xlfn.CONCAT(F59,");") -> 82); | P59: =_xlfn.CONCAT(H59:N59) -> INSERT INTO PEGARULES.TB_MUNICIPIOS_OFERTAS VALUES('AL','Inhapi','','PO',to_date('08/10/2019','dd/mm/yyyy'),82);
A60: AL | B60: Jacare dos Homens | D60: PO | E60: 08/10/2019 | F60: 82 | H60: INSERT INTO PEGARULES.TB_MUNICIPIOS_OFERTAS VALUES( | I60: =_xlfn.CONCAT("'",A60,"'",",") -> 'AL', | J60: =_xlfn.CONCAT("'",B60,"'",",") -> 'Jacare dos Homens', | K60: =_xlfn.CONCAT("'",C60,"'",",") -> '', | L60: =_xlfn.CONCAT("'",D60,"'",",") -> 'PO', | M60: =_xlfn.CONCAT("to_date('",E60,"','dd/mm/yyyy')",",") -> to_date('08/10/2019','dd/mm/yyyy'), | N60: =_xlfn.CONCAT(F60,");") -> 82); | P60: =_xlfn.CONCAT(H60:N60) -> INSERT INTO PEGARULES.TB_MUNICIPIOS_OFERTAS VALUES('AL','Jacare dos Homens','','PO',to_date('08/10/2019','dd/mm/yyyy'),82);
A61: AL | B61: Jacuipe | D61: PO | E61: 08/10/2019 | F61: 82 | H61: INSERT INTO PEGARULES.TB_MUNICIPIOS_OFERTAS VALUES( | I61: =_xlfn.CONCAT("'",A61,"'",",") -> 'AL', | J61: =_xlfn.CONCAT("'",B61,"'",",") -> 'Jacuipe', | K61: =_xlfn.CONCAT("'",C61,"'",",") -> '', | L61: =_xlfn.CONCAT("'",D61,"'",",") -> 'PO', | M61: =_xlfn.CONCAT("to_date('",E61,"','dd/mm/yyyy')",",") -> to_date('08/10/2019','dd/mm/yyyy'), | N61: =_xlfn.CONCAT(F61,");") -> 82); | P61: =_xlfn.CONCAT(H61:N61) -> INSERT INTO PEGARULES.TB_MUNICIPIOS_OFERTAS VALUES('AL','Jacuipe','','PO',to_date('08/10/2019','dd/mm/yyyy'),82);
... A95: AL | B95: Paulo Jacinto | D95: PO | E95: 08/10/2019 | F95: 82 | H95: INSERT INTO PEGARULES.TB_MUNICIPIOS_OFERTAS VALUES( | I95: =_xlfn.CONCAT("'",A95,"'",",") -> 'AL', | J95: =_xlfn.CONCAT("'",B95,"'",",") -> 'Paulo Jacinto', | K95: =_xlfn.CONCAT("'",C95,"'",",") -> '', | L95: =_xlfn.CONCAT("'",D95,"'",",") -> 'PO', | M95: =_xlfn.CONCAT("to_date('",E95,"','dd/mm/yyyy')",",") -> to_date('08/10/2019','dd/mm/yyyy'), | N95: =_xlfn.CONCAT(F95,");") -> 82); | P95: =_xlfn.CONCAT(H95:N95) -> INSERT INTO PEGARULES.TB_MUNICIPIOS_OFERTAS VALUES('AL','Paulo Jacinto','','PO',to_date('08/10/2019','dd/mm/yyyy'),82);
A96: AL | B96: Penedo | C96: BL | D96: PO | E96: 08/10/2019 | F96: 82 | H96: INSERT INTO PEGARULES.TB_MUNICIPIOS_OFERTAS VALUES( | I96: =_xlfn.CONCAT("'",A96,"'",",") -> 'AL', | J96: =_xlfn.CONCAT("'",B96,"'",",") -> 'Penedo', | K96: =_xlfn.CONCAT("'",C96,"'",",") -> 'BL', | L96: =_xlfn.CONCAT("'",D96,"'",",") -> 'PO', | M96: =_xlfn.CONCAT("to_date('",E96,"','dd/mm/yyyy')",",") -> to_date('08/10/2019','dd/mm/yyyy'), | N96: =_xlfn.CONCAT(F96,");") -> 82); | P96: =_xlfn.CONCAT(H96:N96) -> INSERT INTO PEGARULES.TB_MUNICIPIOS_OFERTAS VALUES('AL','Penedo','BL','PO',to_date('08/10/2019','dd/mm/yyyy'),82);
A97: AL | B97: Piacabucu | D97: PO | E97: 08/10/2019 | F97: 82 | H97: INSERT INTO PEGARULES.TB_MUNICIPIOS_OFERTAS VALUES( | I97: =_xlfn.CONCAT("'",A97,"'",",") -> 'AL', | J97: =_xlfn.CONCAT("'",B97,"'",",") -> 'Piacabucu', | K97: =_xlfn.CONCAT("'",C97,"'",",") -> '', | L97: =_xlfn.CONCAT("'",D97,"'",",") -> 'PO', | M97: =_xlfn.CONCAT("to_date('",E97,"','dd/mm/yyyy')",",") -> to_date('08/10/2019','dd/mm/yyyy'), | N97: =_xlfn.CONCAT(F97,");") -> 82); | P97: =_xlfn.CONCAT(H97:N97) -> INSERT INTO PEGARULES.TB_MUNICIPIOS_OFERTAS VALUES('AL','Piacabucu','','PO',to_date('08/10/2019','dd/mm/yyyy'),82);
A98: AL | B98: Pilar | D98: PO | E98: 08/10/2019 | F98: 82 | H98: INSERT INTO PEGARULES.TB_MUNICIPIOS_OFERTAS VALUES( | I98: =_xlfn.CONCAT("'",A98,"'",",") -> 'AL', | J98: =_xlfn.CONCAT("'",B98,"'",",") -> 'Pilar', | K98: =_xlfn.CONCAT("'",C98,"'",",") -> '', | L98: =_xlfn.CONCAT("'",D98,"'",",") -> 'PO', | M98: =_xlfn.CONCAT("to_date('",E98,"','dd/mm/yyyy')",",") -> to_date('08/10/2019','dd/mm/yyyy'), | N98: =_xlfn.CONCAT(F98,");") -> 82); | P98: =_xlfn.CONCAT(H98:N98) -> INSERT INTO PEGARULES.TB_MUNICIPIOS_OFERTAS VALUES('AL','Pilar','','PO',to_date('08/10/2019','dd/mm/yyyy'),82);
A99: AL | B99: Pindoba | D99: PO | E99: 08/10/2019 | F99: 82 | H99: INSERT INTO PEGARULES.TB_MUNICIPIOS_OFERTAS VALUES( | I99: =_xlfn.CONCAT("'",A99,"'",",") -> 'AL', | J99: =_xlfn.CONCAT("'",B99,"'",",") -> 'Pindoba', | K99: =_xlfn.CONCAT("'",C99,"'",",") -> '', | L99: =_xlfn.CONCAT("'",D99,"'",",") -> 'PO', | M99: =_xlfn.CONCAT("to_date('",E99,"','dd/mm/yyyy')",",") -> to_date('08/10/2019','dd/mm/yyyy'), | N99: =_xlfn.CONCAT(F99,");") -> 82); | P99: =_xlfn.CONCAT(H99:N99) -> INSERT INTO PEGARULES.TB_MUNICIPIOS_OFERTAS VALUES('AL','Pindoba','','PO',to_date('08/10/2019','dd/mm/yyyy'),82);
A100: AL | B100: Piranhas | D100: PO | E100: 08/10/2019 | F100: 82 | H100: INSERT INTO PEGARULES.TB_MUNICIPIOS_OFERTAS VALUES( | I100: =_xlfn.CONCAT("'",A100,"'",",") -> 'AL', | J100: =_xlfn.CONCAT("'",B100,"'",",") -> 'Piranhas', | K100: =_xlfn.CONCAT("'",C100,"'",",") -> '', | L100: =_xlfn.CONCAT("'",D100,"'",",") -> 'PO', | M100: =_xlfn.CONCAT("to_date('",E100,"','dd/mm/yyyy')",",") -> to_date('08/10/2019','dd/mm/yyyy'), | N100: =_xlfn.CONCAT(F100,");") -> 82); | P100: =_xlfn.CONCAT(H100:N100) -> INSERT INTO PEGARULES.TB_MUNICIPIOS_OFERTAS VALUES('AL','Piranhas','','PO',to_date('08/10/2019','dd/mm/yyyy'),82);
A101: AL | B101: Poco das Trincheiras | D101: PO | E101: 08/10/2019 | F101: 82 | H101: INSERT INTO PEGARULES.TB_MUNICIPIOS_OFERTAS VALUES( | I101: =_xlfn.CONCAT("'",A101,"'",",") -> 'AL', | J101: =_xlfn.CONCAT("'",B101,"'",",") -> 'Poco das Trincheiras', | K101: =_xlfn.CONCAT("'",C101,"'",",") -> '', | L101: =_xlfn.CONCAT("'",D101,"'",",") -> 'PO', | M101: =_xlfn.CONCAT("to_date('",E101,"','dd/mm/yyyy')",",") -> to_date('08/10/2019','dd/mm/yyyy'), | N101: =_xlfn.CONCAT(F101,");") -> 82); | P101: =_xlfn.CONCAT(H101:N101) -> INSERT INTO PEGARULES.TB_MUNICIPIOS_OFERTAS VALUES('AL','Poco das Trincheiras','','PO',to_date('08/10/2019','dd/mm/yyyy'),82);
A102: AL | B102: Porto Calvo | D102: PO | E102: 08/10/2019 | F102: 82 | H102: INSERT INTO PEGARULES.TB_MUNICIPIOS_OFERTAS VALUES( | I102: =_xlfn.CONCAT("'",A102,"'",",") -> 'AL', | J102: =_xlfn.CONCAT("'",B102,"'",",") -> 'Porto Calvo', | K102: =_xlfn.CONCAT("'",C102,"'",",") -> '', | L102: =_xlfn.CONCAT("'",D102,"'",",") -> 'PO', | M102: =_xlfn.CONCAT("to_date('",E102,"','dd/mm/yyyy')",",") -> to_date('08/10/2019','dd/mm/yyyy'), | N102: =_xlfn.CONCAT(F102,");") -> 82); | P102: =_xlfn.CONCAT(H102:N102) -> INSERT INTO PEGARULES.TB_MUNICIPIOS_OFERTAS VALUES('AL','Porto Calvo','','PO',to_date('08/10/2019','dd/mm/yyyy'),82);
A103: AL | B103: Porto de Pedras | D103: PO | E103: 08/10/2019 | F103: 82 | H103: INSERT INTO PEGARULES.TB_MUNICIPIOS_OFERTAS VALUES( | I103: =_xlfn.CONCAT("'",A103,"'",",") -> 'AL', | J103: =_xlfn.CONCAT("'",B103,"'",",") -> 'Porto de Pedras', | K103: =_xlfn.CONCAT("'",C103,"'",",") -> '', | L103: =_xlfn.CONCAT("'",D103,"'",",") -> 'PO', | M103: =_xlfn.CONCAT("to_date('",E103,"','dd/mm/yyyy')",",") -> to_date('08/10/2019','dd/mm/yyyy'), | N103: =_xlfn.CONCAT(F103,");") -> 82); | P103: =_xlfn.CONCAT(H103:N103) -> INSERT INTO PEGARULES.TB_MUNICIPIOS_OFERTAS VALUES('AL','Porto de Pedras','','PO',to_date('08/10/2019','dd/mm/yyyy'),82);
A104: AL | B104: Porto Real do Colegio | D104: PO | E104: 08/10/2019 | F104: 82 | H104: INSERT INTO PEGARULES.TB_MUNICIPIOS_OFERTAS VALUES( | I104: =_xlfn.CONCAT("'",A104,"'",",") -> 'AL', | J104: =_xlfn.CONCAT("'",B104,"'",",") -> 'Porto Real do Colegio', | K104: =_xlfn.CONCAT("'",C104,"'",",") -> '', | L104: =_xlfn.CONCAT("'",D104,"'",",") -> 'PO', | M104: =_xlfn.CONCAT("to_date('",E104,"','dd/mm/yyyy')",",") -> to_date('08/10/2019','dd/mm/yyyy'), | N104: =_xlfn.CONCAT(F104,");") -> 82); | P104: =_xlfn.CONCAT(H104:N104) -> INSERT INTO PEGARULES.TB_MUNICIPIOS_OFERTAS VALUES('AL','Porto Real do Colegio','','PO',to_date('08/10/2019','dd/mm/yyyy'),82);
A105: AL | B105: Quebrangulo | D105: PO | E105: 08/10/2019 | F105: 82 | H105: INSERT INTO PEGARULES.TB_MUNICIPIOS_OFERTAS VALUES( | I105: =_xlfn.CONCAT("'",A105,"'",",") -> 'AL', | J105: =_xlfn.CONCAT("'",B105,"'",",") -> 'Quebrangulo', | K105: =_xlfn.CONCAT("'",C105,"'",",") -> '', | L105: =_xlfn.CONCAT("'",D105,"'",",") -> 'PO', | M105: =_xlfn.CONCAT("to_date('",E105,"','dd/mm/yyyy')",",") -> to_date('08/10/2019','dd/mm/yyyy'), | N105: =_xlfn.CONCAT(F105,");") -> 82); | P105: =_xlfn.CONCAT(H105:N105) -> INSERT INTO PEGARULES.TB_MUNICIPIOS_OFERTAS VALUES('AL','Quebrangulo','','PO',to_date('08/10/2019','dd/mm/yyyy'),82);
A106: AL | B106: Rio Largo | C106: BL | D106: PO | E106: 08/10/2019 | F106: 82 | H106: INSERT INTO PEGARULES.TB_MUNICIPIOS_OFERTAS VALUES( | I106: =_xlfn.CONCAT("'",A106,"'",",") -> 'AL', | J106: =_xlfn.CONCAT("'",B106,"'",",") -> 'Rio Largo', | K106: =_xlfn.CONCAT("'",C106,"'",",") -> 'BL', | L106: =_xlfn.CONCAT("'",D106,"'",",") -> 'PO', | M106: =_xlfn.CONCAT("to_date('",E106,"','dd/mm/yyyy')",",") -> to_date('08/10/2019','dd/mm/yyyy'), | N106: =_xlfn.CONCAT(F106,");") -> 82); | P106: =_xlfn.CONCAT(H106:N106) -> INSERT INTO PEGARULES.TB_MUNICIPIOS_OFERTAS VALUES('AL','Rio Largo','BL','PO',to_date('08/10/2019','dd/mm/yyyy'),82);
A107: AL | B107: Roteiro | D107: PO | E107: 08/10/2019 | F107: 82 | H107: INSERT INTO PEGARULES.TB_MUNICIPIOS_OFERTAS VALUES( | I107: =_xlfn.CONCAT("'",A107,"'",",") -> 'AL', | J107: =_xlfn.CONCAT("'",B107,"'",",") -> 'Roteiro', | K107: =_xlfn.CONCAT("'",C107,"'",",") -> '', | L107: =_xlfn.CONCAT("'",D107,"'",",") -> 'PO', | M107: =_xlfn.CONCAT("to_date('",E107,"','dd/mm/yyyy')",",") -> to_date('08/10/2019','dd/mm/yyyy'), | N107: =_xlfn.CONCAT(F107,");") -> 82); | P107: =_xlfn.CONCAT(H107:N107) -> INSERT INTO PEGARULES.TB_MUNICIPIOS_OFERTAS VALUES('AL','Roteiro','','PO',to_date('08/10/2019','dd/mm/yyyy'),82);
A108: AL | B108: Santa Luzia do Norte | D108: PO | E108: 08/10/2019 | F108: 82 | H108: INSERT INTO PEGARULES.TB_MUNICIPIOS_OFERTAS VALUES( | I108: =_xlfn.CONCAT("'",A108,"'",",") -> 'AL', | J108: =_xlfn.CONCAT("'",B108,"'",",") -> 'Santa Luzia do Norte', | K108: =_xlfn.CONCAT("'",C108,"'",",") -> '', | L108: =_xlfn.CONCAT("'",D108,"'",",") -> 'PO', | M108: =_xlfn.CONCAT("to_date('",E108,"','dd/mm/yyyy')",",") -> to_date('08/10/2019','dd/mm/yyyy'), | N108: =_xlfn.CONCAT(F108,");") -> 82); | P108: =_xlfn.CONCAT(H108:N108) -> INSERT INTO PEGARULES.TB_MUNICIPIOS_OFERTAS VALUES('AL','Santa Luzia do Norte','','PO',to_date('08/10/2019','dd/mm/yyyy'),82);
A109: AL | B109: Santana do Ipanema | D109: PO | E109: 08/10/2019 | F109: 82 | H109: INSERT INTO PEGARULES.TB_MUNICIPIOS_OFERTAS VALUES( | I109: =_xlfn.CONCAT("'",A109,"'",",") -> 'AL', | J109: =_xlfn.CONCAT("'",B109,"'",",") -> 'Santana do Ipanema', | K109: =_xlfn.CONCAT("'",C109,"'",",") -> '', | L109: =_xlfn.CONCAT("'",D109,"'",",") -> 'PO', | M109: =_xlfn.CONCAT("to_date('",E109,"','dd/mm/yyyy')",",") -> to_date('08/10/2019','dd/mm/yyyy'), | N109: =_xlfn.CONCAT(F109,");") -> 82); | P109: =_xlfn.CONCAT(H109:N109) -> INSERT INTO PEGARULES.TB_MUNICIPIOS_OFERTAS VALUES('AL','Santana do Ipanema','','PO',to_date('08/10/2019','dd/mm/yyyy'),82);
A110: AL | B110: Santana do Mundau | D110: PO | E110: 08/10/2019 | F110: 82 | H110: INSERT INTO PEGARULES.TB_MUNICIPIOS_OFERTAS VALUES( | I110: =_xlfn.CONCAT("'",A110,"'",",") -> 'AL', | J110: =_xlfn.CONCAT("'",B110,"'",",") -> 'Santana do Mundau', | K110: =_xlfn.CONCAT("'",C110,"'",",") -> '', | L110: =_xlfn.CONCAT("'",D110,"'",",") -> 'PO', | M110: =_xlfn.CONCAT("to_date('",E110,"','dd/mm/yyyy')",",") -> to_date('08/10/2019','dd/mm/yyyy'), | N110: =_xlfn.CONCAT(F110,");") -> 82); | P110: =_xlfn.CONCAT(H110:N110) -> INSERT INTO PEGARULES.TB_MUNICIPIOS_OFERTAS VALUES('AL','Santana do Mundau','','PO',to_date('08/10/2019','dd/mm/yyyy'),82);
A111: AL | B111: Sao Bras | D111: PO | E111: 08/10/2019 | F111: 82 | H111: INSERT INTO PEGARULES.TB_MUNICIPIOS_OFERTAS VALUES( | I111: =_xlfn.CONCAT("'",A111,"'",",") -> 'AL', | J111: =_xlfn.CONCAT("'",B111,"'",",") -> 'Sao Bras', | K111: =_xlfn.CONCAT("'",C111,"'",",") -> '', | L111: =_xlfn.CONCAT("'",D111,"'",",") -> 'PO', | M111: =_xlfn.CONCAT("to_date('",E111,"','dd/mm/yyyy')",",") -> to_date('08/10/2019','dd/mm/yyyy'), | N111: =_xlfn.CONCAT(F111,");") -> 82); | P111: =_xlfn.CONCAT(H111:N111) -> INSERT INTO PEGARULES.TB_MUNICIPIOS_OFERTAS VALUES('AL','Sao Bras','','PO',to_date('08/10/2019','dd/mm/yyyy'),82);
A112: AL | B112: Sao Jose da Laje | D112: PO | E112: 08/10/2019 | F112: 82 | H112: INSERT INTO PEGARULES.TB_MUNICIPIOS_OFERTAS VALUES( | I112: =_xlfn.CONCAT("'",A112,"'",",") -> 'AL', | J112: =_xlfn.CONCAT("'",B112,"'",",") -> 'Sao Jose da Laje', | K112: =_xlfn.CONCAT("'",C112,"'",",") -> '', | L112: =_xlfn.CONCAT("'",D112,"'",",") -> 'PO', | M112: =_xlfn.CONCAT("to_date('",E112,"','dd/mm/yyyy')",",") -> to_date('08/10/2019','dd/mm/yyyy'), | N112: =_xlfn.CONCAT(F112,");") -> 82); | P112: =_xlfn.CONCAT(H112:N112) -> INSERT INTO PEGARULES.TB_MUNICIPIOS_OFERTAS VALUES('AL','Sao Jose da Laje','','PO',to_date('08/10/2019','dd/mm/yyyy'),82);
A113: AL | B113: Sao Jose da Tapera | D113: PO | E113: 08/10/2019 | F113: 82 | H113: INSERT INTO PEGARULES.TB_MUNICIPIOS_OFERTAS VALUES( | I113: =_xlfn.CONCAT("'",A113,"'",",") -> 'AL', | J113: =_xlfn.CONCAT("'",B113,"'",",") -> 'Sao Jose da Tapera', | K113: =_xlfn.CONCAT("'",C113,"'",",") -> '', | L113: =_xlfn.CONCAT("'",D113,"'",",") -> 'PO', | M113: =_xlfn.CONCAT("to_date('",E113,"','dd/mm/yyyy')",",") -> to_date('08/10/2019','dd/mm/yyyy'), | N113: =_xlfn.CONCAT(F113,");") -> 82); | P113: =_xlfn.CONCAT(H113:N113) -> INSERT INTO PEGARULES.TB_MUNICIPIOS_OFERTAS VALUES('AL','Sao Jose da Tapera','','PO',to_date('08/10/2019','dd/mm/yyyy'),82);
A114: AL | B114: Sao Luis do Quitunde | D114: PO | E114: 08/10/2019 | F114: 82 | H114: INSERT INTO PEGARULES.TB_MUNICIPIOS_OFERTAS VALUES( | I114: =_xlfn.CONCAT("'",A114,"'",",") -> 'AL', | J114: =_xlfn.CONCAT("'",B114,"'",",") -> 'Sao Luis do Quitunde', | K114: =_xlfn.CONCAT("'",C114,"'",",") -> '', | L114: =_xlfn.CONCAT("'",D114,"'",",") -> 'PO', | M114: =_xlfn.CONCAT("to_date('",E114,"','dd/mm/yyyy')",",") -> to_date('08/10/2019','dd/mm/yyyy'), | N114: =_xlfn.CONCAT(F114,");") -> 82); | P114: =_xlfn.CONCAT(H114:N114) -> INSERT INTO PEGARULES.TB_MUNICIPIOS_OFERTAS VALUES('AL','Sao Luis do Quitunde','','PO',to_date('08/10/2019','dd/mm/yyyy'),82);
A115: AL | B115: Sao Miguel dos Campos | D115: PO | E115: 08/10/2019 | F115: 82 | H115: INSERT INTO PEGARULES.TB_MUNICIPIOS_OFERTAS VALUES( | I115: =_xlfn.CONCAT("'",A115,"'",",") -> 'AL', | J115: =_xlfn.CONCAT("'",B115,"'",",") -> 'Sao Miguel dos Campos', | K115: =_xlfn.CONCAT("'",C115,"'",",") -> '', | L115: =_xlfn.CONCAT("'",D115,"'",",") -> 'PO', | M115: =_xlfn.CONCAT("to_date('",E115,"','dd/mm/yyyy')",",") -> to_date('08/10/2019','dd/mm/yyyy'), | N115: =_xlfn.CONCAT(F115,");") -> 82); | P115: =_xlfn.CONCAT(H115:N115) -> INSERT INTO PEGARULES.TB_MUNICIPIOS_OFERTAS VALUES('AL','Sao Miguel dos Campos','','PO',to_date('08/10/2019','dd/mm/yyyy'),82);
A116: AL | B116: Sao Miguel dos Milagres | D116: PO | E116: 08/10/2019 | F116: 82 | H116: INSERT INTO PEGARULES.TB_MUNICIPIOS_OFERTAS VALUES( | I116: =_xlfn.CONCAT("'",A116,"'",",") -> 'AL', | J116: =_xlfn.CONCAT("'",B116,"'",",") -> 'Sao Miguel dos Milagres', | K116: =_xlfn.CONCAT("'",C116,"'",",") -> '', | L116: =_xlfn.CONCAT("'",D116,"'",",") -> 'PO', | M116: =_xlfn.CONCAT("to_date('",E116,"','dd/mm/yyyy')",",") -> to_date('08/10/2019','dd/mm/yyyy'), | N116: =_xlfn.CONCAT(F116,");") -> 82); | P116: =_xlfn.CONCAT(H116:N116) -> INSERT INTO PEGARULES.TB_MUNICIPIOS_OFERTAS VALUES('AL','Sao Miguel dos Milagres','','PO',to_date('08/10/2019','dd/mm/yyyy'),82);
A117: AL | B117: Sao Sebastiao | C117: BL | D117: PO | E117: 08/10/2019 | F117: 82 | H117: INSERT INTO PEGARULES.TB_MUNICIPIOS_OFERTAS VALUES( | I117: =_xlfn.CONCAT("'",A117,"'",",") -> 'AL', | J117: =_xlfn.CONCAT("'",B117,"'",",") -> 'Sao Sebastiao', | K117: =_xlfn.CONCAT("'",C117,"'",",") -> 'BL', | L117: =_xlfn.CONCAT("'",D117,"'",",") -> 'PO', | M117: =_xlfn.CONCAT("to_date('",E117,"','dd/mm/yyyy')",",") -> to_date('08/10/2019','dd/mm/yyyy'), | N117: =_xlfn.CONCAT(F117,");") -> 82); | P117: =_xlfn.CONCAT(H117:N117) -> INSERT INTO PEGARULES.TB_MUNICIPIOS_OFERTAS VALUES('AL','Sao Sebastiao','BL','PO',to_date('08/10/2019','dd/mm/yyyy'),82);
A118: AL | B118: Satuba | D118: PO | E118: 08/10/2019 | F118: 82 | H118: INSERT INTO PEGARULES.TB_MUNICIPIOS_OFERTAS VALUES( | I118: =_xlfn.CONCAT("'",A118,"'",",") -> 'AL', | J118: =_xlfn.CONCAT("'",B118,"'",",") -> 'Satuba', | K118: =_xlfn.CONCAT("'",C118,"'",",") -> '', | L118: =_xlfn.CONCAT("'",D118,"'",",") -> 'PO', | M118: =_xlfn.CONCAT("to_date('",E118,"','dd/mm/yyyy')",",") -> to_date('08/10/2019','dd/mm/yyyy'), | N118: =_xlfn.CONCAT(F118,");") -> 82); | P118: =_xlfn.CONCAT(H118:N118) -> INSERT INTO PEGARULES.TB_MUNICIPIOS_OFERTAS VALUES('AL','Satuba','','PO',to_date('08/10/2019','dd/mm/yyyy'),82);
A119: AL | B119: Senador Rui Palmeira | D119: PO | E119: 08/10/2019 | F119: 82 | H119: INSERT INTO PEGARULES.TB_MUNICIPIOS_OFERTAS VALUES( | I119: =_xlfn.CONCAT("'",A119,"'",",") -> 'AL', | J119: =_xlfn.CONCAT("'",B119,"'",",") -> 'Senador Rui Palmeira', | K119: =_xlfn.CONCAT("'",C119,"'",",") -> '', | L119: =_xlfn.CONCAT("'",D119,"'",",") -> 'PO', | M119: =_xlfn.CONCAT("to_date('",E119,"','dd/mm/yyyy')",",") -> to_date('08/10/2019','dd/mm/yyyy'), | N119: =_xlfn.CONCAT(F119,");") -> 82); | P119: =_xlfn.CONCAT(H119:N119) -> INSERT INTO PEGARULES.TB_MUNICIPIOS_OFERTAS VALUES('AL','Senador Rui Palmeira','','PO',to_date('08/10/2019','dd/mm/yyyy'),82);
A120: AL | B120: Tanque d'||chr(39)||'Arca | D120: PO | E120: 08/10/2019 | F120: 82 | H120: INSERT INTO PEGARULES.TB_MUNICIPIOS_OFERTAS VALUES( | I120: =_xlfn.CONCAT("'",A120,"'",",") -> 'AL', | J120: =_xlfn.CONCAT("'",B120,"'",",") -> 'Tanque d'||chr(39)||'Arca', | K120: =_xlfn.CONCAT("'",C120,"'",",") -> '', | L120: =_xlfn.CONCAT("'",D120,"'",",") -> 'PO', | M120: =_xlfn.CONCAT("to_date('",E120,"','dd/mm/yyyy')",",") -> to_date('08/10/2019','dd/mm/yyyy'), | N120: =_xlfn.CONCAT(F120,");") -> 82); | P120: =_xlfn.CONCAT(H120:N120) -> INSERT INTO PEGARULES.TB_MUNICIPIOS_OFERTAS VALUES('AL','Tanque d'||chr(39)||'Arca','','PO',to_date('08/10/2019','dd/mm/yyyy'),82);
A121: AL | B121: Taquarana | D121: PO | E121: 08/10/2019 | F121: 82 | H121: INSERT INTO PEGARULES.TB_MUNICIPIOS_OFERTAS VALUES( | I121: =_xlfn.CONCAT("'",A121,"'",",") -> 'AL', | J121: =_xlfn.CONCAT("'",B121,"'",",") -> 'Taquarana', | K121: =_xlfn.CONCAT("'",C121,"'",",") -> '', | L121: =_xlfn.CONCAT("'",D121,"'",",") -> 'PO', | M121: =_xlfn.CONCAT("to_date('",E121,"','dd/mm/yyyy')",",") -> to_date('08/10/2019','dd/mm/yyyy'), | N121: =_xlfn.CONCAT(F121,");") -> 82); | P121: =_xlfn.CONCAT(H121:N121) -> INSERT INTO PEGARULES.TB_MUNICIPIOS_OFERTAS VALUES('AL','Taquarana','','PO',to_date('08/10/2019','dd/mm/yyyy'),82);
A122: AL | B122: Teotonio Vilela | D122: PO | E122: 08/10/2019 | F122: 82 | H122: INSERT INTO PEGARULES.TB_MUNICIPIOS_OFERTAS VALUES( | I122: =_xlfn.CONCAT("'",A122,"'",",") -> 'AL', | J122: =_xlfn.CONCAT("'",B122,"'",",") -> 'Teotonio Vilela', | K122: =_xlfn.CONCAT("'",C122,"'",",") -> '', | L122: =_xlfn.CONCAT("'",D122,"'",",") -> 'PO', | M122: =_xlfn.CONCAT("to_date('",E122,"','dd/mm/yyyy')",",") -> to_date('08/10/2019','dd/mm/yyyy'), | N122: =_xlfn.CONCAT(F122,");") -> 82); | P122: =_xlfn.CONCAT(H122:N122) -> INSERT INTO PEGARULES.TB_MUNICIPIOS_OFERTAS VALUES('AL','Teotonio Vilela','','PO',to_date('08/10/2019','dd/mm/yyyy'),82);
A123: AL | B123: Traipu | D123: PO | E123: 08/10/2019 | F123: 82 | H123: INSERT INTO PEGARULES.TB_MUNICIPIOS_OFERTAS VALUES( | I123: =_xlfn.CONCAT("'",A123,"'",",") -> 'AL', | J123: =_xlfn.CONCAT("'",B123,"'",",") -> 'Traipu', | K123: =_xlfn.CONCAT("'",C123,"'",",") -> '', | L123: =_xlfn.CONCAT("'",D123,"'",",") -> 'PO', | M123: =_xlfn.CONCAT("to_date('",E123,"','dd/mm/yyyy')",",") -> to_date('08/10/2019','dd/mm/yyyy'), | N123: =_xlfn.CONCAT(F123,");") -> 82); | P123: =_xlfn.CONCAT(H123:N123) -> INSERT INTO PEGARULES.TB_MUNICIPIOS_OFERTAS VALUES('AL','Traipu','','PO',to_date('08/10/2019','dd/mm/yyyy'),82);
A124: AL | B124: Uniao dos Palmares | D124: PO | E124: 08/10/2019 | F124: 82 | H124: INSERT INTO PEGARULES.TB_MUNICIPIOS_OFERTAS VALUES( | I124: =_xlfn.CONCAT("'",A124,"'",",") -> 'AL', | J124: =_xlfn.CONCAT("'",B124,"'",",") -> 'Uniao dos Palmares', | K124: =_xlfn.CONCAT("'",C124,"'",",") -> '', | L124: =_xlfn.CONCAT("'",D124,"'",",") -> 'PO', | M124: =_xlfn.CONCAT("to_date('",E124,"','dd/mm/yyyy')",",") -> to_date('08/10/2019','dd/mm/yyyy'), | N124: =_xlfn.CONCAT(F124,");") -> 82); | P124: =_xlfn.CONCAT(H124:N124) -> INSERT INTO PEGARULES.TB_MUNICIPIOS_OFERTAS VALUES('AL','Uniao dos Palmares','','PO',to_date('08/10/2019','dd/mm/yyyy'),82);
A125: AL | B125: Vicosa | D125: PO | E125: 08/10/2019 | F125: 82 | H125: INSERT INTO PEGARULES.TB_MUNICIPIOS_OFERTAS VALUES( | I125: =_xlfn.CONCAT("'",A125,"'",",") -> 'AL', | J125: =_xlfn.CONCAT("'",B125,"'",",") -> 'Vicosa', | K125: =_xlfn.CONCAT("'",C125,"'",",") -> '', | L125: =_xlfn.CONCAT("'",D125,"'",",") -> 'PO', | M125: =_xlfn.CONCAT("to_date('",E125,"','dd/mm/yyyy')",",") -> to_date('08/10/2019','dd/mm/yyyy'), | N125: =_xlfn.CONCAT(F125,");") -> 82); | P125: =_xlfn.CONCAT(H125:N125) -> INSERT INTO PEGARULES.TB_MUNICIPIOS_OFERTAS VALUES('AL','Vicosa','','PO',to_date('08/10/2019','dd/mm/yyyy'),82);
A126: AM | B126: Alvaraes | C126: CONEC LIGHT | D126: PO | E126: 08/10/2019 | F126: 97 | H126: INSERT INTO PEGARULES.TB_MUNICIPIOS_OFERTAS VALUES( | I126: =_xlfn.CONCAT("'",A126,"'",",") -> 'AM', | J126: =_xlfn.CONCAT("'",B126,"'",",") -> 'Alvaraes', | K126: =_xlfn.CONCAT("'",C126,"'",",") -> 'CONEC LIGHT', | L126: =_xlfn.CONCAT("'",D126,"'",",") -> 'PO', | M126: =_xlfn.CONCAT("to_date('",E126,"','dd/mm/yyyy')",",") -> to_date('08/10/2019','dd/mm/yyyy'), | N126: =_xlfn.CONCAT(F126,");") -> 97); | P126: =_xlfn.CONCAT(H126:N126) -> INSERT INTO PEGARULES.TB_MUNICIPIOS_OFERTAS VALUES('AM','Alvaraes','CONEC LIGHT','PO',to_date('08/10/2019','dd/mm/yyyy'),97);
A127: AM | B127: Amatura | C127: CONEC LIGHT | D127: PO | E127: 08/10/2019 | F127: 97 | H127: INSERT INTO PEGARULES.TB_MUNICIPIOS_OFERTAS VALUES( | I127: =_xlfn.CONCAT("'",A127,"'",",") -> 'AM', | J127: =_xlfn.CONCAT("'",B127,"'",",") -> 'Amatura', | K127: =_xlfn.CONCAT("'",C127,"'",",") -> 'CONEC LIGHT', | L127: =_xlfn.CONCAT("'",D127,"'",",") -> 'PO', | M127: =_xlfn.CONCAT("to_date('",E127,"','dd/mm/yyyy')",",") -> to_date('08/10/2019','dd/mm/yyyy'), | N127: =_xlfn.CONCAT(F127,");") -> 97); | P127: =_xlfn.CONCAT(H127:N127) -> INSERT INTO PEGARULES.TB_MUNICIPIOS_OFERTAS VALUES('AM','Amatura','CONEC LIGHT','PO',to_date('08/10/2019','dd/mm/yyyy'),97);
A128: AM | B128: Anama | C128: CONEC LIGHT | D128: PO | E128: 08/10/2019 | F128: 97 | H128: INSERT INTO PEGARULES.TB_MUNICIPIOS_OFERTAS VALUES( | I128: =_xlfn.CONCAT("'",A128,"'",",") -> 'AM', | J128: =_xlfn.CONCAT("'",B128,"'",",") -> 'Anama', | K128: =_xlfn.CONCAT("'",C128,"'",",") -> 'CONEC LIGHT', | L128: =_xlfn.CONCAT("'",D128,"'",",") -> 'PO', | M128: =_xlfn.CONCAT("to_date('",E128,"','dd/mm/yyyy')",",") -> to_date('08/10/2019','dd/mm/yyyy'), | N128: =_xlfn.CONCAT(F128,");") -> 97); | P128: =_xlfn.CONCAT(H128:N128) -> INSERT INTO PEGARULES.TB_MUNICIPIOS_OFERTAS VALUES('AM','Anama','CONEC LIGHT','PO',to_date('08/10/2019','dd/mm/yyyy'),97);
A129: AM | B129: Anori | C129: CONEC LIGHT | D129: PO | E129: 08/10/2019 | F129: 97 | H129: INSERT INTO PEGARULES.TB_MUNICIPIOS_OFERTAS VALUES( | I129: =_xlfn.CONCAT("'",A129,"'",",") -> 'AM', | J129: =_xlfn.CONCAT("'",B129,"'",",") -> 'Anori', | K129: =_xlfn.CONCAT("'",C129,"'",",") -> 'CONEC LIGHT', | L129: =_xlfn.CONCAT("'",D129,"'",",") -> 'PO', | M129: =_xlfn.CONCAT("to_date('",E129,"','dd/mm/yyyy')",",") -> to_date('08/10/2019','dd/mm/yyyy'), | N129: =_xlfn.CONCAT(F129,");") -> 97); | P129: =_xlfn.CONCAT(H129:N129) -> INSERT INTO PEGARULES.TB_MUNICIPIOS_OFERTAS VALUES('AM','Anori','CONEC LIGHT','PO',to_date('08/10/2019','dd/mm/yyyy'),97);
A130: AM | B130: Apui | C130: CONEC LIGHT | D130: PO | E130: 08/10/2019 | F130: 97 | H130: INSERT INTO PEGARULES.TB_MUNICIPIOS_OFERTAS VALUES( | I130: =_xlfn.CONCAT("'",A130,"'",",") -> 'AM', | J130: =_xlfn.CONCAT("'",B130,"'",",") -> 'Apui', | K130: =_xlfn.CONCAT("'",C130,"'",",") -> 'CONEC LIGHT', | L130: =_xlfn.CONCAT("'",D130,"'",",") -> 'PO', | M130: =_xlfn.CONCAT("to_date('",E130,"','dd/mm/yyyy')",",") -> to_date('08/10/2019','dd/mm/yyyy'), | N130: =_xlfn.CONCAT(F130,");") -> 97); | P130: =_xlfn.CONCAT(H130:N130) -> INSERT INTO PEGARULES.TB_MUNICIPIOS_OFERTAS VALUES('AM','Apui','CONEC LIGHT','PO',to_date('08/10/2019','dd/mm/yyyy'),97);
A131: AM | B131: Atalaia do Norte | C131: CONEC LIGHT | D131: PO | E131: 08/10/2019 | F131: 97 | H131: INSERT INTO PEGARULES.TB_MUNICIPIOS_OFERTAS VALUES( | I131: =_xlfn.CONCAT("'",A131,"'",",") -> 'AM', | J131: =_xlfn.CONCAT("'",B131,"'",",") -> 'Atalaia do Norte', | K131: =_xlfn.CONCAT("'",C131,"'",",") -> 'CONEC LIGHT', | L131: =_xlfn.CONCAT("'",D131,"'",",") -> 'PO', | M131: =_xlfn.CONCAT("to_date('",E131,"','dd/mm/yyyy')",",") -> to_date('08/10/2019','dd/mm/yyyy'), | N131: =_xlfn.CONCAT(F131,");") -> 97); | P131: =_xlfn.CONCAT(H131:N131) -> INSERT INTO PEGARULES.TB_MUNICIPIOS_OFERTAS VALUES('AM','Atalaia do Norte','CONEC LIGHT','PO',to_date('08/10/2019','dd/mm/yyyy'),97);
A132: AM | B132: Autazes | D132: PO | E132: 08/10/2019 | F132: 92 | H132: INSERT INTO PEGARULES.TB_MUNICIPIOS_OFERTAS VALUES( | I132: =_xlfn.CONCAT("'",A132,"'",",") -> 'AM', | J132: =_xlfn.CONCAT("'",B132,"'",",") -> 'Autazes', | K132: =_xlfn.CONCAT("'",C132,"'",",") -> '', | L132: =_xlfn.CONCAT("'",D132,"'",",") -> 'PO', | M132: =_xlfn.CONCAT("to_date('",E132,"','dd/mm/yyyy')",",") -> to_date('08/10/2019','dd/mm/yyyy'), | N132: =_xlfn.CONCAT(F132,");") -> 92); | P132: =_xlfn.CONCAT(H132:N132) -> INSERT INTO PEGARULES.TB_MUNICIPIOS_OFERTAS VALUES('AM','Autazes','','PO',to_date('08/10/2019','dd/mm/yyyy'),92);
A133: AM | B133: Barcelos | C133: CONEC LIGHT | D133: PO | E133: 08/10/2019 | F133: 97 | H133: INSERT INTO PEGARULES.TB_MUNICIPIOS_OFERTAS VALUES( | I133: =_xlfn.CONCAT("'",A133,"'",",") -> 'AM', | J133: =_xlfn.CONCAT("'",B133,"'",",") -> 'Barcelos', | K133: =_xlfn.CONCAT("'",C133,"'",",") -> 'CONEC LIGHT', | L133: =_xlfn.CONCAT("'",D133,"'",",") -> 'PO', | M133: =_xlfn.CONCAT("to_date('",E133,"','dd/mm/yyyy')",",") -> to_date('08/10/2019','dd/mm/yyyy'), | N133: =_xlfn.CONCAT(F133,");") -> 97); | P133: =_xlfn.CONCAT(H133:N133) -> INSERT INTO PEGARULES.TB_MUNICIPIOS_OFERTAS VALUES('AM','Barcelos','CONEC LIGHT','PO',to_date('08/10/2019','dd/mm/yyyy'),97);
A134: AM | B134: Barreirinha | D134: PO | E134: 08/10/2019 | F134: 92 | H134: INSERT INTO PEGARULES.TB_MUNICIPIOS_OFERTAS VALUES( | I134: =_xlfn.CONCAT("'",A134,"'",",") -> 'AM', | J134: =_xlfn.CONCAT("'",B134,"'",",") -> 'Barreirinha', | K134: =_xlfn.CONCAT("'",C134,"'",",") -> '', | L134: =_xlfn.CONCAT("'",D134,"'",",") -> 'PO', | M134: =_xlfn.CONCAT("to_date('",E134,"','dd/mm/yyyy')",",") -> to_date('08/10/2019','dd/mm/yyyy'), | N134: =_xlfn.CONCAT(F134,");") -> 92); | P134: =_xlfn.CONCAT(H134:N134) -> INSERT INTO PEGARULES.TB_MUNICIPIOS_OFERTAS VALUES('AM','Barreirinha','','PO',to_date('08/10/2019','dd/mm/yyyy'),92);
A135: AM | B135: Benjamin Constant | C135: CONEC LIGHT | D135: PO | E135: 08/10/2019 | F135: 97 | H135: INSERT INTO PEGARULES.TB_MUNICIPIOS_OFERTAS VALUES( | I135: =_xlfn.CONCAT("'",A135,"'",",") -> 'AM', | J135: =_xlfn.CONCAT("'",B135,"'",",") -> 'Benjamin Constant', | K135: =_xlfn.CONCAT("'",C135,"'",",") -> 'CONEC LIGHT', | L135: =_xlfn.CONCAT("'",D135,"'",",") -> 'PO', | M135: =_xlfn.CONCAT("to_date('",E135,"','dd/mm/yyyy')",",") -> to_date('08/10/2019','dd/mm/yyyy'), | N135: =_xlfn.CONCAT(F135,");") -> 97); | P135: =_xlfn.CONCAT(H135:N135) -> INSERT INTO PEGARULES.TB_MUNICIPIOS_OFERTAS VALUES('AM','Benjamin Constant','CONEC LIGHT','PO',to_date('08/10/2019','dd/mm/yyyy'),97);
A136: AM | B136: Beruri | D136: PO | E136: 08/10/2019 | F136: 97 | H136: INSERT INTO PEGARULES.TB_MUNICIPIOS_OFERTAS VALUES( | I136: =_xlfn.CONCAT("'",A136,"'",",") -> 'AM', | J136: =_xlfn.CONCAT("'",B136,"'",",") -> 'Beruri', | K136: =_xlfn.CONCAT("'",C136,"'",",") -> '', | L136: =_xlfn.CONCAT("'",D136,"'",",") -> 'PO', | M136: =_xlfn.CONCAT("to_date('",E136,"','dd/mm/yyyy')",",") -> to_date('08/10/2019','dd/mm/yyyy'), | N136: =_xlfn.CONCAT(F136,");") -> 97); | P136: =_xlfn.CONCAT(H136:N136) -> INSERT INTO PEGARULES.TB_MUNICIPIOS_OFERTAS VALUES('AM','Beruri','','PO',to_date('08/10/2019','dd/mm/yyyy'),97);
A137: AM | B137: Boa Vista do Ramos | D137: PO | E137: 08/10/2019 | F137: 92 | H137: INSERT INTO PEGARULES.TB_MUNICIPIOS_OFERTAS VALUES( | I137: =_xlfn.CONCAT("'",A137,"'",",") -> 'AM', | J137: =_xlfn.CONCAT("'",B137,"'",",") -> 'Boa Vista do Ramos', | K137: =_xlfn.CONCAT("'",C137,"'",",") -> '', | L137: =_xlfn.CONCAT("'",D137,"'",",") -> 'PO', | M137: =_xlfn.CONCAT("to_date('",E137,"','dd/mm/yyyy')",",") -> to_date('08/10/2019','dd/mm/yyyy'), | N137: =_xlfn.CONCAT(F137,");") -> 92); | P137: =_xlfn.CONCAT(H137:N137) -> INSERT INTO PEGARULES.TB_MUNICIPIOS_OFERTAS VALUES('AM','Boa Vista do Ramos','','PO',to_date('08/10/2019','dd/mm/yyyy'),92);
A138: AM | B138: Boca do Acre | C138: CONEC LIGHT | D138: PO | E138: 08/10/2019 | F138: 97 | H138: INSERT INTO PEGARULES.TB_MUNICIPIOS_OFERTAS VALUES( | I138: =_xlfn.CONCAT("'",A138,"'",",") -> 'AM', | J138: =_xlfn.CONCAT("'",B138,"'",",") -> 'Boca do Acre', | K138: =_xlfn.CONCAT("'",C138,"'",",") -> 'CONEC LIGHT', | L138: =_xlfn.CONCAT("'",D138,"'",",") -> 'PO', | M138: =_xlfn.CONCAT("to_date('",E138,"','dd/mm/yyyy')",",") -> to_date('08/10/2019','dd/mm/yyyy'), | N138: =_xlfn.CONCAT(F138,");") -> 97); | P138: =_xlfn.CONCAT(H138:N138) -> INSERT INTO PEGARULES.TB_MUNICIPIOS_OFERTAS VALUES('AM','Boca do Acre','CONEC LIGHT','PO',to_date('08/10/2019','dd/mm/yyyy'),97);
A139: AM | B139: Borba | D139: PO | E139: 08/10/2019 | F139: 92 | H139: INSERT INTO PEGARULES.TB_MUNICIPIOS_OFERTAS VALUES( | I139: =_xlfn.CONCAT("'",A139,"'",",") -> 'AM', | J139: =_xlfn.CONCAT("'",B139,"'",",") -> 'Borba', | K139: =_xlfn.CONCAT("'",C139,"'",",") -> '', | L139: =_xlfn.CONCAT("'",D139,"'",",") -> 'PO', | M139: =_xlfn.CONCAT("to_date('",E139,"','dd/mm/yyyy')",",") -> to_date('08/10/2019','dd/mm/yyyy'), | N139: =_xlfn.CONCAT(F139,");") -> 92); | P139: =_xlfn.CONCAT(H139:N139) -> INSERT INTO PEGARULES.TB_MUNICIPIOS_OFERTAS VALUES('AM','Borba','','PO',to_date('08/10/2019','dd/mm/yyyy'),92);
A140: AM | B140: Caapiranga | D140: PO | E140: 08/10/2019 | F140: 92 | H140: INSERT INTO PEGARULES.TB_MUNICIPIOS_OFERTAS VALUES( | I140: =_xlfn.CONCAT("'",A140,"'",",") -> 'AM', | J140: =_xlfn.CONCAT("'",B140,"'",",") -> 'Caapiranga', | K140: =_xlfn.CONCAT("'",C140,"'",",") -> '', | L140: =_xlfn.CONCAT("'",D140,"'",",") -> 'PO', | M140: =_xlfn.CONCAT("to_date('",E140,"','dd/mm/yyyy')",",") -> to_date('08/10/2019','dd/mm/yyyy'), | N140: =_xlfn.CONCAT(F140,");") -> 92); | P140: =_xlfn.CONCAT(H140:N140) -> INSERT INTO PEGARULES.TB_MUNICIPIOS_OFERTAS VALUES('AM','Caapiranga','','PO',to_date('08/10/2019','dd/mm/yyyy'),92);
A141: AM | B141: Canutama | C141: CONEC LIGHT | D141: PO | E141: 08/10/2019 | F141: 97 | H141: INSERT INTO PEGARULES.TB_MUNICIPIOS_OFERTAS VALUES( | I141: =_xlfn.CONCAT("'",A141,"'",",") -> 'AM', | J141: =_xlfn.CONCAT("'",B141,"'",",") -> 'Canutama', | K141: =_xlfn.CONCAT("'",C141,"'",",") -> 'CONEC LIGHT', | L141: =_xlfn.CONCAT("'",D141,"'",",") -> 'PO', | M141: =_xlfn.CONCAT("to_date('",E141,"','dd/mm/yyyy')",",") -> to_date('08/10/2019','dd/mm/yyyy'), | N141: =_xlfn.CONCAT(F141,");") -> 97); | P141: =_xlfn.CONCAT(H141:N141) -> INSERT INTO PEGARULES.TB_MUNICIPIOS_OFERTAS VALUES('AM','Canutama','CONEC LIGHT','PO',to_date('08/10/2019','dd/mm/yyyy'),97);
A142: AM | B142: Carauari | C142: CONEC LIGHT | D142: PO | E142: 08/10/2019 | F142: 97 | H142: INSERT INTO PEGARULES.TB_MUNICIPIOS_OFERTAS VALUES( | I142: =_xlfn.CONCAT("'",A142,"'",",") -> 'AM', | J142: =_xlfn.CONCAT("'",B142,"'",",") -> 'Carauari', | K142: =_xlfn.CONCAT("'",C142,"'",",") -> 'CONEC LIGHT', | L142: =_xlfn.CONCAT("'",D142,"'",",") -> 'PO', | M142: =_xlfn.CONCAT("to_date('",E142,"','dd/mm/yyyy')",",") -> to_date('08/10/2019','dd/mm/yyyy'), | N142: =_xlfn.CONCAT(F142,");") -> 97); | P142: =_xlfn.CONCAT(H142:N142) -> INSERT INTO PEGARULES.TB_MUNICIPIOS_OFERTAS VALUES('AM','Carauari','CONEC LIGHT','PO',to_date('08/10/2019','dd/mm/yyyy'),97);
...

Sheet Sheet3
A1: select replace(no_municipio,'''''',chr(39)) as no_municipio from PEGARULES.TB_MUNICIPIOS_OFERTAS
A2: where no_municipio like '%''%';
A3: update PEGARULES.TB_MUNICIPIOS_OFERTAS set no_municipio= replace(no_municipio,'''''',chr(39))
A4: where no_municipio like '%''%';
A5: commit;
A7: select no_municipio from PEGARULES.TB_MUNICIPIOS_OFERTAS
A8: where no_municipio like '%''%';

Sheet Atual_2018-12-13
A1: UF | B1: NO_MUNICIPIO | C1: GRUPO_OFERTA | D1: GRUPO_PORTA_OCIOSAS | E1: DT_CRIACAO
A2: SP | B2: Indiana | E2: 43410
A3: SP | B3: Mesopolis | E3: 43410
A4: SP | B4: Parapua | E4: 43410
A5: SP | B5: Embauba | E5: 43410
A6: SP | B6: Lagoinha | E6: 43410
A7: SP | B7: Macedonia | E7: 43410
A8: SP | B8: Sao Francisco | E8: 43410
A9: SP | B9: Dolcinopolis | E9: 43410
A10: SP | B10: Sao Sebastiao da Grama | E10: 43410
A11: SP | B11: Vera Cruz | E11: 43410
A12: SP | B12: Cajati | E12: 43410
A13: SP | B13: Aspasia | E13: 43410
... A76: SP | B76: Flora Rica | E76: 43410
A77: PR | B77: Abatia | C77: CONEC LIGHT | E77: 43410
A78: PR | B78: Adrianopolis | C78: CONEC LIGHT | E78: 43410
A79: PR | B79: Agudos do Sul | C79: CONEC LIGHT | E79: 43410
A80: PR | B80: Almirante Tamandare | C80: CONEC LIGHT | E80: 43410
A81: PR | B81: Altamira do Parana | C81: CONEC LIGHT | E81: 43410
A82: PR | B82: Altonia | C82: CONEC LIGHT | D82: PO | E82: 43410
A83: PR | B83: Alto Parana | C83: CONEC LIGHT | E83: 43410
A84: PR | B84: Alto Piquiri | C84: CONEC LIGHT BL | D84: PO | E84: 43410
A85: PR | B85: Alvorada do Sul | C85: CONEC LIGHT | E85: 43410
A86: PR | B86: Amapora | C86: CONEC LIGHT | E86: 43410
A87: PR | B87: Ampere | C87: CONEC LIGHT | D87: PO | E87: 43410
A88: PR | B88: Anahy | C88: CONEC LIGHT | E88: 43410
A89: PR | B89: Andira | C89: CONEC LIGHT | D89: PO | E89: 43410
A90: PR | B90: angulo | C90: CONEC LIGHT | E90: 43410
A91: PR | B91: Antonina | C91: CONEC LIGHT | E91: 43410
A92: PR | B92: Antonio Olinto | C92: CONEC LIGHT | E92: 43410
A93: PR | B93: Apucarana | C93: CONEC LIGHT | E93: 43410
A94: PR | B94: Arapongas | C94: CONEC LIGHT | D94: PO | E94: 43410
A95: PR | B95: Arapoti | C95: CONEC LIGHT | D95: PO | E95: 43410
A96: PR | B96: Arapua | C96: CONEC LIGHT | E96: 43410
A97: PR | B97: Araruna | C97: CONEC LIGHT | E97: 43410
A98: PR | B98: Araucaria | C98: CONEC LIGHT | D98: PO | E98: 43410
A99: PR | B99: Ariranha do Ivai | C99: CONEC LIGHT | E99: 43410
A100: PR | B100: Assai | C100: CONEC LIGHT | D100: PO | E100: 43410
A101: PR | B101: Assis Chateaubriand | C101: CONEC LIGHT BL | D101: PO | E101: 43410
A102: PR | B102: Astorga | C102: CONEC LIGHT BL | E102: 43410
A103: PR | B103: Atalaia | C103: CONEC LIGHT | E103: 43410
A104: PR | B104: Balsa Nova | C104: CONEC LIGHT | E104: 43410
A105: PR | B105: Bandeirantes | C105: CONEC LIGHT | D105: PO | E105: 43410
A106: PR | B106: Barbosa Ferraz | C106: CONEC LIGHT | E106: 43410
A107: PR | B107: Barracao | E107: 43410
A108: PR | B108: Barra do Jacare | C108: CONEC LIGHT | E108: 43410
A109: PR | B109: Bela Vista da Caroba | C109: CONEC LIGHT | E109: 43410
A110: PR | B110: Bela Vista do Paraiso | C110: CONEC LIGHT | D110: PO | E110: 43410
A111: PR | B111: Bituruna | C111: CONEC LIGHT | E111: 43410
A112: PR | B112: Boa Esperanca | C112: CONEC LIGHT | E112: 43410
A113: PR | B113: Boa Esperanca do Iguacu | C113: CONEC LIGHT | E113: 43410
A114: PR | B114: Boa Ventura de Sao Roque | C114: CONEC LIGHT | E114: 43410
A115: PR | B115: Boa Vista da Aparecida | C115: CONEC LIGHT | E115: 43410
A116: PR | B116: Bocaiuva do Sul | C116: CONEC LIGHT BL | E116: 43410
A117: PR | B117: Bom Jesus do Sul | C117: CONEC LIGHT BL | D117: PO | E117: 43410
A118: PR | B118: Bom Sucesso | C118: CONEC LIGHT BL | D118: PO | E118: 43410
A119: PR | B119: Bom Sucesso do Sul | C119: CONEC LIGHT | E119: 43410
A120: PR | B120: Borrazopolis | C120: CONEC LIGHT | D120: PO | E120: 43410
A121: PR | B121: Braganey | C121: CONEC LIGHT | E121: 43410
A122: PR | B122: Brasilandia do Sul | C122: CONEC LIGHT BL | D122: PO | E122: 43410
A123: PR | B123: Cafeara | C123: CONEC LIGHT | E123: 43410
A124: PR | B124: Cafelandia | C124: CONEC LIGHT | D124: PO | E124: 43410
A125: PR | B125: Cafezal do Sul | C125: CONEC LIGHT | E125: 43410
A126: PR | B126: California | C126: CONEC LIGHT | E126: 43410
A127: PR | B127: Cambara | C127: CONEC LIGHT | E127: 43410
A128: PR | B128: Cambe | C128: CONEC LIGHT | E128: 43410
A129: PR | B129: Cambira | C129: CONEC LIGHT | E129: 43410
A130: PR | B130: Campina da Lagoa | C130: CONEC LIGHT | E130: 43410
A131: PR | B131: Campina do Simao | C131: CONEC LIGHT | E131: 43410
A132: PR | B132: Campina Grande do Sul | C132: CONEC LIGHT | E132: 43410
A133: PR | B133: Campo Bonito | C133: CONEC LIGHT | D133: PO | E133: 43410
A134: PR | B134: Campo do Tenente | C134: CONEC LIGHT | E134: 43410
A135: SP | B135: Sud Mennucci | E135: 43410
A136: PR | B136: Campo Largo | C136: CONEC LIGHT | E136: 43410
A137: PR | B137: Campo Magro | C137: CONEC LIGHT BL | E137: 43410
A138: MA | B138: Itapecuru Mirim | E138: 43410
A139: MA | B139: Itinga do Maranhao | E139: 43410
A140: MA | B140: Jatoba | E140: 43410
A141: MA | B141: Jenipapo dos Vieiras | E141: 43410
A142: MA | B142: Joao Lisboa | E142: 43410
A143: MA | B143: Joselandia | E143: 43410
A144: MA | B144: Junco do Maranhao | E144: 43410
A145: MA | B145: Lago da Pedra | E145: 43410
A146: MA | B146: Lago do Junco | E146: 43410
A147: MA | B147: Lago Verde | D147: PO | E147: 43410
A148: MA | B148: Lagoa do Mato | E148: 43410
A149: MA | B149: Lago dos Rodrigues | E149: 43410
A150: MA | B150: Lagoa Grande do Maranhao | E150: 43410
A151: MA | B151: Lajeado Novo | E151: 43410
A152: MA | B152: Lima Campos | E152: 43410
A153: MA | B153: Loreto | E153: 43410
A154: MA | B154: Luis Domingues | E154: 43410
A155: MA | B155: Magalhaes de Almeida | E155: 43410
A156: MA | B156: Maracacume | E156: 43410
A157: MA | B157: Maraja do Sena | E157: 43410
A158: MA | B158: Maranhaozinho | E158: 43410
A159: MA | B159: Mata Roma | E159: 43410
... A163: MA | B163: Milagres do Maranhao | E163: 43410
A164: MA | B164: Mirador | C164: BL | D164: PO | E164: 43410
A165: MA | B165: Miranda do Norte | E165: 43410
...

Sheet SQL
A1: pegarules.TB_MUNICIPIOS_OFERTAS
J2: De: | K2: '
A3: =_xlfn.CONCAT("SELECT * FROM ",A1) -> SELECT * FROM pegarules.TB_MUNICIPIOS_OFERTAS | J3: Para: | K3: ||chr(39)||'
A5: =_xlfn.CONCAT("DELETE FROM ",A1,";") -> DELETE FROM pegarules.TB_MUNICIPIOS_OFERTAS;
A6: COMMIT;

Sheet AtualProd_2018-12-13
A1: UF | B1: NO_MUNICIPIO | C1: GRUPO_OFERTA | D1: GRUPO_PORTA_OCIOSAS | E1: DT_CRIACAO
A2: ES | B2: Muqui | C2: CONEC LIGHT | E2: 43423
A3: ES | B3: Nova Venecia | C3: CONEC LIGHT | D3: PO | E3: 43423
A4: ES | B4: Pancas | C4: CONEC LIGHT | E4: 43423
A5: ES | B5: Pedro Canario | C5: CONEC LIGHT BL | E5: 43423
A6: ES | B6: Pinheiros | C6: CONEC LIGHT | E6: 43423
A7: ES | B7: Piuma | C7: CONEC LIGHT | E7: 43423
A8: ES | B8: Ponto Belo | C8: CONEC LIGHT BL | D8: PO | E8: 43423
A9: ES | B9: Presidente Kennedy | C9: CONEC LIGHT | E9: 43423
A10: ES | B10: Rio Bananal | C10: CONEC LIGHT | E10: 43423
A11: ES | B11: Rio Novo do Sul | C11: CONEC LIGHT | D11: PO | E11: 43423
A12: ES | B12: Santa Leopoldina | C12: CONEC LIGHT | D12: PO | E12: 43423
A13: ES | B13: Santa Maria de Jetiba | C13: CONEC LIGHT | E13: 43423
A14: ES | B14: Santa Teresa | C14: CONEC LIGHT | E14: 43423
A15: ES | B15: Sao Domingos do Norte | C15: CONEC LIGHT BL | D15: PO | E15: 43423
A16: ES | B16: Sao Gabriel da Palha | C16: CONEC LIGHT | E16: 43423
A17: ES | B17: Sao Jose do Calcado | C17: CONEC LIGHT BL | D17: PO | E17: 43423
A18: ES | B18: Sao Mateus | C18: CONEC LIGHT BL | D18: PO | E18: 43423
A19: ES | B19: Sao Roque do Canaa | C19: CONEC LIGHT | E19: 43423
A20: ES | B20: Serra | C20: CONEC LIGHT | E20: 43423
A21: ES | B21: Sooretama | C21: CONEC LIGHT | E21: 43423
A22: ES | B22: Vargem Alta | C22: CONEC LIGHT | E22: 43423
A23: ES | B23: Venda Nova do Imigrante | C23: CONEC LIGHT | E23: 43423
A24: ES | B24: Viana | C24: CONEC LIGHT | E24: 43423
A25: ES | B25: Vila Pavao | C25: CONEC LIGHT | E25: 43423
A26: ES | B26: Vila Valerio | C26: CONEC LIGHT | E26: 43423
A27: ES | B27: Vila Velha | C27: CONEC LIGHT | E27: 43423
A28: ES | B28: Vitoria | C28: CONEC LIGHT | E28: 43423
A29: RJ | B29: Angra dos Reis | C29: CONEC LIGHT | E29: 43423
A30: RJ | B30: Aperibe | C30: CONEC LIGHT | E30: 43423
A31: RJ | B31: Araruama | C31: CONEC LIGHT BL | D31: PO | E31: 43423
A32: RJ | B32: Areal | C32: CONEC LIGHT | E32: 43423
A33: RJ | B33: Armacao dos Buzios | C33: CONEC LIGHT | D33: PO | E33: 43423
A34: RJ | B34: Arraial do Cabo | C34: CONEC LIGHT | D34: PO | E34: 43423
A35: RJ | B35: Barra do Pirai | C35: CONEC LIGHT | D35: PO | E35: 43423
A36: RJ | B36: Barra Mansa | C36: CONEC LIGHT | D36: PO | E36: 43423
A37: RJ | B37: Belford Roxo | C37: CONEC LIGHT | D37: PO | E37: 43423
A38: RJ | B38: Bom Jardim | C38: CONEC LIGHT | E38: 43423
A39: RJ | B39: Bom Jesus do Itabapoana | C39: CONEC LIGHT BL | D39: PO | E39: 43423
A40: RJ | B40: Cabo Frio | C40: CONEC LIGHT | E40: 43423
A41: RJ | B41: Cachoeiras de Macacu | C41: CONEC LIGHT | D41: PO | E41: 43423
A42: RJ | B42: Cambuci | C42: CONEC LIGHT BL | D42: PO | E42: 43423
A43: SE | B43: Itabaiana | C43: BL | E43: 43423
A44: SE | B44: Itabaianinha | E44: 43423
A45: SE | B45: Itabi | E45: 43423
A46: SE | B46: Itaporanga D'Ajuda | C46: BL | E46: 43423
A47: SE | B47: Japaratuba | C47: BL | D47: PO | E47: 43423
A48: SE | B48: Japoata | E48: 43423
A49: SE | B49: Lagarto | D49: PO | E49: 43423
A50: SE | B50: Laranjeiras | C50: BL | E50: 43423
A51: SE | B51: Macambira | E51: 43423
A52: SE | B52: Malhada dos Bois | E52: 43423
A53: SE | B53: Malhador | E53: 43423
A54: SE | B54: Maruim | E54: 43423
A55: SE | B55: Moita Bonita | D55: PO | E55: 43423
A56: SE | B56: Monte Alegre de Sergipe | E56: 43423
A57: SE | B57: Muribeca | C57: BL | E57: 43423
A58: SE | B58: Neopolis | E58: 43423
A59: SE | B59: Nossa Senhora Aparecida | E59: 43423
A60: SE | B60: Nossa Senhora da Gloria | E60: 43423
A61: SE | B61: Nossa Senhora das Dores | E61: 43423
A62: SE | B62: Nossa Senhora de Lourdes | E62: 43423
A63: SE | B63: Nossa Senhora do Socorro | D63: PO | E63: 43423
A64: SE | B64: Pacatuba | E64: 43423
A65: SE | B65: Pedra Mole | E65: 43423
A66: SE | B66: Pedrinhas | E66: 43423
A67: SE | B67: Pinhao | E67: 43423
A68: SE | B68: Pirambu | C68: BL | E68: 43423
A69: SE | B69: Poco Redondo | E69: 43423
A70: SE | B70: Poco Verde | E70: 43423
A71: SE | B71: Porto da Folha | E71: 43423
A72: SE | B72: Propria | E72: 43423
A73: SE | B73: Riachao do Dantas | E73: 43423
A74: SE | B74: Riachuelo | E74: 43423
A75: SE | B75: Ribeiropolis | E75: 43423
A76: SE | B76: Rosario do Catete | E76: 43423
A77: SE | B77: Salgado | C77: BL | E77: 43423
A78: SE | B78: Santa Luzia do Itanhy | D78: PO | E78: 43423
A79: SE | B79: Santana do Sao Francisco | E79: 43423
A80: SE | B80: Santa Rosa de Lima | E80: 43423
A81: SE | B81: Santo Amaro das Brotas | E81: 43423
A82: SE | B82: Sao Cristovao | E82: 43423
A83: SE | B83: Sao Domingos | D83: PO | E83: 43423
A84: SE | B84: Sao Francisco | E84: 43423
A85: SE | B85: Sao Miguel do Aleixo | E85: 43423
A86: SE | B86: Simao Dias | E86: 43423
A87: SE | B87: Siriri | E87: 43423
A88: SE | B88: Telha | E88: 43423
A89: SE | B89: Tobias Barreto | D89: PO | E89: 43423
A90: SE | B90: Tomar do Geru | E90: 43423
A91: SE | B91: Umbauba | E91: 43423
A92: BA | B92: Abaira | E92: 43423
A93: BA | B93: Abare | C93: CONEC LIGHT | E93: 43423
A94: BA | B94: Acajutiba | C94: CONEC LIGHT | E94: 43423
A95: BA | B95: Adustina | C95: CONEC LIGHT | E95: 43423
A96: BA | B96: agua Fria | C96: CONEC LIGHT | E96: 43423
A97: BA | B97: erico Cardoso | E97: 43423
A98: BA | B98: Aiquara | E98: 43423
A99: BA | B99: Alagoinhas | C99: CONEC LIGHT | E99: 43423
A100: BA | B100: Alcobaca | E100: 43423
...

Sheet Conectado Light
A1: UFMUNICÍPIO
A2: ACACRELANDIA | B2: Conectado Light | C2: =VLOOKUP(A2,'Exportar Planilha Final'!$C:$C,2,0) -> #N/A
A3: ACASSIS BRASIL | B3: Conectado Light | C3: =VLOOKUP(A3,'Exportar Planilha Final'!$C:$C,2,0) -> #N/A
A4: ACBRASILEIA | B4: Conectado Light | C4: =VLOOKUP(A4,'Exportar Planilha Final'!$C:$C,2,0) -> #N/A
A5: ACBUJARI | B5: Conectado Light | C5: =VLOOKUP(A5,'Exportar Planilha Final'!$C:$C,2,0) -> #N/A
A6: ACCAPIXABA | B6: Conectado Light | C6: =VLOOKUP(A6,'Exportar Planilha Final'!$C:$C,2,0) -> #N/A
A7: ACCRUZEIRO DO SUL | B7: Conectado Light | C7: =VLOOKUP(A7,'Exportar Planilha Final'!$C:$C,2,0) -> #N/A
A8: ACFEIJO | B8: Conectado Light | C8: =VLOOKUP(A8,'Exportar Planilha Final'!$C:$C,2,0) -> #N/A
A9: ACJORDAO | B9: Conectado Light | C9: =VLOOKUP(A9,'Exportar Planilha Final'!$C:$C,2,0) -> #N/A
A10: ACMANCIO LIMA | B10: Conectado Light | C10: =VLOOKUP(A10,'Exportar Planilha Final'!$C:$C,2,0) -> #N/A
A11: ACMANOEL URBANO | B11: Conectado Light | C11: =VLOOKUP(A11,'Exportar Planilha Final'!$C:$C,2,0) -> #N/A
A12: ACMARECHAL THAUMATURGO | B12: Conectado Light | C12: =VLOOKUP(A12,'Exportar Planilha Final'!$C:$C,2,0) -> #N/A
A13: ACPLACIDO DE CASTRO | B13: Conectado Light | C13: =VLOOKUP(A13,'Exportar Planilha Final'!$C:$C,2,0) -> #N/A
... A2752: SCZORTEA | B2752: Conectado Light | C2752: =VLOOKUP(A2752,'Exportar Planilha Final'!$C:$C,2,0) -> #N/A
